Workbook
Name _Toc82616607: '2 EstudiantadoEstProf'!#REF!

Sheet 2 EstudiantadoEstProf
A1: N.P. | B1: Clave Objetivo General | C1: Objetivo General | D1: Clave Objetivo Específico | E1: Objetivo Específico | F1: No. de meta en el PRDI | G1: Meta PRDI | H1: Clave de la meta | I1: Meta del espacio académico | J1: Actividad/Indicador | K1: Método de cálculo | L1: Nombre de las variables | M1: Valor de las variables | R1: Valor de los indicadores | W1: Medición (anual o acumulada) | X1: Área responsable | AN1: ESTATUS
M2: Ref. 2026 | N2: 2027 | O2: 2028 | P2: 2029 | Q2: 2030 | R2: Ref. 2026 | S2: 2027 | T2: 2028 | U2: 2029 | V2: 2030
A3: 1 | B3: PRDI25-29-Obj-36 | C3: Formar estudiantes de excelencia, a través de estudios profesionales pertinentes e inclusivos, con una vinculación permanente con estudiantes y personas egresadas, para su pleno desarrollo profesional y su contribución al bienestar social. | D3: PRDI2025-2029-Obj-58 | E3: Contar con planes de estudio pertinentes y de excelencia, en diferentes modalidades, que incorporen los criterios transversales del SEAES, de indicadores de instancias de evaluación externa y acreditación, y de organismos acreditadores, para formar profesionistas que contribuyan a la conformación de una sociedad más justa, libre, incluyente y pacífica, con una visión de sostenibilidad. | F3: 3 | G3: Incorporar contenidos temáticos o actividades académicas sobre los criterios transversales del seaes, en 30 planes de estudio reestructurados, durante la administración | H3: ACT-PRDI-NS-2726 | I3: meta fac | J3: Actividad | K3: Sin fórmula | L3: Incorporar contenidos temáticos o actividades académicas sobre los criterios transversales del seaes, en planes de estudio reestructurados | R3: =M3 -> 0 | S3: =N3 -> 0 | T3: =O3 -> 0 | U3: =P3 -> 0 | V3: =Q3 -> 0 | W3: Anual
A4: 2 | B4: PRDI25-29-Obj-36 | C4: Formar estudiantes de excelencia, a través de estudios profesionales pertinentes e inclusivos, con una vinculación permanente con estudiantes y personas egresadas, para su pleno desarrollo profesional y su contribución al bienestar social. | D4: PRDI2025-2029-Obj-58 | E4: Contar con planes de estudio pertinentes y de excelencia, en diferentes modalidades, que incorporen los criterios transversales del SEAES, de indicadores de instancias de evaluación externa y acreditación, y de organismos acreditadores, para formar profesionistas que contribuyan a la conformación de una sociedad más justa, libre, incluyente y pacífica, con una visión de sostenibilidad. | F4: 4 | G4: Contar con el acervo de 120 unidades de aprendizaje de estudios profesionales apegados a las referencias documentales básicas durante la administración | H4: ACT-PRDI-NS-2727 | J4: Actividad | K4: Sin fórmula | L4: Contar con el acervo de unidades de aprendizaje de estudios profesionales apegados a las referencias documentales básicas | R4: =M4 -> 0 | S4: =N4 -> 0 | T4: =O4 -> 0 | U4: =P4 -> 0 | V4: =Q4 -> 0 | W4: Anual
A5: 3 | B5: PRDI25-29-Obj-36 | C5: Formar estudiantes de excelencia, a través de estudios profesionales pertinentes e inclusivos, con una vinculación permanente con estudiantes y personas egresadas, para su pleno desarrollo profesional y su contribución al bienestar social. | D5: PRDI2025-2029-Obj-58 | E5: Contar con planes de estudio pertinentes y de excelencia, en diferentes modalidades, que incorporen los criterios transversales del SEAES, de indicadores de instancias de evaluación externa y acreditación, y de organismos acreditadores, para formar profesionistas que contribuyan a la conformación de una sociedad más justa, libre, incluyente y pacífica, con una visión de sostenibilidad. | F5: 7 | G5: Lograr que 89.13% de los programas educativos de estudios profesionales evaluables cuenten con reconocimiento por su excelencia, para 2029 | H5: IND-NS-210 | J5: Indicador | K5: (Número de programas educativos de estudios profesionales con reconocimiento por su excelencia / Número de programas educativos de Estudios Profesionales evaluables)*100 | L5: Número de programas educativos de estudios profesionales con reconocimiento por su excelencia | R5: =IF(M6,M5/M6*100,"0") -> 0 | S5: =IF(N6,N5/N6*100,"0") -> 0 | T5: =IF(O6,O5/O6*100,"0") -> 0 | U5: =IF(P6,P5/P6*100,"0") -> 0 | V5: =IF(Q6,Q5/Q6*100,"0") -> 0 | W5: Anual
L6: Número de programas educativos de Estudios Profesionales evaluables
A7: 4 | B7: PRDI25-29-Obj-36 | C7: Formar estudiantes de excelencia, a través de estudios profesionales pertinentes e inclusivos, con una vinculación permanente con estudiantes y personas egresadas, para su pleno desarrollo profesional y su contribución al bienestar social. | D7: PRDI2025-2029-Obj-58 | E7: Contar con planes de estudio pertinentes y de excelencia, en diferentes modalidades, que incorporen los criterios transversales del SEAES, de indicadores de instancias de evaluación externa y acreditación, y de organismos acreditadores, para formar profesionistas que contribuyan a la conformación de una sociedad más justa, libre, incluyente y pacífica, con una visión de sostenibilidad. | F7: 8 | G7: Lograr que 92.9% de la matrícula en programas educativos de estudios profesionales evaluables, curse en programas educativos reconocidos por su excelencia, para 2029 | H7: IND-PRDI-351 | J7: Indicador | K7: (Matrícula de estudiantes de estudios profesionales del sistema dependiente en programas educativos reconocidos por su excelencia / Matrícula de estudiantes de estudios profesionales del sistema dependiente en programas educativos evaluables)*100 | L7: Matrícula de estudiantes de estudios profesionales del sistema dependiente en programas educativos reconocidos por su excelencia | R7: =IF(M8,M7/M8*100,"0") -> 0 | S7: =IF(N8,N7/N8*100,"0") -> 0 | T7: =IF(O8,O7/O8*100,"0") -> 0 | U7: =IF(P8,P7/P8*100,"0") -> 0 | V7: =IF(Q8,Q7/Q8*100,"0") -> 0 | W7: Anual
L8: Matrícula de estudiantes de estudios profesionales del sistema dependiente en programas educativos evaluables
A9: 5 | B9: PRDI25-29-Obj-36 | C9: Formar estudiantes de excelencia, a través de estudios profesionales pertinentes e inclusivos, con una vinculación permanente con estudiantes y personas egresadas, para su pleno desarrollo profesional y su contribución al bienestar social. | D9: PRDI25-29-Obj-81 | E9: Fortalecer la formación disciplinar e integral del estudiantado y su educación continua, en congruencia con el modelo educativo institucional, para fomentar su desarrollo humano completo y maximizar su potencial académico y profesional, así como su retribución social, en los diferentes sectores. | F9: 9 | G9: Lograr que 72% de los sustentantes que presentan el EGEL obtengan testimonios de desempeño sobresaliente o satisfactorio, para 2029 | H9: IND-PRDI-200 | J9: Indicador | K9: (Número de sustentantes de estudios profesionales que obtienen testimonio de desempeño sobresaliente o satisfactorio en el EGEL / Total de sustentantes de estudios profesionales que presentan los EGEL)*100 | L9: Número de sustentantes de estudios profesionales que obtienen testimonio de desempeño sobresaliente o satisfactorio en el EGEL | R9: =IF(M10,M9/M10*100,"0") -> 0 | S9: =IF(N10,N9/N10*100,"0") -> 0 | T9: =IF(O10,O9/O10*100,"0") -> 0 | U9: =IF(P10,P9/P10*100,"0") -> 0 | V9: =IF(Q10,Q9/Q10*100,"0") -> 0 | W9: Anual
L10: Total de sustentantes de estudios profesionales que presentan los EGEL
A11: 6 | B11: PRDI25-29-Obj-36 | C11: Formar estudiantes de excelencia, a través de estudios profesionales pertinentes e inclusivos, con una vinculación permanente con estudiantes y personas egresadas, para su pleno desarrollo profesional y su contribución al bienestar social. | D11: PRDI25-29-Obj-81 | E11: Fortalecer la formación disciplinar e integral del estudiantado y su educación continua, en congruencia con el modelo educativo institucional, para fomentar su desarrollo humano completo y maximizar su potencial académico y profesional, así como su retribución social, en los diferentes sectores. | F11: 10 | G11: Implementar 1 programa de preparación para EGEL anualmente | H11: ACT-PRDI-NS-2781 | J11: Actividad | K11: Sin fórmula | L11: Implementar un programa de preparación para EGEL | M11: 0 | N11: 0 | P11: 0 | Q11: 0 | R11: =M11 -> 0 | S11: =N11 -> 0 | T11: =O11 -> 0 | U11: =P11 -> 0 | V11: =Q11 -> 0 | W11: Anual
A12: 7 | B12: PRDI25-29-Obj-36 | C12: Formar estudiantes de excelencia, a través de estudios profesionales pertinentes e inclusivos, con una vinculación permanente con estudiantes y personas egresadas, para su pleno desarrollo profesional y su contribución al bienestar social. | D12: PRDI25-29-Obj-81 | E12: Fortalecer la formación disciplinar e integral del estudiantado y su educación continua, en congruencia con el modelo educativo institucional, para fomentar su desarrollo humano completo y maximizar su potencial académico y profesional, así como su retribución social, en los diferentes sectores. | F12: 14 | G12: Lograr que 550 estudiantes de estudios profesionales participen en movilidad intrainstitucional durante la administración | H12: ACT-PRDI-NS-2785 | J12: Actividad | K12: Sin fórmula | L12: Lograr que estudiantes de estudios profesionales participen en movilidad intrainstitucional | R12: =M12 -> 0 | S12: =N12 -> 0 | T12: =O12 -> 0 | U12: =P12 -> 0 | V12: =Q12 -> 0 | W12: Anual
A13: 8 | B13: PRDI25-29-Obj-36 | C13: Formar estudiantes de excelencia, a través de estudios profesionales pertinentes e inclusivos, con una vinculación permanente con estudiantes y personas egresadas, para su pleno desarrollo profesional y su contribución al bienestar social. | D13: PRDI25-29-Obj-81 | E13: Fortalecer la formación disciplinar e integral del estudiantado y su educación continua, en congruencia con el modelo educativo institucional, para fomentar su desarrollo humano completo y maximizar su potencial académico y profesional, así como su retribución social, en los diferentes sectores. | F13: 15 | G13: Lograr anualmente que 100% de los estudiantes de estudios profesionales estén beneficiados con el nuevo Programa Institucional de Tutoría Académica | H13: IND-PRDI-353 | J13: Indicador | K13: (Número de estudiantes de estudios profesionales beneficiados con tutoría/ Total de estudiantes de estudios profesionales) * 100 | L13: Número de estudiantes de estudios profesionales beneficiados con tutoría | R13: =IF(M14,M13/M14*100,"0") -> 0 | S13: =IF(N14,N13/N14*100,"0") -> 0 | T13: =IF(O14,O13/O14*100,"0") -> 0 | U13: =IF(P14,P13/P14*100,"0") -> 0 | V13: =IF(Q14,Q13/Q14*100,"0") -> 0 | W13: Anual
L14: Total de estudiantes de estudios profesionales
A15: 9 | B15: PRDI25-29-Obj-36 | C15: Formar estudiantes de excelencia, a través de estudios profesionales pertinentes e inclusivos, con una vinculación permanente con estudiantes y personas egresadas, para su pleno desarrollo profesional y su contribución al bienestar social. | D15: PRDI25-29-Obj-81 | E15: Fortalecer la formación disciplinar e integral del estudiantado y su educación continua, en congruencia con el modelo educativo institucional, para fomentar su desarrollo humano completo y maximizar su potencial académico y profesional, así como su retribución social, en los diferentes sectores. | F15: 17 | G15: Lograr que 1 030 estudiantes de estudios profesionales participen en movilidad nacional e internacional durante la administración | H15: ACT-PRDI-NS-2789 | J15: Actividad | K15: Sin fórmula | L15: Lograr que estudiantes de estudios profesionales participen en movilidad nacional e internacional | R15: =M15 -> 0 | S15: =N15 -> 0 | T15: =O15 -> 0 | U15: =P15 -> 0 | V15: =Q15 -> 0 | W15: Anual
A16: 10 | B16: PRDI25-29-Obj-36 | C16: Formar estudiantes de excelencia, a través de estudios profesionales pertinentes e inclusivos, con una vinculación permanente con estudiantes y personas egresadas, para su pleno desarrollo profesional y su contribución al bienestar social. | D16: PRDI25-29-Obj-81 | E16: Fortalecer la formación disciplinar e integral del estudiantado y su educación continua, en congruencia con el modelo educativo institucional, para fomentar su desarrollo humano completo y maximizar su potencial académico y profesional, así como su retribución social, en los diferentes sectores. | F16: 19 | G16: Realizar anualmente en los 55 espacios académicos un proyecto colaborativo de beneficio social | H16: ACT-PRDI-NS-2729 | J16: Actividad | K16: Sin fórmula | L16: Realizar en los espacios académicos un proyecto colaborativo de beneficio social | R16: =M16 -> 0 | S16: =N16 -> 0 | T16: =O16 -> 0 | U16: =P16 -> 0 | V16: =Q16 -> 0 | W16: Anual
A17: 11 | B17: PRDI25-29-Obj-36 | C17: Formar estudiantes de excelencia, a través de estudios profesionales pertinentes e inclusivos, con una vinculación permanente con estudiantes y personas egresadas, para su pleno desarrollo profesional y su contribución al bienestar social. | D17: PRDI25-29-Obj-81 | E17: Fortalecer la formación disciplinar e integral del estudiantado y su educación continua, en congruencia con el modelo educativo institucional, para fomentar su desarrollo humano completo y maximizar su potencial académico y profesional, así como su retribución social, en los diferentes sectores. | F17: 21 | G17: Contar con 70 manuales de prácticas apegados a los indicadores del Sistema para Evaluar la Calidad de Medios Educativos anualmente | H17: ACT-PRDI-NS-2792 | J17: Actividad | K17: Sin fórmula | L17: Contar con manuales de prácticas apegados a los indicadores del Sistema para Evaluar la Calidad de Medios Educativos | R17: =M17 -> 0 | S17: =N17 -> 0 | T17: =O17 -> 0 | U17: =P17 -> 0 | V17: =Q17 -> 0 | W17: Anual
A18: 12 | B18: PRDI25-29-Obj-36 | C18: Formar estudiantes de excelencia, a través de estudios profesionales pertinentes e inclusivos, con una vinculación permanente con estudiantes y personas egresadas, para su pleno desarrollo profesional y su contribución al bienestar social. | D18: PRDI25-29-Obj-81 | E18: Fortalecer la formación disciplinar e integral del estudiantado y su educación continua, en congruencia con el modelo educativo institucional, para fomentar su desarrollo humano completo y maximizar su potencial académico y profesional, así como su retribución social, en los diferentes sectores. | F18: 29 | G18: Lograr que 80.03% de las GEI disponibles en SEDUCA sean utilizadas, para 2029 | H18: IND-PRDI-357 | J18: Indicador | K18: (Número de guías de estudio independiente utilizadas / Número total de guías de estudio independiente vigentes disponibles en SEDUCA) *100 | L18: Número de guías de estudio independiente utilizadas | R18: =IF(M19,M18/M19*100,"0") -> 0 | S18: =IF(N19,N18/N19*100,"0") -> 0 | T18: =IF(O19,O18/O19*100,"0") -> 0 | U18: =IF(P19,P18/P19*100,"0") -> 0 | V18: =IF(Q19,Q18/Q19*100,"0") -> 0 | W18: Anual
L19: Número total de guías de estudio independiente vigentes disponibles en SEDUCA
A20: 13 | B20: PRDI25-29-Obj-36 | C20: Formar estudiantes de excelencia, a través de estudios profesionales pertinentes e inclusivos, con una vinculación permanente con estudiantes y personas egresadas, para su pleno desarrollo profesional y su contribución al bienestar social. | D20: PRDI25-29-Obj-81 | E20: Fortalecer la formación disciplinar e integral del estudiantado y su educación continua, en congruencia con el modelo educativo institucional, para fomentar su desarrollo humano completo y maximizar su potencial académico y profesional, así como su retribución social, en los diferentes sectores. | F20: 30 | G20: Incrementar a 52 000 el número de estudiantes de estudios profesionales en la renovada plataforma seduca, para 2029 | H20: ACT-PRDI-NS-2728 | J20: Actividad | K20: Sin fórmula | L20: Incrementar el número de estudiantes de estudios profesionales en la renovada plataforma seduca | R20: =M20 -> 0 | S20: =N20 -> 0 | T20: =O20 -> 0 | U20: =P20 -> 0 | V20: =Q20 -> 0 | W20: Anual
A21: 14 | B21: PRDI25-29-Obj-36 | C21: Formar estudiantes de excelencia, a través de estudios profesionales pertinentes e inclusivos, con una vinculación permanente con estudiantes y personas egresadas, para su pleno desarrollo profesional y su contribución al bienestar social. | D21: PRDI25-29-Obj-81 | E21: Fortalecer la formación disciplinar e integral del estudiantado y su educación continua, en congruencia con el modelo educativo institucional, para fomentar su desarrollo humano completo y maximizar su potencial académico y profesional, así como su retribución social, en los diferentes sectores. | F21: 33 | G21: Desarrollar 470 actividades académicas de educación continua al año | H21: ACT-PRDI-NS-2805 | J21: Actividad | K21: Sin fórmula | L21: Desarrollar actividades académicas de educación continua | R21: =M21 -> 0 | S21: =N21 -> 0 | T21: =O21 -> 0 | U21: =P21 -> 0 | V21: =Q21 -> 0 | W21: Anual
A22: 16 | B22: PRDI25-29-Obj-36 | C22: Formar estudiantes de excelencia, a través de estudios profesionales pertinentes e inclusivos, con una vinculación permanente con estudiantes y personas egresadas, para su pleno desarrollo profesional y su contribución al bienestar social. | D22: PRDI25-29-Obj-81 | E22: Fortalecer la formación disciplinar e integral del estudiantado y su educación continua, en congruencia con el modelo educativo institucional, para fomentar su desarrollo humano completo y maximizar su potencial académico y profesional, así como su retribución social, en los diferentes sectores. | F22: 37 | G22: Certificar en una segunda lengua a 720 estudiantes de estudios profesionales anualmente | H22: ACT-PRDI-NS-2205 | J22: Actividad | K22: Sin fórmula | L22: Certificar internacionalmente en una segunda lengua a estudiantes de estudios profesionales | R22: =M22 -> 0 | S22: =N22 -> 0 | T22: =O22 -> 0 | U22: =P22 -> 0 | V22: =Q22 -> 0 | W22: Anual
A23: 17 | B23: PRDI25-29-Obj-36 | C23: Formar estudiantes de excelencia, a través de estudios profesionales pertinentes e inclusivos, con una vinculación permanente con estudiantes y personas egresadas, para su pleno desarrollo profesional y su contribución al bienestar social. | D23: PRDI25-29-Obj-82 | E23: Contribuir al acceso, permanencia y egreso del alumnado de estudios profesionales para su formación integral y la conclusión de sus estudios profesionales. | F23: 42 | G23: Incrementar la matrícula a 78 002 estudiantes de estudios profesionales en sus diversas modalidades para 2029 | H23: ACT-PRDI-NS-1764 | J23: Actividad | K23: Sin fórmula | L23: Atender la matrícula de Estudios Profesionales en sus diversas modalidades | M23: =M14 -> 0 | N23: =N14 -> 0 | O23: =O14 -> 0 | P23: =P14 -> 0 | Q23: =Q14 -> 0 | R23: =M23 -> 0 | S23: =N23 -> 0 | T23: =O23 -> 0 | U23: =P23 -> 0 | V23: =Q23 -> 0 | W23: Anual
A24: 18 | B24: PRDI25-29-Obj-36 | C24: Formar estudiantes de excelencia, a través de estudios profesionales pertinentes e inclusivos, con una vinculación permanente con estudiantes y personas egresadas, para su pleno desarrollo profesional y su contribución al bienestar social. | D24: PRDI25-29-Obj-82 | E24: Contribuir al acceso, permanencia y egreso del alumnado de estudios profesionales para su formación integral y la conclusión de sus estudios profesionales. | F24: 43 | G24: Contar con una titulación por cohorte a 2029 de 30.5% | H24: IND-PRDI-40 | J24: Indicador | K24: (Titulados al primer año de egreso/Nuevo ingreso n-5 )*100 | L24: Titulados al primer año de egreso | R24: =IF(M25,M24/M25*100,"0") -> 0 | S24: =IF(N25,N24/N25*100,"0") -> 0 | T24: =IF(O25,O24/O25*100,"0") -> 0 | U24: =IF(P25,P24/P25*100,"0") -> 0 | V24: =IF(Q25,Q24/Q25*100,"0") -> 0 | W24: Anual
L25: Nuevo ingreso n-5
A26: 19 | B26: PRDI25-29-Obj-36 | C26: Formar estudiantes de excelencia, a través de estudios profesionales pertinentes e inclusivos, con una vinculación permanente con estudiantes y personas egresadas, para su pleno desarrollo profesional y su contribución al bienestar social. | D26: PRDI25-29-Obj-82 | E26: Contribuir al acceso, permanencia y egreso del alumnado de estudios profesionales para su formación integral y la conclusión de sus estudios profesionales. | F26: 44 | G26: Implementar semestralmente 1 programa de fomento a la titulación | H26: ACT-PRDI-NS-2814 | J26: Actividad | K26: Sin fórmula | L26: Implementar un programa de fomento a la titulación | R26: =M26 -> 0 | S26: =N26 -> 0 | T26: =O26 -> 0 | U26: =P26 -> 0 | V26: =Q26 -> 0 | W26: Anual
A27: 20 | B27: PRDI25-29-Obj-36 | C27: Formar estudiantes de excelencia, a través de estudios profesionales pertinentes e inclusivos, con una vinculación permanente con estudiantes y personas egresadas, para su pleno desarrollo profesional y su contribución al bienestar social. | D27: PRDI25-29-Obj-82 | E27: Contribuir al acceso, permanencia y egreso del alumnado de estudios profesionales para su formación integral y la conclusión de sus estudios profesionales. | F27: 45 | G27: Lograr la eficiencia terminal por cohorte en estudios Profesionales de 53.59% en 2029 | H27: IND-NS-127 | J27: Indicador | K27: (La suma acumulada del número de egresados de la cohorte de estudios profesionales en cada uno de los años que dura la cohorte/Número total de alumnos de ingreso a primer año de la cohorte)*100 | L27: La suma acumulada del número de egresados de la cohorte de estudios profesionales en cada uno de los años que dura la cohorte | R27: =IF(M28,M27/M28*100,"0") -> 0 | S27: =IF(N28,N27/N28*100,"0") -> 0 | T27: =IF(O28,O27/O28*100,"0") -> 0 | U27: =IF(P28,P27/P28*100,"0") -> 0 | V27: =IF(Q28,Q27/Q28*100,"0") -> 0 | W27: Anual
L28: Número total de alumnos de ingreso a primer año de la cohorte
A29: 21 | B29: PRDI25-29-Obj-36 | C29: Formar estudiantes de excelencia, a través de estudios profesionales pertinentes e inclusivos, con una vinculación permanente con estudiantes y personas egresadas, para su pleno desarrollo profesional y su contribución al bienestar social. | D29: PRDI25-29-Obj-82 | E29: Contribuir al acceso, permanencia y egreso del alumnado de estudios profesionales para su formación integral y la conclusión de sus estudios profesionales. | F29: 46 | G29: Disminuir a 7.80% el abandono escolar de estudios profesionales al término de la administración | H29: IND-PRDI-34 | J29: Indicador | K29: (1-((Matrícula total n mas 1-Nuevo ingreso 1o n mas 1+Egresados n)/(Matrícula total n)))*100 | L29: Matrícula total n mas 1 | M29: =M14 -> 0 | N29: =N14 -> 0 | O29: =O14 -> 0 | P29: =P14 -> 0 | R29: =IF(M32,(1-((M29-M30+M31)/(M32)))*100,"0") -> 0 | S29: =IF(N32,(1-((N29-N30+N31)/(N32)))*100,"0") -> 0 | T29: =IF(O32,(1-((O29-O30+O31)/(O32)))*100,"0") -> 0 | U29: =IF(P32,(1-((P29-P30+P31)/(P32)))*100,"0") -> 0 | V29: =IF(Q32,(1-((Q29-Q30+Q31)/(Q32)))*100,"0") -> 0 | W29: Anual
L30: Nuevo ingreso 1o n mas 1
L31: Egresados n
L32: Matrícula total n | N32: =M29 -> 0 | O32: =N29 -> 0 | P32: =O29 -> 0
A33: 22 | B33: PRDI25-29-Obj-36 | C33: Formar estudiantes de excelencia, a través de estudios profesionales pertinentes e inclusivos, con una vinculación permanente con estudiantes y personas egresadas, para su pleno desarrollo profesional y su contribución al bienestar social. | D33: PRDI25-29-Obj-82 | E33: Contribuir al acceso, permanencia y egreso del alumnado de estudios profesionales para su formación integral y la conclusión de sus estudios profesionales. | F33: 53 | G33: Otorgar anualmente 38 000 becas, apoyos o estímulos institucionales a estudiantes de Estudios Profesionales | H33: ACT-PRDI-NS-2297 | J33: Actividad | K33: Sin fórmula | L33: Otorgar becas, apoyos o estímulos a alumnos de estudios profesionales para la permanencia y conclusión de estudios | R33: =M33 -> 0 | S33: =N33 -> 0 | T33: =O33 -> 0 | U33: =P33 -> 0 | V33: =Q33 -> 0 | W33: Anual
A34: 23 | B34: PRDI25-29-Obj-36 | C34: Formar estudiantes de excelencia, a través de estudios profesionales pertinentes e inclusivos, con una vinculación permanente con estudiantes y personas egresadas, para su pleno desarrollo profesional y su contribución al bienestar social. | D34: PRDI25-29-Obj-82 | E34: Contribuir al acceso, permanencia y egreso del alumnado de estudios profesionales para su formación integral y la conclusión de sus estudios profesionales. | F34: 55 | G34: Lograr que 98% del total de estudiantes activos de Estudios Profesionales cuenten con servicios de salud a 2029 | H34: IND-PRDI-366 | J34: Indicador | K34: (Alumnos afiliados al Seguro Facultativo de Estudios Profesionales / Matrícula activa de Estudios Profesionales)*100 | L34: Alumnos afiliados al Seguro Facultativo de Estudios Profesionales | R34: =IF(M35,M34/M35*100,"0") -> 0 | S34: =IF(N35,N34/N35*100,"0") -> 0 | T34: =IF(O35,O34/O35*100,"0") -> 0 | U34: =IF(P35,P34/P35*100,"0") -> 0 | V34: =IF(Q35,Q34/Q35*100,"0") -> 0 | W34: Anual
L35: Matrícula activa de Estudios Profesionales | M35: =M14 -> 0 | N35: =N14 -> 0 | O35: =O14 -> 0 | P35: =P14 -> 0 | Q35: =Q14 -> 0
A36: 24 | B36: PRDI25-29-Obj-36 | C36: Formar estudiantes de excelencia, a través de estudios profesionales pertinentes e inclusivos, con una vinculación permanente con estudiantes y personas egresadas, para su pleno desarrollo profesional y su contribución al bienestar social. | D36: PRDI25-29-Obj-82 | E36: Contribuir al acceso, permanencia y egreso del alumnado de estudios profesionales para su formación integral y la conclusión de sus estudios profesionales. | F36: 57 | G36: Lograr la participación de 32 300 estudiantes y personas egresadas en los sectores gubernamental, productivo y social, mediante las prácticas o estancias profesionales, al cierre de la administración | H36: ACT-PRDI-NS-2285 | J36: Actividad | K36: Sin fórmula | L36: Lograr la participación de alumnos en los sectores gubernamental, productivo y social mediante las prácticas o estancias profesionales | R36: =M36 -> 0 | S36: =N36 -> 0 | T36: =O36 -> 0 | U36: =P36 -> 0 | V36: =Q36 -> 0 | W36: Anual
A37: 25 | B37: PRDI25-29-Obj-36 | C37: Formar estudiantes de excelencia, a través de estudios profesionales pertinentes e inclusivos, con una vinculación permanente con estudiantes y personas egresadas, para su pleno desarrollo profesional y su contribución al bienestar social. | D37: PRDI25-29-Obj-82 | E37: Contribuir al acceso, permanencia y egreso del alumnado de estudios profesionales para su formación integral y la conclusión de sus estudios profesionales. | F37: 58 | G37: Lograr la participación de 500 estudiantes de estudios profesionales en cursos, talleres o actividades de capacitación de empleabilidad, realizadas en conjunto con instituciones externas, anualmente | H37: ACT-PRDI-NS-2826 | J37: Actividad | K37: Sin fórmula | L37: Lograr la participación de estudiantes de estudios profesionales en cursos, talleres o actividades de capacitación de empleabilidad, realizadas en conjunto con instituciones externas | R37: =M37 -> 0 | S37: =N37 -> 0 | T37: =O37 -> 0 | U37: =P37 -> 0 | V37: =Q37 -> 0 | W37: Anual
A38: 26 | B38: PRDI25-29-Obj-36 | C38: Formar estudiantes de excelencia, a través de estudios profesionales pertinentes e inclusivos, con una vinculación permanente con estudiantes y personas egresadas, para su pleno desarrollo profesional y su contribución al bienestar social. | D38: PRDI25-29-Obj-82 | E38: Contribuir al acceso, permanencia y egreso del alumnado de estudios profesionales para su formación integral y la conclusión de sus estudios profesionales. | F38: 61 | G38: Realizar 10 eventos de promoción y difusión en apoyo al desarrollo profesional para el empleo y la inserción laboral, durante la administración | H38: ACT-PRDI-NS-2825 | J38: Actividad | K38: Sin fórmula | L38: Realizar eventos de promoción y difusión en apoyo al desarrollo profesional para el empleo y la inserción laboral | R38: =M38 -> 0 | S38: =N38 -> 0 | T38: =O38 -> 0 | U38: =P38 -> 0 | V38: =Q38 -> 0 | W38: Anual
A39: 27 | B39: PRDI25-29-Obj-36 | C39: Formar estudiantes de excelencia, a través de estudios profesionales pertinentes e inclusivos, con una vinculación permanente con estudiantes y personas egresadas, para su pleno desarrollo profesional y su contribución al bienestar social. | D39: PRDI25-29-Obj-83 | E39: Fortalecer la vinculación, acompañamiento y seguimiento de egresados de estudios profesionales, para favorecer las prácticas profesionales, empleabilidad y colaboración con el sector productivo, con un sentido de identidad. | F39: 64 | G39: Realizar 40 intervenciones de impacto anuales en espacios académicos para fortalecer la vinculación colaborativa entre egresados y estudiantes | H39: ACT-PRDI-NS-2753 | J39: Actividad | K39: Sin fórmula | L39: Realizar intervenciones de impacto en espacios académicos para fortalecer la vinculación colaborativa entre egresados y estudiantes | R39: =M39 -> 0 | S39: =N39 -> 0 | T39: =O39 -> 0 | U39: =P39 -> 0 | V39: =Q39 -> 0 | W39: Anual

Sheet Hoja1
A1: Proyecto | B1: Actividades | C1: Indicadores | D1: Total
A2: 2 EstudiantadoEstProf | B2: 18 | C2: 9 | D2: =B2+C2 -> 27
A3: 3 Est avanzados excelencia | B3: 6 | C3: 1 | D3: =B3+C3 -> 7
A4: 4 Investigación abierta | B4: 3 | C4: 5 | D4: =B4+C4 -> 8
A5: 5 Innovación, desarrollo tec | B5: 2 | C5: 0 | D5: =B5+C5 -> 2
A6: 6 Dif y divulga de la ciencia | B6: 4 | C6: 0 | D6: =B6+C6 -> 4
A7: 7 Cultura desarrollo integral | B7: 6 | C7: 0 | D7: =B7+C7 -> 6
A8: 8 Deporte universitario | B8: 2 | C8: 3 | D8: =B8+C8 -> 5
A9: 9 Fortalecimiento docente | B9: 4 | C9: 6 | D9: =B9+C9 -> 10
A10: 10 Dignificación las y los trab | B10: 0 | C10: 3 | D10: =B10+C10 -> 3
A11: 11 Gestión administrativa | B11: 2 | C11: 0 | D11: =B11+C11 -> 2
A12: 12 Fortalecimiento tecnológico | B12: 2 | C12: 0 | D12: =B12+C12 -> 2
A13: 13 Gobernanza | B13: 8 | C13: 0 | D13: =B13+C13 -> 8
... A19: 22 Sostenibilidad ambiental | B19: 12 | C19: 0 | D19: =B19+C19 -> 12
B20: =SUM(B2:B19) -> 91 | C20: =SUM(C2:C19) -> 32 | D20: =SUM(D2:D19) -> 123

Sheet 3 Est avanzados excelencia
A1: N.P. | B1: Clave Objetivo General | C1: Objetivo General | D1: Clave Objetivo Específico | E1: Objetivo Específico | F1: No. de meta en el PRDI | G1: Meta PRDI | H1: Clave de la meta | I1: Meta del espacio académico | J1: Actividad/Indicador | K1: Método de cálculo | L1: Nombre de las variables | M1: Valor de las variables | R1: Valor de los indicadores | W1: Medición (anual o acumulada) | X1: Área responsable
M2: Ref. 2026 | N2: 2027 | O2: 2028 | P2: 2029 | Q2: 2030 | R2: Ref. 2026 | S2: 2027 | T2: 2028 | U2: 2029 | V2: 2030
A3: 1 | B3: PRDI25-29-Obj-37 | C3: Garantizar una formación en estudios avanzados de excelencia y pertinencia social, a través del desarrollo de programas innovadores con la integración de la investigación de la Agenda Estratégica de Investigación, para asegurar que el conocimiento generado impulse la transformación social. | D3: PRDI2025-2029-Obj-59 | E3: Incrementar la matrícula de estudios avanzados con enfoque de equidad e inclusión regional para diversificar el acceso a la formación de alto nivel. | F3: 6 | G3: Contar con 233 estudiantes de estudios avanzados participantes en estancias cortas o movilidad académica, a 2029 | H3: ACT-PRDI-NS-2838 | J3: Actividad | K3: Sin fórmula | L3: Contar con estudiantes de estudios avanzados participantes en estancias cortas o movilidad académica | R3: =M3 -> 0 | S3: =N3 -> 0 | T3: =O3 -> 0 | U3: =P3 -> 0 | V3: =Q3 -> 0 | W3: Anual
A4: 2 | B4: PRDI25-29-Obj-37 | C4: Garantizar una formación en estudios avanzados de excelencia y pertinencia social, a través del desarrollo de programas innovadores con la integración de la investigación de la Agenda Estratégica de Investigación, para asegurar que el conocimiento generado impulse la transformación social. | D4: PRDI2025-2029-Obj-59 | E4: Incrementar la matrícula de estudios avanzados con enfoque de equidad e inclusión regional para diversificar el acceso a la formación de alto nivel. | F4: 16 | G4: Contar 4 350 alumnos en estudios avanzados, a 2029 | H4: ACT-PRDI-NS-2685 | J4: Actividad | K4: Sin fórmula | L4: Atender la matrícula de estudios avanzados para la generación y aplicación del conocimiento | R4: =M4 -> 0 | S4: =N4 -> 0 | T4: =O4 -> 0 | U4: =P4 -> 0 | V4: =Q4 -> 0 | W4: Anual
A5: 3 | B5: PRDI25-29-Obj-37 | C5: Garantizar una formación en estudios avanzados de excelencia y pertinencia social, a través del desarrollo de programas innovadores con la integración de la investigación de la Agenda Estratégica de Investigación, para asegurar que el conocimiento generado impulse la transformación social. | D5: PRDI25-29-Obj-84 | E5: Consolidar una oferta educativa de estudios avanzados de excelencia, para garantizar la inclusión, la pertinencia social y la alineación con las demandas de los sectores productivo, gubernamental y social. | F5: 12 | G5: Ofertar 1 nuevo programa de estudios avanzados o diplomado superior en los CU y UAP vinculado con entidades de gobierno o industria, anualmente | H5: ACT-PRDI-NS-2844 | J5: Actividad | K5: Sin fórmula | L5: Ofertar nuevos programas de estudios avanzados o diplomado superior en los CU y UAP vinculado con entidades de gobierno o industria | R5: =M5 -> 0 | S5: =N5 -> 0 | T5: =O5 -> 0 | U5: =P5 -> 0 | V5: =Q5 -> 0 | W5: Anual
A6: 4 | B6: PRDI25-29-Obj-37 | C6: Garantizar una formación en estudios avanzados de excelencia y pertinencia social, a través del desarrollo de programas innovadores con la integración de la investigación de la Agenda Estratégica de Investigación, para asegurar que el conocimiento generado impulse la transformación social. | D6: PRDI25-29-Obj-84 | E6: Consolidar una oferta educativa de estudios avanzados de excelencia, para garantizar la inclusión, la pertinencia social y la alineación con las demandas de los sectores productivo, gubernamental y social. | F6: 15 | G6: Registrar 50 protocolos de investigación de alumnos de estudios avanzados con temáticas vinculadas a la Agenda Estratégica de Investigación, anualmente | H6: ACT-PRDI-NS-2847 | J6: Actividad | K6: Sin fórmula | L6: Registrar protocolos de investigación de alumnos de estudios avanzados con temáticas vinculadas a la Agenda Estratégica de Investigación | R6: =M6 -> 0 | S6: =N6 -> 0 | T6: =O6 -> 0 | U6: =P6 -> 0 | V6: =Q6 -> 0 | W6: Anual
A7: 5 | B7: PRDI25-29-Obj-37 | C7: Garantizar una formación en estudios avanzados de excelencia y pertinencia social, a través del desarrollo de programas innovadores con la integración de la investigación de la Agenda Estratégica de Investigación, para asegurar que el conocimiento generado impulse la transformación social. | D7: PRDI25-29-Obj-84 | E7: Consolidar una oferta educativa de estudios avanzados de excelencia, para garantizar la inclusión, la pertinencia social y la alineación con las demandas de los sectores productivo, gubernamental y social. | F7: 18 | G7: Generar protocolos de acción para incrementar la tasa de graduación y la eficiencia terminal en 10 espacios académicos, en 2026 | H7: ACT-PRDI-NS-2848 | J7: Actividad | K7: Sin fórmula | L7: Generar protocolos de acción para incrementar la tasa de graduación y la eficiencia terminal en espacios académicos | R7: =M7 -> 0 | S7: =N7 -> 0 | T7: =O7 -> 0 | U7: =P7 -> 0 | V7: =Q7 -> 0 | W7: Anual
A8: 6 | B8: PRDI25-29-Obj-37 | C8: Garantizar una formación en estudios avanzados de excelencia y pertinencia social, a través del desarrollo de programas innovadores con la integración de la investigación de la Agenda Estratégica de Investigación, para asegurar que el conocimiento generado impulse la transformación social. | D8: PRDI25-29-Obj-84 | E8: Consolidar una oferta educativa de estudios avanzados de excelencia, para garantizar la inclusión, la pertinencia social y la alineación con las demandas de los sectores productivo, gubernamental y social. | F8: 19 | G8: Incrementar a 1190 graduados de estudios avanzados, a 2029 | H8: ACT-PRDI-NS-2849 | J8: Actividad | K8: Sin fórmula | L8: Incrementar graduados de estudios avanzados | R8: =M8 -> 0 | S8: =N8 -> 0 | T8: =O8 -> 0 | U8: =P8 -> 0 | V8: =Q8 -> 0 | W8: Anual
A9: 7 | B9: PRDI25-29-Obj-37 | C9: Garantizar una formación en estudios avanzados de excelencia y pertinencia social, a través del desarrollo de programas innovadores con la integración de la investigación de la Agenda Estratégica de Investigación, para asegurar que el conocimiento generado impulse la transformación social. | D9: PRDI25-29-Obj-84 | E9: Consolidar una oferta educativa de estudios avanzados de excelencia, para garantizar la inclusión, la pertinencia social y la alineación con las demandas de los sectores productivo, gubernamental y social. | F9: 20 | G9: Incrementar a 17.56% la graduación de estudios avanzados por la opción de trabajo terminal de grado, a 2029 | H9: IND-PRDI-365 | J9: Indicador | K9: (Número de alumnos graduados por la opción de trabajo terminal de grado en el año que se reporta/Total de alumnos graduados en el año que se reporta)*100 | L9: Número de alumnos graduados por la opción de trabajo terminal de grado en el año que se reporta | R9: =IF(M10,M9/M10*100,"0") -> 0 | S9: =IF(N10,N9/N10*100,"0") -> 0 | T9: =IF(O10,O9/O10*100,"0") -> 0 | U9: =IF(P10,P9/P10*100,"0") -> 0 | V9: =IF(Q10,Q9/Q10*100,"0") -> 0 | W9: Anual
L10: Total de alumnos graduados en el año que se reporta)*100

Sheet 4 Investigación abierta
A1: N.P. | B1: Clave Objetivo General | C1: Objetivo General | D1: Clave Objetivo Específico | E1: Objetivo Específico | F1: No. de meta en el PRDI | G1: Meta PRDI | H1: Clave de la meta | I1: Meta del espacio académico | J1: Actividad/Indicador | K1: Método de cálculo | L1: Nombre de las variables | M1: Valor de las variables | R1: Valor de los indicadores | W1: Medición (anual o acumulada) | X1: Área responsable
M2: Ref. 2026 | N2: 2027 | O2: 2028 | P2: 2029 | Q2: 2030 | R2: Ref. 2026 | S2: 2027 | T2: 2028 | U2: 2029 | V2: 2030
A3: 1 | B3: PRDI25-29-Obj-38 | C3: Impulsar la investigación científica, humanística, tecnológica y de innovación priorizando la calidad, inclusión, equidad, retribución social y multilingüismo, a través del apoyo a proyectos sólidos, el fortalecimiento de redes en la comunidad investigadora y la optimización de recursos e infraestructura, en el marco del nuevo Modelo de Ciencia Abierta para la Transformación Social | D3: PRDI2025-2029-Obj-60 | E3: Fomentar la investigación abierta, equitativa y de calidad, así como transparentar su dimensión de retribución social, incentivar el diálogo de saberes y la participación activa de la comunidad universitaria de forma incluyente. | F3: 19 | G3: Contar con 200 CA de calidad, a 2028 | H3: ACT-PRDI-NS-2870 | I3: Mantener al menos 3 cuerpos académicos de calidad en cada medición anual de 2027 a 2030. | J3: Actividad | K3: Sin fórmula | L3: Contar con Cuerpos Académicos de calidad | M3: 3 | N3: 3 | O3: 3 | P3: 3 | Q3: 3 | R3: =IF(M3="","",M3) -> 3 | S3: =IF(N3="","",N3) -> 3 | T3: =IF(O3="","",O3) -> 3 | U3: =IF(P3="","",P3) -> 3 | V3: =IF(Q3="","",Q3) -> 3 | W3: Anual | X3: Por validar con el área responsable
A4: 2 | B4: PRDI25-29-Obj-38 | C4: Impulsar la investigación científica, humanística, tecnológica y de innovación priorizando la calidad, inclusión, equidad, retribución social y multilingüismo, a través del apoyo a proyectos sólidos, el fortalecimiento de redes en la comunidad investigadora y la optimización de recursos e infraestructura, en el marco del nuevo Modelo de Ciencia Abierta para la Transformación Social | D4: PRDI2025-2029-Obj-60 | E4: Fomentar la investigación abierta, equitativa y de calidad, así como transparentar su dimensión de retribución social, incentivar el diálogo de saberes y la participación activa de la comunidad universitaria de forma incluyente. | F4: 20 | G4: Mantener 98.68% de los CA que realizan investigación que contribuye a la solución de problemas sociales, a 2029 | H4: IND-PRDI-221 | J4: Indicador | K4: (Número de cuerpos académicos registrados en SEP que realizan investigación que contribuyen a la solución de problemas sociales/Total de cuerpos académicos registrados en SEP)*100 | L4: Número de cuerpos académicos registrados en SEP que realizan investigación que contribuyen a la solución de problemas sociales | R4: =IF(M5,M4/M5*100,"0") -> 0 | S4: =IF(N5,N4/N5*100,"0") -> 0 | T4: =IF(O5,O4/O5*100,"0") -> 0 | U4: =IF(P5,P4/P5*100,"0") -> 0 | V4: =IF(Q5,Q4/Q5*100,"0") -> 0 | W4: Anual
L5: Total de cuerpos académicos registrados en SEP
A6: 3 | B6: PRDI25-29-Obj-38 | C6: Impulsar la investigación científica, humanística, tecnológica y de innovación priorizando la calidad, inclusión, equidad, retribución social y multilingüismo, a través del apoyo a proyectos sólidos, el fortalecimiento de redes en la comunidad investigadora y la optimización de recursos e infraestructura, en el marco del nuevo Modelo de Ciencia Abierta para la Transformación Social | D6: PRDI2025-2029-Obj-60 | E6: Fomentar la investigación abierta, equitativa y de calidad, así como transparentar su dimensión de retribución social, incentivar el diálogo de saberes y la participación activa de la comunidad universitaria de forma incluyente. | F6: 21 | G6: Mantener el 49.59% de los PTC con participación en redes con pares extranjeros, anualmente | H6: IND-PRDI-368 | J6: Indicador | K6: (Número de Profesores de Tiempo Completo con participación en redes con pares extranjeros/Total de Profesores de Tiempo Completo)*100 | L6: Número de Profesores de Tiempo Completo con participación en redes con pares extranjeros | R6: =IF(M7,M6/M7*100,"0") -> 0 | S6: =IF(N7,N6/N7*100,"0") -> 0 | T6: =IF(O7,O6/O7*100,"0") -> 0 | U6: =IF(P7,P6/P7*100,"0") -> 0 | V6: =IF(Q7,Q6/Q7*100,"0") -> 0 | W6: Anual
L7: Total de Profesores de Tiempo Completo
A8: 4 | B8: PRDI25-29-Obj-38 | C8: Impulsar la investigación científica, humanística, tecnológica y de innovación priorizando la calidad, inclusión, equidad, retribución social y multilingüismo, a través del apoyo a proyectos sólidos, el fortalecimiento de redes en la comunidad investigadora y la optimización de recursos e infraestructura, en el marco del nuevo Modelo de Ciencia Abierta para la Transformación Social | D8: PRDI2025-2029-Obj-60 | E8: Fomentar la investigación abierta, equitativa y de calidad, así como transparentar su dimensión de retribución social, incentivar el diálogo de saberes y la participación activa de la comunidad universitaria de forma incluyente. | F8: 22 | G8: Mantener 49.81% de los PTC que participan en redes nacionales, anualmente | H8: IND-PRDI-370 | J8: Indicador | K8: (Número de Profesores de Tiempo Completo con participación en redes nacionales/Total de Profesores de Tiempo Completo)*100 | L8: Número de Profesores de Tiempo Completo con participación en redes nacionales | R8: =IF(M9,M8/M9*100,"0") -> 0 | S8: =IF(N9,N8/N9*100,"0") -> 0 | T8: =IF(O9,O8/O9*100,"0") -> 0 | U8: =IF(P9,P8/P9*100,"0") -> 0 | V8: =IF(Q9,Q8/Q9*100,"0") -> 0 | W8: Anual
L9: Total de Profesores de Tiempo Completo | M9: =M7 -> 0 | N9: =N7 -> 0 | O9: =O7 -> 0 | P9: =P7 -> 0 | Q9: =Q7 -> 0
A10: 5 | B10: PRDI25-29-Obj-38 | C10: Impulsar la investigación científica, humanística, tecnológica y de innovación priorizando la calidad, inclusión, equidad, retribución social y multilingüismo, a través del apoyo a proyectos sólidos, el fortalecimiento de redes en la comunidad investigadora y la optimización de recursos e infraestructura, en el marco del nuevo Modelo de Ciencia Abierta para la Transformación Social | D10: PRDI25-29-Obj-85 | E10: Optimizar el proceso de asignación y gestión de recursos financieros para consolidar la investigación con proyectos que respondan a los principios de calidad, equidad, inclusión, retribución social y multilingüismo. | F10: 3 | G10: Atender las necesidades prioritarias de mantenimiento, equipamiento y medidas de seguridad de 115 laboratorios de investigación, a 2029 | H10: ACT-PRDI-NS-2854 | J10: Actividad | K10: Sin fórmula | L10: Atender las necesidades prioritarias de mantenimiento, equipamiento y medidas de seguridad de laboratorios de investigación | R10: =M10 -> 0 | S10: =N10 -> 0 | T10: =O10 -> 0 | U10: =P10 -> 0 | V10: =Q10 -> 0 | W10: Anual
A11: 6 | B11: PRDI25-29-Obj-38 | C11: Impulsar la investigación científica, humanística, tecnológica y de innovación priorizando la calidad, inclusión, equidad, retribución social y multilingüismo, a través del apoyo a proyectos sólidos, el fortalecimiento de redes en la comunidad investigadora y la optimización de recursos e infraestructura, en el marco del nuevo Modelo de Ciencia Abierta para la Transformación Social | D11: PRDI25-29-Obj-85 | E11: Optimizar el proceso de asignación y gestión de recursos financieros para consolidar la investigación con proyectos que respondan a los principios de calidad, equidad, inclusión, retribución social y multilingüismo. | F11: 7 | G11: Promover la participación en 2 convocatorias externas de proyectos de investigación, anualmente | H11: ACT-PRDI-NS-2858 | J11: Actividad | K11: Sin fórmula | L11: Promover la participación en convocatorias externas de proyectos de investigación | R11: =M11 -> 0 | S11: =N11 -> 0 | T11: =O11 -> 0 | U11: =P11 -> 0 | V11: =Q11 -> 0 | W11: Anual
A12: 7 | B12: PRDI25-29-Obj-38 | C12: Impulsar la investigación científica, humanística, tecnológica y de innovación priorizando la calidad, inclusión, equidad, retribución social y multilingüismo, a través del apoyo a proyectos sólidos, el fortalecimiento de redes en la comunidad investigadora y la optimización de recursos e infraestructura, en el marco del nuevo Modelo de Ciencia Abierta para la Transformación Social | D12: PRDI25-29-Obj-85 | E12: Optimizar el proceso de asignación y gestión de recursos financieros para consolidar la investigación con proyectos que respondan a los principios de calidad, equidad, inclusión, retribución social y multilingüismo. | F12: 17 | G12: Contar con 19.51% de los proyectos de investigación en DT e innovación que cuenten con un plan de transferencia, innovación o impacto social documentado, a 2029 | H12: IND-PRDI-367 | J12: Indicador | K12: (Número de proyectos de investigación en DT e Innovación que cuentan con plan de transferencia, innovación impacto social documentado/Total de proyectos de investigación en DT e Innovación)*100 | L12: Número de proyectos de investigación en DT e Innovación que cuentan con plan de transferencia, innovación impacto social documentado | R12: =IF(M13,M12/M13*100,"0") -> 0 | S12: =IF(N13,N12/N13*100,"0") -> 0 | T12: =IF(O13,O12/O13*100,"0") -> 0 | U12: =IF(P13,P12/P13*100,"0") -> 0 | V12: =IF(Q13,Q12/Q13*100,"0") -> 0 | W12: Anual
L13: Total de proyectos de investigación en DT e Innovación
A14: 8 | B14: PRDI25-29-Obj-38 | C14: Impulsar la investigación científica, humanística, tecnológica y de innovación priorizando la calidad, inclusión, equidad, retribución social y multilingüismo, a través del apoyo a proyectos sólidos, el fortalecimiento de redes en la comunidad investigadora y la optimización de recursos e infraestructura, en el marco del nuevo Modelo de Ciencia Abierta para la Transformación Social | D14: PRDI25-29-Obj-85 | E14: Optimizar el proceso de asignación y gestión de recursos financieros para consolidar la investigación con proyectos que respondan a los principios de calidad, equidad, inclusión, retribución social y multilingüismo. | F14: 18 | G14: Contar con 53.22% de producción científica con sentido social, anualmente | H14: IND-PRDI-225 | J14: Indicador | K14: (Número de producción científica con sentido social/Total de la producción científica reportada)*100 | L14: Número de producción científica con sentido social | R14: =IF(M15,M14/M15*100,"0") -> 0 | S14: =IF(N15,N14/N15*100,"0") -> 0 | T14: =IF(O15,O14/O15*100,"0") -> 0 | U14: =IF(P15,P14/P15*100,"0") -> 0 | V14: =IF(Q15,Q14/Q15*100,"0") -> 0 | W14: Anual
L15: Total de la producción científica reportada

Sheet 5 Innovación, desarrollo tec
A1: N.P. | B1: Clave Objetivo General | C1: Objetivo General | D1: Clave Objetivo Específico | E1: Objetivo Específico | F1: No. de meta en el PRDI | G1: Meta PRDI | H1: Clave de la meta | I1: Meta del espacio académico | J1: Actividad/Indicador | K1: Método de cálculo | L1: Nombre de las variables | M1: Valor de las variables | R1: Valor de los indicadores | W1: Medición (anual o acumulada) | X1: Área responsable
M2: Ref. 2026 | N2: 2027 | O2: 2028 | P2: 2029 | Q2: 2030 | R2: Ref. 2026 | S2: 2027 | T2: 2028 | U2: 2029 | V2: 2030
A3: 1 | B3: PRDI25-29-Obj-39 | C3: Impulsar la innovación y el desarrollo tecnológico de manera sostenible y equitativa, a través de la articulación de plataformas multiactor, la gestión de la propiedad intelectual y transferencia tecnológica, en el marco de proyectos Penta-Hélice. | D3: PRDI25-29-Obj-86 | E3: Fortalecer la gestión institucional de la propiedad intelectual y transferencia tecnológica a través de mecanismos equitativos, sostenibles y con retribución social. | F3: 1 | G3: Contar con 222 expedientes, registros y patentes ante el IMPI, a 2029 | H3: ACT-PRDI-NS-2875 | J3: Actividad | K3: Sin fórmula | L3: Contar con expedientes, registros y patentes ante el IMPI | R3: =M3 -> 0 | S3: =N3 -> 0 | T3: =O3 -> 0 | U3: =P3 -> 0 | V3: =Q3 -> 0 | W3: Anual
A4: 2 | B4: PRDI25-29-Obj-39 | C4: Impulsar la innovación y el desarrollo tecnológico de manera sostenible y equitativa, a través de la articulación de plataformas multiactor, la gestión de la propiedad intelectual y transferencia tecnológica, en el marco de proyectos Penta-Hélice. | D4: PRDI25-29-Obj-86 | E4: Fortalecer la gestión institucional de la propiedad intelectual y transferencia tecnológica a través de mecanismos equitativos, sostenibles y con retribución social. | F4: 7 | G4: Capacitar a 100 miembros de la comunidad universitaria en materia de propiedad intelectual y gestión de activos de conocimiento, anualmente | H4: ACT-PRDI-NS-2881 | J4: Actividad | K4: Sin fórmula | L4: Capacitar a miembros de la comunidad universitaria en materia de propiedad intelectual y gestión de activos de conocimiento | R4: =M4 -> 0 | S4: =N4 -> 0 | T4: =O4 -> 0 | U4: =P4 -> 0 | V4: =Q4 -> 0 | W4: Anual

Sheet 6 Dif y divulga de la ciencia
A1: N.P. | B1: Clave Objetivo General | C1: Objetivo General | D1: Clave Objetivo Específico | E1: Objetivo Específico | F1: No. de meta en el PRDI | G1: Meta PRDI | H1: Clave de la meta | I1: Meta del espacio académico | J1: Actividad/Indicador | K1: Método de cálculo | L1: Nombre de las variables | M1: Valor de las variables | R1: Valor de los indicadores | W1: Medición (anual o acumulada) | X1: Área responsable
M2: Ref. 2026 | N2: 2027 | O2: 2028 | P2: 2029 | Q2: 2030 | R2: Ref. 2026 | S2: 2027 | T2: 2028 | U2: 2029 | V2: 2030
A3: 2 | B3: PRDI25-29-Obj-40 | C3: Comunicar en abierto los resultados de investigación con la finalidad de democratizar el acceso al conocimiento generado en la Universidad y asegurar su máxima difusión y retribución social en formatos accesibles y multilingües que se posicionen como bien público digital. | D3: PRDI25-29-Obj-87 | E3: Fortalecer los procesos editoriales y tecnológicos para sostener y generar libros y revistas científicas como bienes públicos digitales. | F3: 6 | G3: Realizar 1 programa de sostenibilidad y fortalecimiento del Acceso Abierto no comercial para las revistas científicas editadas en la Universidad, anualmente | H3: ACT-PRDI-NS-2890 | J3: Actividad | K3: Sin fórmula | L3: Realizar un programa de sostenibilidad y fortalecimiento del Acceso Abierto no comercial para las revistas científicas editadas en la Universidad | R3: =M3 -> 0 | S3: =N3 -> 0 | T3: =O3 -> 0 | U3: =P3 -> 0 | V3: =Q3 -> 0 | W3: Anual
A4: 3 | B4: PRDI25-29-Obj-40 | C4: Comunicar en abierto los resultados de investigación con la finalidad de democratizar el acceso al conocimiento generado en la Universidad y asegurar su máxima difusión y retribución social en formatos accesibles y multilingües que se posicionen como bien público digital. | D4: PRDI25-29-Obj-87 | E4: Fortalecer los procesos editoriales y tecnológicos para sostener y generar libros y revistas científicas como bienes públicos digitales. | F4: 13 | G4: Capacitar a 1000 miembros de la comunidad universitaria en Ciencia Abierta, anualmente | H4: ACT-PRDI-NS-2897 | J4: Actividad | K4: Sin fórmula | L4: Capacitar a miembros de la comunidad universitaria en Ciencia Abierta | R4: =M4 -> 0 | S4: =N4 -> 0 | T4: =O4 -> 0 | U4: =P4 -> 0 | V4: =Q4 -> 0 | W4: Anual
A5: 4 | B5: PRDI25-29-Obj-40 | C5: Comunicar en abierto los resultados de investigación con la finalidad de democratizar el acceso al conocimiento generado en la Universidad y asegurar su máxima difusión y retribución social en formatos accesibles y multilingües que se posicionen como bien público digital. | D5: PRDI25-29-Obj-87 | E5: Fortalecer los procesos editoriales y tecnológicos para sostener y generar libros y revistas científicas como bienes públicos digitales. | F5: 15 | G5: Realizar 1 evaluación de la calidad, criterios y políticas de Acceso Abierto Diamante de las publicaciones periódicas científicas institucionales, anualmente | H5: ACT-PRDI-NS-2899 | J5: Actividad | K5: Sin fórmula | L5: Realizar evaluaciones de la calidad, criterios y políticas de Acceso Abierto Diamante de las publicaciones periódicas científicas institucionales | R5: =M5 -> 0 | S5: =N5 -> 0 | T5: =O5 -> 0 | U5: =P5 -> 0 | V5: =Q5 -> 0 | W5: Anual

Sheet 7 Cultura desarrollo integral
A1: N.P. | B1: Clave Objetivo General | C1: Objetivo General | D1: Clave Objetivo Específico | E1: Objetivo Específico | F1: No. de meta en el PRDI | G1: Meta PRDI | H1: Clave de la meta | I1: Meta del espacio académico | J1: Actividad/Indicador | K1: Método de cálculo | L1: Nombre de las variables | M1: Valor de las variables | R1: Valor de los indicadores | W1: Medición (anual o acumulada) | X1: Área responsable
M2: Ref. 2026 | N2: 2027 | O2: 2028 | P2: 2029 | Q2: 2030 | R2: Ref. 2026 | S2: 2027 | T2: 2028 | U2: 2029 | V2: 2030
A3: 1 | B3: PRDI25-29-Obj-41 | C3: PRDI25-29-Obj-41 -Fortalecer la cultura a través de proyectos y actividades que articulen la expresión artística y cultural como parte del desarrollo de la comunidad universitaria.. | D3: PRDI25-29-Obj-63 | E3: Fomentar la participación activa de la comunidad universitaria y sociedad en general en actividades culturales innovadoras que fortalezcan la identidad y el sentido de pertenencia institucional que contribuyan a la cohesión social y la igualdad. | F3: 2 | G3: Abrir 850 talleres culturales anualmente en beneficio de la colectividad universitaria de nivel superior | H3: ACT-PRDI-NS-3193 | J3: Actividad | K3: Sin fórmula | L3: Abrir talleres culturales en beneficio de la colectividad universitaria de nivel superior | R3: =M3 -> 0 | S3: =N3 -> 0 | T3: =O3 -> 0 | U3: =P3 -> 0 | V3: =Q3 -> 0 | W3: Anual
A4: 2 | B4: PRDI25-29-Obj-41 | C4: PRDI25-29-Obj-41 -Fortalecer la cultura a través de proyectos y actividades que articulen la expresión artística y cultural como parte del desarrollo de la comunidad universitaria.. | D4: PRDI25-29-Obj-63 | E4: Fomentar la participación activa de la comunidad universitaria y sociedad en general en actividades culturales innovadoras que fortalezcan la identidad y el sentido de pertenencia institucional que contribuyan a la cohesión social y la igualdad. | F4: 4 | G4: Realizar 850 presentaciones artísticas anualmente. | H4: ACT-PRDI-NS-1816 | J4: Actividad | K4: Sin fórmula | L4: Realizar presentaciones artísticas | R4: =M4 -> 0 | S4: =N4 -> 0 | T4: =O4 -> 0 | U4: =P4 -> 0 | V4: =Q4 -> 0 | W4: Anual
A5: 3 | B5: PRDI25-29-Obj-41 | C5: PRDI25-29-Obj-41 -Fortalecer la cultura a través de proyectos y actividades que articulen la expresión artística y cultural como parte del desarrollo de la comunidad universitaria.. | D5: PRDI25-29-Obj-63 | E5: Fomentar la participación activa de la comunidad universitaria y sociedad en general en actividades culturales innovadoras que fortalezcan la identidad y el sentido de pertenencia institucional que contribuyan a la cohesión social y la igualdad. | F5: 8 | G5: Organizar 3 programas de fortalecimiento al talento audiovisual para desarrollar la creatividad cultural de los universitarios, durante la administración | H5: ACT-PRDI-NS-3195 | J5: Actividad | K5: Sin fórmula | L5: Organizar programas de fortalecimiento al talento audiovisual para desarrollar la creatividad cultural de los universitarios | R5: =M5 -> 0 | S5: =N5 -> 0 | T5: =O5 -> 0 | U5: =P5 -> 0 | V5: =Q5 -> 0 | W5: Anual
A6: 4 | B6: PRDI25-29-Obj-41 | C6: PRDI25-29-Obj-41 -Fortalecer la cultura a través de proyectos y actividades que articulen la expresión artística y cultural como parte del desarrollo de la comunidad universitaria.. | D6: PRDI25-29-Obj-88 | E6: Fortalecer espacios de formación y reflexión que integren a la cultura con inclusión y transformación social. | F6: 15 | G6: Organizar 6 programas audiovisuales vanguardistas que fomenten la innovación cultural durante la administración | H6: ACT-PRDI-NS-3200 | J6: Actividad | K6: Sin fórmula | L6: Organizar programas audiovisuales vanguardistas que fomenten la innovación cultural | R6: =M6 -> 0 | S6: =N6 -> 0 | T6: =O6 -> 0 | U6: =P6 -> 0 | V6: =Q6 -> 0 | W6: Anual
A7: 5 | B7: PRDI25-29-Obj-41 | C7: PRDI25-29-Obj-41 -Fortalecer la cultura a través de proyectos y actividades que articulen la expresión artística y cultural como parte del desarrollo de la comunidad universitaria.. | D7: PRDI25-29-Obj-88 | E7: Fortalecer espacios de formación y reflexión que integren a la cultura con inclusión y transformación social. | F7: 17 | G7: Realizar al año, 4 programas artísticos que contribuyan al fortalecimiento cultural de la comunidad universitaria | H7: ACT-PRDI-NS-3202 | J7: Actividad | K7: Sin fórmula | L7: Realizar programas artísticos que contribuyan al fortalecimiento cultural de la comunidad universitaria | R7: =M7 -> 0 | S7: =N7 -> 0 | T7: =O7 -> 0 | U7: =P7 -> 0 | V7: =Q7 -> 0 | W7: Anual
A8: 6 | B8: PRDI25-29-Obj-41 | C8: PRDI25-29-Obj-41 -Fortalecer la cultura a través de proyectos y actividades que articulen la expresión artística y cultural como parte del desarrollo de la comunidad universitaria.. | D8: PRDI25-29-Obj-88 | E8: Fortalecer espacios de formación y reflexión que integren a la cultura con inclusión y transformación social. | F8: 20 | G8: Realizar al año 1 festival cultural que reúna a los talentos de distintos talleres y espacios académicos | H8: ACT-PRDI-NS-3205 | J8: Actividad | K8: Sin fórmula | L8: Realizar festivales culturales que reúna a los talentos de distintos talleres y espacios académicos | R8: =M8 -> 0 | S8: =N8 -> 0 | T8: =O8 -> 0 | U8: =P8 -> 0 | V8: =Q8 -> 0 | W8: Anual

Sheet 8 Deporte universitario
A1: N.P. | B1: Clave Objetivo General | C1: Objetivo General | D1: Clave Objetivo Específico | E1: Objetivo Específico | F1: No. de meta en el PRDI | G1: Meta PRDI | H1: Clave de la meta | I1: Meta del espacio académico | J1: Actividad/Indicador | K1: Método de cálculo | L1: Nombre de las variables | M1: Valor de las variables | R1: Valor de los indicadores | W1: Medición (anual o acumulada) | X1: Área responsable
M2: Ref. 2026 | N2: 2027 | O2: 2028 | P2: 2029 | Q2: 2030 | R2: Ref. 2026 | S2: 2027 | T2: 2028 | U2: 2029 | V2: 2030
A3: 1 | B3: PRDI25-29-Obj-42 | C3: Fortalecer, mediante la promoción y participación, una cultura física para favorecer el desarrollo integral y la adopción de hábitos de bienestar en la comunidad universitaria. | D3: PRDI25-29-Obj-64 | E3: Generar la cultura física en la comunidad universitaria para fomentar hábitos de vida saludable. | F3: 1 | G3: Organizar anualmente 12 eventos regionales que promuevan el bienestar, el autocuidado y la actividad física responsable | H3: ACT-PRDI-NS-2746 | J3: Actividad | K3: Sin fórmula | L3: Organizar eventos regionales que promuevan el bienestar, el autocuidado y la actividad física responsable | R3: =M3 -> 0 | S3: =N3 -> 0 | T3: =O3 -> 0 | U3: =P3 -> 0 | V3: =Q3 -> 0 | W3: Anual
A4: 2 | B4: PRDI25-29-Obj-42 | C4: Fortalecer, mediante la promoción y participación, una cultura física para favorecer el desarrollo integral y la adopción de hábitos de bienestar en la comunidad universitaria. | D4: PRDI25-29-Obj-64 | E4: Generar la cultura física en la comunidad universitaria para fomentar hábitos de vida saludable. | F4: 2 | G4: Mantener anualmente la participación de 41.01% del personal académico en actividades de cultura física | H4: IND-PRDI-372 | J4: Indicador | K4: (Número de académicos que participan en actividades deportivas/ Total del personal académico)*100 | L4: Número de académicos que participan en actividades deportivas | R4: =IF(M5,M4/M5*100,"0") -> 0 | S4: =IF(N5,N4/N5*100,"0") -> 0 | T4: =IF(O5,O4/O5*100,"0") -> 0 | U4: =IF(P5,P4/P5*100,"0") -> 0 | V4: =IF(Q5,Q4/Q5*100,"0") -> 0 | W4: Anual
L5: Total del personal académico
A6: 3 | B6: PRDI25-29-Obj-42 | C6: Fortalecer, mediante la promoción y participación, una cultura física para favorecer el desarrollo integral y la adopción de hábitos de bienestar en la comunidad universitaria. | D6: PRDI25-29-Obj-64 | E6: Generar la cultura física en la comunidad universitaria para fomentar hábitos de vida saludable. | F6: 3 | G6: Lograr que 30.02% del personal administrativo participe en actividades de cultura física, anualmente | H6: IND-PRDI-374 | J6: Indicador | K6: (Número de administrativos en actividades deportivas/ Total del personal administrativo)*100 | L6: Número de administrativos en actividades deportivas | R6: =IF(M7,M6/M7*100,"0") -> 0 | S6: =IF(N7,N6/N7*100,"0") -> 0 | T6: =IF(O7,O6/O7*100,"0") -> 0 | U6: =IF(P7,P6/P7*100,"0") -> 0 | V6: =IF(Q7,Q6/Q7*100,"0") -> 0 | W6: Anual
L7: Total del personal administrativo
A8: 4 | B8: PRDI25-29-Obj-42 | C8: Fortalecer, mediante la promoción y participación, una cultura física para favorecer el desarrollo integral y la adopción de hábitos de bienestar en la comunidad universitaria. | D8: PRDI25-29-Obj-64 | E8: Generar la cultura física en la comunidad universitaria para fomentar hábitos de vida saludable. | F8: 7 | G8: Lograr anualmente que 50% de estudiantes del nivel superior participen en actividades de cultura física | H8: IND-PRDI-377 | J8: Indicador | K8: (Número de estudiantes de nivel superior que participan en actividades deportivas/ Total matrícula estudiantil de estudios profesionales)*100 | L8: Número de estudiantes de nivel superior que participan en actividades deportivas | R8: =IF(M9,M8/M9*100,"0") -> 0 | S8: =IF(N9,N8/N9*100,"0") -> 0 | T8: =IF(O9,O8/O9*100,"0") -> 0 | U8: =IF(P9,P8/P9*100,"0") -> 0 | V8: =IF(Q9,Q8/Q9*100,"0") -> 0 | W8: Anual
L9: Total matrícula estudiantil de estudios profesionales | M9: ='2 EstudiantadoEstProf'!M14 -> 0 | N9: ='2 EstudiantadoEstProf'!N14 -> 0 | O9: ='2 EstudiantadoEstProf'!O14 -> 0 | P9: ='2 EstudiantadoEstProf'!P14 -> 0 | Q9: ='2 EstudiantadoEstProf'!Q14 -> 0
A10: 5 | B10: PRDI25-29-Obj-42 | C10: Fortalecer, mediante la promoción y participación, una cultura física para favorecer el desarrollo integral y la adopción de hábitos de bienestar en la comunidad universitaria. | D10: PRDI25-29-Obj-90 | E10: Ampliar las oportunidades de acceso al deporte dirigidas a la comunidad universitaria para su desarrollo integral y proyección competitiva con equidad e inclusión. | F10: 5 | G10: Contar con la participación anual de 300 deportistas universitarios para impulsar su talento competitivo a nivel estatal, nacional e internacional | H10: ACT-PRDI-NS-2909 | J10: Actividad | K10: Sin fórmula | L10: Contar con la participación deportistas universitarios para impulsar su talento competitivo a nivel estatal, nacional e internacional | R10: =M10 -> 0 | S10: =N10 -> 0 | T10: =O10 -> 0 | U10: =P10 -> 0 | V10: =Q10 -> 0 | W10: Anual

Sheet 9 Fortalecimiento docente
A1: N.P. | B1: Clave Objetivo General | C1: Objetivo General | D1: Clave Objetivo Específico | E1: Objetivo Específico | F1: No. de meta en el PRDI | G1: Meta PRDI | H1: Clave de la meta | I1: Meta del espacio académico | J1: Actividad/Indicador | K1: Método de cálculo | L1: Nombre de las variables | M1: Valor de las variables | R1: Valor de los indicadores | W1: Medición (anual o acumulada) | X1: Área responsable
M2: Ref. 2026 | N2: 2027 | O2: 2028 | P2: 2029 | Q2: 2030 | R2: Ref. 2026 | S2: 2027 | T2: 2028 | U2: 2029 | V2: 2030
A3: 1 | B3: PRDI25-29-Obj-43 | C3: Fortalecer la habilitación académica, científica y el desarrollo integral del personal académico mediante una formación humanista e innovadora, que dignifique su labor, promueva la excelencia educativa y contribuya al bienestar de la comunidad docente. | D3: PRDI2025-2029-Obj-65 | E3: Formar al profesorado de nivel superior integralmente, para promover la excelencia educativa. | F3: 2 | G3: Lograr a 2029 que 65% del personal académico de nivel superior participe en actividades de formación | H3: IND-NS-212 | J3: Indicador | K3: (Número de académicos de nivel superior que participan en actividades de formación./Total de académicos de nivel superior)*100 | L3: Número de académicos de nivel superior que participan en actividades de formación. | R3: =IF(M4,M3/M4*100,"0") -> 0 | S3: =IF(N4,N3/N4*100,"0") -> 0 | T3: =IF(O4,O3/O4*100,"0") -> 0 | U3: =IF(P4,P3/P4*100,"0") -> 0 | V3: =IF(Q4,Q3/Q4*100,"0") -> 0 | W3: Anual
L4: Total de académicos de nivel superior
A5: 2 | B5: PRDI25-29-Obj-43 | C5: Fortalecer la habilitación académica, científica y el desarrollo integral del personal académico mediante una formación humanista e innovadora, que dignifique su labor, promueva la excelencia educativa y contribuya al bienestar de la comunidad docente. | D5: PRDI2025-2029-Obj-65 | E5: Formar al profesorado de nivel superior integralmente, para promover la excelencia educativa. | F5: 3 | G5: Actualizar anualmente a 25.01% del personal académico del nivel superior en conocimientos propios de la disciplina que enseñan | H5: IND-PRDI-371 | J5: Indicador | K5: (Número de personal académico de nivel superior que participa en actividades de capacitación de actualización disciplinar/Total de personal académico de nivel superior)*100 | L5: Número de personal académico de nivel superior que participa en actividades de capacitación de actualización disciplinar | R5: =IF(M6,M5/M6*100,"0") -> 0 | S5: =IF(N6,N5/N6*100,"0") -> 0 | T5: =IF(O6,O5/O6*100,"0") -> 0 | U5: =IF(P6,P5/P6*100,"0") -> 0 | V5: =IF(Q6,Q5/Q6*100,"0") -> 0 | W5: Anual
L6: Total de personal académico de nivel superior | M6: =M4 -> 0 | N6: =N4 -> 0 | O6: =O4 -> 0 | P6: =P4 -> 0 | Q6: =Q4 -> 0
A7: 3 | B7: PRDI25-29-Obj-43 | C7: Fortalecer la habilitación académica, científica y el desarrollo integral del personal académico mediante una formación humanista e innovadora, que dignifique su labor, promueva la excelencia educativa y contribuya al bienestar de la comunidad docente. | D7: PRDI2025-2029-Obj-65 | E7: Formar al profesorado de nivel superior integralmente, para promover la excelencia educativa. | F7: 4 | G7: Lograr que 50% de personal académico de nivel superior se capacite en el desarrollo de competencias didácticas y digitales a 2029 | H7: IND-PRDI-373 | J7: Indicador | K7: (Número de personal académico de nivel superior que participa en actividades de capacitación en el desarrollo de competencias didácticas y digitales/Total de personal académico de nivel superior)*100 | L7: Número de personal académico de nivel superior que participa en actividades de capacitación en el desarrollo de competencias didácticas y digitales | R7: =IF(M8,M7/M8*100,"0") -> 0 | S7: =IF(N8,N7/N8*100,"0") -> 0 | T7: =IF(O8,O7/O8*100,"0") -> 0 | U7: =IF(P8,P7/P8*100,"0") -> 0 | V7: =IF(Q8,Q7/Q8*100,"0") -> 0 | W7: Anual
L8: Total de personal académico de nivel superior | M8: =M4 -> 0 | N8: =N4 -> 0 | O8: =O4 -> 0 | P8: =P4 -> 0 | Q8: =Q4 -> 0
A9: 4 | B9: PRDI25-29-Obj-43 | C9: Fortalecer la habilitación académica, científica y el desarrollo integral del personal académico mediante una formación humanista e innovadora, que dignifique su labor, promueva la excelencia educativa y contribuya al bienestar de la comunidad docente. | D9: PRDI2025-2029-Obj-65 | E9: Formar al profesorado de nivel superior integralmente, para promover la excelencia educativa. | F9: 5 | G9: Capacitar a 100% del personal académico en el nuevo modelo educativo durante la administración | H9: IND-PRDI-375 | J9: Indicador | K9: (Número de personal académico capacitado en el nuevo modelo educativo/Total de personal académico)*100 | L9: Número de personal académico capacitado en el nuevo modelo educativo | R9: =IF(M10,M9/M10*100,"0") -> 0 | S9: =IF(N10,N9/N10*100,"0") -> 0 | T9: =IF(O10,O9/O10*100,"0") -> 0 | U9: =IF(P10,P9/P10*100,"0") -> 0 | V9: =IF(Q10,Q9/Q10*100,"0") -> 0 | W9: Anual
L10: Total de personal académico
A11: 5 | B11: PRDI25-29-Obj-43 | C11: Fortalecer la habilitación académica, científica y el desarrollo integral del personal académico mediante una formación humanista e innovadora, que dignifique su labor, promueva la excelencia educativa y contribuya al bienestar de la comunidad docente. | D11: PRDI2025-2029-Obj-65 | E11: Formar al profesorado de nivel superior integralmente, para promover la excelencia educativa. | F11: 6 | G11: Brindar capacitación en temas transversales a 25.01% del personal académico de nivel superior anualmente | H11: IND-PRDI-376 | J11: Indicador | K11: (Número de personal académico de nivel superior que participa en actividades de capacitación en temas transversales/Total de personal académico de nivel superior)*100 | L11: Número de personal académico de nivel superior que participa en actividades de capacitación en temas transversales | R11: =IF(M12,M11/M12*100,"0") -> 0 | S11: =IF(N12,N11/N12*100,"0") -> 0 | T11: =IF(O12,O11/O12*100,"0") -> 0 | U11: =IF(P12,P11/P12*100,"0") -> 0 | V11: =IF(Q12,Q11/Q12*100,"0") -> 0 | W11: Anual
L12: Total de personal académico de nivel superior | M12: =M4 -> 0 | N12: =N4 -> 0 | O12: =O4 -> 0 | P12: =P4 -> 0 | Q12: =Q4 -> 0
A13: 6 | B13: PRDI25-29-Obj-43 | C13: Fortalecer la habilitación académica, científica y el desarrollo integral del personal académico mediante una formación humanista e innovadora, que dignifique su labor, promueva la excelencia educativa y contribuya al bienestar de la comunidad docente. | D13: PRDI25-29-Obj-92 | E13: Fortalecer la formación y certificación del profesorado en una segunda lengua, con el propósito de consolidar su desarrollo profesional. | F13: 10 | G13: Lograr la certificación internacional en una segunda lengua en nivel C1 de cuatro habilidades de 360 profesores de lengua de estudios profesionales al final de la administración | H13: ACT-PRDI-NS-2923 | J13: Actividad | K13: Sin fórmula | L13: Lograr la certificación internacional en una segunda lengua en nivel C1 de cuatro habilidades de profesores de lengua de estudios profesionales | R13: =M13 -> 0 | S13: =N13 -> 0 | T13: =O13 -> 0 | U13: =P13 -> 0 | V13: =Q13 -> 0 | W13: Anual
A14: 7 | B14: PRDI25-29-Obj-43 | C14: Fortalecer la habilitación académica, científica y el desarrollo integral del personal académico mediante una formación humanista e innovadora, que dignifique su labor, promueva la excelencia educativa y contribuya al bienestar de la comunidad docente. | D14: PRDI25-29-Obj-93 | E14: Mejorar la habilitación académica y científica de los investigadores para su reconocimiento y excelencia. | F14: 13 | G14: Contar con 715 PTC en el SNII para 2029 | H14: ACT-PRDI-NS-2926 | J14: Actividad | K14: Sin fórmula | L14: Contar con PTC en el SNII | R14: =M14 -> 0 | S14: =N14 -> 0 | T14: =O14 -> 0 | U14: =P14 -> 0 | V14: =Q14 -> 0 | W14: Acumulada
A15: 8 | B15: PRDI25-29-Obj-43 | C15: Fortalecer la habilitación académica, científica y el desarrollo integral del personal académico mediante una formación humanista e innovadora, que dignifique su labor, promueva la excelencia educativa y contribuya al bienestar de la comunidad docente. | D15: PRDI25-29-Obj-93 | E15: Mejorar la habilitación académica y científica de los investigadores para su reconocimiento y excelencia. | F15: 14 | G15: Alcanzar 75.06% del profesorado de tiempo completo (PTC) con Perfil PRODEP, para 2029 | H15: IND-PRDI-47 | J15: Indicador | K15: (PTC registrados en la SEP que cuentan con perfil Prodep/Total de PTC registrados en la SEP)*100 | L15: PTC registrados en la SEP que cuentan con perfil Prodep | R15: =IF(M16,M15/M16*100,"0") -> 0 | S15: =IF(N16,N15/N16*100,"0") -> 0 | T15: =IF(O16,O15/O16*100,"0") -> 0 | U15: =IF(P16,P15/P16*100,"0") -> 0 | V15: =IF(Q16,Q15/Q16*100,"0") -> 0 | W15: Acumulada
L16: Total de PTC registrados en la SEP
A17: 9 | B17: PRDI25-29-Obj-43 | C17: Fortalecer la habilitación académica, científica y el desarrollo integral del personal académico mediante una formación humanista e innovadora, que dignifique su labor, promueva la excelencia educativa y contribuya al bienestar de la comunidad docente. | D17: PRDI25-29-Obj-93 | E17: Mejorar la habilitación académica y científica de los investigadores para su reconocimiento y excelencia. | F17: 15 | G17: Lograr 34 participantes del personal académico de Estudios Avanzados en actividades de internacionalización (seminarios, coil, cátedras), durante la administración | H17: ACT-PRDI-NS-2927 | J17: Actividad | K17: Sin fórmula | L17: Lograr participantes del personal académico de Estudios Avanzados en actividades de internacionalización (seminarios, coil, cátedras) | R17: =M17 -> 0 | S17: =N17 -> 0 | T17: =O17 -> 0 | U17: =P17 -> 0 | V17: =Q17 -> 0 | W17: Anual
A18: 10 | B18: PRDI25-29-Obj-43 | C18: Fortalecer la habilitación académica, científica y el desarrollo integral del personal académico mediante una formación humanista e innovadora, que dignifique su labor, promueva la excelencia educativa y contribuya al bienestar de la comunidad docente. | D18: PRDI25-29-Obj-93 | E18: Mejorar la habilitación académica y científica de los investigadores para su reconocimiento y excelencia. | F18: 16 | G18: Lograr que 316 académicos e investigadores participen en estancias internacionales o de movilidad durante la administración | H18: ACT-PRDI-NS-2928 | J18: Actividad | K18: Sin fórmula | L18: Lograr que académicos e investigadores participen en estancias internacionales o de movilidad | R18: =M18 -> 0 | S18: =N18 -> 0 | T18: =O18 -> 0 | U18: =P18 -> 0 | V18: =Q18 -> 0 | W18: Anual

Sheet 10 Dignificación las y los trab
A1: N.P. | B1: Clave Objetivo General | C1: Objetivo General | D1: Clave Objetivo Específico | E1: Objetivo Específico | F1: No. de meta en el PRDI | G1: Meta PRDI | H1: Clave de la meta | I1: Meta del espacio académico | J1: Actividad/Indicador | K1: Método de cálculo | L1: Nombre de las variables | M1: Valor de las variables | R1: Valor de los indicadores | W1: Medición (anual o acumulada) | X1: Área responsable
M2: Ref. 2026 | N2: 2027 | O2: 2028 | P2: 2029 | Q2: 2030 | R2: Ref. 2026 | S2: 2027 | T2: 2028 | U2: 2029 | V2: 2030
A3: 1 | B3: PRDI25-29-Obj-44 | C3: Mejorar la dignificación de las y los trabajadores universitarios a través del reconocimiento institucional y actualización de conocimiento para fortalecer su perfil profesional y personal; lo cual se verá reflejado en un mejor servicio universitario. | D3: PRDI2025-2029-Obj-66 | E3: Fortalecer las competencias laborales del personal administrativo para la mejora de perfiles de puesto. | F3: 1 | G3: Capacitar a 80% de los integrantes del personal administrativo en competencias básicas y técnicas a 2029 | H3: IND-PRDI-378 | J3: Indicador | K3: (Número de personal administrativo capacitado en competencias básicas y técnicas / Total de personal administrativo)*100 | L3: Número de personal administrativo capacitado en en competencias básicas y técnicas | R3: =IF(M4,M3/M4*100,"0") -> 0 | S3: =IF(N4,N3/N4*100,"0") -> 0 | T3: =IF(O4,O3/O4*100,"0") -> 0 | U3: =IF(P4,P3/P4*100,"0") -> 0 | V3: =IF(Q4,Q3/Q4*100,"0") -> 0 | W3: Anual
L4: Total de personal administrativo | M4: ='8 Deporte universitario'!M7 -> 0 | N4: ='8 Deporte universitario'!N7 -> 0 | O4: ='8 Deporte universitario'!O7 -> 0 | P4: ='8 Deporte universitario'!P7 -> 0 | Q4: ='8 Deporte universitario'!Q7 -> 0
A5: 2 | B5: PRDI25-29-Obj-44 | C5: Mejorar la dignificación de las y los trabajadores universitarios a través del reconocimiento institucional y actualización de conocimiento para fortalecer su perfil profesional y personal; lo cual se verá reflejado en un mejor servicio universitario. | D5: PRDI2025-2029-Obj-66 | E5: Fortalecer las competencias laborales del personal administrativo para la mejora de perfiles de puesto. | F5: 2 | G5: Capacitar 35.01% del personal administrativo en competencias transversales, equidad de género, ética y cultura de paz a 2029 | H5: IND-PRDI-380 | J5: Indicador | K5: (Número de personal administrativo capacitado en competencias transversales, equidad de género, ética y paz / Total de personal administrativo)*100 | L5: Número de personal administrativo capacitado en competencias transversales, equidad de género, ética y paz | R5: =IF(M6,M5/M6*100,"0") -> 0 | S5: =IF(N6,N5/N6*100,"0") -> 0 | T5: =IF(O6,O5/O6*100,"0") -> 0 | U5: =IF(P6,P5/P6*100,"0") -> 0 | V5: =IF(Q6,Q5/Q6*100,"0") -> 0 | W5: Anual
L6: Total de personal administrativo | M6: ='8 Deporte universitario'!M7 -> 0 | N6: ='8 Deporte universitario'!N7 -> 0 | O6: ='8 Deporte universitario'!O7 -> 0 | P6: ='8 Deporte universitario'!P7 -> 0 | Q6: ='8 Deporte universitario'!Q7 -> 0
A7: 3 | B7: PRDI25-29-Obj-44 | C7: Mejorar la dignificación de las y los trabajadores universitarios a través del reconocimiento institucional y actualización de conocimiento para fortalecer su perfil profesional y personal; lo cual se verá reflejado en un mejor servicio universitario. | D7: PRDI2025-2029-Obj-66 | E7: Fortalecer las competencias laborales del personal administrativo para la mejora de perfiles de puesto. | F7: 4 | G7: Capacitar a 20% del personal universitario en Tecnologías de la Información y Comunicación, anualmente | H7: IND-PRDI-382 | J7: Indicador | K7: (Número de personal universitario capacitado en temas de Tecnologías de la Información/ Total de personal universitario)*100 | L7: Número de personal universitario capacitado en temas de Tecnologías de la Información | R7: =IF(M8,M7/M8*100,"0") -> 0 | S7: =IF(N8,N7/N8*100,"0") -> 0 | T7: =IF(O8,O7/O8*100,"0") -> 0 | U7: =IF(P8,P7/P8*100,"0") -> 0 | V7: =IF(Q8,Q7/Q8*100,"0") -> 0 | W7: Anual
L8: Total de personal universitario

Sheet 11 Gestión administrativa
A1: N.P. | B1: Clave Objetivo General | C1: Objetivo General | D1: Clave Objetivo Específico | E1: Objetivo Específico | F1: No. de meta en el PRDI | G1: Meta PRDI | H1: Clave de la meta | I1: Meta del espacio académico | J1: Actividad/Indicador | K1: Método de cálculo | L1: Nombre de las variables | M1: Valor de las variables | R1: Valor de los indicadores | W1: Medición (anual o acumulada) | X1: Área responsable
M2: Ref. 2026 | N2: 2027 | O2: 2028 | P2: 2029 | Q2: 2030 | R2: Ref. 2026 | S2: 2027 | T2: 2028 | U2: 2029 | V2: 2030
A3: 1 | B3: PRDI25-29-Obj-45 | C3: Fortalecer la administración universitaria mediante acciones integrales de infraestructura, cultura organizacional de la calidad y proceso orgánico funcional, eficientes para atender las necesidades de la comunidad universitaria. | D3: PRDI25-29-Obj-99 | E3: PRDI25-29-Obj-99 -Fortalecer el proceso orgánico-funcional de la Institución que permita tener una gestión más eficiente en los espacios universitarios. | F3: 24 | G3: Armonizar 70 manuales de organización de espacios universitarios a 2029 | H3: ACT-PRDI-NS-2743 | J3: Actividad | K3: Sin fórmula | L3: Armonizar manuales de organización de espacios universitarios | R3: =M3 -> 0 | S3: =N3 -> 0 | T3: =O3 -> 0 | U3: =P3 -> 0 | V3: =Q3 -> 0 | W3: Anual
A4: 2 | B4: PRDI25-29-Obj-45 | C4: Fortalecer la administración universitaria mediante acciones integrales de infraestructura, cultura organizacional de la calidad y proceso orgánico funcional, eficientes para atender las necesidades de la comunidad universitaria. | D4: PRDI25-29-Obj-99 | E4: PRDI25-29-Obj-99 -Fortalecer el proceso orgánico-funcional de la Institución que permita tener una gestión más eficiente en los espacios universitarios. | F4: 25 | G4: Armonizar 50 manuales de procedimientos de espacios universitarios a 2029 | H4: ACT-PRDI-NS-2957 | J4: Actividad | K4: Sin fórmula | L4: Armonizar manuales de procedimientos de espacios universitarios | R4: =M4 -> 0 | S4: =N4 -> 0 | T4: =O4 -> 0 | U4: =P4 -> 0 | V4: =Q4 -> 0 | W4: Anual

Sheet 12 Fortalecimiento tecnológico
A1: N.P. | B1: Clave Objetivo General | C1: Objetivo General | D1: Clave Objetivo Específico | E1: Objetivo Específico | F1: No. de meta en el PRDI | G1: Meta PRDI | H1: Clave de la meta | I1: Meta del espacio académico | J1: Actividad/Indicador | K1: Método de cálculo | L1: Nombre de las variables | M1: Valor de las variables | R1: Valor de los indicadores | W1: Medición (anual o acumulada) | X1: Área responsable
M2: Ref. 2026 | N2: 2027 | O2: 2028 | P2: 2029 | Q2: 2030 | R2: Ref. 2026 | S2: 2027 | T2: 2028 | U2: 2029 | V2: 2030
A3: 1 | B3: PRDI25-29-Obj-46 | C3: Fortalecer la infraestructura tecnológica de la Universidad mediante la actualización de recursos, cultura digital, modernización de procesos y seguridad de la información para mejorar la gestión académica, administrativa y de investigación. | D3: PRDI25-29-Obj-101 | E3: PRDI25-29-Obj-101 -Fortalecer la cultura digital de la comunidad universitaria para mejorar sus habilidades tecnológicas y promover un uso efectivo de tic. | F3: 7 | G3: Desarrollar 160 guías de estudio independiente (GEI) al año | H3: ACT-PRDI-NS-2968 | J3: Actividad | K3: Sin fórmula | L3: Desarrollar guías de estudio independiente (GEI) | R3: =M3 -> 0 | S3: =N3 -> 0 | T3: =O3 -> 0 | U3: =P3 -> 0 | V3: =Q3 -> 0 | W3: Anual
A4: 2 | B4: PRDI25-29-Obj-46 | C4: Fortalecer la infraestructura tecnológica de la Universidad mediante la actualización de recursos, cultura digital, modernización de procesos y seguridad de la información para mejorar la gestión académica, administrativa y de investigación. | D4: PRDI25-29-Obj-103 | E4: PRDI25-29-Obj-103 -Garantizar la operación continua y eficiente de la infraestructura tecnológica institucional para proporcionar la disponibilidad y funcionalidad de los equipos y sistemas en los espacios académicos. | F4: 10 | G4: Contar con 100% de los espacios académicos con mantenimiento preventivo a equipos de salas de cómputo, anualmente | H4: ACT-PRDI-NS-3242 | J4: Actividad | K4: Sin fórmula | L4: Dar mantenimiento preventivo a equipos de salas de cómputo | R4: =M4 -> 0 | S4: =N4 -> 0 | T4: =O4 -> 0 | U4: =P4 -> 0 | V4: =Q4 -> 0 | W4: Anual

Sheet 13 Gobernanza
A1: N.P. | B1: Clave Objetivo General | C1: Objetivo General | D1: Clave Objetivo Específico | E1: Objetivo Específico | F1: No. de meta en el PRDI | G1: Meta PRDI | H1: Clave de la meta | I1: Meta del espacio académico | J1: Actividad/Indicador | K1: Método de cálculo | L1: Nombre de las variables | M1: Valor de las variables | R1: Valor de los indicadores | W1: Medición (anual o acumulada) | X1: Área responsable
M2: Ref. 2026 | N2: 2027 | O2: 2028 | P2: 2029 | Q2: 2030 | R2: Ref. 2026 | S2: 2027 | T2: 2028 | U2: 2029 | V2: 2030
A3: 1 | B3: PRDI25-29-Obj-47 | C3: Consolidar el diálogo, la participación y transparencia en la vida institucional, mediante la gestión colaborativa, corresponsable y cercana para incrementar el sentido de pertenencia, construyendo la memoria colectiva y la historia institucional, articular la expresión artística y cultural, la seguridad y el deporte en favor de la comunidad universitaria. | D3: PRDI25-29-Obj-104 | E3: Fortalecer la autoprotección y los protocolos de reacción para salvaguardar la seguridad de la comunidad universitaria. | F3: 8 | G3: Realizar anualmente 1 campaña de protección universitaria en materia de autoprotección y reacción ante emergencias para la comunidad universitaria de nivel superior | H3: ACT-PRDI-NS-2980 | J3: Actividad | K3: Sin fórmula | L3: Realizar campañas de protección universitaria en materia de autoprotección y reacción ante emergencias para la comunidad universitaria de nivel superior | R3: =M3 -> 0 | S3: =N3 -> 0 | T3: =O3 -> 0 | U3: =P3 -> 0 | V3: =Q3 -> 0 | W3: Anual
A4: 2 | B4: PRDI25-29-Obj-47 | C4: Consolidar el diálogo, la participación y transparencia en la vida institucional, mediante la gestión colaborativa, corresponsable y cercana para incrementar el sentido de pertenencia, construyendo la memoria colectiva y la historia institucional, articular la expresión artística y cultural, la seguridad y el deporte en favor de la comunidad universitaria. | D4: PRDI25-29-Obj-104 | E4: Fortalecer la autoprotección y los protocolos de reacción para salvaguardar la seguridad de la comunidad universitaria. | F4: 10 | G4: Realizar anualmente 1 simulacro de acuerdo con la convocatoria nacional | H4: ACT-PRDI-NS-2982 | J4: Actividad | K4: Sin fórmula | L4: Realizar simulacro de acuerdo con la convocatoria nacional | R4: =M4 -> 0 | S4: =N4 -> 0 | T4: =O4 -> 0 | U4: =P4 -> 0 | V4: =Q4 -> 0 | W4: Anual
A5: 3 | B5: PRDI25-29-Obj-47 | C5: Consolidar el diálogo, la participación y transparencia en la vida institucional, mediante la gestión colaborativa, corresponsable y cercana para incrementar el sentido de pertenencia, construyendo la memoria colectiva y la historia institucional, articular la expresión artística y cultural, la seguridad y el deporte en favor de la comunidad universitaria. | D5: PRDI25-29-Obj-105 | E5: Capacitar a elementos del personal de Seguridad y Protección Universitaria en materia de perspectiva de género y atención prioritaria a grupos vulnerables para garantizar una atención oportuna. | F5: 11 | G5: Efectuar anualmente 1 campaña del protocolo de atención integral a víctimas en todas las áreas universitarias | H5: ACT-PRDI-NS-2748 | J5: Actividad | K5: Sin fórmula | L5: Efectuar campañas del protocolo de atención integral a víctimas en todas las áreas universitarias | R5: =M5 -> 0 | S5: =N5 -> 0 | T5: =O5 -> 0 | U5: =P5 -> 0 | V5: =Q5 -> 0 | W5: Anual
A6: 4 | B6: PRDI25-29-Obj-47 | C6: Consolidar el diálogo, la participación y transparencia en la vida institucional, mediante la gestión colaborativa, corresponsable y cercana para incrementar el sentido de pertenencia, construyendo la memoria colectiva y la historia institucional, articular la expresión artística y cultural, la seguridad y el deporte en favor de la comunidad universitaria. | D6: PRDI25-29-Obj-105 | E6: Capacitar a elementos del personal de Seguridad y Protección Universitaria en materia de perspectiva de género y atención prioritaria a grupos vulnerables para garantizar una atención oportuna. | F6: 12 | G6: Difundir anualmente 1 campaña de los Protocolos de Seguridad y Protección Civil | H6: ACT-PRDI-NS-2983 | J6: Actividad | K6: Sin fórmula | L6: Difundir la campaña de los Protocolos de Seguridad y Protección Civil | R6: =M6 -> 0 | S6: =N6 -> 0 | T6: =O6 -> 0 | U6: =P6 -> 0 | V6: =Q6 -> 0 | W6: Anual
A7: 5 | B7: PRDI25-29-Obj-47 | C7: Consolidar el diálogo, la participación y transparencia en la vida institucional, mediante la gestión colaborativa, corresponsable y cercana para incrementar el sentido de pertenencia, construyendo la memoria colectiva y la historia institucional, articular la expresión artística y cultural, la seguridad y el deporte en favor de la comunidad universitaria. | D7: PRDI25-29-Obj-105 | E7: Capacitar a elementos del personal de Seguridad y Protección Universitaria en materia de perspectiva de género y atención prioritaria a grupos vulnerables para garantizar una atención oportuna. | F7: 13 | G7: Realizar 1 curso anual dirigido al personal de Protección Universitaria sobre Derechos Humanos y perspectiva de Género | H7: ACT-PRDI-NS-2984 | J7: Actividad | K7: Sin fórmula | L7: Realizar cursos dirigidos al personal de Protección Universitaria sobre Derechos Humanos y perspectiva de Género | R7: =M7 -> 0 | S7: =N7 -> 0 | T7: =O7 -> 0 | U7: =P7 -> 0 | V7: =Q7 -> 0 | W7: Anual
A8: 6 | B8: PRDI25-29-Obj-47 | C8: Consolidar el diálogo, la participación y transparencia en la vida institucional, mediante la gestión colaborativa, corresponsable y cercana para incrementar el sentido de pertenencia, construyendo la memoria colectiva y la historia institucional, articular la expresión artística y cultural, la seguridad y el deporte en favor de la comunidad universitaria. | D8: PRDI25-29-Obj-108 | E8: Preservar entre las y los universitarios una pertenencia universitaria fortalecida, así como la valoración y difusión de contenidos promocionales para consolidar productos editoriales y publicaciones sobre la historia y el acontecer universitario, para impulsar el orgullo de pertenencia. | F8: 20 | G8: Atender anualmente a 15 000 asistentes a conferencias, foros y charlas, relacionados con la pertenencia universitaria | H8: ACT-PRDI-NS-2749 | J8: Actividad | K8: Sin fórmula | L8: Atender anualmente a asistentes a conferencias, foros y charlas, relacionados con la pertenencia universitaria | R8: =M8 -> 0 | S8: =N8 -> 0 | T8: =O8 -> 0 | U8: =P8 -> 0 | V8: =Q8 -> 0 | W8: Anual
A9: 7 | B9: PRDI25-29-Obj-47 | C9: Consolidar el diálogo, la participación y transparencia en la vida institucional, mediante la gestión colaborativa, corresponsable y cercana para incrementar el sentido de pertenencia, construyendo la memoria colectiva y la historia institucional, articular la expresión artística y cultural, la seguridad y el deporte en favor de la comunidad universitaria. | D9: PRDI25-29-Obj-108 | E9: Preservar entre las y los universitarios una pertenencia universitaria fortalecida, así como la valoración y difusión de contenidos promocionales para consolidar productos editoriales y publicaciones sobre la historia y el acontecer universitario, para impulsar el orgullo de pertenencia. | F9: 22 | G9: Contar anualmente con 8 500 asistentes a visitas guiadas | H9: ACT-PRDI-NS-2992 | J9: Actividad | K9: Sin fórmula | L9: Contar con asistentes a visitas guiadas | R9: =M9 -> 0 | S9: =N9 -> 0 | T9: =O9 -> 0 | U9: =P9 -> 0 | V9: =Q9 -> 0 | W9: Anual
A10: 8 | B10: PRDI25-29-Obj-47 | C10: Consolidar el diálogo, la participación y transparencia en la vida institucional, mediante la gestión colaborativa, corresponsable y cercana para incrementar el sentido de pertenencia, construyendo la memoria colectiva y la historia institucional, articular la expresión artística y cultural, la seguridad y el deporte en favor de la comunidad universitaria. | D10: PRDI25-29-Obj-108 | E10: Preservar entre las y los universitarios una pertenencia universitaria fortalecida, así como la valoración y difusión de contenidos promocionales para consolidar productos editoriales y publicaciones sobre la historia y el acontecer universitario, para impulsar el orgullo de pertenencia. | F10: 30 | G10: Lograr que 100% de los espacios universitarios con cronista cuente con una nueva crónica sobre la historia de su espacio, al final de la administración | H10: ACT-PRDI-NS-3243 | J10: Actividad | K10: Sin fórmula | L10: Contar con una nueva crónica sobre la historia del espacio universitario | R10: =M10 -> 0 | S10: =N10 -> 0 | T10: =O10 -> 0 | U10: =P10 -> 0 | V10: =Q10 -> 0 | W10: Anual

Sheet 16 Manejo recursos universitari
A1: N.P. | B1: Clave Objetivo General | C1: Objetivo General | D1: Clave Objetivo Específico | E1: Objetivo Específico | F1: No. de meta en el PRDI | G1: Meta PRDI | H1: Clave de la meta | I1: Meta del espacio académico | J1: Actividad/Indicador | K1: Método de cálculo | L1: Nombre de las variables | M1: Valor de las variables | R1: Valor de los indicadores | W1: Medición (anual o acumulada) | X1: Área responsable
M2: Ref. 2026 | N2: 2027 | O2: 2028 | P2: 2029 | Q2: 2030 | R2: Ref. 2026 | S2: 2027 | T2: 2028 | U2: 2029 | V2: 2030
A3: 1 | B3: PRDI25-29-Obj-50 | C3: Lograr que las finanzas universitarias se administren con integridad, transparencia y eficiencia, mediante la implementación de un presupuesto responsable que contribuya a la sostenibilidad institucional bajo los principios de austeridad, equidad y visión estratégica. | D3: PRDI25-29-Obj-117 | E3: Potenciar de manera eficiente, transparente y sostenible la generación de recursos extraordinarios alternos para que contribuyan a fortalecer las funciones sustantivas y adjetivas de la Universidad. | F3: 5 | G3: Implementar anualmente 1 programa institucional que fortalezca la generación de ingresos extraordinarios | H3: ACT-PRDI-NS-2763 | J3: Actividad | K3: Sin fórmula | L3: Implementar un programa institucional que fortalezca la generación de ingresos extraordinarios | R3: =M3 -> 0 | S3: =N3 -> 0 | T3: =O3 -> 0 | U3: =P3 -> 0 | V3: =Q3 -> 0 | W3: Anual

Sheet 18 Reconocimiento de la diversi
A1: N.P. | B1: Clave Objetivo General | C1: Objetivo General | D1: Clave Objetivo Específico | E1: Objetivo Específico | F1: No. de meta en el PRDI | G1: Meta PRDI | H1: Clave de la meta | I1: Meta del espacio académico | J1: Actividad/Indicador | K1: Método de cálculo | L1: Nombre de las variables | M1: Valor de las variables | R1: Valor de los indicadores | W1: Medición (anual o acumulada) | X1: Área responsable
M2: Ref. 2026 | N2: 2027 | O2: 2028 | P2: 2029 | Q2: 2030 | R2: Ref. 2026 | S2: 2027 | T2: 2028 | U2: 2029 | V2: 2030
A3: 1 | B3: PRDI25-29-Obj-52 | C3: Fortalecer una cultura universitaria incluyente, equitativa y libre de discriminación mediante la implementación de acciones integrales de reconocimiento, atención y prevención, que incorporen la perspectiva de diversidad, género y cuidados. | D3: PRDI2025-2029-Obj-74 | E3: Fortalecer la igualdad y la inclusión entre la comunidad universitaria para reconocer y respetar la diversidad social. | F3: 1 | G3: Sensibilizar durante la administración a 40% de estudiantado de estudios profesionales en temas de inclusión a grupos históricamente vulnerados | H3: IND-PRDI-431 | J3: Indicador | K3: (Número de estudiantes sensibilizados / Total del estudiantado)*100 | L3: Número de estudiantes sensibilizados | R3: =IF(M4,M3/M4*100,"0") -> 0 | S3: =IF(N4,N3/N4*100,"0") -> 0 | T3: =IF(O4,O3/O4*100,"0") -> 0 | U3: =IF(P4,P3/P4*100,"0") -> 0 | V3: =IF(Q4,Q3/Q4*100,"0") -> 0 | W3: Anual
L4: Total del estudiantado
A5: 2 | B5: PRDI25-29-Obj-52 | C5: Fortalecer una cultura universitaria incluyente, equitativa y libre de discriminación mediante la implementación de acciones integrales de reconocimiento, atención y prevención, que incorporen la perspectiva de diversidad, género y cuidados. | D5: PRDI25-29-Obj-122 | E5: Mejorar los mecanismos y las prácticas institucionales para generar entornos libres de discriminación. | F5: 3 | G5: Difundir 3 materiales de divulgación al año (guías, cartillas y manuales) orientados a promover el respeto y reconocimiento de las identidades entre la comunidad universitaria | H5: ACT-PRDI-NS-3075 | J5: Actividad | K5: Sin fórmula | L5: Difundir materiales de divulgación (guías, cartillas y manuales) orientados a promover el respeto y reconocimiento de las identidades entre la comunidad universitaria | R5: =M5 -> 0 | S5: =N5 -> 0 | T5: =O5 -> 0 | U5: =P5 -> 0 | V5: =Q5 -> 0 | W5: Anual
A6: 3 | B6: PRDI25-29-Obj-52 | C6: Fortalecer una cultura universitaria incluyente, equitativa y libre de discriminación mediante la implementación de acciones integrales de reconocimiento, atención y prevención, que incorporen la perspectiva de diversidad, género y cuidados. | D6: PRDI25-29-Obj-124 | E6: Impulsar programas de apoyo dirigidos a grupos en situación de vulnerabilidad, para fomentar su inclusión, desarrollo académico y laboral dentro de la Universidad. | F6: 6 | G6: Incrementar a 4.90% los proyectos de investigación en materia de cultura de paz y estudios de género respecto al total de proyectos de investigación, para 2029 | H6: IND-PRDI-407 | J6: Indicador | K6: (Proyectos de investigación en materia de cultura de paz y estudios de género/Total de proyectos de investigación)*100 | L6: Proyectos de investigación en materia de cultura de paz y estudios de género | R6: =IF(M7,M6/M7*100,"0") -> 0 | S6: =IF(N7,N6/N7*100,"0") -> 0 | T6: =IF(O7,O6/O7*100,"0") -> 0 | U6: =IF(P7,P6/P7*100,"0") -> 0 | V6: =IF(Q7,Q6/Q7*100,"0") -> 0 | W6: Anual
L7: Total de proyectos de investigación
A8: 4 | B8: PRDI25-29-Obj-52 | C8: Fortalecer una cultura universitaria incluyente, equitativa y libre de discriminación mediante la implementación de acciones integrales de reconocimiento, atención y prevención, que incorporen la perspectiva de diversidad, género y cuidados. | D8: PRDI25-29-Obj-124 | E8: Impulsar programas de apoyo dirigidos a grupos en situación de vulnerabilidad, para fomentar su inclusión, desarrollo académico y laboral dentro de la Universidad. | F8: 7 | G8: Implementar 2 eventos socioculturales al año con temáticas de inclusión y vulnerabilidad | H8: ACT-PRDI-NS-3081 | J8: Actividad | K8: Sin fórmula | L8: Implementar eventos socioculturales con temáticas de inclusión y vulnerabilidad | R8: =M8 -> 0 | S8: =N8 -> 0 | T8: =O8 -> 0 | U8: =P8 -> 0 | V8: =Q8 -> 0 | W8: Anual
A9: 5 | B9: PRDI25-29-Obj-52 | C9: Fortalecer una cultura universitaria incluyente, equitativa y libre de discriminación mediante la implementación de acciones integrales de reconocimiento, atención y prevención, que incorporen la perspectiva de diversidad, género y cuidados. | D9: PRDI25-29-Obj-124 | E9: Impulsar programas de apoyo dirigidos a grupos en situación de vulnerabilidad, para fomentar su inclusión, desarrollo académico y laboral dentro de la Universidad. | F9: 13 | G9: Realizar 1 actividad anual sobre equidad social y de género | H9: ACT-PRDI-NS-3087 | J9: Actividad | K9: Sin fórmula | L9: Realizar actividades sobre equidad social y de género | R9: =M9 -> 0 | S9: =N9 -> 0 | T9: =O9 -> 0 | U9: =P9 -> 0 | V9: =Q9 -> 0 | W9: Anual
A10: 6 | B10: PRDI25-29-Obj-52 | C10: Fortalecer una cultura universitaria incluyente, equitativa y libre de discriminación mediante la implementación de acciones integrales de reconocimiento, atención y prevención, que incorporen la perspectiva de diversidad, género y cuidados. | D10: PRDI25-29-Obj-125 | E10: Incorporar la perspectiva de cuidados y corresponsabilidad en los procesos institucionales para garantizar entornos seguros en los espacios universitarios. | F10: 16 | G10: Implementar 4 programas de sensibilización al año en temas de corresponsabilidad y autocuidado | H10: ACT-PRDI-NS-2767 | J10: Actividad | K10: Sin fórmula | L10: Implementar programas de sensibilización en temas de corresponsabilidad y autocuidado | R10: =M10 -> 0 | S10: =N10 -> 0 | T10: =O10 -> 0 | U10: =P10 -> 0 | V10: =Q10 -> 0 | W10: Anual
A11: 7 | B11: PRDI25-29-Obj-52 | C11: Fortalecer una cultura universitaria incluyente, equitativa y libre de discriminación mediante la implementación de acciones integrales de reconocimiento, atención y prevención, que incorporen la perspectiva de diversidad, género y cuidados. | D11: PRDI25-29-Obj-125 | E11: Incorporar la perspectiva de cuidados y corresponsabilidad en los procesos institucionales para garantizar entornos seguros en los espacios universitarios. | F11: 24 | G11: Realizar anualmente 10 talleres articulados que fortalezcan el Programa Universitario de Bienestar Integral | H11: ACT-PRDI-NS-3097 | J11: Actividad | K11: Sin fórmula | L11: Realizar talleres articulados que fortalezcan el Programa Universitario de Bienestar Integral | R11: =M11 -> 0 | S11: =N11 -> 0 | T11: =O11 -> 0 | U11: =P11 -> 0 | V11: =Q11 -> 0 | W11: Anual
A12: 8 | B12: PRDI25-29-Obj-52 | C12: Fortalecer una cultura universitaria incluyente, equitativa y libre de discriminación mediante la implementación de acciones integrales de reconocimiento, atención y prevención, que incorporen la perspectiva de diversidad, género y cuidados. | D12: PRDI25-29-Obj-125 | E12: Incorporar la perspectiva de cuidados y corresponsabilidad en los procesos institucionales para garantizar entornos seguros en los espacios universitarios. | F12: 25 | G12: Certificar anualmente a 10% del personal académico, administrativo de confianza y directivo en materia de bienestar integral | H12: ACT-POA-NS-2650 | J12: Actividad | K12: Sin fórmula | L12: Capacitar anualmente al personal académico, administrativo de confianza y directivo de nivel superior en materia de bienestar integral. | R12: =M12 -> 0 | S12: =N12 -> 0 | T12: =O12 -> 0 | U12: =P12 -> 0 | V12: =Q12 -> 0 | W12: Anual

Sheet 19 Constr cultura de paz 
A1: N.P. | B1: Clave Objetivo General | C1: Objetivo General | D1: Clave Objetivo Específico | E1: Objetivo Específico | F1: No. de meta en el PRDI | G1: Meta PRDI | H1: Clave de la meta | I1: Meta del espacio académico | J1: Actividad/Indicador | K1: Método de cálculo | L1: Nombre de las variables | M1: Valor de las variables | R1: Valor de los indicadores | W1: Medición (anual o acumulada) | X1: Área responsable
M2: Ref. 2026 | N2: 2027 | O2: 2028 | P2: 2029 | Q2: 2030 | R2: Ref. 2026 | S2: 2027 | T2: 2028 | U2: 2029 | V2: 2030
A3: 1 | B3: PRDI25-29-Obj-53 | C3: Promover la construcción de una cultura de paz en la comunidad universitaria, mediante estrategias educativas, participativas y de sensibilización que fortalezcan la convivencia armónica y el respeto a los derechos humanos. | D3: PRDI25-29-Obj-126 | E3: Generar capacidades individuales y colectivas para la gestión pacífica de los conflictos, la convivencia respetuosa y la prevención de situaciones de violencia entre la comunidad universitaria. | F3: 8 | G3: Certificar anualmente a 10.03% del personal académico, administrativo de confianza y directivo, en competencias básicas de mediación, gestión pacífica de conflictos y atención a las violencias | H3: ACT-POA-NS-2651 | I3: Mantener al menos 5 acciones de capacitación registradas en cada medición anual de 2027 a 2030. | J3: Actividad | K3: Sin fórmula | L3: Capacitar anualmente a personal académico, administrativo de confianza y directivo del nivel superior, en competencias básicas de mediación, gestión pacífica de conflictos y atención a las violencias | M3: 5 | N3: 5 | O3: 5 | P3: 5 | Q3: 5 | R3: =IF(M3="","",M3) -> 5 | S3: =IF(N3="","",N3) -> 5 | T3: =IF(O3="","",O3) -> 5 | U3: =IF(P3="","",P3) -> 5 | V3: =IF(Q3="","",Q3) -> 5 | W3: Anual | X3: Por validar con el área responsable
A4: 2 | B4: PRDI25-29-Obj-53 | C4: Promover la construcción de una cultura de paz en la comunidad universitaria, mediante estrategias educativas, participativas y de sensibilización que fortalezcan la convivencia armónica y el respeto a los derechos humanos. | D4: PRDI25-29-Obj-126 | E4: Generar capacidades individuales y colectivas para la gestión pacífica de los conflictos, la convivencia respetuosa y la prevención de situaciones de violencia entre la comunidad universitaria. | F4: 13 | G4: Involucrar a 400 estudiantes en actividades comunitarias, proyectos de intervención social y programas extracurriculares orientados a la construcción de paz durante la administración | H4: ACT-PRDI-NS-3188 | J4: Actividad | K4: Sin fórmula | L4: Involucrar a estudiantes en actividades comunitarias, proyectos de intervención social y programas extracurriculares orientados a la construcción de paz | R4: =M4 -> 0 | S4: =N4 -> 0 | T4: =O4 -> 0 | U4: =P4 -> 0 | V4: =Q4 -> 0 | W4: Anual
A5: 3 | B5: PRDI25-29-Obj-53 | C5: Promover la construcción de una cultura de paz en la comunidad universitaria, mediante estrategias educativas, participativas y de sensibilización que fortalezcan la convivencia armónica y el respeto a los derechos humanos. | D5: PRDI25-29-Obj-127 | E5: Fomentar una cultura institucional de respeto e igualdad para prevenir conductas violentas dentro de los espacios universitarios. | F5: 14 | G5: Lograr que 100% de los espacios académicos, realicen actividades culturales con temáticas de igualdad de género y cultura de paz, durante la administración | H5: ACT-PRDI-NS-3244 | J5: Actividad | K5: Sin fórmula | L5: Realizar actividades culturales con temáticas de igualdad de género y cultura de paz | R5: =M5 -> 0 | S5: =N5 -> 0 | T5: =O5 -> 0 | U5: =P5 -> 0 | V5: =Q5 -> 0 | W5: Anual
A6: 4 | B6: PRDI25-29-Obj-53 | C6: Promover la construcción de una cultura de paz en la comunidad universitaria, mediante estrategias educativas, participativas y de sensibilización que fortalezcan la convivencia armónica y el respeto a los derechos humanos. | D6: PRDI25-29-Obj-127 | E6: Fomentar una cultura institucional de respeto e igualdad para prevenir conductas violentas dentro de los espacios universitarios. | F6: 15 | G6: Realizar 2 campañas anuales para difundir los protocolos institucionales de atención y prevención de violencias a toda la comunidad universitaria | H6: ACT-PRDI-NS-3189 | J6: Actividad | K6: Sin fórmula | L6: Realizar campañas para difundir los protocolos institucionales de atención y prevención de violencias a toda la comunidad universitaria | R6: =M6 -> 0 | S6: =N6 -> 0 | T6: =O6 -> 0 | U6: =P6 -> 0 | V6: =Q6 -> 0 | W6: Anual
A7: 5 | B7: PRDI25-29-Obj-53 | C7: Promover la construcción de una cultura de paz en la comunidad universitaria, mediante estrategias educativas, participativas y de sensibilización que fortalezcan la convivencia armónica y el respeto a los derechos humanos. | D7: PRDI25-29-Obj-128 | E7: Evaluar el impacto de las acciones implementadas para medir los avances en la construcción de una cultura de paz y la transformación de las relaciones interpersonales e institucionales. | F7: 18 | G7: Lograr la participación de 40% de la comunidad universitaria en actividades y programas que promuevan la convivencia pacífica, la inclusión y el respeto, durante la administración | H7: IND-PRDI-420 | J7: Indicador | K7: (Número de participantes en actividades y programas que promuevan la convivencia pacífica, la inclusión y el respeto/Número de integrantes de la comunidad universitaria)*100 | L7: Número de participantes en actividades y programas que promuevan la convivencia pacífica, la inclusión y el respeto | R7: =IF(M8,M7/M8*100,"0") -> 0 | S7: =IF(N8,N7/N8*100,"0") -> 0 | T7: =IF(O8,O7/O8*100,"0") -> 0 | U7: =IF(P8,P7/P8*100,"0") -> 0 | V7: =IF(Q8,Q7/Q8*100,"0") -> 0 | W7: Anual
L8: Número de integrantes de la comunidad universitaria
A9: 6 | B9: PRDI25-29-Obj-53 | C9: Promover la construcción de una cultura de paz en la comunidad universitaria, mediante estrategias educativas, participativas y de sensibilización que fortalezcan la convivencia armónica y el respeto a los derechos humanos. | D9: PRDI25-29-Obj-75 | E9: Fortalecer la educación para la paz, la no violencia y los derechos humanos para lograr la convivencia pacífica en los espacios universitarios. | F9: 3 | G9: Realizar 1 jornada anual sobre los 16 días de activismo con diversas actividades (conferencias, talleres, capacitaciones) presenciales y virtuales en los diversos espacios de la universidad | H9: ACT-PRDI-NS-2766 | J9: Actividad | K9: Sin fórmula | L9: Realizar jornadas sobre los 16 días de activismo con diversas actividades (conferencias, talleres, capacitaciones) presenciales y virtuales en los diversos espacios de la universidad | R9: =M9 -> 0 | S9: =N9 -> 0 | T9: =O9 -> 0 | U9: =P9 -> 0 | V9: =Q9 -> 0 | W9: Anual
A10: 7 | B10: PRDI25-29-Obj-53 | C10: Promover la construcción de una cultura de paz en la comunidad universitaria, mediante estrategias educativas, participativas y de sensibilización que fortalezcan la convivencia armónica y el respeto a los derechos humanos. | D10: PRDI25-29-Obj-75 | E10: Fortalecer la educación para la paz, la no violencia y los derechos humanos para lograr la convivencia pacífica en los espacios universitarios. | F10: 5 | G10: Publicar 30 contenidos anuales en las redes sociales oficiales sobre temas que promuevan la igualdad sustantiva, la prevención de las violencias, la inclusión, el cuidado y la cultura de paz | H10: ACT-PRDI-NS-3178 | J10: Actividad | K10: Sin fórmula | L10: Publicar contenidos en las redes sociales oficiales sobre temas que promuevan la igualdad sustantiva, la prevención de las violencias, la inclusión, el cuidado y la cultura de paz | R10: =M10 -> 0 | S10: =N10 -> 0 | T10: =O10 -> 0 | U10: =P10 -> 0 | V10: =Q10 -> 0 | W10: Anual

Sheet 20 Retribución social 
A1: N.P. | B1: Clave Objetivo General | C1: Objetivo General | D1: Clave Objetivo Específico | E1: Objetivo Específico | F1: No. de meta en el PRDI | G1: Meta PRDI | H1: Clave de la meta | I1: Meta del espacio académico | J1: Actividad/Indicador | K1: Método de cálculo | L1: Nombre de las variables | M1: Valor de las variables | R1: Valor de los indicadores | W1: Medición (anual o acumulada) | X1: Área responsable
M2: Ref. 2026 | N2: 2027 | O2: 2028 | P2: 2029 | Q2: 2030 | R2: Ref. 2026 | S2: 2027 | T2: 2028 | U2: 2029 | V2: 2030
A3: 1 | B3: PRDI25-29-Obj-54 | C3: Fomentar la vinculación estratégica de la Universidad con los sectores social, productivo y gubernamental, para el desarrollo de proyectos inclusivos y sostenibles, que favorezcan el desarrollo humano y la salud; fomenten las competencias profesionales; promuevan la conciencia ética, motiven la responsabilidad social, el interés colectivo; y sean promotores del desarrollo tecnológico y la innovación. | D3: PRDI2025-2029-Obj-76 | E3: Fortalecer las competencias emprendedoras y empresariales de la comunidad universitaria y la sociedad en general, para la creación y consolidación de proyectos innovadores, sostenibles y de alto impacto que contribuyan al desarrollo regional. | F3: 2 | G3: Coordinar cada año 15 eventos de emprendimiento con los responsables del Programa Emprendedor de todos los espacios académicos | H3: ACT-PRDI-NS-3103 | J3: Actividad | K3: Sin fórmula | L3: Coordinar eventos de emprendimiento con los responsables del Programa Emprendedor de todos los espacios académicos | R3: =M3 -> 0 | S3: =N3 -> 0 | T3: =O3 -> 0 | U3: =P3 -> 0 | V3: =Q3 -> 0 | W3: Anual
A4: 2 | B4: PRDI25-29-Obj-54 | C4: Fomentar la vinculación estratégica de la Universidad con los sectores social, productivo y gubernamental, para el desarrollo de proyectos inclusivos y sostenibles, que favorezcan el desarrollo humano y la salud; fomenten las competencias profesionales; promuevan la conciencia ética, motiven la responsabilidad social, el interés colectivo; y sean promotores del desarrollo tecnológico y la innovación. | D4: PRDI2025-2029-Obj-76 | E4: Fortalecer las competencias emprendedoras y empresariales de la comunidad universitaria y la sociedad en general, para la creación y consolidación de proyectos innovadores, sostenibles y de alto impacto que contribuyan al desarrollo regional. | F4: 6 | G4: Realizar 8 pláticas o talleres al año para desarrollar proyectos de negocio, innovación y desarrollo tecnológico, dirigidos a la comunidad universitaria y abiertos a la sociedad en general | H4: ACT-PRDI-NS-3107 | J4: Actividad | K4: Sin fórmula | L4: Realizar pláticas o talleres para desarrollar proyectos de negocio, innovación y desarrollo tecnológico, dirigidos a la comunidad universitaria y abiertos a la sociedad en general | R4: =M4 -> 0 | S4: =N4 -> 0 | T4: =O4 -> 0 | U4: =P4 -> 0 | V4: =Q4 -> 0 | W4: Anual
A5: 3 | B5: PRDI25-29-Obj-54 | C5: Fomentar la vinculación estratégica de la Universidad con los sectores social, productivo y gubernamental, para el desarrollo de proyectos inclusivos y sostenibles, que favorezcan el desarrollo humano y la salud; fomenten las competencias profesionales; promuevan la conciencia ética, motiven la responsabilidad social, el interés colectivo; y sean promotores del desarrollo tecnológico y la innovación. | D5: PRDI25-29-Obj-129 | E5: Promover el desarrollo humano, económico, social y medioambiental de las comunidades, especialmente de los grupos sociales minoritarios o vulnerables, a partir de la intervención universitaria, inter y multidisciplinaria. | F5: 12 | G5: Capacitar al año a 250 universitarios y público en general en temas relacionados con la economía social y solidaria | H5: ACT-PRDI-NS-3113 | J5: Actividad | K5: Sin fórmula | L5: Capacitar a universitarios y público en general en temas relacionados con la economía social y solidaria | R5: =M5 -> 0 | S5: =N5 -> 0 | T5: =O5 -> 0 | U5: =P5 -> 0 | V5: =Q5 -> 0 | W5: Anual
A6: 4 | B6: PRDI25-29-Obj-54 | C6: Fomentar la vinculación estratégica de la Universidad con los sectores social, productivo y gubernamental, para el desarrollo de proyectos inclusivos y sostenibles, que favorezcan el desarrollo humano y la salud; fomenten las competencias profesionales; promuevan la conciencia ética, motiven la responsabilidad social, el interés colectivo; y sean promotores del desarrollo tecnológico y la innovación. | D6: PRDI25-29-Obj-129 | E6: Promover el desarrollo humano, económico, social y medioambiental de las comunidades, especialmente de los grupos sociales minoritarios o vulnerables, a partir de la intervención universitaria, inter y multidisciplinaria. | F6: 14 | G6: Atender 40 proyectos de economía social y solidaria en el territorio mexiquense al cierre de la administración | H6: ACT-PRDI-NS-2755 | J6: Actividad | K6: Sin fórmula | L6: Atender proyectos de economía social y solidaria en el territorio mexiquense | R6: =M6 -> 0 | S6: =N6 -> 0 | T6: =O6 -> 0 | U6: =P6 -> 0 | V6: =Q6 -> 0 | W6: Anual
A7: 5 | B7: PRDI25-29-Obj-54 | C7: Fomentar la vinculación estratégica de la Universidad con los sectores social, productivo y gubernamental, para el desarrollo de proyectos inclusivos y sostenibles, que favorezcan el desarrollo humano y la salud; fomenten las competencias profesionales; promuevan la conciencia ética, motiven la responsabilidad social, el interés colectivo; y sean promotores del desarrollo tecnológico y la innovación. | D7: PRDI25-29-Obj-129 | E7: Promover el desarrollo humano, económico, social y medioambiental de las comunidades, especialmente de los grupos sociales minoritarios o vulnerables, a partir de la intervención universitaria, inter y multidisciplinaria. | F7: 15 | G7: Ejecutar 6 colaboraciones de impacto social con organizaciones locales o sectores productivos de mediano y largo plazo durante la administración | H7: ACT-PRDI-NS-3115 | J7: Actividad | K7: Sin fórmula | L7: Ejecutar colaboraciones de impacto social con organizaciones locales o sectores productivos de mediano y largo plazo | R7: =M7 -> 0 | S7: =N7 -> 0 | T7: =O7 -> 0 | U7: =P7 -> 0 | V7: =Q7 -> 0 | W7: Anual
A8: 6 | B8: PRDI25-29-Obj-54 | C8: Fomentar la vinculación estratégica de la Universidad con los sectores social, productivo y gubernamental, para el desarrollo de proyectos inclusivos y sostenibles, que favorezcan el desarrollo humano y la salud; fomenten las competencias profesionales; promuevan la conciencia ética, motiven la responsabilidad social, el interés colectivo; y sean promotores del desarrollo tecnológico y la innovación. | D8: PRDI25-29-Obj-129 | E8: Promover el desarrollo humano, económico, social y medioambiental de las comunidades, especialmente de los grupos sociales minoritarios o vulnerables, a partir de la intervención universitaria, inter y multidisciplinaria. | F8: 16 | G8: Lograr cada año la participación de 35 espacios académicos en servicios comunitarios de beneficio social y proyectos de Brigadas Universitarias Multidisciplinarias (BUM TUAEMEX) | H8: ACT-PRDI-NS-3116 | J8: Actividad | K8: Sin fórmula | L8: Lograr la participación de espacios académicos en servicios comunitarios de beneficio social y proyectos de Brigadas Universitarias Multidisciplinarias (BUM TUUAEMEX) | R8: =M8 -> 0 | S8: =N8 -> 0 | T8: =O8 -> 0 | U8: =P8 -> 0 | V8: =Q8 -> 0 | W8: Anual
A9: 7 | B9: PRDI25-29-Obj-54 | C9: Fomentar la vinculación estratégica de la Universidad con los sectores social, productivo y gubernamental, para el desarrollo de proyectos inclusivos y sostenibles, que favorezcan el desarrollo humano y la salud; fomenten las competencias profesionales; promuevan la conciencia ética, motiven la responsabilidad social, el interés colectivo; y sean promotores del desarrollo tecnológico y la innovación. | D9: PRDI25-29-Obj-130 | E9: PRDI25-29-Obj-130 -Impulsar la colaboración con instancias de los sectores público y privado para fortalecer el desarrollo de competencias profesionales, transversales y complementarias en el estudiantado, favorecer su empleabilidad y contribuir al progreso socialmente responsable. | F9: 20 | G9: Incrementar 5% al año la participación de universitarios en el Programa de Competencias Laborales | H9: IND-PRDI-410 | J9: Indicador | K9: ((Número de universitarios participantes en el programa de competencias laborales en el año actual/Número de universitarios participantes en el programa de competencias laborales en el año anterior)-1)*100 | L9: Número de universitarios participantes en el programa de competencias laborales en el año actual | R9: =IF(M10,((M9/M10)-1)*100,"0") -> 0 | S9: =IF(N10,((N9/N10)-1)*100,"0") -> 0 | T9: =IF(O10,((O9/O10)-1)*100,"0") -> 0 | U9: =IF(P10,((P9/P10)-1)*100,"0") -> 0 | V9: =IF(Q10,((Q9/Q10)-1)*100,"0") -> 0 | W9: Anual
L10: Número de universitarios participantes en el programa de competencias laborales en el año anterior
A11: 8 | B11: PRDI25-29-Obj-54 | C11: Fomentar la vinculación estratégica de la Universidad con los sectores social, productivo y gubernamental, para el desarrollo de proyectos inclusivos y sostenibles, que favorezcan el desarrollo humano y la salud; fomenten las competencias profesionales; promuevan la conciencia ética, motiven la responsabilidad social, el interés colectivo; y sean promotores del desarrollo tecnológico y la innovación. | D11: PRDI25-29-Obj-130 | E11: Impulsar la colaboración con instancias de los sectores público y privado para fortalecer el desarrollo de competencias profesionales, transversales y complementarias en el estudiantado, favorecer su empleabilidad y contribuir al progreso socialmente responsable. | F11: 25 | G11: Mantener 35 colaboraciones al año con empresas, instituciones y organizaciones para el Catálogo de descuentos universitarios | H11: ACT-PRDI-NS-3125 | J11: Actividad | K11: Sin fórmula | L11: Mantener colaboraciones con empresas, instituciones y organizaciones para el Catálogo de descuentos universitarios | R11: =M11 -> 0 | S11: =N11 -> 0 | T11: =O11 -> 0 | U11: =P11 -> 0 | V11: =Q11 -> 0 | W11: Anual
A12: 9 | B12: PRDI25-29-Obj-54 | C12: Fomentar la vinculación estratégica de la Universidad con los sectores social, productivo y gubernamental, para el desarrollo de proyectos inclusivos y sostenibles, que favorezcan el desarrollo humano y la salud; fomenten las competencias profesionales; promuevan la conciencia ética, motiven la responsabilidad social, el interés colectivo; y sean promotores del desarrollo tecnológico y la innovación. | D12: PRDI25-29-Obj-131 | E12: Fortalecer la formación, evaluación y certificación lingüística para impulsar la empleabilidad, la movilidad académica y la proyección cultural de la comunidad universitaria y la sociedad. | F12: 37 | G12: Aperturar anualmente 1 grupo de lenguas originarias en algún espacio universitario, CELE o extensión de CELE | H12: ACT-PRDI-NS-3135 | J12: Actividad | K12: Sin fórmula | L12: Aperturar grupos de lenguas originarias en algún espacio universitario, CELE o extensión de CELE | R12: =M12 -> 0 | S12: =N12 -> 0 | T12: =O12 -> 0 | U12: =P12 -> 0 | V12: =Q12 -> 0 | W12: Anual
A13: 10 | B13: PRDI25-29-Obj-54 | C13: Fomentar la vinculación estratégica de la Universidad con los sectores social, productivo y gubernamental, para el desarrollo de proyectos inclusivos y sostenibles, que favorezcan el desarrollo humano y la salud; fomenten las competencias profesionales; promuevan la conciencia ética, motiven la responsabilidad social, el interés colectivo; y sean promotores del desarrollo tecnológico y la innovación. | D13: PRDI25-29-Obj-132 | E13: PRDI25-29-Obj-132 -Fortalecer la promoción, prevención y atención a la salud de primer nivel para mejorar el bienestar integral y la calidad de vida de la comunidad universitaria y la sociedad mexiquense. | F13: 42 | G13: Lograr que 100% de los espacios académicos cuenten con servicios de Atención Psicológica al cierre de la administración | H13: ACT-PRDI-NS-3245 | J13: Actividad | K13: Sin fórmula | L13: Contar con el Servicio de Atención Psicologíca | R13: =M13 -> 0 | S13: =N13 -> 0 | T13: =O13 -> 0 | U13: =P13 -> 0 | V13: =Q13 -> 0 | W13: Anual

Sheet 21 Comunicación universitaria
A1: N.P. | B1: Clave Objetivo General | C1: Objetivo General | D1: Clave Objetivo Específico | E1: Objetivo Específico | F1: No. de meta en el PRDI | G1: Meta PRDI | H1: Clave de la meta | I1: Meta del espacio académico | J1: Actividad/Indicador | K1: Método de cálculo | L1: Nombre de las variables | M1: Valor de las variables | R1: Valor de los indicadores | W1: Medición (anual o acumulada) | X1: Área responsable
M2: Ref. 2026 | N2: 2027 | O2: 2028 | P2: 2029 | Q2: 2030 | R2: Ref. 2026 | S2: 2027 | T2: 2028 | U2: 2029 | V2: 2030
A3: 1 | B3: PRDI25-29-Obj-55 | C3: Promover una comunicación social efectiva y cercana que fortalezca la identidad institucional de la uaemex, impulsando la inclusión y el diálogo abierto con toda la comunidad universitaria y la sociedad, a fin de difundir y consolidar valores que contribuyan al desarrollo académico, cultural y social. | D3: PRDI25-29-Obj-77 | E3: Impulsar canales efectivos de comunicación que faciliten el diálogo continuo con la comunidad universitaria, promoviendo la participación, la difusión de logros y el empleo de plataformas tecnológicas modernas. | F3: 2 | G3: Realizar 3 campañas anuales que promuevan los valores universitarios de cercanía, inclusión y progresismo tanto en medios impresos como digitales | H3: ACT-PRDI-NS-2723 | J3: Actividad | K3: Sin fórmula | L3: Realizar campañas que promuevan los valores universitarios de cercanía, inclusión y progresismo tanto en medios impresos como digitales en apego al enfoque institucional | R3: =M3 -> 0 | S3: =N3 -> 0 | T3: =O3 -> 0 | U3: =P3 -> 0 | V3: =Q3 -> 0 | W3: Anual

Sheet 22 Sostenibilidad ambiental 
A1: N.P. | B1: Clave Objetivo General | C1: Objetivo General | D1: Clave Objetivo Específico | E1: Objetivo Específico | F1: No. de meta en el PRDI | G1: Meta PRDI | H1: Clave de la meta | I1: Meta del espacio académico | J1: Actividad/Indicador | K1: Método de cálculo | L1: Nombre de las variables | M1: Valor de las variables | R1: Valor de los indicadores | W1: Medición (anual o acumulada) | X1: Área responsable
M2: Ref. 2026 | N2: 2027 | O2: 2028 | P2: 2029 | Q2: 2030 | R2: Ref. 2026 | S2: 2027 | T2: 2028 | U2: 2029 | V2: 2030
A3: 1 | B3: PRDI25-29-Obj-56 | C3: PRDI25-29-Obj-56 -Fortalecer una cultura de respeto mediante la educación ambiental, que permita la conservación y protección del medio ambiente entre la comunidad universitaria, para alcanzar el desarrollo sostenible. | D3: PRDI2025-2029-Obj-78 | E3: PRDI2025-2029-Obj-78 -Impulsar acciones sustentables para reducir el impacto negativo en el medio ambiente, ocasionado por las funciones sustantivas y adjetivas de la Institución. | F3: 7 | G3: Establecer 1 programa de reducción del uso de unicel y desechables | H3: ACT-PRDI-NS-3154 | J3: Actividad | K3: Sin fórmula | L3: Establecer un programa de reducción del uso de unicel y desechables | R3: =M3 -> 0 | S3: =N3 -> 0 | T3: =O3 -> 0 | U3: =P3 -> 0 | V3: =Q3 -> 0 | W3: Anual
A4: 2 | B4: PRDI25-29-Obj-56 | C4: PRDI25-29-Obj-56 -Fortalecer una cultura de respeto mediante la educación ambiental, que permita la conservación y protección del medio ambiente entre la comunidad universitaria, para alcanzar el desarrollo sostenible. | D4: PRDI2025-2029-Obj-78 | E4: PRDI2025-2029-Obj-78 -Impulsar acciones sustentables para reducir el impacto negativo en el medio ambiente, ocasionado por las funciones sustantivas y adjetivas de la Institución. | F4: 8 | G4: Operar anualmente 1 campaña de acopio de residuos de aceite vegetal-comestible generado en las cafeterías de los espacios académicos y cocinas de la Licenciatura en Gastronomía | H4: ACT-PRDI-NS-3155 | J4: Actividad | K4: Sin fórmula | L4: Operar campañas de acopio de residuos de aceite vegetal-comestible generado en las cafeterías de los espacios académicos | R4: =M4 -> 0 | S4: =N4 -> 0 | T4: =O4 -> 0 | U4: =P4 -> 0 | V4: =Q4 -> 0 | W4: Anual
A5: 3 | B5: PRDI25-29-Obj-56 | C5: PRDI25-29-Obj-56 -Fortalecer una cultura de respeto mediante la educación ambiental, que permita la conservación y protección del medio ambiente entre la comunidad universitaria, para alcanzar el desarrollo sostenible. | D5: PRDI2025-2029-Obj-78 | E5: PRDI2025-2029-Obj-78 -Impulsar acciones sustentables para reducir el impacto negativo en el medio ambiente, ocasionado por las funciones sustantivas y adjetivas de la Institución. | F5: 10 | G5: Realizar anualmente 1 campaña institucional de reforestación que incluya las 4 regiones con presencia universitaria | H5: ACT-PRDI-NS-3157 | J5: Actividad | K5: Sin fórmula | L5: Realizar campañas institucionales de reforestación que incluya las regiones con presencia universitaria | R5: =M5 -> 0 | S5: =N5 -> 0 | T5: =O5 -> 0 | U5: =P5 -> 0 | V5: =Q5 -> 0 | W5: Anual
A6: 4 | B6: PRDI25-29-Obj-56 | C6: PRDI25-29-Obj-56 -Fortalecer una cultura de respeto mediante la educación ambiental, que permita la conservación y protección del medio ambiente entre la comunidad universitaria, para alcanzar el desarrollo sostenible. | D6: PRDI2025-2029-Obj-78 | E6: PRDI2025-2029-Obj-78 -Impulsar acciones sustentables para reducir el impacto negativo en el medio ambiente, ocasionado por las funciones sustantivas y adjetivas de la Institución. | F6: 13 | G6: Operar anualmente 1 programa de mantenimiento y fortalecimiento de huertos universitarios | H6: ACT-PRDI-NS-3161 | J6: Actividad | K6: Sin fórmula | L6: Operar un programa de mantenimiento y fortalecimiento de huertos universitarios | R6: =M6 -> 0 | S6: =N6 -> 0 | T6: =O6 -> 0 | U6: =P6 -> 0 | V6: =Q6 -> 0 | W6: Anual
A7: 5 | B7: PRDI25-29-Obj-56 | C7: PRDI25-29-Obj-56 -Fortalecer una cultura de respeto mediante la educación ambiental, que permita la conservación y protección del medio ambiente entre la comunidad universitaria, para alcanzar el desarrollo sostenible. | D7: PRDI2025-2029-Obj-78 | E7: PRDI2025-2029-Obj-78 -Impulsar acciones sustentables para reducir el impacto negativo en el medio ambiente, ocasionado por las funciones sustantivas y adjetivas de la Institución. | F7: 15 | G7: Lograr que 100% de los espacios académicos operen el Plan Institucional de Manejo de Residuos Sólidos Urbanos a 2029 | H7: ACT-PRDI-NS-3247 | J7: Actividad | K7: Sin fórmula | L7: Operar el plan de manejo de residuos sólidos urbano | R7: =M7 -> 0 | S7: =N7 -> 0 | T7: =O7 -> 0 | U7: =P7 -> 0 | V7: =Q7 -> 0 | W7: Anual
A8: 6 | B8: PRDI25-29-Obj-56 | C8: PRDI25-29-Obj-56 -Fortalecer una cultura de respeto mediante la educación ambiental, que permita la conservación y protección del medio ambiente entre la comunidad universitaria, para alcanzar el desarrollo sostenible. | D8: PRDI2025-2029-Obj-78 | E8: PRDI2025-2029-Obj-78 -Impulsar acciones sustentables para reducir el impacto negativo en el medio ambiente, ocasionado por las funciones sustantivas y adjetivas de la Institución. | F8: 16 | G8: Promover en 22 espacios académicos el proceso de compostaje de los residuos orgánicos de poda y jardinería a 2029 | H8: ACT-PRDI-NS-3163 | J8: Actividad | K8: Sin fórmula | L8: Promover en espacios académicos el proceso de compostaje de los residuos orgánicos de poda y jardinería | R8: =M8 -> 0 | S8: =N8 -> 0 | T8: =O8 -> 0 | U8: =P8 -> 0 | V8: =Q8 -> 0 | W8: Anual
A9: 7 | B9: PRDI25-29-Obj-56 | C9: PRDI25-29-Obj-56 -Fortalecer una cultura de respeto mediante la educación ambiental, que permita la conservación y protección del medio ambiente entre la comunidad universitaria, para alcanzar el desarrollo sostenible. | D9: PRDI25-29-Obj-135 | E9: PRDI25-29-Obj-135 -Formar agentes universitarios de cambio comprometidos para la construcción de un medio ambiente sostenible. | F9: 1 | G9: Capacitar anualmente a 1 736 estudiantes de nivel superior en temas de sustentabilidad | H9: ACT-PRDI-NS-2747 | J9: Actividad | K9: Sin fórmula | L9: Capacitar a estudiantes de nivel superior en temas de sustentabilidad | R9: =M9 -> 0 | S9: =N9 -> 0 | T9: =O9 -> 0 | U9: =P9 -> 0 | V9: =Q9 -> 0 | W9: Anual
A10: 8 | B10: PRDI25-29-Obj-56 | C10: PRDI25-29-Obj-56 -Fortalecer una cultura de respeto mediante la educación ambiental, que permita la conservación y protección del medio ambiente entre la comunidad universitaria, para alcanzar el desarrollo sostenible. | D10: PRDI25-29-Obj-135 | E10: PRDI25-29-Obj-135 -Formar agentes universitarios de cambio comprometidos para la construcción de un medio ambiente sostenible. | F10: 3 | G10: Capacitar a 1 034 integrantes del personal docente en temas de sustentabilidad a 2029 | H10: ACT-PRDI-NS-2392 | J10: Actividad | K10: Sin fórmula | L10: Capacitar a académicos en temas de sustentabilidad | R10: =M10 -> 0 | S10: =N10 -> 0 | T10: =O10 -> 0 | U10: =P10 -> 0 | V10: =Q10 -> 0 | W10: Anual
A11: 9 | B11: PRDI25-29-Obj-56 | C11: PRDI25-29-Obj-56 -Fortalecer una cultura de respeto mediante la educación ambiental, que permita la conservación y protección del medio ambiente entre la comunidad universitaria, para alcanzar el desarrollo sostenible. | D11: PRDI25-29-Obj-135 | E11: PRDI25-29-Obj-135 -Formar agentes universitarios de cambio comprometidos para la construcción de un medio ambiente sostenible. | F11: 4 | G11: Capacitar a 2 115 integrantes del personal administrativo en temas de sustentabilidad a 2029 | H11: ACT-PRDI-NS-2391 | J11: Actividad | K11: Sin fórmula | L11: Capacitar a administrativos en temas de sustentabilidad | R11: =M11 -> 0 | S11: =N11 -> 0 | T11: =O11 -> 0 | U11: =P11 -> 0 | V11: =Q11 -> 0 | W11: Anual
A12: 10 | B12: PRDI25-29-Obj-56 | C12: PRDI25-29-Obj-56 -Fortalecer una cultura de respeto mediante la educación ambiental, que permita la conservación y protección del medio ambiente entre la comunidad universitaria, para alcanzar el desarrollo sostenible. | D12: PRDI25-29-Obj-136 | E12: PRDI25-29-Obj-136 -Desarrollar una cultura de sustentabilidad, aplicable a las funciones adjetivas y sustantivas de la Universidad para contribuir al uso eficiente de los recursos. | F12: 21 | G12: Implementar 1 programa de cuidado y ahorro de agua en 100% de los espacios universitarios a 2029 | H12: ACT-PRDI-NS-3248 | J12: Actividad | K12: Sin fórmula | L12: Implementar un programa de cuidado y ahorro de agua | R12: =M12 -> 0 | S12: =N12 -> 0 | T12: =O12 -> 0 | U12: =P12 -> 0 | V12: =Q12 -> 0 | W12: Anual
A13: 11 | B13: PRDI25-29-Obj-56 | C13: PRDI25-29-Obj-56 -Fortalecer una cultura de respeto mediante la educación ambiental, que permita la conservación y protección del medio ambiente entre la comunidad universitaria, para alcanzar el desarrollo sostenible. | D13: PRDI25-29-Obj-136 | E13: PRDI25-29-Obj-136 -Desarrollar una cultura de sustentabilidad, aplicable a las funciones adjetivas y sustantivas de la Universidad para contribuir al uso eficiente de los recursos. | F13: 22 | G13: Ejecutar anualmente 1 programa institucional de eficiencia energética | H13: ACT-PRDI-NS-3170 | J13: Actividad | K13: Sin fórmula | L13: Ejecutar el programa institucional de eficiencia energética | R13: =M13 -> 0 | S13: =N13 -> 0 | T13: =O13 -> 0 | U13: =P13 -> 0 | V13: =Q13 -> 0 | W13: Anual
A14: 12 | B14: PRDI25-29-Obj-56 | C14: PRDI25-29-Obj-56 -Fortalecer una cultura de respeto mediante la educación ambiental, que permita la conservación y protección del medio ambiente entre la comunidad universitaria, para alcanzar el desarrollo sostenible. | D14: PRDI25-29-Obj-136 | E14: PRDI25-29-Obj-136 -Desarrollar una cultura de sustentabilidad, aplicable a las funciones adjetivas y sustantivas de la Universidad para contribuir al uso eficiente de los recursos. | F14: 23 | G14: Efectuar anualmente 1 programa institucional de reducción de uso de papel | H14: ACT-PRDI-NS-3171 | J14: Actividad | K14: Sin fórmula | L14: Efectua rel programa institucional de reducción de uso de papel | R14: =M14 -> 0 | S14: =N14 -> 0 | T14: =O14 -> 0 | U14: =P14 -> 0 | V14: =Q14 -> 0 | W14: Anual

Sheet Indicadores x proyec
A4: I. Estudiantado con oportunidades para su pleno desarrollo personal
A5: 2. Estudiantado con oportunidades para su pleno desarrollo y pertinencia en los estudios profesionales
A6: Num Progresivo de meta | B6: Meta | C6: Valor de los indicadores | I6: Medición (anual o acumulada) | J6: Área responsable
C7: Ref. 2025 | D7: 2026 | E7: 2027 | F7: 2028 | G7: 2029 | H7: 2030
A8: 3 | B8: ='2 EstudiantadoEstProf'!I5 -> 0 | C8: ='2 EstudiantadoEstProf'!#REF! -> #REF! | D8: ='2 EstudiantadoEstProf'!R5 -> 0 | E8: ='2 EstudiantadoEstProf'!S5 -> 0 | F8: ='2 EstudiantadoEstProf'!T5 -> 0 | G8: ='2 EstudiantadoEstProf'!U5 -> 0 | H8: ='2 EstudiantadoEstProf'!V5 -> 0 | I8: ='2 EstudiantadoEstProf'!W3 -> Anual | J8: ='2 EstudiantadoEstProf'!X5 -> 0
A10: 4 | B10: ='2 EstudiantadoEstProf'!I7 -> 0 | C10: ='2 EstudiantadoEstProf'!#REF! -> #REF! | D10: ='2 EstudiantadoEstProf'!R7 -> 0 | E10: ='2 EstudiantadoEstProf'!S7 -> 0 | F10: ='2 EstudiantadoEstProf'!T7 -> 0 | G10: ='2 EstudiantadoEstProf'!U7 -> 0 | H10: ='2 EstudiantadoEstProf'!V7 -> 0 | I10: ='2 EstudiantadoEstProf'!W5 -> Anual | J10: ='2 EstudiantadoEstProf'!X7 -> 0
A12: 5 | B12: ='2 EstudiantadoEstProf'!I9 -> 0 | C12: ='2 EstudiantadoEstProf'!#REF! -> #REF! | D12: ='2 EstudiantadoEstProf'!R9 -> 0 | E12: ='2 EstudiantadoEstProf'!S9 -> 0 | F12: ='2 EstudiantadoEstProf'!T9 -> 0 | G12: ='2 EstudiantadoEstProf'!U9 -> 0 | H12: ='2 EstudiantadoEstProf'!V9 -> 0 | I12: ='2 EstudiantadoEstProf'!W9 -> Anual | J12: ='2 EstudiantadoEstProf'!X9 -> 0
A14: 8 | B14: ='2 EstudiantadoEstProf'!I13 -> 0 | C14: ='2 EstudiantadoEstProf'!#REF! -> #REF! | D14: ='2 EstudiantadoEstProf'!R13 -> 0 | E14: ='2 EstudiantadoEstProf'!S13 -> 0 | F14: ='2 EstudiantadoEstProf'!T13 -> 0 | G14: ='2 EstudiantadoEstProf'!U13 -> 0 | H14: ='2 EstudiantadoEstProf'!V13 -> 0 | I14: ='2 EstudiantadoEstProf'!W13 -> Anual | J14: ='2 EstudiantadoEstProf'!X13 -> 0
A16: 12 | B16: ='2 EstudiantadoEstProf'!I18 -> 0 | C16: ='2 EstudiantadoEstProf'!#REF! -> #REF! | D16: ='2 EstudiantadoEstProf'!R18 -> 0 | E16: ='2 EstudiantadoEstProf'!S18 -> 0 | F16: ='2 EstudiantadoEstProf'!T18 -> 0 | G16: ='2 EstudiantadoEstProf'!U18 -> 0 | H16: ='2 EstudiantadoEstProf'!V18 -> 0 | I16: ='2 EstudiantadoEstProf'!W18 -> Anual | J16: ='2 EstudiantadoEstProf'!X18 -> 0
A18: 18 | B18: ='2 EstudiantadoEstProf'!I24 -> 0 | C18: ='2 EstudiantadoEstProf'!#REF! -> #REF! | D18: ='2 EstudiantadoEstProf'!R24 -> 0 | E18: ='2 EstudiantadoEstProf'!S24 -> 0 | F18: ='2 EstudiantadoEstProf'!T24 -> 0 | G18: ='2 EstudiantadoEstProf'!U24 -> 0 | H18: ='2 EstudiantadoEstProf'!V24 -> 0 | I18: ='2 EstudiantadoEstProf'!W24 -> Anual | J18: ='2 EstudiantadoEstProf'!X24 -> 0
A20: 20 | B20: ='2 EstudiantadoEstProf'!I27 -> 0 | C20: ='2 EstudiantadoEstProf'!#REF! -> #REF! | D20: ='2 EstudiantadoEstProf'!R27 -> 0 | E20: ='2 EstudiantadoEstProf'!S27 -> 0 | F20: ='2 EstudiantadoEstProf'!T27 -> 0 | G20: ='2 EstudiantadoEstProf'!U27 -> 0 | H20: ='2 EstudiantadoEstProf'!V27 -> 0 | I20: ='2 EstudiantadoEstProf'!W27 -> Anual | J20: ='2 EstudiantadoEstProf'!X27 -> 0
A22: 21 | B22: ='2 EstudiantadoEstProf'!I29 -> 0 | C22: ='2 EstudiantadoEstProf'!#REF! -> #REF! | D22: ='2 EstudiantadoEstProf'!R29 -> 0 | E22: ='2 EstudiantadoEstProf'!S29 -> 0 | F22: ='2 EstudiantadoEstProf'!T29 -> 0 | G22: ='2 EstudiantadoEstProf'!U29 -> 0 | H22: ='2 EstudiantadoEstProf'!V29 -> 0 | I22: ='2 EstudiantadoEstProf'!W29 -> Anual | J22: ='2 EstudiantadoEstProf'!X29 -> 0
A26: 23 | B26: ='2 EstudiantadoEstProf'!I34 -> 0 | C26: ='2 EstudiantadoEstProf'!#REF! -> #REF! | D26: ='2 EstudiantadoEstProf'!R34 -> 0 | E26: ='2 EstudiantadoEstProf'!S34 -> 0 | F26: ='2 EstudiantadoEstProf'!T34 -> 0 | G26: ='2 EstudiantadoEstProf'!U34 -> 0 | H26: ='2 EstudiantadoEstProf'!V34 -> 0 | I26: ='2 EstudiantadoEstProf'!W34 -> Anual | J26: ='2 EstudiantadoEstProf'!X34 -> 0
A29: 3. Estudios avanzados de excelencia y pertinencia social
A30: Num Progresivo de meta | B30: Meta | C30: Valor de los indicadores | I30: Medición (anual o acumulada) | J30: Área responsable
C31: Ref. 2025 | D31: 2026 | E31: 2027 | F31: 2028 | G31: 2029 | H31: 2030
A32: 7 | B32: ='3 Est avanzados excelencia'!I9 -> 0 | C32: ='3 Est avanzados excelencia'!#REF! -> #REF! | D32: ='3 Est avanzados excelencia'!R9 -> 0 | E32: ='3 Est avanzados excelencia'!S9 -> 0 | F32: ='3 Est avanzados excelencia'!T9 -> 0 | G32: ='3 Est avanzados excelencia'!U9 -> 0 | H32: ='3 Est avanzados excelencia'!V9 -> 0 | I32: ='3 Est avanzados excelencia'!W9 -> Anual | J32: ='3 Est avanzados excelencia'!X9 -> 0
A35: 4. Investigación abierta, inclusiva, equitativa y de calidad
A36: Num Progresivo de meta | B36: Meta | C36: Valor de los indicadores | I36: Medición (anual o acumulada) | J36: Área responsable
C37: Ref. 2025 | D37: 2026 | E37: 2027 | F37: 2028 | G37: 2029 | H37: 2030
A38: 2 | B38: ='4 Investigación abierta'!I4 -> 0 | C38: ='4 Investigación abierta'!#REF! -> #REF! | D38: ='4 Investigación abierta'!R4 -> 0 | E38: ='4 Investigación abierta'!S4 -> 0 | F38: ='4 Investigación abierta'!T4 -> 0 | G38: ='4 Investigación abierta'!U4 -> 0 | H38: ='4 Investigación abierta'!V4 -> 0 | I38: ='4 Investigación abierta'!W4 -> Anual | J38: ='4 Investigación abierta'!X4 -> 0
A40: 3 | B40: ='4 Investigación abierta'!I6 -> 0 | C40: ='4 Investigación abierta'!#REF! -> #REF! | D40: ='4 Investigación abierta'!R6 -> 0 | E40: ='4 Investigación abierta'!S6 -> 0 | F40: ='4 Investigación abierta'!T6 -> 0 | G40: ='4 Investigación abierta'!U6 -> 0 | H40: ='4 Investigación abierta'!V6 -> 0 | I40: ='4 Investigación abierta'!W6 -> Anual | J40: ='4 Investigación abierta'!X6 -> 0
A42: 4 | B42: ='4 Investigación abierta'!I8 -> 0 | C42: ='4 Investigación abierta'!#REF! -> #REF! | D42: ='4 Investigación abierta'!R8 -> 0 | E42: ='4 Investigación abierta'!S8 -> 0 | F42: ='4 Investigación abierta'!T8 -> 0 | G42: ='4 Investigación abierta'!U8 -> 0 | H42: ='4 Investigación abierta'!V8 -> 0 | I42: ='4 Investigación abierta'!W8 -> Anual | J42: ='4 Investigación abierta'!X8 -> 0
A44: 7 | B44: ='4 Investigación abierta'!I12 -> 0 | C44: ='4 Investigación abierta'!#REF! -> #REF! | D44: ='4 Investigación abierta'!R12 -> 0 | E44: ='4 Investigación abierta'!S12 -> 0 | F44: ='4 Investigación abierta'!T12 -> 0 | G44: ='4 Investigación abierta'!U12 -> 0 | H44: ='4 Investigación abierta'!V12 -> 0 | I44: ='4 Investigación abierta'!W12 -> Anual | J44: ='4 Investigación abierta'!X12 -> 0
A46: 8 | B46: ='4 Investigación abierta'!I14 -> 0 | C46: ='4 Investigación abierta'!#REF! -> #REF! | D46: ='4 Investigación abierta'!R14 -> 0 | E46: ='4 Investigación abierta'!S14 -> 0 | F46: ='4 Investigación abierta'!T14 -> 0 | G46: ='4 Investigación abierta'!U14 -> 0 | H46: ='4 Investigación abierta'!V14 -> 0 | I46: ='4 Investigación abierta'!W14 -> Anual | J46: ='4 Investigación abierta'!X14 -> 0
A49: 8 Deporte universitario
A50: Num Progresivo de meta | B50: Meta | C50: Valor de los indicadores | I50: Medición (anual o acumulada) | J50: Área responsable
C51: Ref. 2025 | D51: 2026 | E51: 2027 | F51: 2028 | G51: 2029 | H51: 2030
A52: 2 | B52: ='8 Deporte universitario'!I4 -> 0 | C52: ='8 Deporte universitario'!#REF! -> #REF! | D52: ='8 Deporte universitario'!R4 -> 0 | E52: ='8 Deporte universitario'!S4 -> 0 | F52: ='8 Deporte universitario'!T4 -> 0 | G52: ='8 Deporte universitario'!U4 -> 0 | H52: ='8 Deporte universitario'!V4 -> 0 | I52: ='8 Deporte universitario'!W4 -> Anual | J52: ='8 Deporte universitario'!X4 -> 0
A54: 3 | B54: ='8 Deporte universitario'!I6 -> 0 | C54: ='8 Deporte universitario'!#REF! -> #REF! | D54: ='8 Deporte universitario'!R6 -> 0 | E54: ='8 Deporte universitario'!S6 -> 0 | F54: ='8 Deporte universitario'!T6 -> 0 | G54: ='8 Deporte universitario'!U6 -> 0 | H54: ='8 Deporte universitario'!V6 -> 0 | I54: ='8 Deporte universitario'!W6 -> Anual | J54: ='8 Deporte universitario'!X6 -> 0
A56: 4 | B56: ='8 Deporte universitario'!I8 -> 0 | C56: ='8 Deporte universitario'!#REF! -> #REF! | D56: ='8 Deporte universitario'!R8 -> 0 | E56: ='8 Deporte universitario'!S8 -> 0 | F56: ='8 Deporte universitario'!T8 -> 0 | G56: ='8 Deporte universitario'!U8 -> 0 | H56: ='8 Deporte universitario'!V8 -> 0 | I56: ='8 Deporte universitario'!W8 -> Anual | J56: ='8 Deporte universitario'!X8 -> 0
A59: 9 Fortalecimiento de la formación integral del docente
A60: Num Progresivo de meta | B60: Meta | C60: Valor de los indicadores | I60: Medición (anual o acumulada) | J60: Área responsable
C61: Ref. 2025 | D61: 2026 | E61: 2027 | F61: 2028 | G61: 2029 | H61: 2030
A62: 1 | B62: {='9 Fortalecimiento docente'!I3:I4} -> 0 | C62: ='9 Fortalecimiento docente'!#REF! -> #REF! | D62: ='9 Fortalecimiento docente'!R3 -> 0 | E62: ='9 Fortalecimiento docente'!S3 -> 0 | F62: ='9 Fortalecimiento docente'!T3 -> 0 | G62: ='9 Fortalecimiento docente'!U3 -> 0 | H62: ='9 Fortalecimiento docente'!V3 -> 0 | I62: ='9 Fortalecimiento docente'!W3 -> Anual | J62: ='9 Fortalecimiento docente'!X3 -> 0
B63: 0
A64: 2 | B64: {='9 Fortalecimiento docente'!I5:I6} -> 0 | C64: ='9 Fortalecimiento docente'!#REF! -> #REF! | D64: ='9 Fortalecimiento docente'!R5 -> 0 | E64: ='9 Fortalecimiento docente'!S5 -> 0 | F64: ='9 Fortalecimiento docente'!T5 -> 0 | G64: ='9 Fortalecimiento docente'!U5 -> 0 | H64: ='9 Fortalecimiento docente'!V5 -> 0 | I64: ='9 Fortalecimiento docente'!W5 -> Anual | J64: ='9 Fortalecimiento docente'!X5 -> 0
B65: 0
A66: 3 | B66: {='9 Fortalecimiento docente'!I7:I8} -> 0 | C66: ='9 Fortalecimiento docente'!#REF! -> #REF! | D66: ='9 Fortalecimiento docente'!R7 -> 0 | E66: ='9 Fortalecimiento docente'!S7 -> 0 | F66: ='9 Fortalecimiento docente'!T7 -> 0 | G66: ='9 Fortalecimiento docente'!U7 -> 0 | H66: ='9 Fortalecimiento docente'!V7 -> 0 | I66: ='9 Fortalecimiento docente'!W7 -> Anual | J66: ='9 Fortalecimiento docente'!X7 -> 0
B67: 0
A68: 4 | B68: {='9 Fortalecimiento docente'!I9:I10} -> 0 | C68: ='9 Fortalecimiento docente'!#REF! -> #REF! | D68: ='9 Fortalecimiento docente'!R9 -> 0 | E68: ='9 Fortalecimiento docente'!S9 -> 0 | F68: ='9 Fortalecimiento docente'!T9 -> 0 | G68: ='9 Fortalecimiento docente'!U9 -> 0 | H68: ='9 Fortalecimiento docente'!V9 -> 0 | I68: ='9 Fortalecimiento docente'!W9 -> Anual | J68: ='9 Fortalecimiento docente'!X9 -> 0
B69: 0
A70: 5 | B70: {='9 Fortalecimiento docente'!I11:I12} -> 0 | C70: ='9 Fortalecimiento docente'!#REF! -> #REF! | D70: ='9 Fortalecimiento docente'!R11 -> 0 | E70: ='9 Fortalecimiento docente'!S11 -> 0 | F70: ='9 Fortalecimiento docente'!T11 -> 0 | G70: ='9 Fortalecimiento docente'!U11 -> 0 | H70: ='9 Fortalecimiento docente'!V11 -> 0 | I70: ='9 Fortalecimiento docente'!W11 -> Anual | J70: ='9 Fortalecimiento docente'!X11 -> 0
B71: 0
A72: 8 | B72: ='9 Fortalecimiento docente'!I15 -> 0 | C72: ='9 Fortalecimiento docente'!#REF! -> #REF! | D72: ='9 Fortalecimiento docente'!R15 -> 0 | E72: ='9 Fortalecimiento docente'!S15 -> 0 | F72: ='9 Fortalecimiento docente'!T15 -> 0 | G72: ='9 Fortalecimiento docente'!U15 -> 0 | H72: ='9 Fortalecimiento docente'!V15 -> 0 | I72: ='9 Fortalecimiento docente'!W15 -> Acumulada | J72: ='9 Fortalecimiento docente'!X15 -> 0
A75: 10 Dignificación de las y los trabajadores universitarios
A76: Num Progresivo de meta | B76: Meta | C76: Valor de los indicadores | I76: Medición (anual o acumulada) | J76: Área responsable
C77: Ref. 2025 | D77: 2026 | E77: 2027 | F77: 2028 | G77: 2029 | H77: 2030
A78: 1 | B78: ='10 Dignificación las y los trab'!I3 -> 0 | C78: ='10 Dignificación las y los trab'!#REF! -> #REF! | D78: ='10 Dignificación las y los trab'!R3 -> 0 | E78: ='10 Dignificación las y los trab'!S3 -> 0 | F78: ='10 Dignificación las y los trab'!T3 -> 0 | G78: ='10 Dignificación las y los trab'!U3 -> 0 | H78: ='10 Dignificación las y los trab'!V3 -> 0 | I78: ='10 Dignificación las y los trab'!W3 -> Anual | J78: ='10 Dignificación las y los trab'!X3 -> 0
A80: 2 | B80: ='10 Dignificación las y los trab'!I5 -> 0 | C80: ='10 Dignificación las y los trab'!#REF! -> #REF! | D80: ='10 Dignificación las y los trab'!R5 -> 0 | E80: ='10 Dignificación las y los trab'!S5 -> 0 | F80: ='10 Dignificación las y los trab'!T5 -> 0 | G80: ='10 Dignificación las y los trab'!U5 -> 0 | H80: ='10 Dignificación las y los trab'!V5 -> 0 | I80: ='10 Dignificación las y los trab'!W5 -> Anual | J80: ='10 Dignificación las y los trab'!X5 -> 0
A82: 3 | B82: ='10 Dignificación las y los trab'!I7 -> 0 | C82: ='10 Dignificación las y los trab'!#REF! -> #REF! | D82: ='10 Dignificación las y los trab'!R7 -> 0 | E82: ='10 Dignificación las y los trab'!S7 -> 0 | F82: ='10 Dignificación las y los trab'!T7 -> 0 | G82: ='10 Dignificación las y los trab'!U7 -> 0 | H82: ='10 Dignificación las y los trab'!V7 -> 0 | I82: ='10 Dignificación las y los trab'!W7 -> Anual | J82: ='10 Dignificación las y los trab'!X7 -> 0
A85: 18 Reconocimiento de la diversidad social en la universidad
A86: Num Progresivo de meta | B86: Meta | C86: Valor de los indicadores | I86: Medición (anual o acumulada) | J86: Área responsable
C87: Ref. 2025 | D87: 2026 | E87: 2027 | F87: 2028 | G87: 2029 | H87: 2030
A88: 1 | B88: {='18 Reconocimiento de la diversi'!I3:I4} -> 0 | C88: {='18 Reconocimiento de la diversi'!#REF!} -> #REF! | D88: {='18 Reconocimiento de la diversi'!R3:R4} -> 0 | E88: {='18 Reconocimiento de la diversi'!S3:S4} -> 0 | F88: {='18 Reconocimiento de la diversi'!T3:T4} -> 0 | G88: {='18 Reconocimiento de la diversi'!U3:U4} -> 0 | H88: {='18 Reconocimiento de la diversi'!V3:V4} -> 0 | I88: {='18 Reconocimiento de la diversi'!W3:W4} -> Anual | J88: {='18 Reconocimiento de la diversi'!X3:X4} -> 0
B89: 0 | D89: 0 | E89: 0 | F89: 0 | G89: 0 | H89: 0 | I89: 0 | J89: 0
A90: 3 | B90: {='18 Reconocimiento de la diversi'!I6:I7} -> 0 | C90: {='18 Reconocimiento de la diversi'!#REF!} -> #REF! | D90: {='18 Reconocimiento de la diversi'!R6:R7} -> 0 | E90: {='18 Reconocimiento de la diversi'!S6:S7} -> 0 | F90: {='18 Reconocimiento de la diversi'!T6:T7} -> 0 | G90: {='18 Reconocimiento de la diversi'!U6:U7} -> 0 | H90: {='18 Reconocimiento de la diversi'!V6:V7} -> 0 | I90: {='18 Reconocimiento de la diversi'!W6:W7} -> Anual | J90: {='18 Reconocimiento de la diversi'!X6:X7} -> 0
B91: 0 | D91: 0 | E91: 0 | F91: 0 | G91: 0 | H91: 0 | I91: 0 | J91: 0
A93: 19 Construcción de una cultura de paz
A94: Num Progresivo de meta | B94: Meta | C94: Valor de los indicadores | I94: Medición (anual o acumulada) | J94: Área responsable
C95: Ref. 2025 | D95: 2026 | E95: 2027 | F95: 2028 | G95: 2029 | H95: 2030
A96: 1 | B96: {='19 Constr cultura de paz '!I3:I3} -> Mantener al menos 5 acciones de capacitación registradas en cada medición anual de 2027 a 2030. | C96: {='19 Constr cultura de paz '!#REF!} -> #REF! | D96: {='19 Constr cultura de paz '!R3:R3} -> 5 | E96: {='19 Constr cultura de paz '!S3:S3} -> 5 | F96: {='19 Constr cultura de paz '!T3:T3} -> 5 | G96: {='19 Constr cultura de paz '!U3:U3} -> 5 | H96: {='19 Constr cultura de paz '!V3:V3} -> 5 | I96: {='19 Constr cultura de paz '!W3:W3} -> Anual | J96: {='19 Constr cultura de paz '!X3:X3} -> Por validar con el área responsable
A98: 5 | B98: {='19 Constr cultura de paz '!I7:I8} -> 0 | C98: {='19 Constr cultura de paz '!#REF!} -> #REF! | D98: {='19 Constr cultura de paz '!R7:R8} -> 0 | E98: {='19 Constr cultura de paz '!S7:S8} -> 0 | F98: {='19 Constr cultura de paz '!T7:T8} -> 0 | G98: {='19 Constr cultura de paz '!U7:U8} -> 0 | H98: {='19 Constr cultura de paz '!V7:V8} -> 0 | I98: {='19 Constr cultura de paz '!W7:W8} -> Anual | J98: {='19 Constr cultura de paz '!X7:X8} -> 0
B99: 0 | D99: 0 | E99: 0 | F99: 0 | G99: 0 | H99: 0 | I99: 0 | J99: 0
A101: 20 Retribución social a través de trabajos colaborativos con la sociedad mexiquense
A102: Num Progresivo de meta | B102: Meta | C102: Valor de los indicadores | I102: Medición (anual o acumulada) | J102: Área responsable
C103: Ref. 2025 | D103: 2026 | E103: 2027 | F103: 2028 | G103: 2029
A104: 7 | B104: {='20 Retribución social '!I9:I10} -> 0 | C104: {='20 Retribución social '!#REF!} -> #REF! | D104: {='20 Retribución social '!R9:R10} -> 0 | E104: {='20 Retribución social '!S9:S10} -> 0 | F104: {='20 Retribución social '!T9:T10} -> 0 | G104: {='20 Retribución social '!U9:U10} -> 0 | H104: {='20 Retribución social '!V9:V10} -> 0 | I104: {='20 Retribución social '!W9:W10} -> Anual | J104: {='20 Retribución social '!X9:X10} -> 0
B105: 0 | D105: 0 | E105: 0 | F105: 0 | G105: 0 | H105: 0 | I105: 0 | J105: 0

Sheet Apertura programática
F1: Fecha de toma de protesta | J1: 46265
A4: I. Estudiantado con oportunidades para su pleno desarrollo personal
A5: Estudiantado con oportunidades para su pleno desarrollo y pertinencia en los estudios profesionales
A6: No. | B6: Meta | C6: Ref. 2026 | D6: 2027 | E6: 2028 | F6: 2029 | G6: =TEXT($J$1,"mmmm") -> agosto | H6: Medición | I6: Área responsable
G7: 2030
A8: 1 | B8: =IF('2 EstudiantadoEstProf'!I3<>0,'2 EstudiantadoEstProf'!I3," -") -> meta fac | C8: =IF('2 EstudiantadoEstProf'!R3<>0,'2 EstudiantadoEstProf'!R3,"-") -> - | D8: =IF('2 EstudiantadoEstProf'!S3<>0,'2 EstudiantadoEstProf'!S3,"-") -> - | E8: =IF('2 EstudiantadoEstProf'!T3<>0,'2 EstudiantadoEstProf'!T3,"-") -> - | F8: =IF('2 EstudiantadoEstProf'!U3<>0,'2 EstudiantadoEstProf'!U3,"-") -> - | G8: =IF('2 EstudiantadoEstProf'!V3<>0,'2 EstudiantadoEstProf'!V3,"-") -> - | H8: ='2 EstudiantadoEstProf'!W3 -> Anual | I8: =IF('2 EstudiantadoEstProf'!X3<>0,'2 EstudiantadoEstProf'!X3,"-") -> -
A9: 2 | B9: =IF('2 EstudiantadoEstProf'!I4<>0,'2 EstudiantadoEstProf'!I4," -") -> - | C9: =IF('2 EstudiantadoEstProf'!R4<>0,'2 EstudiantadoEstProf'!R4,"-") -> - | D9: =IF('2 EstudiantadoEstProf'!S4<>0,'2 EstudiantadoEstProf'!S4,"-") -> - | E9: =IF('2 EstudiantadoEstProf'!T4<>0,'2 EstudiantadoEstProf'!T4,"-") -> - | F9: =IF('2 EstudiantadoEstProf'!U4<>0,'2 EstudiantadoEstProf'!U4,"-") -> - | G9: =IF('2 EstudiantadoEstProf'!V4<>0,'2 EstudiantadoEstProf'!V4,"-") -> - | H9: ='2 EstudiantadoEstProf'!W4 -> Anual | I9: =IF('2 EstudiantadoEstProf'!X4<>0,'2 EstudiantadoEstProf'!X4,"-") -> -
A10: 3 | B10: =IF('Indicadores x proyec'!B8<>0,'Indicadores x proyec'!B8,"-") -> - | C10: =IF('Indicadores x proyec'!D8/100<>0,'Indicadores x proyec'!D8/100,"-") -> - | D10: =IF('Indicadores x proyec'!E8/100<>0,'Indicadores x proyec'!E8/100,"-") -> - | E10: =IF('Indicadores x proyec'!F8/100<>0,'Indicadores x proyec'!F8/100,"-") -> - | F10: =IF('Indicadores x proyec'!G8/100<>0,'Indicadores x proyec'!G8/100,"-") -> - | G10: =IF('Indicadores x proyec'!H8/100<>0,'Indicadores x proyec'!H8/100,"-") -> - | H10: ='Indicadores x proyec'!I10 -> Anual | I10: =IF('Indicadores x proyec'!J8<>0,'Indicadores x proyec'!J8,"-") -> -
A11: 4 | B11: =IF('Indicadores x proyec'!B10<>0,'Indicadores x proyec'!B10,"-") -> - | C11: =IF('Indicadores x proyec'!D10/100<>0,'Indicadores x proyec'!D10/100,"-") -> - | D11: =IF('Indicadores x proyec'!E10/100<>0,'Indicadores x proyec'!E10/100,"-") -> - | E11: =IF('Indicadores x proyec'!F10/100<>0,'Indicadores x proyec'!F10/100,"-") -> - | F11: =IF('Indicadores x proyec'!G10/100<>0,'Indicadores x proyec'!G10/100,"-") -> - | G11: =IF('Indicadores x proyec'!H10/100<>0,'Indicadores x proyec'!H10/100,"-") -> - | H11: ='Indicadores x proyec'!I10 -> Anual | I11: =IF('Indicadores x proyec'!J10<>0,'Indicadores x proyec'!J10,"-") -> -
A12: 5 | B12: =IF('Indicadores x proyec'!B12<>0,'Indicadores x proyec'!B12,"-") -> - | C12: =IF('Indicadores x proyec'!D12/100<>0,'Indicadores x proyec'!D12/100,"-") -> - | D12: =IF('Indicadores x proyec'!E12/100<>0,'Indicadores x proyec'!E12/100,"-") -> - | E12: =IF('Indicadores x proyec'!F12/100<>0,'Indicadores x proyec'!F12/100,"-") -> - | F12: =IF('Indicadores x proyec'!G12/100<>0,'Indicadores x proyec'!G12/100,"-") -> - | G12: =IF('Indicadores x proyec'!H12/100<>0,'Indicadores x proyec'!H12/100,"-") -> - | H12: ='Indicadores x proyec'!I12 -> Anual | I12: =IF('Indicadores x proyec'!J12<>0,'Indicadores x proyec'!J12,"-") -> -
A13: 6 | B13: =IF('2 EstudiantadoEstProf'!I11<>0,'2 EstudiantadoEstProf'!I11,"-") -> - | C13: =IF('2 EstudiantadoEstProf'!R11<>0,'2 EstudiantadoEstProf'!R11,"-") -> - | D13: =IF('2 EstudiantadoEstProf'!S11<>0,'2 EstudiantadoEstProf'!S11,"-") -> - | E13: =IF('2 EstudiantadoEstProf'!T11<>0,'2 EstudiantadoEstProf'!T11,"-") -> - | F13: =IF('2 EstudiantadoEstProf'!U11<>0,'2 EstudiantadoEstProf'!U11,"-") -> - | G13: =IF('2 EstudiantadoEstProf'!V11<>0,'2 EstudiantadoEstProf'!V11,"-") -> - | H13: ='2 EstudiantadoEstProf'!W11 -> Anual | I13: =IF('2 EstudiantadoEstProf'!X11<>0,'2 EstudiantadoEstProf'!X11,"-") -> -
A14: 7 | B14: =IF('2 EstudiantadoEstProf'!I12<>0,'2 EstudiantadoEstProf'!I12,"-") -> - | C14: =IF('2 EstudiantadoEstProf'!R12<>0,'2 EstudiantadoEstProf'!R12,"-") -> - | D14: =IF('2 EstudiantadoEstProf'!S12<>0,'2 EstudiantadoEstProf'!S12,"-") -> - | E14: =IF('2 EstudiantadoEstProf'!T12<>0,'2 EstudiantadoEstProf'!T12,"-") -> - | F14: =IF('2 EstudiantadoEstProf'!U12<>0,'2 EstudiantadoEstProf'!U12,"-") -> - | G14: =IF('2 EstudiantadoEstProf'!V12<>0,'2 EstudiantadoEstProf'!V12,"-") -> - | H14: ='2 EstudiantadoEstProf'!W12 -> Anual | I14: =IF('2 EstudiantadoEstProf'!X12<>0,'2 EstudiantadoEstProf'!X12,"-") -> -
A15: 8 | B15: =IF('Indicadores x proyec'!B14<>0,'Indicadores x proyec'!B14,"-") -> - | C15: =IF('Indicadores x proyec'!D14/100<>0,'Indicadores x proyec'!D14/100,"-") -> - | D15: =IF('Indicadores x proyec'!E14/100<>0,'Indicadores x proyec'!E14/100,"-") -> - | E15: =IF('Indicadores x proyec'!F14/100<>0,'Indicadores x proyec'!F14/100,"-") -> - | F15: =IF('Indicadores x proyec'!G14/100<>0,'Indicadores x proyec'!G14/100,"-") -> - | G15: =IF('Indicadores x proyec'!H14/100<>0,'Indicadores x proyec'!H14/100,"-") -> - | H15: ='Indicadores x proyec'!I14 -> Anual | I15: =IF('Indicadores x proyec'!J14<>0,'Indicadores x proyec'!J14,"-") -> -
A16: 9 | B16: =IF('2 EstudiantadoEstProf'!I15<>0,'2 EstudiantadoEstProf'!I15,"-") -> - | C16: =IF('2 EstudiantadoEstProf'!R15<>0,'2 EstudiantadoEstProf'!R15,"-") -> - | D16: =IF('2 EstudiantadoEstProf'!S15<>0,'2 EstudiantadoEstProf'!S15,"-") -> - | E16: =IF('2 EstudiantadoEstProf'!T15<>0,'2 EstudiantadoEstProf'!T15,"-") -> - | F16: =IF('2 EstudiantadoEstProf'!U15<>0,'2 EstudiantadoEstProf'!U15,"-") -> - | G16: =IF('2 EstudiantadoEstProf'!V15<>0,'2 EstudiantadoEstProf'!V15,"-") -> - | H16: =IF('2 EstudiantadoEstProf'!W15<>0,'2 EstudiantadoEstProf'!W15,"-") -> Anual | I16: =IF('2 EstudiantadoEstProf'!X15<>0,'2 EstudiantadoEstProf'!X15,"-") -> -
A17: 10 | B17: =IF('2 EstudiantadoEstProf'!I16<>0,'2 EstudiantadoEstProf'!I16,"-") -> - | C17: =IF('2 EstudiantadoEstProf'!R16<>0,'2 EstudiantadoEstProf'!R16,"-") -> - | D17: =IF('2 EstudiantadoEstProf'!S16<>0,'2 EstudiantadoEstProf'!S16,"-") -> - | E17: =IF('2 EstudiantadoEstProf'!T16<>0,'2 EstudiantadoEstProf'!T16,"-") -> - | F17: =IF('2 EstudiantadoEstProf'!U16<>0,'2 EstudiantadoEstProf'!U16,"-") -> - | G17: =IF('2 EstudiantadoEstProf'!V16<>0,'2 EstudiantadoEstProf'!V16,"-") -> - | H17: =IF('2 EstudiantadoEstProf'!W16<>0,'2 EstudiantadoEstProf'!W16,"-") -> Anual | I17: =IF('2 EstudiantadoEstProf'!X16<>0,'2 EstudiantadoEstProf'!X16,"-") -> -
A18: 11 | B18: =IF('2 EstudiantadoEstProf'!I17<>0,'2 EstudiantadoEstProf'!I17,"-") -> - | C18: =IF('2 EstudiantadoEstProf'!R17<>0,'2 EstudiantadoEstProf'!R17,"-") -> - | D18: =IF('2 EstudiantadoEstProf'!S17<>0,'2 EstudiantadoEstProf'!S17,"-") -> - | E18: =IF('2 EstudiantadoEstProf'!T17<>0,'2 EstudiantadoEstProf'!T17,"-") -> - | F18: =IF('2 EstudiantadoEstProf'!U17<>0,'2 EstudiantadoEstProf'!U17,"-") -> - | G18: =IF('2 EstudiantadoEstProf'!V17<>0,'2 EstudiantadoEstProf'!V17,"-") -> - | H18: =IF('2 EstudiantadoEstProf'!W17<>0,'2 EstudiantadoEstProf'!W17,"-") -> Anual | I18: =IF('2 EstudiantadoEstProf'!X17<>0,'2 EstudiantadoEstProf'!X17,"-") -> -
A19: 12 | B19: =IF('Indicadores x proyec'!B16<>0,'Indicadores x proyec'!B16,"-") -> - | C19: =IF('Indicadores x proyec'!D16/100<>0,'Indicadores x proyec'!D16/100,"-") -> - | D19: =IF('Indicadores x proyec'!E16/100<>0,'Indicadores x proyec'!E16/100,"-") -> - | E19: =IF('Indicadores x proyec'!F16/100<>0,'Indicadores x proyec'!F16/100,"-") -> - | F19: =IF('Indicadores x proyec'!G16/100<>0,'Indicadores x proyec'!G16/100,"-") -> - | G19: =IF('Indicadores x proyec'!H16/100<>0,'Indicadores x proyec'!H16/100,"-") -> - | H19: ='Indicadores x proyec'!I16 -> Anual | I19: =IF('Indicadores x proyec'!J16<>0,'Indicadores x proyec'!J16,"-") -> -
A20: 13 | B20: =IF('2 EstudiantadoEstProf'!I20<>0,'2 EstudiantadoEstProf'!I20,"-") -> - | C20: =IF('2 EstudiantadoEstProf'!R20<>0,'2 EstudiantadoEstProf'!R20,"-") -> - | D20: =IF('2 EstudiantadoEstProf'!S20<>0,'2 EstudiantadoEstProf'!S20,"-") -> - | E20: =IF('2 EstudiantadoEstProf'!T20<>0,'2 EstudiantadoEstProf'!T20,"-") -> - | F20: =IF('2 EstudiantadoEstProf'!U20<>0,'2 EstudiantadoEstProf'!U20,"-") -> - | G20: =IF('2 EstudiantadoEstProf'!V20<>0,'2 EstudiantadoEstProf'!V20,"-") -> - | H20: =IF('2 EstudiantadoEstProf'!W20<>0,'2 EstudiantadoEstProf'!W20,"-") -> Anual | I20: =IF('2 EstudiantadoEstProf'!X20<>0,'2 EstudiantadoEstProf'!X20,"-") -> -
A21: 14 | B21: =IF('2 EstudiantadoEstProf'!I21<>0,'2 EstudiantadoEstProf'!I21,"-") -> - | C21: =IF('2 EstudiantadoEstProf'!R21<>0,'2 EstudiantadoEstProf'!R21,"-") -> - | D21: =IF('2 EstudiantadoEstProf'!S21<>0,'2 EstudiantadoEstProf'!S21,"-") -> - | E21: =IF('2 EstudiantadoEstProf'!T21<>0,'2 EstudiantadoEstProf'!T21,"-") -> - | F21: =IF('2 EstudiantadoEstProf'!U21<>0,'2 EstudiantadoEstProf'!U21,"-") -> - | G21: =IF('2 EstudiantadoEstProf'!V21<>0,'2 EstudiantadoEstProf'!V21,"-") -> - | H21: =IF('2 EstudiantadoEstProf'!W21<>0,'2 EstudiantadoEstProf'!W21,"-") -> Anual | I21: =IF('2 EstudiantadoEstProf'!X21<>0,'2 EstudiantadoEstProf'!X21,"-") -> -
A22: 15 | B22: =IF('2 EstudiantadoEstProf'!I22<>0,'2 EstudiantadoEstProf'!I22,"-") -> - | C22: =IF('2 EstudiantadoEstProf'!R22<>0,'2 EstudiantadoEstProf'!R22,"-") -> - | D22: =IF('2 EstudiantadoEstProf'!S22<>0,'2 EstudiantadoEstProf'!S22,"-") -> - | E22: =IF('2 EstudiantadoEstProf'!T22<>0,'2 EstudiantadoEstProf'!T22,"-") -> - | F22: =IF('2 EstudiantadoEstProf'!U22<>0,'2 EstudiantadoEstProf'!U22,"-") -> - | G22: =IF('2 EstudiantadoEstProf'!V22<>0,'2 EstudiantadoEstProf'!V22,"-") -> - | H22: =IF('2 EstudiantadoEstProf'!W22<>0,'2 EstudiantadoEstProf'!W22,"-") -> Anual | I22: =IF('2 EstudiantadoEstProf'!X22<>0,'2 EstudiantadoEstProf'!X22,"-") -> -
A23: 16 | B23: =IF('2 EstudiantadoEstProf'!I23<>0,'2 EstudiantadoEstProf'!I23,"-") -> - | C23: =IF('2 EstudiantadoEstProf'!R23<>0,'2 EstudiantadoEstProf'!R23,"-") -> - | D23: =IF('2 EstudiantadoEstProf'!S23<>0,'2 EstudiantadoEstProf'!S23,"-") -> - | E23: =IF('2 EstudiantadoEstProf'!T23<>0,'2 EstudiantadoEstProf'!T23,"-") -> - | F23: =IF('2 EstudiantadoEstProf'!U23<>0,'2 EstudiantadoEstProf'!U23,"-") -> - | G23: =IF('2 EstudiantadoEstProf'!V23<>0,'2 EstudiantadoEstProf'!V23,"-") -> - | H23: =IF('2 EstudiantadoEstProf'!W23<>0,'2 EstudiantadoEstProf'!W23,"-") -> Anual | I23: =IF('2 EstudiantadoEstProf'!X23<>0,'2 EstudiantadoEstProf'!X23,"-") -> -
A24: 17 | B24: =IF('Indicadores x proyec'!B18<>0,'Indicadores x proyec'!B18,"-") -> - | C24: =IF('Indicadores x proyec'!D18/100<>0,'Indicadores x proyec'!D18/100,"-") -> - | D24: =IF('Indicadores x proyec'!E18/100<>0,'Indicadores x proyec'!E18/100,"-") -> - | E24: =IF('Indicadores x proyec'!F18/100<>0,'Indicadores x proyec'!F18/100,"-") -> - | F24: =IF('Indicadores x proyec'!G18/100<>0,'Indicadores x proyec'!G18/100,"-") -> - | G24: =IF('Indicadores x proyec'!H18/100<>0,'Indicadores x proyec'!H18/100,"-") -> - | H24: ='Indicadores x proyec'!I18 -> Anual | I24: =IF('Indicadores x proyec'!J18<>0,'Indicadores x proyec'!J18,"-") -> -
A25: 18 | B25: =IF('2 EstudiantadoEstProf'!I26<>0,'2 EstudiantadoEstProf'!I26,"-") -> - | C25: =IF('2 EstudiantadoEstProf'!R26<>0,'2 EstudiantadoEstProf'!R26,"-") -> - | D25: =IF('2 EstudiantadoEstProf'!S26<>0,'2 EstudiantadoEstProf'!S26,"-") -> - | E25: =IF('2 EstudiantadoEstProf'!T26<>0,'2 EstudiantadoEstProf'!T26,"-") -> - | F25: =IF('2 EstudiantadoEstProf'!U26<>0,'2 EstudiantadoEstProf'!U26,"-") -> - | G25: =IF('2 EstudiantadoEstProf'!V26<>0,'2 EstudiantadoEstProf'!V26,"-") -> - | H25: =IF('2 EstudiantadoEstProf'!W26<>0,'2 EstudiantadoEstProf'!W26,"-") -> Anual | I25: =IF('2 EstudiantadoEstProf'!X26<>0,'2 EstudiantadoEstProf'!X26,"-") -> -
A26: 19 | B26: =IF('Indicadores x proyec'!B20<>0,'Indicadores x proyec'!B20,"-") -> - | C26: =IF('Indicadores x proyec'!D20/100<>0,'Indicadores x proyec'!D20/100,"-") -> - | D26: =IF('Indicadores x proyec'!E20/100<>0,'Indicadores x proyec'!E20/100,"-") -> - | E26: =IF('Indicadores x proyec'!F20/100<>0,'Indicadores x proyec'!F20/100,"-") -> - | F26: =IF('Indicadores x proyec'!G20/100<>0,'Indicadores x proyec'!G20/100,"-") -> - | G26: =IF('Indicadores x proyec'!H20/100<>0,'Indicadores x proyec'!H20/100,"-") -> - | H26: ='Indicadores x proyec'!I20 -> Anual | I26: =IF('Indicadores x proyec'!J20<>0,'Indicadores x proyec'!J20,"-") -> -
A27: 20 | B27: =IF('Indicadores x proyec'!B22<>0,'Indicadores x proyec'!B22,"-") -> - | C27: =IF('2 EstudiantadoEstProf'!R29/100<>0,'2 EstudiantadoEstProf'!R29/100,"-") -> - | D27: =IF('2 EstudiantadoEstProf'!S29/100<>0,'2 EstudiantadoEstProf'!S29/100,"-") -> - | E27: =IF('2 EstudiantadoEstProf'!T29/100<>0,'2 EstudiantadoEstProf'!T29/100,"-") -> - | F27: =IF('2 EstudiantadoEstProf'!U29/100<>0,'2 EstudiantadoEstProf'!U29/100,"-") -> - | G27: =IF('2 EstudiantadoEstProf'!V29/100<>0,'2 EstudiantadoEstProf'!V29/100,"-") -> - | H27: ='Indicadores x proyec'!I22 -> Anual | I27: =IF('Indicadores x proyec'!J22<>0,'Indicadores x proyec'!J22,"-") -> -
A28: 21 | B28: =IF('2 EstudiantadoEstProf'!I33<>0,'2 EstudiantadoEstProf'!I33,"-") -> - | C28: =IF('2 EstudiantadoEstProf'!R33<>0,'2 EstudiantadoEstProf'!R33,"-") -> - | D28: =IF('2 EstudiantadoEstProf'!S33<>0,'2 EstudiantadoEstProf'!S33,"-") -> - | E28: =IF('2 EstudiantadoEstProf'!T33<>0,'2 EstudiantadoEstProf'!T33,"-") -> - | F28: =IF('2 EstudiantadoEstProf'!U33<>0,'2 EstudiantadoEstProf'!U33,"-") -> - | G28: =IF('2 EstudiantadoEstProf'!V33<>0,'2 EstudiantadoEstProf'!V33,"-") -> - | H28: =IF('2 EstudiantadoEstProf'!W33<>0,'2 EstudiantadoEstProf'!W33,"-") -> Anual | I28: =IF('2 EstudiantadoEstProf'!X33<>0,'2 EstudiantadoEstProf'!X33,"-") -> -
A29: 22 | B29: =IF('Indicadores x proyec'!B26<>0,'Indicadores x proyec'!B26,"-") -> - | C29: =IF('Indicadores x proyec'!D26/100<>0,'Indicadores x proyec'!D26/100,"-") -> - | D29: =IF('Indicadores x proyec'!E26/100<>0,'Indicadores x proyec'!E26/100,"-") -> - | E29: =IF('Indicadores x proyec'!F26/100<>0,'Indicadores x proyec'!F26/100,"-") -> - | F29: =IF('Indicadores x proyec'!G26/100<>0,'Indicadores x proyec'!G26/100,"-") -> - | G29: =IF('Indicadores x proyec'!H26/100<>0,'Indicadores x proyec'!H26/100,"-") -> - | H29: ='Indicadores x proyec'!I26 -> Anual | I29: =IF('Indicadores x proyec'!J26<>0,'Indicadores x proyec'!J26,"-") -> -
A30: 23 | B30: =IF('2 EstudiantadoEstProf'!I36<>0,'2 EstudiantadoEstProf'!I36,"-") -> - | C30: =IF('2 EstudiantadoEstProf'!R36<>0,'2 EstudiantadoEstProf'!R36,"-") -> - | D30: =IF('2 EstudiantadoEstProf'!S36<>0,'2 EstudiantadoEstProf'!S36,"-") -> - | E30: =IF('2 EstudiantadoEstProf'!T36<>0,'2 EstudiantadoEstProf'!T36,"-") -> - | F30: =IF('2 EstudiantadoEstProf'!U36<>0,'2 EstudiantadoEstProf'!U36,"-") -> - | G30: =IF('2 EstudiantadoEstProf'!V36<>0,'2 EstudiantadoEstProf'!V36,"-") -> - | H30: =IF('2 EstudiantadoEstProf'!W36<>0,'2 EstudiantadoEstProf'!W36,"-") -> Anual | I30: =IF('2 EstudiantadoEstProf'!X36<>0,'2 EstudiantadoEstProf'!X36,"-") -> -
A31: 24 | B31: =IF('2 EstudiantadoEstProf'!I37<>0,'2 EstudiantadoEstProf'!I37,"-") -> - | C31: =IF('2 EstudiantadoEstProf'!R37<>0,'2 EstudiantadoEstProf'!R37,"-") -> - | D31: =IF('2 EstudiantadoEstProf'!S37<>0,'2 EstudiantadoEstProf'!S37,"-") -> - | E31: =IF('2 EstudiantadoEstProf'!T37<>0,'2 EstudiantadoEstProf'!T37,"-") -> - | F31: =IF('2 EstudiantadoEstProf'!U37<>0,'2 EstudiantadoEstProf'!U37,"-") -> - | G31: =IF('2 EstudiantadoEstProf'!V37<>0,'2 EstudiantadoEstProf'!V37,"-") -> - | H31: =IF('2 EstudiantadoEstProf'!W37<>0,'2 EstudiantadoEstProf'!W37,"-") -> Anual | I31: =IF('2 EstudiantadoEstProf'!X37<>0,'2 EstudiantadoEstProf'!X37,"-") -> -
A32: 25 | B32: =IF('2 EstudiantadoEstProf'!I38<>0,'2 EstudiantadoEstProf'!I38,"-") -> - | C32: =IF('2 EstudiantadoEstProf'!R38<>0,'2 EstudiantadoEstProf'!R38,"-") -> - | D32: =IF('2 EstudiantadoEstProf'!S38<>0,'2 EstudiantadoEstProf'!S38,"-") -> - | E32: =IF('2 EstudiantadoEstProf'!T38<>0,'2 EstudiantadoEstProf'!T38,"-") -> - | F32: =IF('2 EstudiantadoEstProf'!U38<>0,'2 EstudiantadoEstProf'!U38,"-") -> - | G32: =IF('2 EstudiantadoEstProf'!V38<>0,'2 EstudiantadoEstProf'!V38,"-") -> - | H32: =IF('2 EstudiantadoEstProf'!W38<>0,'2 EstudiantadoEstProf'!W38,"-") -> Anual | I32: =IF('2 EstudiantadoEstProf'!X38<>0,'2 EstudiantadoEstProf'!X38,"-") -> -
A33: 26 | B33: =IF('2 EstudiantadoEstProf'!I39<>0,'2 EstudiantadoEstProf'!I39,"-") -> - | C33: =IF('2 EstudiantadoEstProf'!R39<>0,'2 EstudiantadoEstProf'!R39,"-") -> - | D33: =IF('2 EstudiantadoEstProf'!S39<>0,'2 EstudiantadoEstProf'!S39,"-") -> - | E33: =IF('2 EstudiantadoEstProf'!T39<>0,'2 EstudiantadoEstProf'!T39,"-") -> - | F33: =IF('2 EstudiantadoEstProf'!U39<>0,'2 EstudiantadoEstProf'!U39,"-") -> - | G33: =IF('2 EstudiantadoEstProf'!V39<>0,'2 EstudiantadoEstProf'!V39,"-") -> - | H33: =IF('2 EstudiantadoEstProf'!W39<>0,'2 EstudiantadoEstProf'!W39,"-") -> Anual | I33: =IF('2 EstudiantadoEstProf'!X39<>0,'2 EstudiantadoEstProf'!X39,"-") -> -
A36: Estudios avanzados de excelencia y pertinencia social
A37: No. | B37: Meta | C37: Ref. 2026 | D37: 2027 | E37: 2028 | F37: 2029 | G37: =TEXT($J$1,"mmmm") -> agosto | H37: Medición | I37: Área responsable
G38: 2030
A39: 1 | B39: =IF('3 Est avanzados excelencia'!I3<>0,'3 Est avanzados excelencia'!I3,"-") -> - | C39: =IF('3 Est avanzados excelencia'!R3<>0,'3 Est avanzados excelencia'!R3,"-") -> - | D39: =IF('3 Est avanzados excelencia'!S3<>0,'3 Est avanzados excelencia'!S3,"-") -> - | E39: =IF('3 Est avanzados excelencia'!T3<>0,'3 Est avanzados excelencia'!T3,"-") -> - | F39: =IF('3 Est avanzados excelencia'!U3<>0,'3 Est avanzados excelencia'!U3,"-") -> - | G39: =IF('3 Est avanzados excelencia'!V3<>0,'3 Est avanzados excelencia'!V3,"-") -> - | H39: =IF('3 Est avanzados excelencia'!W3<>0,'3 Est avanzados excelencia'!W3,"-") -> Anual | I39: =IF('3 Est avanzados excelencia'!X3<>0,'3 Est avanzados excelencia'!X3,"-") -> -
A40: 2 | B40: =IF('3 Est avanzados excelencia'!I4<>0,'3 Est avanzados excelencia'!I4,"-") -> - | C40: =IF('3 Est avanzados excelencia'!R4<>0,'3 Est avanzados excelencia'!R4,"-") -> - | D40: =IF('3 Est avanzados excelencia'!S4<>0,'3 Est avanzados excelencia'!S4,"-") -> - | E40: =IF('3 Est avanzados excelencia'!T4<>0,'3 Est avanzados excelencia'!T4,"-") -> - | F40: =IF('3 Est avanzados excelencia'!U4<>0,'3 Est avanzados excelencia'!U4,"-") -> - | G40: =IF('3 Est avanzados excelencia'!V4<>0,'3 Est avanzados excelencia'!V4,"-") -> - | H40: =IF('3 Est avanzados excelencia'!W4<>0,'3 Est avanzados excelencia'!W4,"-") -> Anual | I40: =IF('3 Est avanzados excelencia'!X4<>0,'3 Est avanzados excelencia'!X4,"-") -> -
A41: 3 | B41: =IF('3 Est avanzados excelencia'!I5<>0,'3 Est avanzados excelencia'!I5,"-") -> - | C41: =IF('3 Est avanzados excelencia'!R5<>0,'3 Est avanzados excelencia'!R5,"-") -> - | D41: =IF('3 Est avanzados excelencia'!S5<>0,'3 Est avanzados excelencia'!S5,"-") -> - | E41: =IF('3 Est avanzados excelencia'!T5<>0,'3 Est avanzados excelencia'!T5,"-") -> - | F41: =IF('3 Est avanzados excelencia'!U5<>0,'3 Est avanzados excelencia'!U5,"-") -> - | G41: =IF('3 Est avanzados excelencia'!V5<>0,'3 Est avanzados excelencia'!V5,"-") -> - | H41: =IF('3 Est avanzados excelencia'!W5<>0,'3 Est avanzados excelencia'!W5,"-") -> Anual | I41: =IF('3 Est avanzados excelencia'!X5<>0,'3 Est avanzados excelencia'!X5,"-") -> -
A42: 4 | B42: =IF('3 Est avanzados excelencia'!I6<>0,'3 Est avanzados excelencia'!I6,"-") -> - | C42: =IF('3 Est avanzados excelencia'!R6<>0,'3 Est avanzados excelencia'!R6,"-") -> - | D42: =IF('3 Est avanzados excelencia'!S6<>0,'3 Est avanzados excelencia'!S6,"-") -> - | E42: =IF('3 Est avanzados excelencia'!T6<>0,'3 Est avanzados excelencia'!T6,"-") -> - | F42: =IF('3 Est avanzados excelencia'!U6<>0,'3 Est avanzados excelencia'!U6,"-") -> - | G42: =IF('3 Est avanzados excelencia'!V6<>0,'3 Est avanzados excelencia'!V6,"-") -> - | H42: =IF('3 Est avanzados excelencia'!W6<>0,'3 Est avanzados excelencia'!W6,"-") -> Anual | I42: =IF('3 Est avanzados excelencia'!X6<>0,'3 Est avanzados excelencia'!X6,"-") -> -
A43: 5 | B43: =IF('3 Est avanzados excelencia'!I7<>0,'3 Est avanzados excelencia'!I7,"-") -> - | C43: =IF('3 Est avanzados excelencia'!R7<>0,'3 Est avanzados excelencia'!R7,"-") -> - | D43: =IF('3 Est avanzados excelencia'!S7<>0,'3 Est avanzados excelencia'!S7,"-") -> - | E43: =IF('3 Est avanzados excelencia'!T7<>0,'3 Est avanzados excelencia'!T7,"-") -> - | F43: =IF('3 Est avanzados excelencia'!U7<>0,'3 Est avanzados excelencia'!U7,"-") -> - | G43: =IF('3 Est avanzados excelencia'!V7<>0,'3 Est avanzados excelencia'!V7,"-") -> - | H43: =IF('3 Est avanzados excelencia'!W7<>0,'3 Est avanzados excelencia'!W7,"-") -> Anual | I43: =IF('3 Est avanzados excelencia'!X7<>0,'3 Est avanzados excelencia'!X7,"-") -> -
A44: 6 | B44: =IF('3 Est avanzados excelencia'!I8<>0,'3 Est avanzados excelencia'!I8,"-") -> - | C44: =IF('3 Est avanzados excelencia'!R8<>0,'3 Est avanzados excelencia'!R8,"-") -> - | D44: =IF('3 Est avanzados excelencia'!S8<>0,'3 Est avanzados excelencia'!S8,"-") -> - | E44: =IF('3 Est avanzados excelencia'!T8<>0,'3 Est avanzados excelencia'!T8,"-") -> - | F44: =IF('3 Est avanzados excelencia'!U8<>0,'3 Est avanzados excelencia'!U8,"-") -> - | G44: =IF('3 Est avanzados excelencia'!V8<>0,'3 Est avanzados excelencia'!V8,"-") -> - | H44: =IF('3 Est avanzados excelencia'!W8<>0,'3 Est avanzados excelencia'!W8,"-") -> Anual | I44: =IF('3 Est avanzados excelencia'!X8<>0,'3 Est avanzados excelencia'!X8,"-") -> -
A45: 7 | B45: =IF('Indicadores x proyec'!B32<>0,'Indicadores x proyec'!B32,"-") -> - | C45: =IF('Indicadores x proyec'!D32/100<>0,'Indicadores x proyec'!D32/100,"-") -> - | D45: =IF('Indicadores x proyec'!E32/100<>0,'Indicadores x proyec'!E32/100,"-") -> - | E45: =IF('Indicadores x proyec'!F32/100<>0,'Indicadores x proyec'!F32/100,"-") -> - | F45: =IF('Indicadores x proyec'!G32/100<>0,'Indicadores x proyec'!G32/100,"-") -> - | G45: =IF('Indicadores x proyec'!H32/100<>0,'Indicadores x proyec'!H32/100,"-") -> - | H45: =IF('Indicadores x proyec'!I32<>0,'Indicadores x proyec'!I32,"-") -> Anual | I45: =IF('Indicadores x proyec'!J32<>0,'Indicadores x proyec'!J32,"-") -> -
A48: II. Investigación y desarrollo académico de calidad y equidad
A49: Investigación abierta, inclusiva, equitativa y de calidad
A50: No. | B50: Meta | C50: Ref. 2026 | D50: 2027 | E50: 2028 | F50: 2029 | G50: =TEXT($J$1,"mmmm") -> agosto | H50: Medición | I50: Área responsable
G51: 2030
A52: 1 | B52: =IF('4 Investigación abierta'!I3<>0,'4 Investigación abierta'!I3,"-") -> Mantener al menos 3 cuerpos académicos de calidad en cada medición anual de 2027 a 2030. | C52: =IF('4 Investigación abierta'!R3<>0,'4 Investigación abierta'!R3,"-") -> 3 | D52: =IF('4 Investigación abierta'!S3<>0,'4 Investigación abierta'!S3,"-") -> 3 | E52: =IF('4 Investigación abierta'!T3<>0,'4 Investigación abierta'!T3,"-") -> 3 | F52: =IF('4 Investigación abierta'!U3<>0,'4 Investigación abierta'!U3,"-") -> 3 | G52: =IF('4 Investigación abierta'!V3<>0,'4 Investigación abierta'!V3,"-") -> 3 | H52: =IF('4 Investigación abierta'!W3<>0,'4 Investigación abierta'!W3,"-") -> Anual | I52: =IF('4 Investigación abierta'!X3<>0,'4 Investigación abierta'!X3,"-") -> Por validar con el área responsable
A53: 2 | B53: =IF('Indicadores x proyec'!B38<>0,'Indicadores x proyec'!B38,"-") -> - | C53: =IF('Indicadores x proyec'!D38/100<>0,'Indicadores x proyec'!D38/100,"-") -> - | D53: =IF('Indicadores x proyec'!E38/100<>0,'Indicadores x proyec'!E38/100,"-") -> - | E53: =IF('Indicadores x proyec'!F38/100<>0,'Indicadores x proyec'!F38/100,"-") -> - | F53: =IF('Indicadores x proyec'!G38/100<>0,'Indicadores x proyec'!G38/100,"-") -> - | G53: =IF('Indicadores x proyec'!H38/100<>0,'Indicadores x proyec'!H38/100,"-") -> - | H53: =IF('Indicadores x proyec'!I38<>0,'Indicadores x proyec'!I38,"-") -> Anual | I53: =IF('Indicadores x proyec'!J38<>0,'Indicadores x proyec'!J38,"-") -> -
A54: 3 | B54: =IF('Indicadores x proyec'!B40<>0,'Indicadores x proyec'!B40,"-") -> - | C54: =IF('Indicadores x proyec'!D40/100<>0,'Indicadores x proyec'!D40/100,"-") -> - | D54: =IF('Indicadores x proyec'!E40/100<>0,'Indicadores x proyec'!E40/100,"-") -> - | E54: =IF('Indicadores x proyec'!F40/100<>0,'Indicadores x proyec'!F40/100,"-") -> - | F54: =IF('Indicadores x proyec'!G40/100<>0,'Indicadores x proyec'!G40/100,"-") -> - | G54: =IF('Indicadores x proyec'!H40/100<>0,'Indicadores x proyec'!H40/100,"-") -> - | H54: =IF('Indicadores x proyec'!I40<>0,'Indicadores x proyec'!I40,"-") -> Anual | I54: =IF('Indicadores x proyec'!J40<>0,'Indicadores x proyec'!J40,"-") -> -
A55: 4 | B55: =IF('Indicadores x proyec'!B42<>0,'Indicadores x proyec'!B42,"-") -> - | C55: =IF('Indicadores x proyec'!D42/100<>0,'Indicadores x proyec'!D42/100,"-") -> - | D55: =IF('Indicadores x proyec'!E42/100<>0,'Indicadores x proyec'!E42/100,"-") -> - | E55: =IF('Indicadores x proyec'!F42/100<>0,'Indicadores x proyec'!F42/100,"-") -> - | F55: =IF('Indicadores x proyec'!G42/100<>0,'Indicadores x proyec'!G42/100,"-") -> - | G55: =IF('Indicadores x proyec'!H42/100<>0,'Indicadores x proyec'!H42/100,"-") -> - | H55: =IF('Indicadores x proyec'!I42<>0,'Indicadores x proyec'!I42,"-") -> Anual | I55: =IF('Indicadores x proyec'!J42<>0,'Indicadores x proyec'!J42,"-") -> -
A56: 5 | B56: =IF('4 Investigación abierta'!I10<>0,'4 Investigación abierta'!I10,"-") -> - | C56: =IF('4 Investigación abierta'!R10<>0,'4 Investigación abierta'!R10,"-") -> - | D56: =IF('4 Investigación abierta'!S10<>0,'4 Investigación abierta'!S10,"-") -> - | E56: =IF('4 Investigación abierta'!T10<>0,'4 Investigación abierta'!T10,"-") -> - | F56: =IF('4 Investigación abierta'!U10<>0,'4 Investigación abierta'!U10,"-") -> - | G56: =IF('4 Investigación abierta'!V10<>0,'4 Investigación abierta'!V10,"-") -> - | H56: =IF('4 Investigación abierta'!W10<>0,'4 Investigación abierta'!W10,"-") -> Anual | I56: =IF('4 Investigación abierta'!X10<>0,'4 Investigación abierta'!X10,"-") -> -
A57: 6 | B57: =IF('4 Investigación abierta'!I11<>0,'4 Investigación abierta'!I11,"-") -> - | C57: =IF('4 Investigación abierta'!R11<>0,'4 Investigación abierta'!R11,"-") -> - | D57: =IF('4 Investigación abierta'!S11<>0,'4 Investigación abierta'!S11,"-") -> - | E57: =IF('4 Investigación abierta'!T11<>0,'4 Investigación abierta'!T11,"-") -> - | F57: =IF('4 Investigación abierta'!U11<>0,'4 Investigación abierta'!U11,"-") -> - | G57: =IF('4 Investigación abierta'!V11<>0,'4 Investigación abierta'!V11,"-") -> - | H57: =IF('4 Investigación abierta'!W11<>0,'4 Investigación abierta'!W11,"-") -> Anual | I57: =IF('4 Investigación abierta'!X11<>0,'4 Investigación abierta'!X11,"-") -> -
A58: 7 | B58: =IF('Indicadores x proyec'!B44<>0,'Indicadores x proyec'!B44,"-") -> - | C58: =IF('Indicadores x proyec'!D44/100<>0,'Indicadores x proyec'!D44/100,"-") -> - | D58: =IF('Indicadores x proyec'!E44/100<>0,'Indicadores x proyec'!E44/100,"-") -> - | E58: =IF('Indicadores x proyec'!F44/100<>0,'Indicadores x proyec'!F44/100,"-") -> - | F58: =IF('Indicadores x proyec'!G44/100<>0,'Indicadores x proyec'!G44/100,"-") -> - | G58: =IF('Indicadores x proyec'!H44/100<>0,'Indicadores x proyec'!H44/100,"-") -> - | H58: =IF('Indicadores x proyec'!I44<>0,'Indicadores x proyec'!I44,"-") -> Anual | I58: =IF('Indicadores x proyec'!J44<>0,'Indicadores x proyec'!J44,"-") -> -
A59: 8 | B59: =IF('Indicadores x proyec'!B46<>0,'Indicadores x proyec'!B46,"-") -> - | C59: =IF('Indicadores x proyec'!D46/100<>0,'Indicadores x proyec'!D46/100,"-") -> - | D59: =IF('Indicadores x proyec'!E46/100<>0,'Indicadores x proyec'!E46/100,"-") -> - | E59: =IF('Indicadores x proyec'!F46/100<>0,'Indicadores x proyec'!F46/100,"-") -> - | F59: =IF('Indicadores x proyec'!G46/100<>0,'Indicadores x proyec'!G46/100,"-") -> - | G59: =IF('Indicadores x proyec'!H46/100<>0,'Indicadores x proyec'!H46/100,"-") -> - | H59: =IF('Indicadores x proyec'!I46<>0,'Indicadores x proyec'!I46,"-") -> Anual | I59: =IF('Indicadores x proyec'!J46<>0,'Indicadores x proyec'!J46,"-") -> -
A62: Innovación, desarrollo tecnológico y transferencia sostenible y equitativa
A63: No. | B63: Meta | C63: Ref. 2026 | D63: 2027 | E63: 2028 | F63: 2029 | G63: =TEXT($J$1,"mmmm") -> agosto | H63: Medición | I63: Área responsable
G64: 2030
A65: 1 | B65: =IF('5 Innovación, desarrollo tec'!I3<>0,'5 Innovación, desarrollo tec'!I3,"-") -> - | C65: =IF('5 Innovación, desarrollo tec'!R3<>0,'5 Innovación, desarrollo tec'!R3,"-") -> - | D65: =IF('5 Innovación, desarrollo tec'!S3<>0,'5 Innovación, desarrollo tec'!S3,"-") -> - | E65: =IF('5 Innovación, desarrollo tec'!T3<>0,'5 Innovación, desarrollo tec'!T3,"-") -> - | F65: =IF('5 Innovación, desarrollo tec'!U3<>0,'5 Innovación, desarrollo tec'!U3,"-") -> - | G65: =IF('5 Innovación, desarrollo tec'!V3<>0,'5 Innovación, desarrollo tec'!V3,"-") -> - | H65: =IF('5 Innovación, desarrollo tec'!W3<>0,'5 Innovación, desarrollo tec'!W3,"-") -> Anual | I65: =IF('5 Innovación, desarrollo tec'!X3<>0,'5 Innovación, desarrollo tec'!X3,"-") -> -
A66: 2 | B66: =IF('5 Innovación, desarrollo tec'!I4<>0,'5 Innovación, desarrollo tec'!I4,"-") -> - | C66: =IF('5 Innovación, desarrollo tec'!R4<>0,'5 Innovación, desarrollo tec'!R4,"-") -> - | D66: =IF('5 Innovación, desarrollo tec'!S4<>0,'5 Innovación, desarrollo tec'!S4,"-") -> - | E66: =IF('5 Innovación, desarrollo tec'!T4<>0,'5 Innovación, desarrollo tec'!T4,"-") -> - | F66: =IF('5 Innovación, desarrollo tec'!U4<>0,'5 Innovación, desarrollo tec'!U4,"-") -> - | G66: =IF('5 Innovación, desarrollo tec'!V4<>0,'5 Innovación, desarrollo tec'!V4,"-") -> - | H66: =IF('5 Innovación, desarrollo tec'!W4<>0,'5 Innovación, desarrollo tec'!W4,"-") -> Anual | I66: =IF('5 Innovación, desarrollo tec'!X4<>0,'5 Innovación, desarrollo tec'!X4,"-") -> -
A69: Difusión y divulgación de la ciencia abierta a través de bienes públicos del conocimiento
A70: No. | B70: Meta | C70: Ref. 2026 | D70: 2027 | E70: 2028 | F70: 2029 | G70: =TEXT($J$1,"mmmm") -> agosto | H70: Medición | I70: Área responsable
G71: 2030
A72: 1 | B72: =IF('6 Dif y divulga de la ciencia'!I3<>0,'6 Dif y divulga de la ciencia'!I3,"-") -> - | C72: =IF('6 Dif y divulga de la ciencia'!R3<>0,'6 Dif y divulga de la ciencia'!R3,"-") -> - | D72: =IF('6 Dif y divulga de la ciencia'!S3<>0,'6 Dif y divulga de la ciencia'!S3,"-") -> - | E72: =IF('6 Dif y divulga de la ciencia'!T3<>0,'6 Dif y divulga de la ciencia'!T3,"-") -> - | F72: =IF('6 Dif y divulga de la ciencia'!U3<>0,'6 Dif y divulga de la ciencia'!U3,"-") -> - | G72: =IF('6 Dif y divulga de la ciencia'!V3<>0,'6 Dif y divulga de la ciencia'!V3,"-") -> - | H72: =IF('6 Dif y divulga de la ciencia'!W3<>0,'6 Dif y divulga de la ciencia'!W3,"-") -> Anual | I72: =IF('6 Dif y divulga de la ciencia'!X3<>0,'6 Dif y divulga de la ciencia'!X3,"-") -> -
A73: 2 | B73: =IF('6 Dif y divulga de la ciencia'!I4<>0,'6 Dif y divulga de la ciencia'!I4,"-") -> - | C73: =IF('6 Dif y divulga de la ciencia'!R4<>0,'6 Dif y divulga de la ciencia'!R4,"-") -> - | D73: =IF('6 Dif y divulga de la ciencia'!S4<>0,'6 Dif y divulga de la ciencia'!S4,"-") -> - | E73: =IF('6 Dif y divulga de la ciencia'!T4<>0,'6 Dif y divulga de la ciencia'!T4,"-") -> - | F73: =IF('6 Dif y divulga de la ciencia'!U4<>0,'6 Dif y divulga de la ciencia'!U4,"-") -> - | G73: =IF('6 Dif y divulga de la ciencia'!V4<>0,'6 Dif y divulga de la ciencia'!V4,"-") -> - | H73: =IF('6 Dif y divulga de la ciencia'!W4<>0,'6 Dif y divulga de la ciencia'!W4,"-") -> Anual | I73: =IF('6 Dif y divulga de la ciencia'!X4<>0,'6 Dif y divulga de la ciencia'!X4,"-") -> -
A74: 3 | B74: =IF('6 Dif y divulga de la ciencia'!I5<>0,'6 Dif y divulga de la ciencia'!I5,"-") -> - | C74: =IF('6 Dif y divulga de la ciencia'!R5<>0,'6 Dif y divulga de la ciencia'!R5,"-") -> - | D74: =IF('6 Dif y divulga de la ciencia'!S5<>0,'6 Dif y divulga de la ciencia'!S5,"-") -> - | E74: =IF('6 Dif y divulga de la ciencia'!T5<>0,'6 Dif y divulga de la ciencia'!T5,"-") -> - | F74: =IF('6 Dif y divulga de la ciencia'!U5<>0,'6 Dif y divulga de la ciencia'!U5,"-") -> - | G74: =IF('6 Dif y divulga de la ciencia'!V5<>0,'6 Dif y divulga de la ciencia'!V5,"-") -> - | H74: =IF('6 Dif y divulga de la ciencia'!W5<>0,'6 Dif y divulga de la ciencia'!W5,"-") -> Anual | I74: =IF('6 Dif y divulga de la ciencia'!X5<>0,'6 Dif y divulga de la ciencia'!X5,"-") -> -
A76: III. Cultura y deporte para el desarrollo integral de la comunidad universitaria
A77: Cultura para el desarrollo integral de la comunidad universitaria
A78: No. | B78: Meta | C78: Ref. 2026 | D78: 2027 | E78: 2028 | F78: 2029 | G78: =TEXT($J$1,"mmmm") -> agosto | H78: Medición | I78: Área responsable
G79: 2030
A80: 1 | B80: =IF('7 Cultura desarrollo integral'!I3<>0,'7 Cultura desarrollo integral'!I3,"-") -> - | C80: =IF('7 Cultura desarrollo integral'!R3<>0,'7 Cultura desarrollo integral'!R3,"-") -> - | D80: =IF('7 Cultura desarrollo integral'!S3<>0,'7 Cultura desarrollo integral'!S3,"-") -> - | E80: =IF('7 Cultura desarrollo integral'!T3<>0,'7 Cultura desarrollo integral'!T3,"-") -> - | F80: =IF('7 Cultura desarrollo integral'!U3<>0,'7 Cultura desarrollo integral'!U3,"-") -> - | G80: =IF('7 Cultura desarrollo integral'!V3<>0,'7 Cultura desarrollo integral'!V3,"-") -> - | H80: =IF('7 Cultura desarrollo integral'!W3<>0,'7 Cultura desarrollo integral'!W3,"-") -> Anual | I80: =IF('7 Cultura desarrollo integral'!X3<>0,'7 Cultura desarrollo integral'!X3,"-") -> -
A81: 2 | B81: =IF('7 Cultura desarrollo integral'!I4<>0,'7 Cultura desarrollo integral'!I4,"-") -> - | C81: =IF('7 Cultura desarrollo integral'!R4<>0,'7 Cultura desarrollo integral'!R4,"-") -> - | D81: =IF('7 Cultura desarrollo integral'!S4<>0,'7 Cultura desarrollo integral'!S4,"-") -> - | E81: =IF('7 Cultura desarrollo integral'!T4<>0,'7 Cultura desarrollo integral'!T4,"-") -> - | F81: =IF('7 Cultura desarrollo integral'!U4<>0,'7 Cultura desarrollo integral'!U4,"-") -> - | G81: =IF('7 Cultura desarrollo integral'!V4<>0,'7 Cultura desarrollo integral'!V4,"-") -> - | H81: =IF('7 Cultura desarrollo integral'!W4<>0,'7 Cultura desarrollo integral'!W4,"-") -> Anual | I81: =IF('7 Cultura desarrollo integral'!X4<>0,'7 Cultura desarrollo integral'!X4,"-") -> -
A82: 3 | B82: =IF('7 Cultura desarrollo integral'!I5<>0,'7 Cultura desarrollo integral'!I5,"-") -> - | C82: =IF('7 Cultura desarrollo integral'!R5<>0,'7 Cultura desarrollo integral'!R5,"-") -> - | D82: =IF('7 Cultura desarrollo integral'!S5<>0,'7 Cultura desarrollo integral'!S5,"-") -> - | E82: =IF('7 Cultura desarrollo integral'!T5<>0,'7 Cultura desarrollo integral'!T5,"-") -> - | F82: =IF('7 Cultura desarrollo integral'!U5<>0,'7 Cultura desarrollo integral'!U5,"-") -> - | G82: =IF('7 Cultura desarrollo integral'!V5<>0,'7 Cultura desarrollo integral'!V5,"-") -> - | H82: =IF('7 Cultura desarrollo integral'!W5<>0,'7 Cultura desarrollo integral'!W5,"-") -> Anual | I82: =IF('7 Cultura desarrollo integral'!X5<>0,'7 Cultura desarrollo integral'!X5,"-") -> -
A83: 4 | B83: =IF('7 Cultura desarrollo integral'!I6<>0,'7 Cultura desarrollo integral'!I6,"-") -> - | C83: =IF('7 Cultura desarrollo integral'!R6<>0,'7 Cultura desarrollo integral'!R6,"-") -> - | D83: =IF('7 Cultura desarrollo integral'!S6<>0,'7 Cultura desarrollo integral'!S6,"-") -> - | E83: =IF('7 Cultura desarrollo integral'!T6<>0,'7 Cultura desarrollo integral'!T6,"-") -> - | F83: =IF('7 Cultura desarrollo integral'!U6<>0,'7 Cultura desarrollo integral'!U6,"-") -> - | G83: =IF('7 Cultura desarrollo integral'!V6<>0,'7 Cultura desarrollo integral'!V6,"-") -> - | H83: =IF('7 Cultura desarrollo integral'!W6<>0,'7 Cultura desarrollo integral'!W6,"-") -> Anual | I83: =IF('7 Cultura desarrollo integral'!X6<>0,'7 Cultura desarrollo integral'!X6,"-") -> -
A84: 5 | B84: =IF('7 Cultura desarrollo integral'!I7<>0,'7 Cultura desarrollo integral'!I7,"-") -> - | C84: =IF('7 Cultura desarrollo integral'!R7<>0,'7 Cultura desarrollo integral'!R7,"-") -> - | D84: =IF('7 Cultura desarrollo integral'!S7<>0,'7 Cultura desarrollo integral'!S7,"-") -> - | E84: =IF('7 Cultura desarrollo integral'!T7<>0,'7 Cultura desarrollo integral'!T7,"-") -> - | F84: =IF('7 Cultura desarrollo integral'!U7<>0,'7 Cultura desarrollo integral'!U7,"-") -> - | G84: =IF('7 Cultura desarrollo integral'!V7<>0,'7 Cultura desarrollo integral'!V7,"-") -> - | H84: =IF('7 Cultura desarrollo integral'!W7<>0,'7 Cultura desarrollo integral'!W7,"-") -> Anual | I84: =IF('7 Cultura desarrollo integral'!X7<>0,'7 Cultura desarrollo integral'!X7,"-") -> -
A85: 6 | B85: =IF('7 Cultura desarrollo integral'!I8<>0,'7 Cultura desarrollo integral'!I8,"-") -> - | C85: =IF('7 Cultura desarrollo integral'!R8<>0,'7 Cultura desarrollo integral'!R8,"-") -> - | D85: =IF('7 Cultura desarrollo integral'!S8<>0,'7 Cultura desarrollo integral'!S8,"-") -> - | E85: =IF('7 Cultura desarrollo integral'!T8<>0,'7 Cultura desarrollo integral'!T8,"-") -> - | F85: =IF('7 Cultura desarrollo integral'!U8<>0,'7 Cultura desarrollo integral'!U8,"-") -> - | G85: =IF('7 Cultura desarrollo integral'!V8<>0,'7 Cultura desarrollo integral'!V8,"-") -> - | H85: =IF('7 Cultura desarrollo integral'!W8<>0,'7 Cultura desarrollo integral'!W8,"-") -> Anual | I85: =IF('7 Cultura desarrollo integral'!X8<>0,'7 Cultura desarrollo integral'!X8,"-") -> -
A88: Deporte universitario
A89: No. | B89: Meta | C89: Ref. 2026 | D89: 2027 | E89: 2028 | F89: 2029 | G89: =TEXT($J$1,"mmmm") -> agosto | H89: Medición | I89: Área responsable
G90: 2030
A91: 1 | B91: =IF('8 Deporte universitario'!I3<>0,'8 Deporte universitario'!I3,"-") -> - | C91: =IF('8 Deporte universitario'!R3<>0,'8 Deporte universitario'!R3,"-") -> - | D91: =IF('8 Deporte universitario'!S3<>0,'8 Deporte universitario'!S3,"-") -> - | E91: =IF('8 Deporte universitario'!T3<>0,'8 Deporte universitario'!T3,"-") -> - | F91: =IF('8 Deporte universitario'!U3<>0,'8 Deporte universitario'!U3,"-") -> - | G91: =IF('8 Deporte universitario'!V3<>0,'8 Deporte universitario'!V3,"-") -> - | H91: =IF('8 Deporte universitario'!W3<>0,'8 Deporte universitario'!W3,"-") -> Anual | I91: =IF('8 Deporte universitario'!X3<>0,'8 Deporte universitario'!X3,"-") -> -
A92: 2 | B92: =IF('Indicadores x proyec'!B52<>0,'Indicadores x proyec'!B52,"-") -> - | C92: =IF('Indicadores x proyec'!D52/100<>0,'Indicadores x proyec'!D52/100,"-") -> - | D92: =IF('Indicadores x proyec'!E52/100<>0,'Indicadores x proyec'!E52/100,"-") -> - | E92: =IF('Indicadores x proyec'!F52/100<>0,'Indicadores x proyec'!F52/100,"-") -> - | F92: =IF('Indicadores x proyec'!G52/100<>0,'Indicadores x proyec'!G52/100,"-") -> - | G92: =IF('Indicadores x proyec'!H52/100<>0,'Indicadores x proyec'!H52/100,"-") -> - | H92: =IF('Indicadores x proyec'!I52<>0,'Indicadores x proyec'!I52,"-") -> Anual | I92: =IF('Indicadores x proyec'!J52<>0,'Indicadores x proyec'!J52,"-") -> -
A93: 3 | B93: =IF('Indicadores x proyec'!B54<>0,'Indicadores x proyec'!B54,"-") -> - | C93: =IF('Indicadores x proyec'!D54/100<>0,'Indicadores x proyec'!D54/100,"-") -> - | D93: =IF('Indicadores x proyec'!E54/100<>0,'Indicadores x proyec'!E54/100,"-") -> - | E93: =IF('Indicadores x proyec'!F54/100<>0,'Indicadores x proyec'!F54/100,"-") -> - | F93: =IF('Indicadores x proyec'!G54/100<>0,'Indicadores x proyec'!G54/100,"-") -> - | G93: =IF('Indicadores x proyec'!H54/100<>0,'Indicadores x proyec'!H54/100,"-") -> - | H93: =IF('Indicadores x proyec'!I54<>0,'Indicadores x proyec'!I54,"-") -> Anual | I93: =IF('Indicadores x proyec'!J54<>0,'Indicadores x proyec'!J54,"-") -> -
A94: 4 | B94: =IF('Indicadores x proyec'!B56<>0,'Indicadores x proyec'!B56,"-") -> - | C94: =IF('Indicadores x proyec'!D56/100<>0,'Indicadores x proyec'!D56/100,"-") -> - | D94: =IF('Indicadores x proyec'!E56/100<>0,'Indicadores x proyec'!E56/100,"-") -> - | E94: =IF('Indicadores x proyec'!F56/100<>0,'Indicadores x proyec'!F56/100,"-") -> - | F94: =IF('Indicadores x proyec'!G56/100<>0,'Indicadores x proyec'!G56/100,"-") -> - | G94: =IF('Indicadores x proyec'!H56/100<>0,'Indicadores x proyec'!H56/100,"-") -> - | H94: =IF('Indicadores x proyec'!I56<>0,'Indicadores x proyec'!I56,"-") -> Anual | I94: =IF('Indicadores x proyec'!J56<>0,'Indicadores x proyec'!J56,"-") -> -
A95: 5 | B95: =IF('8 Deporte universitario'!I10<>0,'8 Deporte universitario'!I10,"-") -> - | C95: =IF('8 Deporte universitario'!R10<>0,'8 Deporte universitario'!R10,"-") -> - | D95: =IF('8 Deporte universitario'!S10<>0,'8 Deporte universitario'!S10,"-") -> - | E95: =IF('8 Deporte universitario'!T10<>0,'8 Deporte universitario'!T10,"-") -> - | F95: =IF('8 Deporte universitario'!U10<>0,'8 Deporte universitario'!U10,"-") -> - | G95: =IF('8 Deporte universitario'!V10<>0,'8 Deporte universitario'!V10,"-") -> - | H95: =IF('8 Deporte universitario'!W10<>0,'8 Deporte universitario'!W10,"-") -> Anual | I95: =IF('8 Deporte universitario'!X10<>0,'8 Deporte universitario'!X10,"-") -> -
A98: IV. Dignificación del personal académico y administrativo
A99: Fortalecimiento de la formación integral del docente
A100: No. | B100: Meta | C100: Ref. 2026 | D100: 2027 | E100: 2028 | F100: 2029 | G100: =TEXT($J$1,"mmmm") -> agosto | H100: Medición | I100: Área responsable
G101: 2030
A102: 1 | B102: =IF('Indicadores x proyec'!B62<>0,'Indicadores x proyec'!B62,"-") -> - | C102: =IF('Indicadores x proyec'!D62/100<>0,'Indicadores x proyec'!D62/100,"-") -> - | D102: =IF('Indicadores x proyec'!E62/100<>0,'Indicadores x proyec'!E62/100,"-") -> - | E102: =IF('Indicadores x proyec'!F62/100<>0,'Indicadores x proyec'!F62/100,"-") -> - | F102: =IF('Indicadores x proyec'!G62/100<>0,'Indicadores x proyec'!G62/100,"-") -> - | G102: =IF('Indicadores x proyec'!H62/100<>0,'Indicadores x proyec'!H62/100,"-") -> - | H102: =IF('Indicadores x proyec'!I62<>0,'Indicadores x proyec'!I62,"-") -> Anual | I102: =IF('Indicadores x proyec'!J62<>0,'Indicadores x proyec'!J62,"-") -> -
A103: 2 | B103: =IF('Indicadores x proyec'!B64<>0,'Indicadores x proyec'!B64,"-") -> - | C103: =IF('Indicadores x proyec'!D64/100<>0,'Indicadores x proyec'!D64/100,"-") -> - | D103: =IF('Indicadores x proyec'!E64/100<>0,'Indicadores x proyec'!E64/100,"-") -> - | E103: =IF('Indicadores x proyec'!F64/100<>0,'Indicadores x proyec'!F64/100,"-") -> - | F103: =IF('Indicadores x proyec'!G64/100<>0,'Indicadores x proyec'!G64/100,"-") -> - | G103: =IF('Indicadores x proyec'!H64/100<>0,'Indicadores x proyec'!H64/100,"-") -> - | H103: =IF('Indicadores x proyec'!I64<>0,'Indicadores x proyec'!I64,"-") -> Anual | I103: =IF('Indicadores x proyec'!J64<>0,'Indicadores x proyec'!J64,"-") -> -
A104: 3 | B104: =IF('Indicadores x proyec'!B66<>0,'Indicadores x proyec'!B66,"-") -> - | C104: =IF('Indicadores x proyec'!D66/100<>0,'Indicadores x proyec'!D66/100,"-") -> - | D104: =IF('Indicadores x proyec'!E66/100<>0,'Indicadores x proyec'!E66/100,"-") -> - | E104: =IF('Indicadores x proyec'!F66/100<>0,'Indicadores x proyec'!F66/100,"-") -> - | F104: =IF('Indicadores x proyec'!G66/100<>0,'Indicadores x proyec'!G66/100,"-") -> - | G104: =IF('Indicadores x proyec'!H66/100<>0,'Indicadores x proyec'!H66/100,"-") -> - | H104: =IF('Indicadores x proyec'!I66<>0,'Indicadores x proyec'!I66,"-") -> Anual | I104: =IF('Indicadores x proyec'!J66<>0,'Indicadores x proyec'!J66,"-") -> -
A105: 4 | B105: =IF('Indicadores x proyec'!B68<>0,'Indicadores x proyec'!B68,"-") -> - | C105: =IF('Indicadores x proyec'!D68/100<>0,'Indicadores x proyec'!D68/100,"-") -> - | D105: =IF('Indicadores x proyec'!E68/100<>0,'Indicadores x proyec'!E68/100,"-") -> - | E105: =IF('Indicadores x proyec'!F68/100<>0,'Indicadores x proyec'!F68/100,"-") -> - | F105: =IF('Indicadores x proyec'!G68/100<>0,'Indicadores x proyec'!G68/100,"-") -> - | G105: =IF('Indicadores x proyec'!H68/100<>0,'Indicadores x proyec'!H68/100,"-") -> - | H105: =IF('Indicadores x proyec'!I68<>0,'Indicadores x proyec'!I68,"-") -> Anual | I105: =IF('Indicadores x proyec'!J68<>0,'Indicadores x proyec'!J68,"-") -> -
A106: 5 | B106: =IF('Indicadores x proyec'!B70<>0,'Indicadores x proyec'!B70,"-") -> - | C106: =IF('Indicadores x proyec'!D70/100<>0,'Indicadores x proyec'!D70/100,"-") -> - | D106: =IF('Indicadores x proyec'!E70/100<>0,'Indicadores x proyec'!E70/100,"-") -> - | E106: =IF('Indicadores x proyec'!F70/100<>0,'Indicadores x proyec'!F70/100,"-") -> - | F106: =IF('Indicadores x proyec'!G70/100<>0,'Indicadores x proyec'!G70/100,"-") -> - | G106: =IF('Indicadores x proyec'!H70/100<>0,'Indicadores x proyec'!H70/100,"-") -> - | H106: =IF('Indicadores x proyec'!I70<>0,'Indicadores x proyec'!I70,"-") -> Anual | I106: =IF('Indicadores x proyec'!J70<>0,'Indicadores x proyec'!J70,"-") -> -
A107: 6 | B107: =IF('9 Fortalecimiento docente'!I13<>0,'9 Fortalecimiento docente'!I13,"-") -> - | C107: =IF('9 Fortalecimiento docente'!R13<>0,'9 Fortalecimiento docente'!R13,"-") -> - | D107: =IF('9 Fortalecimiento docente'!S13<>0,'9 Fortalecimiento docente'!S13,"-") -> - | E107: =IF('9 Fortalecimiento docente'!T13<>0,'9 Fortalecimiento docente'!T13,"-") -> - | F107: =IF('9 Fortalecimiento docente'!U13<>0,'9 Fortalecimiento docente'!U13,"-") -> - | G107: =IF('9 Fortalecimiento docente'!V13<>0,'9 Fortalecimiento docente'!V13,"-") -> - | H107: =IF('9 Fortalecimiento docente'!W13<>0,'9 Fortalecimiento docente'!W13,"-") -> Anual | I107: =IF('9 Fortalecimiento docente'!X13<>0,'9 Fortalecimiento docente'!X13,"-") -> -
A108: 7 | B108: =IF('9 Fortalecimiento docente'!I14<>0,'9 Fortalecimiento docente'!I14,"-") -> - | C108: =IF('9 Fortalecimiento docente'!R14<>0,'9 Fortalecimiento docente'!R14,"-") -> - | D108: =IF('9 Fortalecimiento docente'!S14<>0,'9 Fortalecimiento docente'!S14,"-") -> - | E108: =IF('9 Fortalecimiento docente'!T14<>0,'9 Fortalecimiento docente'!T14,"-") -> - | F108: =IF('9 Fortalecimiento docente'!U14<>0,'9 Fortalecimiento docente'!U14,"-") -> - | G108: =IF('9 Fortalecimiento docente'!V14<>0,'9 Fortalecimiento docente'!V14,"-") -> - | H108: =IF('9 Fortalecimiento docente'!W14<>0,'9 Fortalecimiento docente'!W14,"-") -> Acumulada | I108: =IF('9 Fortalecimiento docente'!X14<>0,'9 Fortalecimiento docente'!X14,"-") -> -
A109: 8 | B109: =IF('Indicadores x proyec'!B72<>0,'Indicadores x proyec'!B72,"-") -> - | C109: =IF('Indicadores x proyec'!D72/100<>0,'Indicadores x proyec'!D72/100,"-") -> - | D109: =IF('Indicadores x proyec'!E72/100<>0,'Indicadores x proyec'!E72/100,"-") -> - | E109: =IF('Indicadores x proyec'!F72/100<>0,'Indicadores x proyec'!F72/100,"-") -> - | F109: =IF('Indicadores x proyec'!G72/100<>0,'Indicadores x proyec'!G72/100,"-") -> - | G109: =IF('Indicadores x proyec'!H72/100<>0,'Indicadores x proyec'!H72/100,"-") -> - | H109: =IF('Indicadores x proyec'!I72<>0,'Indicadores x proyec'!I72,"-") -> Acumulada | I109: =IF('Indicadores x proyec'!J72<>0,'Indicadores x proyec'!J72,"-") -> -
A110: 9 | B110: =IF('9 Fortalecimiento docente'!I17<>0,'9 Fortalecimiento docente'!I17,"-") -> - | C110: =IF('9 Fortalecimiento docente'!R17<>0,'9 Fortalecimiento docente'!R17,"-") -> - | D110: =IF('9 Fortalecimiento docente'!S17<>0,'9 Fortalecimiento docente'!S17,"-") -> - | E110: =IF('9 Fortalecimiento docente'!T17<>0,'9 Fortalecimiento docente'!T17,"-") -> - | F110: =IF('9 Fortalecimiento docente'!U17<>0,'9 Fortalecimiento docente'!U17,"-") -> - | G110: =IF('9 Fortalecimiento docente'!V17<>0,'9 Fortalecimiento docente'!V17,"-") -> - | H110: =IF('9 Fortalecimiento docente'!W17<>0,'9 Fortalecimiento docente'!W17,"-") -> Anual | I110: =IF('9 Fortalecimiento docente'!X17<>0,'9 Fortalecimiento docente'!X17,"-") -> -
A111: 10 | B111: =IF('9 Fortalecimiento docente'!I18<>0,'9 Fortalecimiento docente'!I18,"-") -> - | C111: =IF('9 Fortalecimiento docente'!R18<>0,'9 Fortalecimiento docente'!R18,"-") -> - | D111: =IF('9 Fortalecimiento docente'!S18<>0,'9 Fortalecimiento docente'!S18,"-") -> - | E111: =IF('9 Fortalecimiento docente'!T18<>0,'9 Fortalecimiento docente'!T18,"-") -> - | F111: =IF('9 Fortalecimiento docente'!U18<>0,'9 Fortalecimiento docente'!U18,"-") -> - | G111: =IF('9 Fortalecimiento docente'!V18<>0,'9 Fortalecimiento docente'!V18,"-") -> - | H111: =IF('9 Fortalecimiento docente'!W18<>0,'9 Fortalecimiento docente'!W18,"-") -> Anual | I111: =IF('9 Fortalecimiento docente'!X18<>0,'9 Fortalecimiento docente'!X18,"-") -> -
A114: Dignificación de las y los trabajadores universitarios
A115: No. | B115: Meta | C115: Ref. 2026 | D115: 2027 | E115: 2028 | F115: 2029 | G115: =TEXT($J$1,"mmmm") -> agosto | H115: Medición | I115: Área responsable
G116: 2029
A117: 1 | B117: =IF('Indicadores x proyec'!B78<>0,'Indicadores x proyec'!B78,"-") -> - | C117: =IF('Indicadores x proyec'!D78/100<>0,'Indicadores x proyec'!D78/100,"-") -> - | D117: =IF('Indicadores x proyec'!E78/100<>0,'Indicadores x proyec'!E78/100,"-") -> - | E117: =IF('Indicadores x proyec'!F78/100<>0,'Indicadores x proyec'!F78/100,"-") -> - | F117: =IF('Indicadores x proyec'!G78/100<>0,'Indicadores x proyec'!G78/100,"-") -> - | G117: =IF('Indicadores x proyec'!H78/100<>0,'Indicadores x proyec'!H78/100,"-") -> - | H117: =IF('Indicadores x proyec'!I78<>0,'Indicadores x proyec'!I78,"-") -> Anual | I117: =IF('Indicadores x proyec'!J78<>0,'Indicadores x proyec'!J78,"-") -> -
...

Sheet Metas adicionales
A1: Proyecto | B1: Meta del espacio académico | C1: Actividad/Indicador | D1: Método de cálculo (sólo si la meta es un indicador) | E1: Nombre de las variables (sólo si la meta es un indicador) | P1: Medición (anual o acumulada) | Q1: Área responsable
F2: Ref. 2026 | G2: 2027 | H2: 2028 | I2: 2029 | J2: 2030 | K2: Ref. 2026 | L2: 2027 | M2: 2028 | N2: 2029 | O2: 2030
A3: 2. Estudiantado con oportunidades para su pleno desarrollo y pertinencia en los estudios profesionales | B3: Validar y documentar el valor de Ref. 2026 durante 2027 y, una vez confirmado, mantenerlo o mejorarlo hasta 2030. | C3: Indicador | D3: La memoria de cálculo no aporta variables completas para este indicador en Ref. 2026; el dato histórico anterior queda como contexto y no como línea base del plan. | E3: Espacio académico | K3: =IF(F3="","",F3) | L3: =IF(G3="","",G3) | M3: =IF(H3="","",H3) | N3: =IF(I3="","",I3) | O3: =IF(J3="","",J3) | P3: Anual | Q3: Por validar con el área responsable
A4: 2. Estudiantado con oportunidades para su pleno desarrollo y pertinencia en los estudios profesionales | B4: Realizar 1 revisión documentada de las trayectorias y asignaturas con mayor rezago en 2027 y actualizarla una vez al año de 2028 a 2030. | C4: Actividad | D4: Sin fórmula | E4: Cumplimiento anual de la meta (0=no, 1=sí) | G4: 1 | H4: 1 | I4: 1 | J4: 1 | K4: =IF(F4="","",F4) | L4: =IF(G4="","",G4) -> 1 | M4: =IF(H4="","",H4) -> 1 | N4: =IF(I4="","",I4) -> 1 | O4: =IF(J4="","",J4) -> 1 | P4: Anual | Q4: Por validar con el área responsable
A5: 2. Estudiantado con oportunidades para su pleno desarrollo y pertinencia en los estudios profesionales | B5: Realizar 1 reunión y 1 encuesta a estudiantes de cada licenciatura cada año de 2028 a 2030 y documentar los ajustes derivados. | C5: Actividad | D5: Sin fórmula | E5: Cumplimiento anual de la meta (0=no, 1=sí) | H5: 1 | I5: 1 | J5: 1 | K5: =IF(F5="","",F5) | L5: =IF(G5="","",G5) | M5: =IF(H5="","",H5) -> 1 | N5: =IF(I5="","",I5) -> 1 | O5: =IF(J5="","",J5) -> 1 | P5: Anual | Q5: Por validar con el área responsable
A6: 3. Estudios avanzados de excelencia y pertinencia social | B6: Validar y documentar el valor de Ref. 2026 durante 2027 y, una vez confirmado, mantenerlo o mejorarlo hasta 2030. | C6: Indicador | D6: La memoria de cálculo no aporta variables completas para este indicador en Ref. 2026; el dato histórico anterior queda como contexto y no como línea base del plan. | E6: Matricula_UAEMEX | K6: =IF(F6="","",F6) | L6: =IF(G6="","",G6) | M6: =IF(H6="","",H6) | N6: =IF(I6="","",I6) | O6: =IF(J6="","",J6) | P6: Anual | Q6: Por validar con el área responsable
