Workbook
Name _Toc82616607: '2 EstudiantadoEstProf'!#REF!

Sheet 2 EstudiantadoEstProf
A1: N.P. | B1: Clave Objetivo General | C1: Objetivo General | D1: Clave Objetivo Específico | E1: Objetivo Específico | F1: No. de meta en el PRDI | G1: Meta PRDI | H1: Clave de la meta | I1: Meta del espacio académico | J1: Actividad/Indicador | K1: Método de cálculo | L1: Nombre de las variables | M1: Valor de las variables | R1: Valor de los indicadores | W1: Medición (anual o acumulada) | X1: Área responsable | AN1: ESTATUS
M2: Ref. 2026 | N2: 2027 | O2: 2028 | P2: 2029 | Q2: 2030 | R2: Ref. 2026 | S2: 2027 | T2: 2028 | U2: 2029 | V2: 2030
A3: 1 | B3: PRDI25-29-Obj-36 | C3: Formar estudiantes de excelencia, a través de estudios profesionales pertinentes e inclusivos, con una vinculación permanente con estudiantes y personas egresadas, para su pleno desarrollo profesional y su contribución al bienestar social. | D3: PRDI2025-2029-Obj-58 | E3: Contar con planes de estudio pertinentes y de excelencia, en diferentes modalidades, que incorporen los criterios transversales del SEAES, de indicadores de instancias de evaluación externa y acreditación, y de organismos acreditadores, para formar profesionistas que contribuyan a la conformación de una sociedad más justa, libre, incluyente y pacífica, con una visión de sostenibilidad. | F3: 3 | G3: Incorporar contenidos temáticos o actividades académicas sobre los criterios transversales del seaes, en 30 planes de estudio reestructurados, durante la administración | H3: ACT-PRDI-NS-2726 | I3: Contribuir desde la Facultad de Ingeniería al cumplimiento de la meta PRDI “Incorporar contenidos temáticos o actividades académicas sobre los criterios transversales del seaes, en 30 planes de estudio reestructurados, durante la administración”, con valores absolutos programados de 2027: 1, 2028: 0, 2029: 0, 2030: 0. | J3: Actividad | K3: Sin fórmula | L3: Incorporar contenidos temáticos o actividades académicas sobre los criterios transversales del seaes, en planes de estudio reestructurados | N3: 1 | O3: 0 | P3: 0 | Q3: 0 | R3: =IF(M3="","",M3) | S3: =IF(N3="","",N3) -> 1 | T3: =IF(O3="","",O3) -> 0 | U3: =IF(P3="","",P3) -> 0 | V3: =IF(Q3="","",Q3) -> 0 | W3: Anual | X3: Subdirección Académica y coordinaciones de licenciatura
A4: 2 | B4: PRDI25-29-Obj-36 | C4: Formar estudiantes de excelencia, a través de estudios profesionales pertinentes e inclusivos, con una vinculación permanente con estudiantes y personas egresadas, para su pleno desarrollo profesional y su contribución al bienestar social. | D4: PRDI2025-2029-Obj-58 | E4: Contar con planes de estudio pertinentes y de excelencia, en diferentes modalidades, que incorporen los criterios transversales del SEAES, de indicadores de instancias de evaluación externa y acreditación, y de organismos acreditadores, para formar profesionistas que contribuyan a la conformación de una sociedad más justa, libre, incluyente y pacífica, con una visión de sostenibilidad. | F4: 4 | G4: Contar con el acervo de 120 unidades de aprendizaje de estudios profesionales apegados a las referencias documentales básicas durante la administración | H4: ACT-PRDI-NS-2727 | I4: Contribuir desde la Facultad de Ingeniería al cumplimiento de la meta PRDI “Contar con el acervo de 120 unidades de aprendizaje de estudios profesionales apegados a las referencias documentales básicas durante la administración”, con valores absolutos programados de 2027: 1, 2028: 1, 2029: 1, 2030: 0. | J4: Actividad | K4: Sin fórmula | L4: Contar con el acervo de unidades de aprendizaje de estudios profesionales apegados a las referencias documentales básicas | N4: 1 | O4: 1 | P4: 1 | Q4: 0 | R4: =IF(M4="","",M4) | S4: =IF(N4="","",N4) -> 1 | T4: =IF(O4="","",O4) -> 1 | U4: =IF(P4="","",P4) -> 1 | V4: =IF(Q4="","",Q4) -> 0 | W4: Anual | X4: Subdirección Académica y coordinaciones de licenciatura
A5: 3 | B5: PRDI25-29-Obj-36 | C5: Formar estudiantes de excelencia, a través de estudios profesionales pertinentes e inclusivos, con una vinculación permanente con estudiantes y personas egresadas, para su pleno desarrollo profesional y su contribución al bienestar social. | D5: PRDI2025-2029-Obj-58 | E5: Contar con planes de estudio pertinentes y de excelencia, en diferentes modalidades, que incorporen los criterios transversales del SEAES, de indicadores de instancias de evaluación externa y acreditación, y de organismos acreditadores, para formar profesionistas que contribuyan a la conformación de una sociedad más justa, libre, incluyente y pacífica, con una visión de sostenibilidad. | F5: 7 | G5: Lograr que 89.13% de los programas educativos de estudios profesionales evaluables cuenten con reconocimiento por su excelencia, para 2029 | H5: IND-NS-210 | I5: Mejorar o mantener de forma conservadora en la Facultad de Ingeniería el indicador IND-NS-210, con la trayectoria 2027: 80%, 2028: 80%, 2029: 80%, 2030: 80%, sustentada en referencia PRDI; no existe serie histórica directamente comparable para la variable. | J5: Indicador | K5: (Número de programas educativos de estudios profesionales con reconocimiento por su excelencia / Número de programas educativos de Estudios Profesionales evaluables)*100 | L5: Número de programas educativos de estudios profesionales con reconocimiento por su excelencia | N5: 4 | O5: 4 | P5: 4 | Q5: 4 | R5: =IF(M6,M5/M6*100,"") | S5: =IF(N6,N5/N6*100,"") -> 80 | T5: =IF(O6,O5/O6*100,"") -> 80 | U5: =IF(P6,P5/P6*100,"") -> 80 | V5: =IF(Q6,Q5/Q6*100,"") -> 80 | W5: Anual | X5: Subdirección Académica y coordinaciones de licenciatura
L6: Número de programas educativos de Estudios Profesionales evaluables | N6: 5 | O6: 5 | P6: 5 | Q6: 5
A7: 4 | B7: PRDI25-29-Obj-36 | C7: Formar estudiantes de excelencia, a través de estudios profesionales pertinentes e inclusivos, con una vinculación permanente con estudiantes y personas egresadas, para su pleno desarrollo profesional y su contribución al bienestar social. | D7: PRDI2025-2029-Obj-58 | E7: Contar con planes de estudio pertinentes y de excelencia, en diferentes modalidades, que incorporen los criterios transversales del SEAES, de indicadores de instancias de evaluación externa y acreditación, y de organismos acreditadores, para formar profesionistas que contribuyan a la conformación de una sociedad más justa, libre, incluyente y pacífica, con una visión de sostenibilidad. | F7: 8 | G7: Lograr que 92.9% de la matrícula en programas educativos de estudios profesionales evaluables, curse en programas educativos reconocidos por su excelencia, para 2029 | H7: IND-PRDI-351 | I7: Mejorar o mantener de forma conservadora en la Facultad de Ingeniería el indicador IND-PRDI-351, con la trayectoria 2027: 88.89%, 2028: 90.25%, 2029: 91.55%, 2030: 92.91%, sustentada en referencia PRDI; no existe serie histórica directamente comparable para la variable. | J7: Indicador | K7: (Matrícula de estudiantes de estudios profesionales del sistema dependiente en programas educativos reconocidos por su excelencia / Matrícula de estudiantes de estudios profesionales del sistema dependiente en programas educativos evaluables)*100 | L7: Matrícula de estudiantes de estudios profesionales del sistema dependiente en programas educativos reconocidos por su excelencia | N7: 2657 | O7: 2711 | P7: 2764 | Q7: 2819 | R7: =IF(M8,M7/M8*100,"") | S7: =IF(N8,N7/N8*100,"") -> 88.892606 | T7: =IF(O8,O7/O8*100,"") -> 90.246338 | U7: =IF(P8,P7/P8*100,"") -> 91.553495 | V7: =IF(Q8,Q7/Q8*100,"") -> 92.913645 | W7: Anual | X7: Subdirección Académica y coordinaciones de licenciatura
L8: Matrícula de estudiantes de estudios profesionales del sistema dependiente en programas educativos evaluables | N8: 2989 | O8: 3004 | P8: 3019 | Q8: 3034
A9: 5 | B9: PRDI25-29-Obj-36 | C9: Formar estudiantes de excelencia, a través de estudios profesionales pertinentes e inclusivos, con una vinculación permanente con estudiantes y personas egresadas, para su pleno desarrollo profesional y su contribución al bienestar social. | D9: PRDI25-29-Obj-81 | E9: Fortalecer la formación disciplinar e integral del estudiantado y su educación continua, en congruencia con el modelo educativo institucional, para fomentar su desarrollo humano completo y maximizar su potencial académico y profesional, así como su retribución social, en los diferentes sectores. | F9: 9 | G9: Lograr que 72% de los sustentantes que presentan el EGEL obtengan testimonios de desempeño sobresaliente o satisfactorio, para 2029 | H9: IND-PRDI-200 | I9: Mejorar o mantener de forma conservadora en la Facultad de Ingeniería el indicador IND-PRDI-200, con la trayectoria 2027: 68%, 2028: 70%, 2029: 71.29%, 2030: 71.57%, sustentada en referencia PRDI; no existe serie histórica directamente comparable para la variable. | J9: Indicador | K9: (Número de sustentantes de estudios profesionales que obtienen testimonio de desempeño sobresaliente o satisfactorio en el EGEL / Total de sustentantes de estudios profesionales que presentan los EGEL)*100 | L9: Número de sustentantes de estudios profesionales que obtienen testimonio de desempeño sobresaliente o satisfactorio en el EGEL | N9: 68 | O9: 70 | P9: 72 | Q9: 73 | R9: =IF(M10,M9/M10*100,"") | S9: =IF(N10,N9/N10*100,"") -> 68 | T9: =IF(O10,O9/O10*100,"") -> 70 | U9: =IF(P10,P9/P10*100,"") -> 71.287129 | V9: =IF(Q10,Q9/Q10*100,"") -> 71.568627 | W9: Anual | X9: Subdirección Académica y coordinaciones de licenciatura
L10: Total de sustentantes de estudios profesionales que presentan los EGEL | N10: 100 | O10: 100 | P10: 101 | Q10: 102
A11: 6 | B11: PRDI25-29-Obj-36 | C11: Formar estudiantes de excelencia, a través de estudios profesionales pertinentes e inclusivos, con una vinculación permanente con estudiantes y personas egresadas, para su pleno desarrollo profesional y su contribución al bienestar social. | D11: PRDI25-29-Obj-81 | E11: Fortalecer la formación disciplinar e integral del estudiantado y su educación continua, en congruencia con el modelo educativo institucional, para fomentar su desarrollo humano completo y maximizar su potencial académico y profesional, así como su retribución social, en los diferentes sectores. | F11: 10 | G11: Implementar 1 programa de preparación para EGEL anualmente | H11: ACT-PRDI-NS-2781 | I11: Contribuir desde la Facultad de Ingeniería al cumplimiento de la meta PRDI “Implementar 1 programa de preparación para EGEL anualmente”, con valores absolutos programados de 2027: 1, 2028: 1, 2029: 1, 2030: 1. | J11: Actividad | K11: Sin fórmula | L11: Implementar un programa de preparación para EGEL | M11: 0 | N11: 1 | O11: 1 | P11: 1 | Q11: 1 | R11: =IF(M11="","",M11) -> 0 | S11: =IF(N11="","",N11) -> 1 | T11: =IF(O11="","",O11) -> 1 | U11: =IF(P11="","",P11) -> 1 | V11: =IF(Q11="","",Q11) -> 1 | W11: Anual | X11: Subdirección Académica y coordinaciones de licenciatura
A12: 7 | B12: PRDI25-29-Obj-36 | C12: Formar estudiantes de excelencia, a través de estudios profesionales pertinentes e inclusivos, con una vinculación permanente con estudiantes y personas egresadas, para su pleno desarrollo profesional y su contribución al bienestar social. | D12: PRDI25-29-Obj-81 | E12: Fortalecer la formación disciplinar e integral del estudiantado y su educación continua, en congruencia con el modelo educativo institucional, para fomentar su desarrollo humano completo y maximizar su potencial académico y profesional, así como su retribución social, en los diferentes sectores. | F12: 14 | G12: Lograr que 550 estudiantes de estudios profesionales participen en movilidad intrainstitucional durante la administración | H12: ACT-PRDI-NS-2785 | I12: Contribuir desde la Facultad de Ingeniería al cumplimiento de la meta PRDI “Lograr que 550 estudiantes de estudios profesionales participen en movilidad intrainstitucional durante la administración”, con valores absolutos programados de 2027: 3, 2028: 3, 2029: 2, 2030: 2. | J12: Actividad | K12: Sin fórmula | L12: Lograr que estudiantes de estudios profesionales participen en movilidad intrainstitucional | N12: 3 | O12: 3 | P12: 2 | Q12: 2 | R12: =IF(M12="","",M12) | S12: =IF(N12="","",N12) -> 3 | T12: =IF(O12="","",O12) -> 3 | U12: =IF(P12="","",P12) -> 2 | V12: =IF(Q12="","",Q12) -> 2 | W12: Anual | X12: Subdirección Académica y coordinaciones de licenciatura
A13: 8 | B13: PRDI25-29-Obj-36 | C13: Formar estudiantes de excelencia, a través de estudios profesionales pertinentes e inclusivos, con una vinculación permanente con estudiantes y personas egresadas, para su pleno desarrollo profesional y su contribución al bienestar social. | D13: PRDI25-29-Obj-81 | E13: Fortalecer la formación disciplinar e integral del estudiantado y su educación continua, en congruencia con el modelo educativo institucional, para fomentar su desarrollo humano completo y maximizar su potencial académico y profesional, así como su retribución social, en los diferentes sectores. | F13: 15 | G13: Lograr anualmente que 100% de los estudiantes de estudios profesionales estén beneficiados con el nuevo Programa Institucional de Tutoría Académica | H13: IND-PRDI-353 | I13: Mejorar o mantener de forma conservadora en la Facultad de Ingeniería el indicador IND-PRDI-353, con la trayectoria 2027: 98.13%, 2028: 98.74%, 2029: 99.37%, 2030: 100%, sustentada en serie histórica directamente comparable del sitio. | J13: Indicador | K13: (Número de estudiantes de estudios profesionales beneficiados con tutoría/ Total de estudiantes de estudios profesionales) * 100 | L13: Número de estudiantes de estudios profesionales beneficiados con tutoría | N13: 2933 | O13: 2966 | P13: 3000 | Q13: 3034 | R13: =IF(M14,M13/M14*100,"") | S13: =IF(N14,N13/N14*100,"") -> 98.126464 | T13: =IF(O14,O13/O14*100,"") -> 98.73502 | U13: =IF(P14,P13/P14*100,"") -> 99.370653 | V13: =IF(Q14,Q13/Q14*100,"") -> 100 | W13: Anual | X13: Subdirección Académica y coordinaciones de licenciatura
L14: Total de estudiantes de estudios profesionales | N14: 2989 | O14: 3004 | P14: 3019 | Q14: 3034
A15: 9 | B15: PRDI25-29-Obj-36 | C15: Formar estudiantes de excelencia, a través de estudios profesionales pertinentes e inclusivos, con una vinculación permanente con estudiantes y personas egresadas, para su pleno desarrollo profesional y su contribución al bienestar social. | D15: PRDI25-29-Obj-81 | E15: Fortalecer la formación disciplinar e integral del estudiantado y su educación continua, en congruencia con el modelo educativo institucional, para fomentar su desarrollo humano completo y maximizar su potencial académico y profesional, así como su retribución social, en los diferentes sectores. | F15: 17 | G15: Lograr que 1 030 estudiantes de estudios profesionales participen en movilidad nacional e internacional durante la administración | H15: ACT-PRDI-NS-2789 | I15: Contribuir desde la Facultad de Ingeniería al cumplimiento de la meta PRDI “Lograr que 1 030 estudiantes de estudios profesionales participen en movilidad nacional e internacional durante la administración”, con valores absolutos programados de 2027: 5, 2028: 5, 2029: 5, 2030: 4. | J15: Actividad | K15: Sin fórmula | L15: Lograr que estudiantes de estudios profesionales participen en movilidad nacional e internacional | N15: 5 | O15: 5 | P15: 5 | Q15: 4 | R15: =IF(M15="","",M15) | S15: =IF(N15="","",N15) -> 5 | T15: =IF(O15="","",O15) -> 5 | U15: =IF(P15="","",P15) -> 5 | V15: =IF(Q15="","",Q15) -> 4 | W15: Anual | X15: Subdirección Académica y coordinaciones de licenciatura
A16: 10 | B16: PRDI25-29-Obj-36 | C16: Formar estudiantes de excelencia, a través de estudios profesionales pertinentes e inclusivos, con una vinculación permanente con estudiantes y personas egresadas, para su pleno desarrollo profesional y su contribución al bienestar social. | D16: PRDI25-29-Obj-81 | E16: Fortalecer la formación disciplinar e integral del estudiantado y su educación continua, en congruencia con el modelo educativo institucional, para fomentar su desarrollo humano completo y maximizar su potencial académico y profesional, así como su retribución social, en los diferentes sectores. | F16: 19 | G16: Realizar anualmente en los 55 espacios académicos un proyecto colaborativo de beneficio social | H16: ACT-PRDI-NS-2729 | I16: Contribuir desde la Facultad de Ingeniería al cumplimiento de la meta PRDI “Realizar anualmente en los 55 espacios académicos un proyecto colaborativo de beneficio social”, con valores absolutos programados de 2027: 1, 2028: 1, 2029: 1, 2030: 1. | J16: Actividad | K16: Sin fórmula | L16: Realizar en los espacios académicos un proyecto colaborativo de beneficio social | N16: 1 | O16: 1 | P16: 1 | Q16: 1 | R16: =IF(M16="","",M16) | S16: =IF(N16="","",N16) -> 1 | T16: =IF(O16="","",O16) -> 1 | U16: =IF(P16="","",P16) -> 1 | V16: =IF(Q16="","",Q16) -> 1 | W16: Anual | X16: Subdirección Académica y coordinaciones de licenciatura
A17: 11 | B17: PRDI25-29-Obj-36 | C17: Formar estudiantes de excelencia, a través de estudios profesionales pertinentes e inclusivos, con una vinculación permanente con estudiantes y personas egresadas, para su pleno desarrollo profesional y su contribución al bienestar social. | D17: PRDI25-29-Obj-81 | E17: Fortalecer la formación disciplinar e integral del estudiantado y su educación continua, en congruencia con el modelo educativo institucional, para fomentar su desarrollo humano completo y maximizar su potencial académico y profesional, así como su retribución social, en los diferentes sectores. | F17: 21 | G17: Contar con 70 manuales de prácticas apegados a los indicadores del Sistema para Evaluar la Calidad de Medios Educativos anualmente | H17: ACT-PRDI-NS-2792 | I17: Contribuir desde la Facultad de Ingeniería al cumplimiento de la meta PRDI “Contar con 70 manuales de prácticas apegados a los indicadores del Sistema para Evaluar la Calidad de Medios Educativos anualmente”, con valores absolutos programados de 2027: 2, 2028: 2, 2029: 2, 2030: 2. | J17: Actividad | K17: Sin fórmula | L17: Contar con manuales de prácticas apegados a los indicadores del Sistema para Evaluar la Calidad de Medios Educativos | N17: 2 | O17: 2 | P17: 2 | Q17: 2 | R17: =IF(M17="","",M17) | S17: =IF(N17="","",N17) -> 2 | T17: =IF(O17="","",O17) -> 2 | U17: =IF(P17="","",P17) -> 2 | V17: =IF(Q17="","",Q17) -> 2 | W17: Anual | X17: Subdirección Académica y coordinaciones de licenciatura
A18: 12 | B18: PRDI25-29-Obj-36 | C18: Formar estudiantes de excelencia, a través de estudios profesionales pertinentes e inclusivos, con una vinculación permanente con estudiantes y personas egresadas, para su pleno desarrollo profesional y su contribución al bienestar social. | D18: PRDI25-29-Obj-81 | E18: Fortalecer la formación disciplinar e integral del estudiantado y su educación continua, en congruencia con el modelo educativo institucional, para fomentar su desarrollo humano completo y maximizar su potencial académico y profesional, así como su retribución social, en los diferentes sectores. | F18: 29 | G18: Lograr que 80.03% de las GEI disponibles en SEDUCA sean utilizadas, para 2029 | H18: IND-PRDI-357 | I18: Mejorar o mantener de forma conservadora en la Facultad de Ingeniería el indicador IND-PRDI-357, con la trayectoria 2027: 80%, 2028: 80%, 2029: 80%, 2030: 80%, sustentada en referencia PRDI; no existe serie histórica directamente comparable para la variable. | J18: Indicador | K18: (Número de guías de estudio independiente utilizadas / Número total de guías de estudio independiente vigentes disponibles en SEDUCA) *100 | L18: Número de guías de estudio independiente utilizadas | N18: 8 | O18: 8 | P18: 8 | Q18: 8 | R18: =IF(M19,M18/M19*100,"") | S18: =IF(N19,N18/N19*100,"") -> 80 | T18: =IF(O19,O18/O19*100,"") -> 80 | U18: =IF(P19,P18/P19*100,"") -> 80 | V18: =IF(Q19,Q18/Q19*100,"") -> 80 | W18: Anual | X18: Subdirección Académica y coordinaciones de licenciatura
L19: Número total de guías de estudio independiente vigentes disponibles en SEDUCA | N19: 10 | O19: 10 | P19: 10 | Q19: 10
A20: 13 | B20: PRDI25-29-Obj-36 | C20: Formar estudiantes de excelencia, a través de estudios profesionales pertinentes e inclusivos, con una vinculación permanente con estudiantes y personas egresadas, para su pleno desarrollo profesional y su contribución al bienestar social. | D20: PRDI25-29-Obj-81 | E20: Fortalecer la formación disciplinar e integral del estudiantado y su educación continua, en congruencia con el modelo educativo institucional, para fomentar su desarrollo humano completo y maximizar su potencial académico y profesional, así como su retribución social, en los diferentes sectores. | F20: 30 | G20: Incrementar a 52 000 el número de estudiantes de estudios profesionales en la renovada plataforma seduca, para 2029 | H20: ACT-PRDI-NS-2728 | I20: Contribuir desde la Facultad de Ingeniería al cumplimiento de la meta PRDI “Incrementar a 52 000 el número de estudiantes de estudios profesionales en la renovada plataforma seduca, para 2029”, con valores absolutos programados de 2027: 473, 2028: 710, 2029: 946, 2030: 946. | J20: Actividad | K20: Sin fórmula | L20: Incrementar el número de estudiantes de estudios profesionales en la renovada plataforma seduca | N20: 473 | O20: 710 | P20: 946 | Q20: 946 | R20: =IF(M20="","",M20) | S20: =IF(N20="","",N20) -> 473 | T20: =IF(O20="","",O20) -> 710 | U20: =IF(P20="","",P20) -> 946 | V20: =IF(Q20="","",Q20) -> 946 | W20: Anual | X20: Subdirección Académica y coordinaciones de licenciatura
A21: 14 | B21: PRDI25-29-Obj-36 | C21: Formar estudiantes de excelencia, a través de estudios profesionales pertinentes e inclusivos, con una vinculación permanente con estudiantes y personas egresadas, para su pleno desarrollo profesional y su contribución al bienestar social. | D21: PRDI25-29-Obj-81 | E21: Fortalecer la formación disciplinar e integral del estudiantado y su educación continua, en congruencia con el modelo educativo institucional, para fomentar su desarrollo humano completo y maximizar su potencial académico y profesional, así como su retribución social, en los diferentes sectores. | F21: 33 | G21: Desarrollar 470 actividades académicas de educación continua al año | H21: ACT-PRDI-NS-2805 | I21: Contribuir desde la Facultad de Ingeniería al cumplimiento de la meta PRDI “Desarrollar 470 actividades académicas de educación continua al año”, con valores absolutos programados de 2027: 9, 2028: 9, 2029: 9, 2030: 9. | J21: Actividad | K21: Sin fórmula | L21: Desarrollar actividades académicas de educación continua | N21: 9 | O21: 9 | P21: 9 | Q21: 9 | R21: =IF(M21="","",M21) | S21: =IF(N21="","",N21) -> 9 | T21: =IF(O21="","",O21) -> 9 | U21: =IF(P21="","",P21) -> 9 | V21: =IF(Q21="","",Q21) -> 9 | W21: Anual | X21: Subdirección Académica y coordinaciones de licenciatura
A22: 16 | B22: PRDI25-29-Obj-36 | C22: Formar estudiantes de excelencia, a través de estudios profesionales pertinentes e inclusivos, con una vinculación permanente con estudiantes y personas egresadas, para su pleno desarrollo profesional y su contribución al bienestar social. | D22: PRDI25-29-Obj-81 | E22: Fortalecer la formación disciplinar e integral del estudiantado y su educación continua, en congruencia con el modelo educativo institucional, para fomentar su desarrollo humano completo y maximizar su potencial académico y profesional, así como su retribución social, en los diferentes sectores. | F22: 37 | G22: Certificar en una segunda lengua a 720 estudiantes de estudios profesionales anualmente | H22: ACT-PRDI-NS-2205 | I22: Contribuir desde la Facultad de Ingeniería al cumplimiento de la meta PRDI “Certificar en una segunda lengua a 720 estudiantes de estudios profesionales anualmente”, con valores absolutos programados de 2027: 14, 2028: 14, 2029: 14, 2030: 14. | J22: Actividad | K22: Sin fórmula | L22: Certificar internacionalmente en una segunda lengua a estudiantes de estudios profesionales | N22: 14 | O22: 14 | P22: 14 | Q22: 14 | R22: =IF(M22="","",M22) | S22: =IF(N22="","",N22) -> 14 | T22: =IF(O22="","",O22) -> 14 | U22: =IF(P22="","",P22) -> 14 | V22: =IF(Q22="","",Q22) -> 14 | W22: Anual | X22: Subdirección Académica y coordinaciones de licenciatura
A23: 17 | B23: PRDI25-29-Obj-36 | C23: Formar estudiantes de excelencia, a través de estudios profesionales pertinentes e inclusivos, con una vinculación permanente con estudiantes y personas egresadas, para su pleno desarrollo profesional y su contribución al bienestar social. | D23: PRDI25-29-Obj-82 | E23: Contribuir al acceso, permanencia y egreso del alumnado de estudios profesionales para su formación integral y la conclusión de sus estudios profesionales. | F23: 42 | G23: Incrementar la matrícula a 78 002 estudiantes de estudios profesionales en sus diversas modalidades para 2029 | H23: ACT-PRDI-NS-1764 | I23: Contribuir desde la Facultad de Ingeniería al cumplimiento de la meta PRDI “Incrementar la matrícula a 78 002 estudiantes de estudios profesionales en sus diversas modalidades para 2029”, con valores absolutos programados de 2027: 3004, 2028: 3019, 2029: 3034, 2030: 3049. Sustento en la Matriz de consistencia: «Realizar 1 reunión y 1 encuesta a estudiantes de cada licenciatura cada año de 2028 a 2030 y documentar los ajustes derivados.» | J23: Actividad | K23: Sin fórmula | L23: Atender la matrícula de Estudios Profesionales en sus diversas modalidades | M23: =M14 -> 0 | N23: 3004 | O23: 3019 | P23: 3034 | Q23: 3049 | R23: =IF(M23="","",M23) -> 0 | S23: =IF(N23="","",N23) -> 3004 | T23: =IF(O23="","",O23) -> 3019 | U23: =IF(P23="","",P23) -> 3034 | V23: =IF(Q23="","",Q23) -> 3049 | W23: Anual | X23: Subdirección Académica y coordinaciones de licenciatura
A24: 18 | B24: PRDI25-29-Obj-36 | C24: Formar estudiantes de excelencia, a través de estudios profesionales pertinentes e inclusivos, con una vinculación permanente con estudiantes y personas egresadas, para su pleno desarrollo profesional y su contribución al bienestar social. | D24: PRDI25-29-Obj-82 | E24: Contribuir al acceso, permanencia y egreso del alumnado de estudios profesionales para su formación integral y la conclusión de sus estudios profesionales. | F24: 43 | G24: Contar con una titulación por cohorte a 2029 de 30.5% | H24: IND-PRDI-40 | I24: Mejorar o mantener de forma conservadora en la Facultad de Ingeniería el indicador IND-PRDI-40, con la trayectoria 2027: 3%, 2028: 4%, 2029: 4.95%, 2030: 5.88%, sustentada en serie histórica directamente comparable del sitio. | J24: Indicador | K24: (Titulados al primer año de egreso/Nuevo ingreso n-5 )*100 | L24: Titulados al primer año de egreso | N24: 3 | O24: 4 | P24: 5 | Q24: 6 | R24: =IF(M25,M24/M25*100,"") | S24: =IF(N25,N24/N25*100,"") -> 3 | T24: =IF(O25,O24/O25*100,"") -> 4 | U24: =IF(P25,P24/P25*100,"") -> 4.950495 | V24: =IF(Q25,Q24/Q25*100,"") -> 5.8823529 | W24: Anual | X24: Subdirección Académica y coordinaciones de licenciatura
L25: Nuevo ingreso n-5 | N25: 100 | O25: 100 | P25: 101 | Q25: 102
A26: 19 | B26: PRDI25-29-Obj-36 | C26: Formar estudiantes de excelencia, a través de estudios profesionales pertinentes e inclusivos, con una vinculación permanente con estudiantes y personas egresadas, para su pleno desarrollo profesional y su contribución al bienestar social. | D26: PRDI25-29-Obj-82 | E26: Contribuir al acceso, permanencia y egreso del alumnado de estudios profesionales para su formación integral y la conclusión de sus estudios profesionales. | F26: 44 | G26: Implementar semestralmente 1 programa de fomento a la titulación | H26: ACT-PRDI-NS-2814 | I26: Contribuir desde la Facultad de Ingeniería al cumplimiento de la meta PRDI “Implementar semestralmente 1 programa de fomento a la titulación”, con valores absolutos programados de 2027: 0, 2028: 0, 2029: 2, 2030: 0. | J26: Actividad | K26: Sin fórmula | L26: Implementar un programa de fomento a la titulación | N26: 0 | O26: 0 | P26: 2 | Q26: 0 | R26: =IF(M26="","",M26) | S26: =IF(N26="","",N26) -> 0 | T26: =IF(O26="","",O26) -> 0 | U26: =IF(P26="","",P26) -> 2 | V26: =IF(Q26="","",Q26) -> 0 | W26: Anual | X26: Subdirección Académica y coordinaciones de licenciatura
A27: 20 | B27: PRDI25-29-Obj-36 | C27: Formar estudiantes de excelencia, a través de estudios profesionales pertinentes e inclusivos, con una vinculación permanente con estudiantes y personas egresadas, para su pleno desarrollo profesional y su contribución al bienestar social. | D27: PRDI25-29-Obj-82 | E27: Contribuir al acceso, permanencia y egreso del alumnado de estudios profesionales para su formación integral y la conclusión de sus estudios profesionales. | F27: 45 | G27: Lograr la eficiencia terminal por cohorte en estudios Profesionales de 53.59% en 2029 | H27: IND-NS-127 | I27: Mejorar o mantener de forma conservadora en la Facultad de Ingeniería el indicador IND-NS-127, con la trayectoria 2027: 5.19%, 2028: 6.19%, 2029: 7.19%, 2030: 8.21%, sustentada en serie histórica directamente comparable del sitio. | J27: Indicador | K27: (La suma acumulada del número de egresados de la cohorte de estudios profesionales en cada uno de los años que dura la cohorte/Número total de alumnos de ingreso a primer año de la cohorte)*100 | L27: La suma acumulada del número de egresados de la cohorte de estudios profesionales en cada uno de los años que dura la cohorte | N27: 155 | O27: 186 | P27: 217 | Q27: 249 | R27: =IF(M28,M27/M28*100,"") | S27: =IF(N28,N27/N28*100,"") -> 5.1856808 | T27: =IF(O28,O27/O28*100,"") -> 6.1917443 | U27: =IF(P28,P27/P28*100,"") -> 7.1878105 | V27: =IF(Q28,Q27/Q28*100,"") -> 8.2069875 | W27: Anual | X27: Subdirección Académica y coordinaciones de licenciatura
L28: Número total de alumnos de ingreso a primer año de la cohorte | N28: 2989 | O28: 3004 | P28: 3019 | Q28: 3034
A29: 21 | B29: PRDI25-29-Obj-36 | C29: Formar estudiantes de excelencia, a través de estudios profesionales pertinentes e inclusivos, con una vinculación permanente con estudiantes y personas egresadas, para su pleno desarrollo profesional y su contribución al bienestar social. | D29: PRDI25-29-Obj-82 | E29: Contribuir al acceso, permanencia y egreso del alumnado de estudios profesionales para su formación integral y la conclusión de sus estudios profesionales. | F29: 46 | G29: Disminuir a 7.80% el abandono escolar de estudios profesionales al término de la administración | H29: IND-PRDI-34 | I29: Mejorar o mantener de forma conservadora en la Facultad de Ingeniería el indicador IND-PRDI-34, con la trayectoria 2027: 8.03%, 2028: 7.96%, 2029: 7.88%, 2030: 7.81%, sustentada en serie histórica directamente comparable del sitio. | J29: Indicador | K29: (1-((Matrícula total n mas 1-Nuevo ingreso 1o n mas 1+Egresados n)/(Matrícula total n)))*100 | L29: Matrícula total n mas 1 | M29: =M14 -> 0 | N29: 3004 | O29: 3019 | P29: 3034 | Q29: 3049 | R29: =IF(M32,(1-((M29-M30+M31)/M32))*100,"") | S29: =IF(N32,(1-((N29-N30+N31)/N32))*100,"") -> 8.0294413 | T29: =IF(O32,(1-((O29-O30+O31)/O32))*100,"") -> 7.9560586 | U29: =IF(P32,(1-((P29-P30+P31)/P32))*100,"") -> 7.8834051 | V29: =IF(Q32,(1-((Q29-Q30+Q31)/Q32))*100,"") -> 7.81147 | W29: Anual | X29: Subdirección Académica y coordinaciones de licenciatura
L30: Nuevo ingreso 1o n mas 1 | N30: 722 | O30: 726 | P30: 729 | Q30: 733
L31: Egresados n | N31: 467 | O31: 472 | P31: 476 | Q31: 481
L32: Matrícula total n | N32: 2989 | O32: 3004 | P32: 3019 | Q32: 3034
A33: 22 | B33: PRDI25-29-Obj-36 | C33: Formar estudiantes de excelencia, a través de estudios profesionales pertinentes e inclusivos, con una vinculación permanente con estudiantes y personas egresadas, para su pleno desarrollo profesional y su contribución al bienestar social. | D33: PRDI25-29-Obj-82 | E33: Contribuir al acceso, permanencia y egreso del alumnado de estudios profesionales para su formación integral y la conclusión de sus estudios profesionales. | F33: 53 | G33: Otorgar anualmente 38 000 becas, apoyos o estímulos institucionales a estudiantes de Estudios Profesionales | H33: ACT-PRDI-NS-2297 | I33: Contribuir desde la Facultad de Ingeniería al cumplimiento de la meta PRDI “Otorgar anualmente 38 000 becas, apoyos o estímulos institucionales a estudiantes de Estudios Profesionales”, con valores absolutos programados de 2027: 691, 2028: 691, 2029: 691, 2030: 691. | J33: Actividad | K33: Sin fórmula | L33: Otorgar becas, apoyos o estímulos a alumnos de estudios profesionales para la permanencia y conclusión de estudios | N33: 691 | O33: 691 | P33: 691 | Q33: 691 | R33: =IF(M33="","",M33) | S33: =IF(N33="","",N33) -> 691 | T33: =IF(O33="","",O33) -> 691 | U33: =IF(P33="","",P33) -> 691 | V33: =IF(Q33="","",Q33) -> 691 | W33: Anual | X33: Subdirección Académica y coordinaciones de licenciatura
A34: 23 | B34: PRDI25-29-Obj-36 | C34: Formar estudiantes de excelencia, a través de estudios profesionales pertinentes e inclusivos, con una vinculación permanente con estudiantes y personas egresadas, para su pleno desarrollo profesional y su contribución al bienestar social. | D34: PRDI25-29-Obj-82 | E34: Contribuir al acceso, permanencia y egreso del alumnado de estudios profesionales para su formación integral y la conclusión de sus estudios profesionales. | F34: 55 | G34: Lograr que 98% del total de estudiantes activos de Estudios Profesionales cuenten con servicios de salud a 2029 | H34: IND-PRDI-366 | I34: Mejorar o mantener de forma conservadora en la Facultad de Ingeniería el indicador IND-PRDI-366, con la trayectoria 2027: 94.01%, 2028: 95.34%, 2029: 96.65%, 2030: 97.99%, sustentada en referencia PRDI; no existe serie histórica directamente comparable para la variable. | J34: Indicador | K34: (Alumnos afiliados al Seguro Facultativo de Estudios Profesionales / Matrícula activa de Estudios Profesionales)*100 | L34: Alumnos afiliados al Seguro Facultativo de Estudios Profesionales | N34: 2810 | O34: 2864 | P34: 2918 | Q34: 2973 | R34: =IF(M35,M34/M35*100,"") | S34: =IF(N35,N34/N35*100,"") -> 94.011375 | T34: =IF(O35,O34/O35*100,"") -> 95.339547 | U34: =IF(P35,P34/P35*100,"") -> 96.654521 | V34: =IF(Q35,Q34/Q35*100,"") -> 97.989453 | W34: Anual | X34: Subdirección Académica y coordinaciones de licenciatura
L35: Matrícula activa de Estudios Profesionales | M35: =M14 -> 0 | N35: 2989 | O35: 3004 | P35: 3019 | Q35: 3034
A36: 24 | B36: PRDI25-29-Obj-36 | C36: Formar estudiantes de excelencia, a través de estudios profesionales pertinentes e inclusivos, con una vinculación permanente con estudiantes y personas egresadas, para su pleno desarrollo profesional y su contribución al bienestar social. | D36: PRDI25-29-Obj-82 | E36: Contribuir al acceso, permanencia y egreso del alumnado de estudios profesionales para su formación integral y la conclusión de sus estudios profesionales. | F36: 57 | G36: Lograr la participación de 32 300 estudiantes y personas egresadas en los sectores gubernamental, productivo y social, mediante las prácticas o estancias profesionales, al cierre de la administración | H36: ACT-PRDI-NS-2285 | I36: Contribuir desde la Facultad de Ingeniería al cumplimiento de la meta PRDI “Lograr la participación de 32 300 estudiantes y personas egresadas en los sectores gubernamental, productivo y social, mediante las prácticas o estancias profesionales, al cierre de la administración”, con valores absolutos programados de 2027: 0, 2028: 0, 2029: 588, 2030: 0. | J36: Actividad | K36: Sin fórmula | L36: Lograr la participación de alumnos en los sectores gubernamental, productivo y social mediante las prácticas o estancias profesionales | N36: 0 | O36: 0 | P36: 588 | Q36: 0 | R36: =IF(M36="","",M36) | S36: =IF(N36="","",N36) -> 0 | T36: =IF(O36="","",O36) -> 0 | U36: =IF(P36="","",P36) -> 588 | V36: =IF(Q36="","",Q36) -> 0 | W36: Anual | X36: Subdirección Académica y coordinaciones de licenciatura
A37: 25 | B37: PRDI25-29-Obj-36 | C37: Formar estudiantes de excelencia, a través de estudios profesionales pertinentes e inclusivos, con una vinculación permanente con estudiantes y personas egresadas, para su pleno desarrollo profesional y su contribución al bienestar social. | D37: PRDI25-29-Obj-82 | E37: Contribuir al acceso, permanencia y egreso del alumnado de estudios profesionales para su formación integral y la conclusión de sus estudios profesionales. | F37: 58 | G37: Lograr la participación de 500 estudiantes de estudios profesionales en cursos, talleres o actividades de capacitación de empleabilidad, realizadas en conjunto con instituciones externas, anualmente | H37: ACT-PRDI-NS-2826 | I37: Contribuir desde la Facultad de Ingeniería al cumplimiento de la meta PRDI “Lograr la participación de 500 estudiantes de estudios profesionales en cursos, talleres o actividades de capacitación de empleabilidad, realizadas en conjunto con instituciones externas, anualmente”, con valores absolutos programados de 2027: 10, 2028: 10, 2029: 10, 2030: 10. | J37: Actividad | K37: Sin fórmula | L37: Lograr la participación de estudiantes de estudios profesionales en cursos, talleres o actividades de capacitación de empleabilidad, realizadas en conjunto con instituciones externas | N37: 10 | O37: 10 | P37: 10 | Q37: 10 | R37: =IF(M37="","",M37) | S37: =IF(N37="","",N37) -> 10 | T37: =IF(O37="","",O37) -> 10 | U37: =IF(P37="","",P37) -> 10 | V37: =IF(Q37="","",Q37) -> 10 | W37: Anual | X37: Subdirección Académica y coordinaciones de licenciatura
A38: 26 | B38: PRDI25-29-Obj-36 | C38: Formar estudiantes de excelencia, a través de estudios profesionales pertinentes e inclusivos, con una vinculación permanente con estudiantes y personas egresadas, para su pleno desarrollo profesional y su contribución al bienestar social. | D38: PRDI25-29-Obj-82 | E38: Contribuir al acceso, permanencia y egreso del alumnado de estudios profesionales para su formación integral y la conclusión de sus estudios profesionales. | F38: 61 | G38: Realizar 10 eventos de promoción y difusión en apoyo al desarrollo profesional para el empleo y la inserción laboral, durante la administración | H38: ACT-PRDI-NS-2825 | I38: Contribuir desde la Facultad de Ingeniería al cumplimiento de la meta PRDI “Realizar 10 eventos de promoción y difusión en apoyo al desarrollo profesional para el empleo y la inserción laboral, durante la administración”, con valores absolutos programados de 2027: 1, 2028: 0, 2029: 0, 2030: 0. Sustento en la Matriz de consistencia: «Realizar 1 revisión documentada de las trayectorias y asignaturas con mayor rezago en 2027 y actualizarla una vez al año de 2028 a 2030.» | J38: Actividad | K38: Sin fórmula | L38: Realizar eventos de promoción y difusión en apoyo al desarrollo profesional para el empleo y la inserción laboral | N38: 1 | O38: 0 | P38: 0 | Q38: 0 | R38: =IF(M38="","",M38) | S38: =IF(N38="","",N38) -> 1 | T38: =IF(O38="","",O38) -> 0 | U38: =IF(P38="","",P38) -> 0 | V38: =IF(Q38="","",Q38) -> 0 | W38: Anual | X38: Subdirección Académica y coordinaciones de licenciatura
A39: 27 | B39: PRDI25-29-Obj-36 | C39: Formar estudiantes de excelencia, a través de estudios profesionales pertinentes e inclusivos, con una vinculación permanente con estudiantes y personas egresadas, para su pleno desarrollo profesional y su contribución al bienestar social. | D39: PRDI25-29-Obj-83 | E39: Fortalecer la vinculación, acompañamiento y seguimiento de egresados de estudios profesionales, para favorecer las prácticas profesionales, empleabilidad y colaboración con el sector productivo, con un sentido de identidad. | F39: 64 | G39: Realizar 40 intervenciones de impacto anuales en espacios académicos para fortalecer la vinculación colaborativa entre egresados y estudiantes | H39: ACT-PRDI-NS-2753 | I39: Contribuir desde la Facultad de Ingeniería al cumplimiento de la meta PRDI “Realizar 40 intervenciones de impacto anuales en espacios académicos para fortalecer la vinculación colaborativa entre egresados y estudiantes”, con valores absolutos programados de 2027: 1, 2028: 1, 2029: 1, 2030: 1. Sustento en la Matriz de consistencia: «Validar y documentar el valor de Ref. 2026 durante 2027 y, una vez confirmado, mantenerlo o mejorarlo hasta 2030.» | J39: Actividad | K39: Sin fórmula | L39: Realizar intervenciones de impacto en espacios académicos para fortalecer la vinculación colaborativa entre egresados y estudiantes | N39: 1 | O39: 1 | P39: 1 | Q39: 1 | R39: =IF(M39="","",M39) | S39: =IF(N39="","",N39) -> 1 | T39: =IF(O39="","",O39) -> 1 | U39: =IF(P39="","",P39) -> 1 | V39: =IF(Q39="","",Q39) -> 1 | W39: Anual | X39: Subdirección Académica y coordinaciones de licenciatura

Sheet Hoja1
A1: Proyecto | B1: Actividades | C1: Indicadores | D1: Total
A2: 2 EstudiantadoEstProf | B2: 18 | C2: 9 | D2: =B2+C2 -> 27
A3: 3 Est avanzados excelencia | B3: 6 | C3: 1 | D3: =B3+C3 -> 7
A4: 4 Investigación abierta | B4: 3 | C4: 5 | D4: =B4+C4 -> 8
A5: 5 Innovación, desarrollo tec | B5: 2 | C5: 0 | D5: =B5+C5 -> 2
A6: 6 Dif y divulga de la ciencia | B6: 4 | C6: 0 | D6: =B6+C6 -> 4
A7: 7 Cultura desarrollo integral | B7: 6 | C7: 0 | D7: =B7+C7 -> 6
A8: 8 Deporte universitario | B8: 2 | C8: 3 | D8: =B8+C8 -> 5
A9: 9 Fortalecimiento docente | B9: 4 | C9: 6 | D9: =B9+C9 -> 10
A10: 10 Dignificación las y los trab | B10: 0 | C10: 3 | D10: =B10+C10 -> 3
A11: 11 Gestión administrativa | B11: 2 | C11: 0 | D11: =B11+C11 -> 2
A12: 12 Fortalecimiento tecnológico | B12: 2 | C12: 0 | D12: =B12+C12 -> 2
A13: 13 Gobernanza | B13: 8 | C13: 0 | D13: =B13+C13 -> 8
... A19: 22 Sostenibilidad ambiental | B19: 12 | C19: 0 | D19: =B19+C19 -> 12
B20: =SUM(B2:B19) -> 91 | C20: =SUM(C2:C19) -> 32 | D20: =SUM(D2:D19) -> 123

Sheet 3 Est avanzados excelencia
A1: N.P. | B1: Clave Objetivo General | C1: Objetivo General | D1: Clave Objetivo Específico | E1: Objetivo Específico | F1: No. de meta en el PRDI | G1: Meta PRDI | H1: Clave de la meta | I1: Meta del espacio académico | J1: Actividad/Indicador | K1: Método de cálculo | L1: Nombre de las variables | M1: Valor de las variables | R1: Valor de los indicadores | W1: Medición (anual o acumulada) | X1: Área responsable
M2: Ref. 2026 | N2: 2027 | O2: 2028 | P2: 2029 | Q2: 2030 | R2: Ref. 2026 | S2: 2027 | T2: 2028 | U2: 2029 | V2: 2030
A3: 1 | B3: PRDI25-29-Obj-37 | C3: Garantizar una formación en estudios avanzados de excelencia y pertinencia social, a través del desarrollo de programas innovadores con la integración de la investigación de la Agenda Estratégica de Investigación, para asegurar que el conocimiento generado impulse la transformación social. | D3: PRDI2025-2029-Obj-59 | E3: Incrementar la matrícula de estudios avanzados con enfoque de equidad e inclusión regional para diversificar el acceso a la formación de alto nivel. | F3: 6 | G3: Contar con 233 estudiantes de estudios avanzados participantes en estancias cortas o movilidad académica, a 2029 | H3: ACT-PRDI-NS-2838 | I3: Contribuir desde la Facultad de Ingeniería al cumplimiento de la meta PRDI “Contar con 233 estudiantes de estudios avanzados participantes en estancias cortas o movilidad académica, a 2029”, con valores absolutos programados de 2027: 3, 2028: 4, 2029: 5, 2030: 5. Sustento en la Matriz de consistencia: «Realizar 1 reunión y 1 encuesta a estudiantes y profesorado de posgrado cada año de 2028 a 2030 y documentar los ajustes derivados.» | J3: Actividad | K3: Sin fórmula | L3: Contar con estudiantes de estudios avanzados participantes en estancias cortas o movilidad académica | N3: 3 | O3: 4 | P3: 5 | Q3: 5 | R3: =IF(M3="","",M3) | S3: =IF(N3="","",N3) -> 3 | T3: =IF(O3="","",O3) -> 4 | U3: =IF(P3="","",P3) -> 5 | V3: =IF(Q3="","",Q3) -> 5 | W3: Anual | X3: Coordinación de Estudios Avanzados
A4: 2 | B4: PRDI25-29-Obj-37 | C4: Garantizar una formación en estudios avanzados de excelencia y pertinencia social, a través del desarrollo de programas innovadores con la integración de la investigación de la Agenda Estratégica de Investigación, para asegurar que el conocimiento generado impulse la transformación social. | D4: PRDI2025-2029-Obj-59 | E4: Incrementar la matrícula de estudios avanzados con enfoque de equidad e inclusión regional para diversificar el acceso a la formación de alto nivel. | F4: 16 | G4: Contar 4 350 alumnos en estudios avanzados, a 2029 | H4: ACT-PRDI-NS-2685 | I4: Contribuir desde la Facultad de Ingeniería al cumplimiento de la meta PRDI “Contar 4 350 alumnos en estudios avanzados, a 2029”, con valores absolutos programados de 2027: 40, 2028: 60, 2029: 80, 2030: 80. | J4: Actividad | K4: Sin fórmula | L4: Atender la matrícula de estudios avanzados para la generación y aplicación del conocimiento | N4: 40 | O4: 60 | P4: 80 | Q4: 80 | R4: =IF(M4="","",M4) | S4: =IF(N4="","",N4) -> 40 | T4: =IF(O4="","",O4) -> 60 | U4: =IF(P4="","",P4) -> 80 | V4: =IF(Q4="","",Q4) -> 80 | W4: Anual | X4: Coordinación de Estudios Avanzados
A5: 3 | B5: PRDI25-29-Obj-37 | C5: Garantizar una formación en estudios avanzados de excelencia y pertinencia social, a través del desarrollo de programas innovadores con la integración de la investigación de la Agenda Estratégica de Investigación, para asegurar que el conocimiento generado impulse la transformación social. | D5: PRDI25-29-Obj-84 | E5: Consolidar una oferta educativa de estudios avanzados de excelencia, para garantizar la inclusión, la pertinencia social y la alineación con las demandas de los sectores productivo, gubernamental y social. | F5: 12 | G5: Ofertar 1 nuevo programa de estudios avanzados o diplomado superior en los CU y UAP vinculado con entidades de gobierno o industria, anualmente | H5: ACT-PRDI-NS-2844 | I5: Contribuir desde la Facultad de Ingeniería al cumplimiento de la meta PRDI “Ofertar 1 nuevo programa de estudios avanzados o diplomado superior en los CU y UAP vinculado con entidades de gobierno o industria, anualmente”, con valores absolutos programados de 2027: 1, 2028: 1, 2029: 1, 2030: 1. | J5: Actividad | K5: Sin fórmula | L5: Ofertar nuevos programas de estudios avanzados o diplomado superior en los CU y UAP vinculado con entidades de gobierno o industria | N5: 1 | O5: 1 | P5: 1 | Q5: 1 | R5: =IF(M5="","",M5) | S5: =IF(N5="","",N5) -> 1 | T5: =IF(O5="","",O5) -> 1 | U5: =IF(P5="","",P5) -> 1 | V5: =IF(Q5="","",Q5) -> 1 | W5: Anual | X5: Coordinación de Estudios Avanzados
A6: 4 | B6: PRDI25-29-Obj-37 | C6: Garantizar una formación en estudios avanzados de excelencia y pertinencia social, a través del desarrollo de programas innovadores con la integración de la investigación de la Agenda Estratégica de Investigación, para asegurar que el conocimiento generado impulse la transformación social. | D6: PRDI25-29-Obj-84 | E6: Consolidar una oferta educativa de estudios avanzados de excelencia, para garantizar la inclusión, la pertinencia social y la alineación con las demandas de los sectores productivo, gubernamental y social. | F6: 15 | G6: Registrar 50 protocolos de investigación de alumnos de estudios avanzados con temáticas vinculadas a la Agenda Estratégica de Investigación, anualmente | H6: ACT-PRDI-NS-2847 | I6: Contribuir desde la Facultad de Ingeniería al cumplimiento de la meta PRDI “Registrar 50 protocolos de investigación de alumnos de estudios avanzados con temáticas vinculadas a la Agenda Estratégica de Investigación, anualmente”, con valores absolutos programados de 2027: 1, 2028: 1, 2029: 1, 2030: 1. | J6: Actividad | K6: Sin fórmula | L6: Registrar protocolos de investigación de alumnos de estudios avanzados con temáticas vinculadas a la Agenda Estratégica de Investigación | N6: 1 | O6: 1 | P6: 1 | Q6: 1 | R6: =IF(M6="","",M6) | S6: =IF(N6="","",N6) -> 1 | T6: =IF(O6="","",O6) -> 1 | U6: =IF(P6="","",P6) -> 1 | V6: =IF(Q6="","",Q6) -> 1 | W6: Anual | X6: Coordinación de Estudios Avanzados
A7: 5 | B7: PRDI25-29-Obj-37 | C7: Garantizar una formación en estudios avanzados de excelencia y pertinencia social, a través del desarrollo de programas innovadores con la integración de la investigación de la Agenda Estratégica de Investigación, para asegurar que el conocimiento generado impulse la transformación social. | D7: PRDI25-29-Obj-84 | E7: Consolidar una oferta educativa de estudios avanzados de excelencia, para garantizar la inclusión, la pertinencia social y la alineación con las demandas de los sectores productivo, gubernamental y social. | F7: 18 | G7: Generar protocolos de acción para incrementar la tasa de graduación y la eficiencia terminal en 10 espacios académicos, en 2026 | H7: ACT-PRDI-NS-2848 | I7: Contribuir desde la Facultad de Ingeniería al cumplimiento de la meta PRDI “Generar protocolos de acción para incrementar la tasa de graduación y la eficiencia terminal en 10 espacios académicos, en 2026”, con valores absolutos programados de 2027: 0, 2028: 0, 2029: 1, 2030: 0. | J7: Actividad | K7: Sin fórmula | L7: Generar protocolos de acción para incrementar la tasa de graduación y la eficiencia terminal en espacios académicos | N7: 0 | O7: 0 | P7: 1 | Q7: 0 | R7: =IF(M7="","",M7) | S7: =IF(N7="","",N7) -> 0 | T7: =IF(O7="","",O7) -> 0 | U7: =IF(P7="","",P7) -> 1 | V7: =IF(Q7="","",Q7) -> 0 | W7: Anual | X7: Coordinación de Estudios Avanzados
A8: 6 | B8: PRDI25-29-Obj-37 | C8: Garantizar una formación en estudios avanzados de excelencia y pertinencia social, a través del desarrollo de programas innovadores con la integración de la investigación de la Agenda Estratégica de Investigación, para asegurar que el conocimiento generado impulse la transformación social. | D8: PRDI25-29-Obj-84 | E8: Consolidar una oferta educativa de estudios avanzados de excelencia, para garantizar la inclusión, la pertinencia social y la alineación con las demandas de los sectores productivo, gubernamental y social. | F8: 19 | G8: Incrementar a 1190 graduados de estudios avanzados, a 2029 | H8: ACT-PRDI-NS-2849 | I8: Contribuir desde la Facultad de Ingeniería al cumplimiento de la meta PRDI “Incrementar a 1190 graduados de estudios avanzados, a 2029”, con valores absolutos programados de 2027: 11, 2028: 17, 2029: 22, 2030: 22. Sustento en la Matriz de consistencia: «Realizar 1 revisión documentada de el ingreso, la permanencia y el egreso por posgrado en 2027 y actualizarla una vez al año de 2028 a 2030.» | J8: Actividad | K8: Sin fórmula | L8: Incrementar graduados de estudios avanzados | N8: 11 | O8: 17 | P8: 22 | Q8: 22 | R8: =IF(M8="","",M8) | S8: =IF(N8="","",N8) -> 11 | T8: =IF(O8="","",O8) -> 17 | U8: =IF(P8="","",P8) -> 22 | V8: =IF(Q8="","",Q8) -> 22 | W8: Anual | X8: Coordinación de Estudios Avanzados
A9: 7 | B9: PRDI25-29-Obj-37 | C9: Garantizar una formación en estudios avanzados de excelencia y pertinencia social, a través del desarrollo de programas innovadores con la integración de la investigación de la Agenda Estratégica de Investigación, para asegurar que el conocimiento generado impulse la transformación social. | D9: PRDI25-29-Obj-84 | E9: Consolidar una oferta educativa de estudios avanzados de excelencia, para garantizar la inclusión, la pertinencia social y la alineación con las demandas de los sectores productivo, gubernamental y social. | F9: 20 | G9: Incrementar a 17.56% la graduación de estudios avanzados por la opción de trabajo terminal de grado, a 2029 | H9: IND-PRDI-365 | I9: Mejorar o mantener de forma conservadora en la Facultad de Ingeniería el indicador IND-PRDI-365, con la trayectoria 2027: 15.15%, 2028: 18.18%, 2029: 18.18%, 2030: 18.18%, sustentada en referencia PRDI; no existe serie histórica directamente comparable para la variable. Sustento en la Matriz de consistencia: «Validar y documentar el valor de Ref. 2026 durante 2027 y, una vez confirmado, mantenerlo o mejorarlo hasta 2030.» | J9: Indicador | K9: (Número de alumnos graduados por la opción de trabajo terminal de grado en el año que se reporta/Total de alumnos graduados en el año que se reporta)*100 | L9: Número de alumnos graduados por la opción de trabajo terminal de grado en el año que se reporta | N9: 5 | O9: 6 | P9: 6 | Q9: 6 | R9: =IF(M10,M9/M10*100,"") | S9: =IF(N10,N9/N10*100,"") -> 15.151515 | T9: =IF(O10,O9/O10*100,"") -> 18.181818 | U9: =IF(P10,P9/P10*100,"") -> 18.181818 | V9: =IF(Q10,Q9/Q10*100,"") -> 18.181818 | W9: Anual | X9: Coordinación de Estudios Avanzados
L10: Total de alumnos graduados en el año que se reporta)*100 | N10: 33 | O10: 33 | P10: 33 | Q10: 33

Sheet 4 Investigación abierta
A1: N.P. | B1: Clave Objetivo General | C1: Objetivo General | D1: Clave Objetivo Específico | E1: Objetivo Específico | F1: No. de meta en el PRDI | G1: Meta PRDI | H1: Clave de la meta | I1: Meta del espacio académico | J1: Actividad/Indicador | K1: Método de cálculo | L1: Nombre de las variables | M1: Valor de las variables | R1: Valor de los indicadores | W1: Medición (anual o acumulada) | X1: Área responsable
M2: Ref. 2026 | N2: 2027 | O2: 2028 | P2: 2029 | Q2: 2030 | R2: Ref. 2026 | S2: 2027 | T2: 2028 | U2: 2029 | V2: 2030
A3: 1 | B3: PRDI25-29-Obj-38 | C3: Impulsar la investigación científica, humanística, tecnológica y de innovación priorizando la calidad, inclusión, equidad, retribución social y multilingüismo, a través del apoyo a proyectos sólidos, el fortalecimiento de redes en la comunidad investigadora y la optimización de recursos e infraestructura, en el marco del nuevo Modelo de Ciencia Abierta para la Transformación Social | D3: PRDI2025-2029-Obj-60 | E3: Fomentar la investigación abierta, equitativa y de calidad, así como transparentar su dimensión de retribución social, incentivar el diálogo de saberes y la participación activa de la comunidad universitaria de forma incluyente. | F3: 19 | G3: Contar con 200 CA de calidad, a 2028 | H3: ACT-PRDI-NS-2870 | I3: Contribuir desde la Facultad de Ingeniería al cumplimiento de la meta PRDI “Contar con 200 CA de calidad, a 2028”, con valores absolutos programados de 2027: 3, 2028: 3, 2029: 3, 2030: 3. Sustento en la Matriz de consistencia: «Mantener al menos 3 cuerpos académicos de calidad en cada medición anual de 2027 a 2030.» | J3: Actividad | K3: Sin fórmula | L3: Contar con Cuerpos Académicos de calidad | M3: 3 | N3: 3 | O3: 3 | P3: 3 | Q3: 3 | R3: =IF(M3="","",M3) -> 3 | S3: =IF(N3="","",N3) -> 3 | T3: =IF(O3="","",O3) -> 3 | U3: =IF(P3="","",P3) -> 3 | V3: =IF(Q3="","",Q3) -> 3 | W3: Anual | X3: Coordinación de Investigación
A4: 2 | B4: PRDI25-29-Obj-38 | C4: Impulsar la investigación científica, humanística, tecnológica y de innovación priorizando la calidad, inclusión, equidad, retribución social y multilingüismo, a través del apoyo a proyectos sólidos, el fortalecimiento de redes en la comunidad investigadora y la optimización de recursos e infraestructura, en el marco del nuevo Modelo de Ciencia Abierta para la Transformación Social | D4: PRDI2025-2029-Obj-60 | E4: Fomentar la investigación abierta, equitativa y de calidad, así como transparentar su dimensión de retribución social, incentivar el diálogo de saberes y la participación activa de la comunidad universitaria de forma incluyente. | F4: 20 | G4: Mantener 98.68% de los CA que realizan investigación que contribuye a la solución de problemas sociales, a 2029 | H4: IND-PRDI-221 | I4: Mejorar o mantener de forma conservadora en la Facultad de Ingeniería el indicador IND-PRDI-221, con la trayectoria 2027: 100%, 2028: 100%, 2029: 100%, 2030: 100%, sustentada en serie histórica directamente comparable del sitio. | J4: Indicador | K4: (Número de cuerpos académicos registrados en SEP que realizan investigación que contribuyen a la solución de problemas sociales/Total de cuerpos académicos registrados en SEP)*100 | L4: Número de cuerpos académicos registrados en SEP que realizan investigación que contribuyen a la solución de problemas sociales | N4: 3 | O4: 3 | P4: 3 | Q4: 3 | R4: =IF(M5,M4/M5*100,"") | S4: =IF(N5,N4/N5*100,"") -> 100 | T4: =IF(O5,O4/O5*100,"") -> 100 | U4: =IF(P5,P4/P5*100,"") -> 100 | V4: =IF(Q5,Q4/Q5*100,"") -> 100 | W4: Anual | X4: Coordinación de Investigación
L5: Total de cuerpos académicos registrados en SEP | N5: 3 | O5: 3 | P5: 3 | Q5: 3
A6: 3 | B6: PRDI25-29-Obj-38 | C6: Impulsar la investigación científica, humanística, tecnológica y de innovación priorizando la calidad, inclusión, equidad, retribución social y multilingüismo, a través del apoyo a proyectos sólidos, el fortalecimiento de redes en la comunidad investigadora y la optimización de recursos e infraestructura, en el marco del nuevo Modelo de Ciencia Abierta para la Transformación Social | D6: PRDI2025-2029-Obj-60 | E6: Fomentar la investigación abierta, equitativa y de calidad, así como transparentar su dimensión de retribución social, incentivar el diálogo de saberes y la participación activa de la comunidad universitaria de forma incluyente. | F6: 21 | G6: Mantener el 49.59% de los PTC con participación en redes con pares extranjeros, anualmente | H6: IND-PRDI-368 | I6: Mejorar o mantener de forma conservadora en la Facultad de Ingeniería el indicador IND-PRDI-368, con la trayectoria 2027: 47.14%, 2028: 48.57%, 2029: 49.3%, 2030: 49.3%, sustentada en referencia PRDI; no existe serie histórica directamente comparable para la variable. | J6: Indicador | K6: (Número de Profesores de Tiempo Completo con participación en redes con pares extranjeros/Total de Profesores de Tiempo Completo)*100 | L6: Número de Profesores de Tiempo Completo con participación en redes con pares extranjeros | N6: 33 | O6: 34 | P6: 35 | Q6: 35 | R6: =IF(M7,M6/M7*100,"") | S6: =IF(N7,N6/N7*100,"") -> 47.142857 | T6: =IF(O7,O6/O7*100,"") -> 48.571429 | U6: =IF(P7,P6/P7*100,"") -> 49.295775 | V6: =IF(Q7,Q6/Q7*100,"") -> 49.295775 | W6: Anual | X6: Coordinación de Investigación
L7: Total de Profesores de Tiempo Completo | N7: 70 | O7: 70 | P7: 71 | Q7: 71
A8: 4 | B8: PRDI25-29-Obj-38 | C8: Impulsar la investigación científica, humanística, tecnológica y de innovación priorizando la calidad, inclusión, equidad, retribución social y multilingüismo, a través del apoyo a proyectos sólidos, el fortalecimiento de redes en la comunidad investigadora y la optimización de recursos e infraestructura, en el marco del nuevo Modelo de Ciencia Abierta para la Transformación Social | D8: PRDI2025-2029-Obj-60 | E8: Fomentar la investigación abierta, equitativa y de calidad, así como transparentar su dimensión de retribución social, incentivar el diálogo de saberes y la participación activa de la comunidad universitaria de forma incluyente. | F8: 22 | G8: Mantener 49.81% de los PTC que participan en redes nacionales, anualmente | H8: IND-PRDI-370 | I8: Mejorar o mantener de forma conservadora en la Facultad de Ingeniería el indicador IND-PRDI-370, con la trayectoria 2027: 47.14%, 2028: 48.57%, 2029: 49.3%, 2030: 49.3%, sustentada en referencia PRDI; no existe serie histórica directamente comparable para la variable. | J8: Indicador | K8: (Número de Profesores de Tiempo Completo con participación en redes nacionales/Total de Profesores de Tiempo Completo)*100 | L8: Número de Profesores de Tiempo Completo con participación en redes nacionales | N8: 33 | O8: 34 | P8: 35 | Q8: 35 | R8: =IF(M9,M8/M9*100,"") | S8: =IF(N9,N8/N9*100,"") -> 47.142857 | T8: =IF(O9,O8/O9*100,"") -> 48.571429 | U8: =IF(P9,P8/P9*100,"") -> 49.295775 | V8: =IF(Q9,Q8/Q9*100,"") -> 49.295775 | W8: Anual | X8: Coordinación de Investigación
L9: Total de Profesores de Tiempo Completo | M9: =M7 -> 0 | N9: 70 | O9: 70 | P9: 71 | Q9: 71
A10: 5 | B10: PRDI25-29-Obj-38 | C10: Impulsar la investigación científica, humanística, tecnológica y de innovación priorizando la calidad, inclusión, equidad, retribución social y multilingüismo, a través del apoyo a proyectos sólidos, el fortalecimiento de redes en la comunidad investigadora y la optimización de recursos e infraestructura, en el marco del nuevo Modelo de Ciencia Abierta para la Transformación Social | D10: PRDI25-29-Obj-85 | E10: Optimizar el proceso de asignación y gestión de recursos financieros para consolidar la investigación con proyectos que respondan a los principios de calidad, equidad, inclusión, retribución social y multilingüismo. | F10: 3 | G10: Atender las necesidades prioritarias de mantenimiento, equipamiento y medidas de seguridad de 115 laboratorios de investigación, a 2029 | H10: ACT-PRDI-NS-2854 | I10: Contribuir desde la Facultad de Ingeniería al cumplimiento de la meta PRDI “Atender las necesidades prioritarias de mantenimiento, equipamiento y medidas de seguridad de 115 laboratorios de investigación, a 2029”, con valores absolutos programados de 2027: 2, 2028: 3, 2029: 3, 2030: 3. | J10: Actividad | K10: Sin fórmula | L10: Atender las necesidades prioritarias de mantenimiento, equipamiento y medidas de seguridad de laboratorios de investigación | N10: 2 | O10: 3 | P10: 3 | Q10: 3 | R10: =IF(M10="","",M10) | S10: =IF(N10="","",N10) -> 2 | T10: =IF(O10="","",O10) -> 3 | U10: =IF(P10="","",P10) -> 3 | V10: =IF(Q10="","",Q10) -> 3 | W10: Anual | X10: Coordinación de Investigación
A11: 6 | B11: PRDI25-29-Obj-38 | C11: Impulsar la investigación científica, humanística, tecnológica y de innovación priorizando la calidad, inclusión, equidad, retribución social y multilingüismo, a través del apoyo a proyectos sólidos, el fortalecimiento de redes en la comunidad investigadora y la optimización de recursos e infraestructura, en el marco del nuevo Modelo de Ciencia Abierta para la Transformación Social | D11: PRDI25-29-Obj-85 | E11: Optimizar el proceso de asignación y gestión de recursos financieros para consolidar la investigación con proyectos que respondan a los principios de calidad, equidad, inclusión, retribución social y multilingüismo. | F11: 7 | G11: Promover la participación en 2 convocatorias externas de proyectos de investigación, anualmente | H11: ACT-PRDI-NS-2858 | I11: Contribuir desde la Facultad de Ingeniería al cumplimiento de la meta PRDI “Promover la participación en 2 convocatorias externas de proyectos de investigación, anualmente”, con valores absolutos programados de 2027: 1, 2028: 1, 2029: 1, 2030: 1. Sustento en la Matriz de consistencia: «Realizar 1 revisión documentada de los productos y colaboraciones de investigación en 2027 y actualizarla una vez al año de 2028 a 2030.» | J11: Actividad | K11: Sin fórmula | L11: Promover la participación en convocatorias externas de proyectos de investigación | N11: 1 | O11: 1 | P11: 1 | Q11: 1 | R11: =IF(M11="","",M11) | S11: =IF(N11="","",N11) -> 1 | T11: =IF(O11="","",O11) -> 1 | U11: =IF(P11="","",P11) -> 1 | V11: =IF(Q11="","",Q11) -> 1 | W11: Anual | X11: Coordinación de Investigación
A12: 7 | B12: PRDI25-29-Obj-38 | C12: Impulsar la investigación científica, humanística, tecnológica y de innovación priorizando la calidad, inclusión, equidad, retribución social y multilingüismo, a través del apoyo a proyectos sólidos, el fortalecimiento de redes en la comunidad investigadora y la optimización de recursos e infraestructura, en el marco del nuevo Modelo de Ciencia Abierta para la Transformación Social | D12: PRDI25-29-Obj-85 | E12: Optimizar el proceso de asignación y gestión de recursos financieros para consolidar la investigación con proyectos que respondan a los principios de calidad, equidad, inclusión, retribución social y multilingüismo. | F12: 17 | G12: Contar con 19.51% de los proyectos de investigación en DT e innovación que cuenten con un plan de transferencia, innovación o impacto social documentado, a 2029 | H12: IND-PRDI-367 | I12: Mejorar o mantener de forma conservadora en la Facultad de Ingeniería el indicador IND-PRDI-367, con la trayectoria 2027: 20%, 2028: 20%, 2029: 20%, 2030: 20%, sustentada en referencia PRDI; no existe serie histórica directamente comparable para la variable. | J12: Indicador | K12: (Número de proyectos de investigación en DT e Innovación que cuentan con plan de transferencia, innovación impacto social documentado/Total de proyectos de investigación en DT e Innovación)*100 | L12: Número de proyectos de investigación en DT e Innovación que cuentan con plan de transferencia, innovación impacto social documentado | N12: 4 | O12: 4 | P12: 4 | Q12: 4 | R12: =IF(M13,M12/M13*100,"") | S12: =IF(N13,N12/N13*100,"") -> 20 | T12: =IF(O13,O12/O13*100,"") -> 20 | U12: =IF(P13,P12/P13*100,"") -> 20 | V12: =IF(Q13,Q12/Q13*100,"") -> 20 | W12: Anual | X12: Coordinación de Investigación
L13: Total de proyectos de investigación en DT e Innovación | N13: 20 | O13: 20 | P13: 20 | Q13: 20
A14: 8 | B14: PRDI25-29-Obj-38 | C14: Impulsar la investigación científica, humanística, tecnológica y de innovación priorizando la calidad, inclusión, equidad, retribución social y multilingüismo, a través del apoyo a proyectos sólidos, el fortalecimiento de redes en la comunidad investigadora y la optimización de recursos e infraestructura, en el marco del nuevo Modelo de Ciencia Abierta para la Transformación Social | D14: PRDI25-29-Obj-85 | E14: Optimizar el proceso de asignación y gestión de recursos financieros para consolidar la investigación con proyectos que respondan a los principios de calidad, equidad, inclusión, retribución social y multilingüismo. | F14: 18 | G14: Contar con 53.22% de producción científica con sentido social, anualmente | H14: IND-PRDI-225 | I14: Mejorar o mantener de forma conservadora en la Facultad de Ingeniería el indicador IND-PRDI-225, con la trayectoria 2027: 50%, 2028: 52.5%, 2029: 52.5%, 2030: 53.66%, sustentada en referencia PRDI; no existe serie histórica directamente comparable para la variable. Sustento en la Matriz de consistencia: «Registrar 1 acuerdo de mejora sobre los productos y colaboraciones de investigación en 2028 y revisar su cumplimiento anualmente hasta 2030.» | J14: Indicador | K14: (Número de producción científica con sentido social/Total de la producción científica reportada)*100 | L14: Número de producción científica con sentido social | N14: 20 | O14: 21 | P14: 21 | Q14: 22 | R14: =IF(M15,M14/M15*100,"") | S14: =IF(N15,N14/N15*100,"") -> 50 | T14: =IF(O15,O14/O15*100,"") -> 52.5 | U14: =IF(P15,P14/P15*100,"") -> 52.5 | V14: =IF(Q15,Q14/Q15*100,"") -> 53.658537 | W14: Anual | X14: Coordinación de Investigación
L15: Total de la producción científica reportada | N15: 40 | O15: 40 | P15: 40 | Q15: 41

Sheet 5 Innovación, desarrollo tec
A1: N.P. | B1: Clave Objetivo General | C1: Objetivo General | D1: Clave Objetivo Específico | E1: Objetivo Específico | F1: No. de meta en el PRDI | G1: Meta PRDI | H1: Clave de la meta | I1: Meta del espacio académico | J1: Actividad/Indicador | K1: Método de cálculo | L1: Nombre de las variables | M1: Valor de las variables | R1: Valor de los indicadores | W1: Medición (anual o acumulada) | X1: Área responsable
M2: Ref. 2026 | N2: 2027 | O2: 2028 | P2: 2029 | Q2: 2030 | R2: Ref. 2026 | S2: 2027 | T2: 2028 | U2: 2029 | V2: 2030
A3: 1 | B3: PRDI25-29-Obj-39 | C3: Impulsar la innovación y el desarrollo tecnológico de manera sostenible y equitativa, a través de la articulación de plataformas multiactor, la gestión de la propiedad intelectual y transferencia tecnológica, en el marco de proyectos Penta-Hélice. | D3: PRDI25-29-Obj-86 | E3: Fortalecer la gestión institucional de la propiedad intelectual y transferencia tecnológica a través de mecanismos equitativos, sostenibles y con retribución social. | F3: 1 | G3: Contar con 222 expedientes, registros y patentes ante el IMPI, a 2029 | H3: ACT-PRDI-NS-2875 | I3: Contribuir desde la Facultad de Ingeniería al cumplimiento de la meta PRDI “Contar con 222 expedientes, registros y patentes ante el IMPI, a 2029”, con valores absolutos programados de 2027: 3, 2028: 4, 2029: 5, 2030: 5. Sustento en la Matriz de consistencia: «Realizar 1 revisión documentada de las capacidades de laboratorios y la demanda externa en 2027 y actualizarla una vez al año de 2028 a 2030.» | J3: Actividad | K3: Sin fórmula | L3: Contar con expedientes, registros y patentes ante el IMPI | N3: 3 | O3: 4 | P3: 5 | Q3: 5 | R3: =IF(M3="","",M3) | S3: =IF(N3="","",N3) -> 3 | T3: =IF(O3="","",O3) -> 4 | U3: =IF(P3="","",P3) -> 5 | V3: =IF(Q3="","",Q3) -> 5 | W3: Anual | X3: Coordinación de Investigación y Vinculación
A4: 2 | B4: PRDI25-29-Obj-39 | C4: Impulsar la innovación y el desarrollo tecnológico de manera sostenible y equitativa, a través de la articulación de plataformas multiactor, la gestión de la propiedad intelectual y transferencia tecnológica, en el marco de proyectos Penta-Hélice. | D4: PRDI25-29-Obj-86 | E4: Fortalecer la gestión institucional de la propiedad intelectual y transferencia tecnológica a través de mecanismos equitativos, sostenibles y con retribución social. | F4: 7 | G4: Capacitar a 100 miembros de la comunidad universitaria en materia de propiedad intelectual y gestión de activos de conocimiento, anualmente | H4: ACT-PRDI-NS-2881 | I4: Contribuir desde la Facultad de Ingeniería al cumplimiento de la meta PRDI “Capacitar a 100 miembros de la comunidad universitaria en materia de propiedad intelectual y gestión de activos de conocimiento, anualmente”, con valores absolutos programados de 2027: 2, 2028: 2, 2029: 2, 2030: 2. Sustento en la Matriz de consistencia: «Integrar 1 cartera de capacidades, prototipos y necesidades externas en 2027 y actualizarla cada año hasta 2030.» «Registrar 1 acuerdo de mejora sobre las capacidades de laboratorios y la demanda externa en 2028 y revisar su cumplimiento anualmente hasta 2030.» | J4: Actividad | K4: Sin fórmula | L4: Capacitar a miembros de la comunidad universitaria en materia de propiedad intelectual y gestión de activos de conocimiento | N4: 2 | O4: 2 | P4: 2 | Q4: 2 | R4: =IF(M4="","",M4) | S4: =IF(N4="","",N4) -> 2 | T4: =IF(O4="","",O4) -> 2 | U4: =IF(P4="","",P4) -> 2 | V4: =IF(Q4="","",Q4) -> 2 | W4: Anual | X4: Coordinación de Investigación y Vinculación

Sheet 6 Dif y divulga de la ciencia
A1: N.P. | B1: Clave Objetivo General | C1: Objetivo General | D1: Clave Objetivo Específico | E1: Objetivo Específico | F1: No. de meta en el PRDI | G1: Meta PRDI | H1: Clave de la meta | I1: Meta del espacio académico | J1: Actividad/Indicador | K1: Método de cálculo | L1: Nombre de las variables | M1: Valor de las variables | R1: Valor de los indicadores | W1: Medición (anual o acumulada) | X1: Área responsable
M2: Ref. 2026 | N2: 2027 | O2: 2028 | P2: 2029 | Q2: 2030 | R2: Ref. 2026 | S2: 2027 | T2: 2028 | U2: 2029 | V2: 2030
A3: 2 | B3: PRDI25-29-Obj-40 | C3: Comunicar en abierto los resultados de investigación con la finalidad de democratizar el acceso al conocimiento generado en la Universidad y asegurar su máxima difusión y retribución social en formatos accesibles y multilingües que se posicionen como bien público digital. | D3: PRDI25-29-Obj-87 | E3: Fortalecer los procesos editoriales y tecnológicos para sostener y generar libros y revistas científicas como bienes públicos digitales. | F3: 6 | G3: Realizar 1 programa de sostenibilidad y fortalecimiento del Acceso Abierto no comercial para las revistas científicas editadas en la Universidad, anualmente | H3: ACT-PRDI-NS-2890 | I3: Contribuir desde la Facultad de Ingeniería al cumplimiento de la meta PRDI “Realizar 1 programa de sostenibilidad y fortalecimiento del Acceso Abierto no comercial para las revistas científicas editadas en la Universidad, anualmente”, con valores absolutos programados de 2027: 1, 2028: 1, 2029: 1, 2030: 1. Sustento en la Matriz de consistencia: «Registrar 1 acuerdo de mejora sobre los públicos y el alcance de la divulgación en 2028 y revisar su cumplimiento anualmente hasta 2030.» | J3: Actividad | K3: Sin fórmula | L3: Realizar un programa de sostenibilidad y fortalecimiento del Acceso Abierto no comercial para las revistas científicas editadas en la Universidad | N3: 1 | O3: 1 | P3: 1 | Q3: 1 | R3: =IF(M3="","",M3) | S3: =IF(N3="","",N3) -> 1 | T3: =IF(O3="","",O3) -> 1 | U3: =IF(P3="","",P3) -> 1 | V3: =IF(Q3="","",Q3) -> 1 | W3: Anual | X3: Coordinación de Investigación y Difusión Científica
A4: 3 | B4: PRDI25-29-Obj-40 | C4: Comunicar en abierto los resultados de investigación con la finalidad de democratizar el acceso al conocimiento generado en la Universidad y asegurar su máxima difusión y retribución social en formatos accesibles y multilingües que se posicionen como bien público digital. | D4: PRDI25-29-Obj-87 | E4: Fortalecer los procesos editoriales y tecnológicos para sostener y generar libros y revistas científicas como bienes públicos digitales. | F4: 13 | G4: Capacitar a 1000 miembros de la comunidad universitaria en Ciencia Abierta, anualmente | H4: ACT-PRDI-NS-2897 | I4: Contribuir desde la Facultad de Ingeniería al cumplimiento de la meta PRDI “Capacitar a 1000 miembros de la comunidad universitaria en Ciencia Abierta, anualmente”, con valores absolutos programados de 2027: 19, 2028: 19, 2029: 19, 2030: 19. Sustento en la Matriz de consistencia: «Realizar 1 revisión documentada de los públicos y el alcance de la divulgación en 2027 y actualizarla una vez al año de 2028 a 2030.» | J4: Actividad | K4: Sin fórmula | L4: Capacitar a miembros de la comunidad universitaria en Ciencia Abierta | N4: 19 | O4: 19 | P4: 19 | Q4: 19 | R4: =IF(M4="","",M4) | S4: =IF(N4="","",N4) -> 19 | T4: =IF(O4="","",O4) -> 19 | U4: =IF(P4="","",P4) -> 19 | V4: =IF(Q4="","",Q4) -> 19 | W4: Anual | X4: Coordinación de Investigación y Difusión Científica
A5: 4 | B5: PRDI25-29-Obj-40 | C5: Comunicar en abierto los resultados de investigación con la finalidad de democratizar el acceso al conocimiento generado en la Universidad y asegurar su máxima difusión y retribución social en formatos accesibles y multilingües que se posicionen como bien público digital. | D5: PRDI25-29-Obj-87 | E5: Fortalecer los procesos editoriales y tecnológicos para sostener y generar libros y revistas científicas como bienes públicos digitales. | F5: 15 | G5: Realizar 1 evaluación de la calidad, criterios y políticas de Acceso Abierto Diamante de las publicaciones periódicas científicas institucionales, anualmente | H5: ACT-PRDI-NS-2899 | I5: Contribuir desde la Facultad de Ingeniería al cumplimiento de la meta PRDI “Realizar 1 evaluación de la calidad, criterios y políticas de Acceso Abierto Diamante de las publicaciones periódicas científicas institucionales, anualmente”, con valores absolutos programados de 2027: 1, 2028: 1, 2029: 1, 2030: 1. Sustento en la Matriz de consistencia: «Establecer 1 registro de divulgación en 2027 y publicar 1 informe anual de productos y alcance entre 2028 y 2030.» | J5: Actividad | K5: Sin fórmula | L5: Realizar evaluaciones de la calidad, criterios y políticas de Acceso Abierto Diamante de las publicaciones periódicas científicas institucionales | N5: 1 | O5: 1 | P5: 1 | Q5: 1 | R5: =IF(M5="","",M5) | S5: =IF(N5="","",N5) -> 1 | T5: =IF(O5="","",O5) -> 1 | U5: =IF(P5="","",P5) -> 1 | V5: =IF(Q5="","",Q5) -> 1 | W5: Anual | X5: Coordinación de Investigación y Difusión Científica

Sheet 7 Cultura desarrollo integral
A1: N.P. | B1: Clave Objetivo General | C1: Objetivo General | D1: Clave Objetivo Específico | E1: Objetivo Específico | F1: No. de meta en el PRDI | G1: Meta PRDI | H1: Clave de la meta | I1: Meta del espacio académico | J1: Actividad/Indicador | K1: Método de cálculo | L1: Nombre de las variables | M1: Valor de las variables | R1: Valor de los indicadores | W1: Medición (anual o acumulada) | X1: Área responsable
M2: Ref. 2026 | N2: 2027 | O2: 2028 | P2: 2029 | Q2: 2030 | R2: Ref. 2026 | S2: 2027 | T2: 2028 | U2: 2029 | V2: 2030
A3: 1 | B3: PRDI25-29-Obj-41 | C3: PRDI25-29-Obj-41 -Fortalecer la cultura a través de proyectos y actividades que articulen la expresión artística y cultural como parte del desarrollo de la comunidad universitaria.. | D3: PRDI25-29-Obj-63 | E3: Fomentar la participación activa de la comunidad universitaria y sociedad en general en actividades culturales innovadoras que fortalezcan la identidad y el sentido de pertenencia institucional que contribuyan a la cohesión social y la igualdad. | F3: 2 | G3: Abrir 850 talleres culturales anualmente en beneficio de la colectividad universitaria de nivel superior | H3: ACT-PRDI-NS-3193 | I3: Contribuir desde la Facultad de Ingeniería al cumplimiento de la meta PRDI “Abrir 850 talleres culturales anualmente en beneficio de la colectividad universitaria de nivel superior”, con valores absolutos programados de 2027: 16, 2028: 16, 2029: 16, 2030: 16. Sustento en la Matriz de consistencia: «Realizar 1 reunión y 1 encuesta a estudiantes y responsables culturales cada año de 2028 a 2030 y documentar los ajustes derivados.» | J3: Actividad | K3: Sin fórmula | L3: Abrir talleres culturales en beneficio de la colectividad universitaria de nivel superior | N3: 16 | O3: 16 | P3: 16 | Q3: 16 | R3: =IF(M3="","",M3) | S3: =IF(N3="","",N3) -> 16 | T3: =IF(O3="","",O3) -> 16 | U3: =IF(P3="","",P3) -> 16 | V3: =IF(Q3="","",Q3) -> 16 | W3: Anual | X3: Coordinación de Difusión Cultural
A4: 2 | B4: PRDI25-29-Obj-41 | C4: PRDI25-29-Obj-41 -Fortalecer la cultura a través de proyectos y actividades que articulen la expresión artística y cultural como parte del desarrollo de la comunidad universitaria.. | D4: PRDI25-29-Obj-63 | E4: Fomentar la participación activa de la comunidad universitaria y sociedad en general en actividades culturales innovadoras que fortalezcan la identidad y el sentido de pertenencia institucional que contribuyan a la cohesión social y la igualdad. | F4: 4 | G4: Realizar 850 presentaciones artísticas anualmente. | H4: ACT-PRDI-NS-1816 | I4: Contribuir desde la Facultad de Ingeniería al cumplimiento de la meta PRDI “Realizar 850 presentaciones artísticas anualmente.”, con valores absolutos programados de 2027: 16, 2028: 16, 2029: 16, 2030: 16. | J4: Actividad | K4: Sin fórmula | L4: Realizar presentaciones artísticas | N4: 16 | O4: 16 | P4: 16 | Q4: 16 | R4: =IF(M4="","",M4) | S4: =IF(N4="","",N4) -> 16 | T4: =IF(O4="","",O4) -> 16 | U4: =IF(P4="","",P4) -> 16 | V4: =IF(Q4="","",Q4) -> 16 | W4: Anual | X4: Coordinación de Difusión Cultural
A5: 3 | B5: PRDI25-29-Obj-41 | C5: PRDI25-29-Obj-41 -Fortalecer la cultura a través de proyectos y actividades que articulen la expresión artística y cultural como parte del desarrollo de la comunidad universitaria.. | D5: PRDI25-29-Obj-63 | E5: Fomentar la participación activa de la comunidad universitaria y sociedad en general en actividades culturales innovadoras que fortalezcan la identidad y el sentido de pertenencia institucional que contribuyan a la cohesión social y la igualdad. | F5: 8 | G5: Organizar 3 programas de fortalecimiento al talento audiovisual para desarrollar la creatividad cultural de los universitarios, durante la administración | H5: ACT-PRDI-NS-3195 | I5: Contribuir desde la Facultad de Ingeniería al cumplimiento de la meta PRDI “Organizar 3 programas de fortalecimiento al talento audiovisual para desarrollar la creatividad cultural de los universitarios, durante la administración”, con valores absolutos programados de 2027: 1, 2028: 0, 2029: 0, 2030: 0. | J5: Actividad | K5: Sin fórmula | L5: Organizar programas de fortalecimiento al talento audiovisual para desarrollar la creatividad cultural de los universitarios | N5: 1 | O5: 0 | P5: 0 | Q5: 0 | R5: =IF(M5="","",M5) | S5: =IF(N5="","",N5) -> 1 | T5: =IF(O5="","",O5) -> 0 | U5: =IF(P5="","",P5) -> 0 | V5: =IF(Q5="","",Q5) -> 0 | W5: Anual | X5: Coordinación de Difusión Cultural
A6: 4 | B6: PRDI25-29-Obj-41 | C6: PRDI25-29-Obj-41 -Fortalecer la cultura a través de proyectos y actividades que articulen la expresión artística y cultural como parte del desarrollo de la comunidad universitaria.. | D6: PRDI25-29-Obj-88 | E6: Fortalecer espacios de formación y reflexión que integren a la cultura con inclusión y transformación social. | F6: 15 | G6: Organizar 6 programas audiovisuales vanguardistas que fomenten la innovación cultural durante la administración | H6: ACT-PRDI-NS-3200 | I6: Contribuir desde la Facultad de Ingeniería al cumplimiento de la meta PRDI “Organizar 6 programas audiovisuales vanguardistas que fomenten la innovación cultural durante la administración”, con valores absolutos programados de 2027: 1, 2028: 0, 2029: 0, 2030: 0. | J6: Actividad | K6: Sin fórmula | L6: Organizar programas audiovisuales vanguardistas que fomenten la innovación cultural | N6: 1 | O6: 0 | P6: 0 | Q6: 0 | R6: =IF(M6="","",M6) | S6: =IF(N6="","",N6) -> 1 | T6: =IF(O6="","",O6) -> 0 | U6: =IF(P6="","",P6) -> 0 | V6: =IF(Q6="","",Q6) -> 0 | W6: Anual | X6: Coordinación de Difusión Cultural
A7: 5 | B7: PRDI25-29-Obj-41 | C7: PRDI25-29-Obj-41 -Fortalecer la cultura a través de proyectos y actividades que articulen la expresión artística y cultural como parte del desarrollo de la comunidad universitaria.. | D7: PRDI25-29-Obj-88 | E7: Fortalecer espacios de formación y reflexión que integren a la cultura con inclusión y transformación social. | F7: 17 | G7: Realizar al año, 4 programas artísticos que contribuyan al fortalecimiento cultural de la comunidad universitaria | H7: ACT-PRDI-NS-3202 | I7: Contribuir desde la Facultad de Ingeniería al cumplimiento de la meta PRDI “Realizar al año, 4 programas artísticos que contribuyan al fortalecimiento cultural de la comunidad universitaria”, con valores absolutos programados de 2027: 1, 2028: 1, 2029: 1, 2030: 1. Sustento en la Matriz de consistencia: «Realizar 1 revisión documentada de las barreras de participación cultural en 2027 y actualizarla una vez al año de 2028 a 2030.» | J7: Actividad | K7: Sin fórmula | L7: Realizar programas artísticos que contribuyan al fortalecimiento cultural de la comunidad universitaria | N7: 1 | O7: 1 | P7: 1 | Q7: 1 | R7: =IF(M7="","",M7) | S7: =IF(N7="","",N7) -> 1 | T7: =IF(O7="","",O7) -> 1 | U7: =IF(P7="","",P7) -> 1 | V7: =IF(Q7="","",Q7) -> 1 | W7: Anual | X7: Coordinación de Difusión Cultural
A8: 6 | B8: PRDI25-29-Obj-41 | C8: PRDI25-29-Obj-41 -Fortalecer la cultura a través de proyectos y actividades que articulen la expresión artística y cultural como parte del desarrollo de la comunidad universitaria.. | D8: PRDI25-29-Obj-88 | E8: Fortalecer espacios de formación y reflexión que integren a la cultura con inclusión y transformación social. | F8: 20 | G8: Realizar al año 1 festival cultural que reúna a los talentos de distintos talleres y espacios académicos | H8: ACT-PRDI-NS-3205 | I8: Contribuir desde la Facultad de Ingeniería al cumplimiento de la meta PRDI “Realizar al año 1 festival cultural que reúna a los talentos de distintos talleres y espacios académicos”, con valores absolutos programados de 2027: 1, 2028: 1, 2029: 1, 2030: 1. Sustento en la Matriz de consistencia: «Realizar 1 diagnóstico de participación cultural en 2027 y revisar 1 programa anual de talleres entre 2028 y 2030.» | J8: Actividad | K8: Sin fórmula | L8: Realizar festivales culturales que reúna a los talentos de distintos talleres y espacios académicos | N8: 1 | O8: 1 | P8: 1 | Q8: 1 | R8: =IF(M8="","",M8) | S8: =IF(N8="","",N8) -> 1 | T8: =IF(O8="","",O8) -> 1 | U8: =IF(P8="","",P8) -> 1 | V8: =IF(Q8="","",Q8) -> 1 | W8: Anual | X8: Coordinación de Difusión Cultural

Sheet 8 Deporte universitario
A1: N.P. | B1: Clave Objetivo General | C1: Objetivo General | D1: Clave Objetivo Específico | E1: Objetivo Específico | F1: No. de meta en el PRDI | G1: Meta PRDI | H1: Clave de la meta | I1: Meta del espacio académico | J1: Actividad/Indicador | K1: Método de cálculo | L1: Nombre de las variables | M1: Valor de las variables | R1: Valor de los indicadores | W1: Medición (anual o acumulada) | X1: Área responsable
M2: Ref. 2026 | N2: 2027 | O2: 2028 | P2: 2029 | Q2: 2030 | R2: Ref. 2026 | S2: 2027 | T2: 2028 | U2: 2029 | V2: 2030
A3: 1 | B3: PRDI25-29-Obj-42 | C3: Fortalecer, mediante la promoción y participación, una cultura física para favorecer el desarrollo integral y la adopción de hábitos de bienestar en la comunidad universitaria. | D3: PRDI25-29-Obj-64 | E3: Generar la cultura física en la comunidad universitaria para fomentar hábitos de vida saludable. | F3: 1 | G3: Organizar anualmente 12 eventos regionales que promuevan el bienestar, el autocuidado y la actividad física responsable | H3: ACT-PRDI-NS-2746 | I3: Contribuir desde la Facultad de Ingeniería al cumplimiento de la meta PRDI “Organizar anualmente 12 eventos regionales que promuevan el bienestar, el autocuidado y la actividad física responsable”, con valores absolutos programados de 2027: 1, 2028: 1, 2029: 1, 2030: 1. | J3: Actividad | K3: Sin fórmula | L3: Organizar eventos regionales que promuevan el bienestar, el autocuidado y la actividad física responsable | N3: 1 | O3: 1 | P3: 1 | Q3: 1 | R3: =IF(M3="","",M3) | S3: =IF(N3="","",N3) -> 1 | T3: =IF(O3="","",O3) -> 1 | U3: =IF(P3="","",P3) -> 1 | V3: =IF(Q3="","",Q3) -> 1 | W3: Anual | X3: Coordinación de Actividades Deportivas
A4: 2 | B4: PRDI25-29-Obj-42 | C4: Fortalecer, mediante la promoción y participación, una cultura física para favorecer el desarrollo integral y la adopción de hábitos de bienestar en la comunidad universitaria. | D4: PRDI25-29-Obj-64 | E4: Generar la cultura física en la comunidad universitaria para fomentar hábitos de vida saludable. | F4: 2 | G4: Mantener anualmente la participación de 41.01% del personal académico en actividades de cultura física | H4: IND-PRDI-372 | I4: Mejorar o mantener de forma conservadora en la Facultad de Ingeniería el indicador IND-PRDI-372, con la trayectoria 2027: 39.08%, 2028: 39.65%, 2029: 40.42%, 2030: 40.97%, sustentada en referencia PRDI; no existe serie histórica directamente comparable para la variable. | J4: Indicador | K4: (Número de académicos que participan en actividades deportivas/ Total del personal académico)*100 | L4: Número de académicos que participan en actividades deportivas | N4: 111 | O4: 113 | P4: 116 | Q4: 118 | R4: =IF(M5,M4/M5*100,"") | S4: =IF(N5,N4/N5*100,"") -> 39.084507 | T4: =IF(O5,O4/O5*100,"") -> 39.649123 | U4: =IF(P5,P4/P5*100,"") -> 40.418118 | V4: =IF(Q5,Q4/Q5*100,"") -> 40.972222 | W4: Anual | X4: Coordinación de Actividades Deportivas
L5: Total del personal académico | N5: 284 | O5: 285 | P5: 287 | Q5: 288
A6: 3 | B6: PRDI25-29-Obj-42 | C6: Fortalecer, mediante la promoción y participación, una cultura física para favorecer el desarrollo integral y la adopción de hábitos de bienestar en la comunidad universitaria. | D6: PRDI25-29-Obj-64 | E6: Generar la cultura física en la comunidad universitaria para fomentar hábitos de vida saludable. | F6: 3 | G6: Lograr que 30.02% del personal administrativo participe en actividades de cultura física, anualmente | H6: IND-PRDI-374 | I6: Mejorar o mantener de forma conservadora en la Facultad de Ingeniería el indicador IND-PRDI-374, con la trayectoria 2027: 29.11%, 2028: 29.11%, 2029: 30%, 2030: 30%, sustentada en referencia PRDI; no existe serie histórica directamente comparable para la variable. Sustento en la Matriz de consistencia: «Realizar 1 revisión documentada de el acceso a espacios y actividades deportivas en 2027 y actualizarla una vez al año de 2028 a 2030.» | J6: Indicador | K6: (Número de administrativos en actividades deportivas/ Total del personal administrativo)*100 | L6: Número de administrativos en actividades deportivas | N6: 23 | O6: 23 | P6: 24 | Q6: 24 | R6: =IF(M7,M6/M7*100,"") | S6: =IF(N7,N6/N7*100,"") -> 29.113924 | T6: =IF(O7,O6/O7*100,"") -> 29.113924 | U6: =IF(P7,P6/P7*100,"") -> 30 | V6: =IF(Q7,Q6/Q7*100,"") -> 30 | W6: Anual | X6: Coordinación de Actividades Deportivas
L7: Total del personal administrativo | N7: 79 | O7: 79 | P7: 80 | Q7: 80
A8: 4 | B8: PRDI25-29-Obj-42 | C8: Fortalecer, mediante la promoción y participación, una cultura física para favorecer el desarrollo integral y la adopción de hábitos de bienestar en la comunidad universitaria. | D8: PRDI25-29-Obj-64 | E8: Generar la cultura física en la comunidad universitaria para fomentar hábitos de vida saludable. | F8: 7 | G8: Lograr anualmente que 50% de estudiantes del nivel superior participen en actividades de cultura física | H8: IND-PRDI-377 | I8: Mejorar o mantener de forma conservadora en la Facultad de Ingeniería el indicador IND-PRDI-377, con la trayectoria 2027: 47.51%, 2028: 48.34%, 2029: 49.16%, 2030: 50%, sustentada en referencia PRDI; no existe serie histórica directamente comparable para la variable. Sustento en la Matriz de consistencia: «Realizar 1 reunión y 1 encuesta a estudiantes y responsables deportivos cada año de 2028 a 2030 y documentar los ajustes derivados.» | J8: Indicador | K8: (Número de estudiantes de nivel superior que participan en actividades deportivas/ Total matrícula estudiantil de estudios profesionales)*100 | L8: Número de estudiantes de nivel superior que participan en actividades deportivas | N8: 1420 | O8: 1452 | P8: 1484 | Q8: 1517 | R8: =IF(M9,M8/M9*100,"") | S8: =IF(N9,N8/N9*100,"") -> 47.507528 | T8: =IF(O9,O8/O9*100,"") -> 48.335553 | U8: =IF(P9,P8/P9*100,"") -> 49.155349 | V8: =IF(Q9,Q8/Q9*100,"") -> 50 | W8: Anual | X8: Coordinación de Actividades Deportivas
L9: Total matrícula estudiantil de estudios profesionales | M9: ='2 EstudiantadoEstProf'!M14 -> 0 | N9: 2989 | O9: 3004 | P9: 3019 | Q9: 3034
A10: 5 | B10: PRDI25-29-Obj-42 | C10: Fortalecer, mediante la promoción y participación, una cultura física para favorecer el desarrollo integral y la adopción de hábitos de bienestar en la comunidad universitaria. | D10: PRDI25-29-Obj-90 | E10: Ampliar las oportunidades de acceso al deporte dirigidas a la comunidad universitaria para su desarrollo integral y proyección competitiva con equidad e inclusión. | F10: 5 | G10: Contar con la participación anual de 300 deportistas universitarios para impulsar su talento competitivo a nivel estatal, nacional e internacional | H10: ACT-PRDI-NS-2909 | I10: Contribuir desde la Facultad de Ingeniería al cumplimiento de la meta PRDI “Contar con la participación anual de 300 deportistas universitarios para impulsar su talento competitivo a nivel estatal, nacional e internacional”, con valores absolutos programados de 2027: 6, 2028: 6, 2029: 6, 2030: 6. Sustento en la Matriz de consistencia: «Realizar 1 diagnóstico deportivo en 2027 y publicar 1 programa anual de actividades entre 2028 y 2030.» | J10: Actividad | K10: Sin fórmula | L10: Contar con la participación deportistas universitarios para impulsar su talento competitivo a nivel estatal, nacional e internacional | N10: 6 | O10: 6 | P10: 6 | Q10: 6 | R10: =IF(M10="","",M10) | S10: =IF(N10="","",N10) -> 6 | T10: =IF(O10="","",O10) -> 6 | U10: =IF(P10="","",P10) -> 6 | V10: =IF(Q10="","",Q10) -> 6 | W10: Anual | X10: Coordinación de Actividades Deportivas

Sheet 9 Fortalecimiento docente
A1: N.P. | B1: Clave Objetivo General | C1: Objetivo General | D1: Clave Objetivo Específico | E1: Objetivo Específico | F1: No. de meta en el PRDI | G1: Meta PRDI | H1: Clave de la meta | I1: Meta del espacio académico | J1: Actividad/Indicador | K1: Método de cálculo | L1: Nombre de las variables | M1: Valor de las variables | R1: Valor de los indicadores | W1: Medición (anual o acumulada) | X1: Área responsable
M2: Ref. 2026 | N2: 2027 | O2: 2028 | P2: 2029 | Q2: 2030 | R2: Ref. 2026 | S2: 2027 | T2: 2028 | U2: 2029 | V2: 2030
A3: 1 | B3: PRDI25-29-Obj-43 | C3: Fortalecer la habilitación académica, científica y el desarrollo integral del personal académico mediante una formación humanista e innovadora, que dignifique su labor, promueva la excelencia educativa y contribuya al bienestar de la comunidad docente. | D3: PRDI2025-2029-Obj-65 | E3: Formar al profesorado de nivel superior integralmente, para promover la excelencia educativa. | F3: 2 | G3: Lograr a 2029 que 65% del personal académico de nivel superior participe en actividades de formación | H3: IND-NS-212 | I3: Mejorar o mantener de forma conservadora en la Facultad de Ingeniería el indicador IND-NS-212, con la trayectoria 2027: 61.62%, 2028: 62.81%, 2029: 63.76%, 2030: 64.93%, sustentada en referencia PRDI; no existe serie histórica directamente comparable para la variable. | J3: Indicador | K3: (Número de académicos de nivel superior que participan en actividades de formación./Total de académicos de nivel superior)*100 | L3: Número de académicos de nivel superior que participan en actividades de formación. | N3: 175 | O3: 179 | P3: 183 | Q3: 187 | R3: =IF(M4,M3/M4*100,"") | S3: =IF(N4,N3/N4*100,"") -> 61.619718 | T3: =IF(O4,O3/O4*100,"") -> 62.807018 | U3: =IF(P4,P3/P4*100,"") -> 63.763066 | V3: =IF(Q4,Q3/Q4*100,"") -> 64.930556 | W3: Anual | X3: Subdirección Académica
L4: Total de académicos de nivel superior | N4: 284 | O4: 285 | P4: 287 | Q4: 288
A5: 2 | B5: PRDI25-29-Obj-43 | C5: Fortalecer la habilitación académica, científica y el desarrollo integral del personal académico mediante una formación humanista e innovadora, que dignifique su labor, promueva la excelencia educativa y contribuya al bienestar de la comunidad docente. | D5: PRDI2025-2029-Obj-65 | E5: Formar al profesorado de nivel superior integralmente, para promover la excelencia educativa. | F5: 3 | G5: Actualizar anualmente a 25.01% del personal académico del nivel superior en conocimientos propios de la disciplina que enseñan | H5: IND-PRDI-371 | I5: Mejorar o mantener de forma conservadora en la Facultad de Ingeniería el indicador IND-PRDI-371, con la trayectoria 2027: 23.59%, 2028: 24.21%, 2029: 24.74%, 2030: 25%, sustentada en referencia PRDI; no existe serie histórica directamente comparable para la variable. | J5: Indicador | K5: (Número de personal académico de nivel superior que participa en actividades de capacitación de actualización disciplinar/Total de personal académico de nivel superior)*100 | L5: Número de personal académico de nivel superior que participa en actividades de capacitación de actualización disciplinar | N5: 67 | O5: 69 | P5: 71 | Q5: 72 | R5: =IF(M6,M5/M6*100,"") | S5: =IF(N6,N5/N6*100,"") -> 23.591549 | T5: =IF(O6,O5/O6*100,"") -> 24.210526 | U5: =IF(P6,P5/P6*100,"") -> 24.738676 | V5: =IF(Q6,Q5/Q6*100,"") -> 25 | W5: Anual | X5: Subdirección Académica
L6: Total de personal académico de nivel superior | M6: =M4 -> 0 | N6: 284 | O6: 285 | P6: 287 | Q6: 288
A7: 3 | B7: PRDI25-29-Obj-43 | C7: Fortalecer la habilitación académica, científica y el desarrollo integral del personal académico mediante una formación humanista e innovadora, que dignifique su labor, promueva la excelencia educativa y contribuya al bienestar de la comunidad docente. | D7: PRDI2025-2029-Obj-65 | E7: Formar al profesorado de nivel superior integralmente, para promover la excelencia educativa. | F7: 4 | G7: Lograr que 50% de personal académico de nivel superior se capacite en el desarrollo de competencias didácticas y digitales a 2029 | H7: IND-PRDI-373 | I7: Mejorar o mantener de forma conservadora en la Facultad de Ingeniería el indicador IND-PRDI-373, con la trayectoria 2027: 47.54%, 2028: 48.42%, 2029: 49.13%, 2030: 50%, sustentada en referencia PRDI; no existe serie histórica directamente comparable para la variable. Sustento en la Matriz de consistencia: «Realizar 1 revisión documentada de las necesidades didácticas y de tutoría en 2027 y actualizarla una vez al año de 2028 a 2030.» | J7: Indicador | K7: (Número de personal académico de nivel superior que participa en actividades de capacitación en el desarrollo de competencias didácticas y digitales/Total de personal académico de nivel superior)*100 | L7: Número de personal académico de nivel superior que participa en actividades de capacitación en el desarrollo de competencias didácticas y digitales | N7: 135 | O7: 138 | P7: 141 | Q7: 144 | R7: =IF(M8,M7/M8*100,"") | S7: =IF(N8,N7/N8*100,"") -> 47.535211 | T7: =IF(O8,O7/O8*100,"") -> 48.421053 | U7: =IF(P8,P7/P8*100,"") -> 49.12892 | V7: =IF(Q8,Q7/Q8*100,"") -> 50 | W7: Anual | X7: Subdirección Académica
L8: Total de personal académico de nivel superior | M8: =M4 -> 0 | N8: 284 | O8: 285 | P8: 287 | Q8: 288
A9: 4 | B9: PRDI25-29-Obj-43 | C9: Fortalecer la habilitación académica, científica y el desarrollo integral del personal académico mediante una formación humanista e innovadora, que dignifique su labor, promueva la excelencia educativa y contribuya al bienestar de la comunidad docente. | D9: PRDI2025-2029-Obj-65 | E9: Formar al profesorado de nivel superior integralmente, para promover la excelencia educativa. | F9: 5 | G9: Capacitar a 100% del personal académico en el nuevo modelo educativo durante la administración | H9: IND-PRDI-375 | I9: Mejorar o mantener de forma conservadora en la Facultad de Ingeniería el indicador IND-PRDI-375, con la trayectoria 2027: 96.13%, 2028: 97.19%, 2029: 98.61%, 2030: 100%, sustentada en referencia PRDI; no existe serie histórica directamente comparable para la variable. | J9: Indicador | K9: (Número de personal académico capacitado en el nuevo modelo educativo/Total de personal académico)*100 | L9: Número de personal académico capacitado en el nuevo modelo educativo | N9: 273 | O9: 277 | P9: 283 | Q9: 288 | R9: =IF(M10,M9/M10*100,"") | S9: =IF(N10,N9/N10*100,"") -> 96.126761 | T9: =IF(O10,O9/O10*100,"") -> 97.192982 | U9: =IF(P10,P9/P10*100,"") -> 98.606272 | V9: =IF(Q10,Q9/Q10*100,"") -> 100 | W9: Anual | X9: Subdirección Académica
L10: Total de personal académico | N10: 284 | O10: 285 | P10: 287 | Q10: 288
A11: 5 | B11: PRDI25-29-Obj-43 | C11: Fortalecer la habilitación académica, científica y el desarrollo integral del personal académico mediante una formación humanista e innovadora, que dignifique su labor, promueva la excelencia educativa y contribuya al bienestar de la comunidad docente. | D11: PRDI2025-2029-Obj-65 | E11: Formar al profesorado de nivel superior integralmente, para promover la excelencia educativa. | F11: 6 | G11: Brindar capacitación en temas transversales a 25.01% del personal académico de nivel superior anualmente | H11: IND-PRDI-376 | I11: Mejorar o mantener de forma conservadora en la Facultad de Ingeniería el indicador IND-PRDI-376, con la trayectoria 2027: 23.59%, 2028: 24.21%, 2029: 24.74%, 2030: 25%, sustentada en referencia PRDI; no existe serie histórica directamente comparable para la variable. | J11: Indicador | K11: (Número de personal académico de nivel superior que participa en actividades de capacitación en temas transversales/Total de personal académico de nivel superior)*100 | L11: Número de personal académico de nivel superior que participa en actividades de capacitación en temas transversales | N11: 67 | O11: 69 | P11: 71 | Q11: 72 | R11: =IF(M12,M11/M12*100,"") | S11: =IF(N12,N11/N12*100,"") -> 23.591549 | T11: =IF(O12,O11/O12*100,"") -> 24.210526 | U11: =IF(P12,P11/P12*100,"") -> 24.738676 | V11: =IF(Q12,Q11/Q12*100,"") -> 25 | W11: Anual | X11: Subdirección Académica
L12: Total de personal académico de nivel superior | M12: =M4 -> 0 | N12: 284 | O12: 285 | P12: 287 | Q12: 288
A13: 6 | B13: PRDI25-29-Obj-43 | C13: Fortalecer la habilitación académica, científica y el desarrollo integral del personal académico mediante una formación humanista e innovadora, que dignifique su labor, promueva la excelencia educativa y contribuya al bienestar de la comunidad docente. | D13: PRDI25-29-Obj-92 | E13: Fortalecer la formación y certificación del profesorado en una segunda lengua, con el propósito de consolidar su desarrollo profesional. | F13: 10 | G13: Lograr la certificación internacional en una segunda lengua en nivel C1 de cuatro habilidades de 360 profesores de lengua de estudios profesionales al final de la administración | H13: ACT-PRDI-NS-2923 | I13: Contribuir desde la Facultad de Ingeniería al cumplimiento de la meta PRDI “Lograr la certificación internacional en una segunda lengua en nivel C1 de cuatro habilidades de 360 profesores de lengua de estudios profesionales al final de la administración”, con valores absolutos programados de 2027: 0, 2028: 0, 2029: 7, 2030: 0. | J13: Actividad | K13: Sin fórmula | L13: Lograr la certificación internacional en una segunda lengua en nivel C1 de cuatro habilidades de profesores de lengua de estudios profesionales | N13: 0 | O13: 0 | P13: 7 | Q13: 0 | R13: =IF(M13="","",M13) | S13: =IF(N13="","",N13) -> 0 | T13: =IF(O13="","",O13) -> 0 | U13: =IF(P13="","",P13) -> 7 | V13: =IF(Q13="","",Q13) -> 0 | W13: Anual | X13: Subdirección Académica
A14: 7 | B14: PRDI25-29-Obj-43 | C14: Fortalecer la habilitación académica, científica y el desarrollo integral del personal académico mediante una formación humanista e innovadora, que dignifique su labor, promueva la excelencia educativa y contribuya al bienestar de la comunidad docente. | D14: PRDI25-29-Obj-93 | E14: Mejorar la habilitación académica y científica de los investigadores para su reconocimiento y excelencia. | F14: 13 | G14: Contar con 715 PTC en el SNII para 2029 | H14: ACT-PRDI-NS-2926 | I14: Contribuir desde la Facultad de Ingeniería al cumplimiento de la meta PRDI “Contar con 715 PTC en el SNII para 2029”, con valores absolutos programados de 2027: 7, 2028: 10, 2029: 13, 2030: 13. | J14: Actividad | K14: Sin fórmula | L14: Contar con PTC en el SNII | N14: 7 | O14: 10 | P14: 13 | Q14: 13 | R14: =IF(M14="","",M14) | S14: =IF(N14="","",N14) -> 7 | T14: =IF(O14="","",O14) -> 10 | U14: =IF(P14="","",P14) -> 13 | V14: =IF(Q14="","",Q14) -> 13 | W14: Acumulada | X14: Subdirección Académica
A15: 8 | B15: PRDI25-29-Obj-43 | C15: Fortalecer la habilitación académica, científica y el desarrollo integral del personal académico mediante una formación humanista e innovadora, que dignifique su labor, promueva la excelencia educativa y contribuya al bienestar de la comunidad docente. | D15: PRDI25-29-Obj-93 | E15: Mejorar la habilitación académica y científica de los investigadores para su reconocimiento y excelencia. | F15: 14 | G15: Alcanzar 75.06% del profesorado de tiempo completo (PTC) con Perfil PRODEP, para 2029 | H15: IND-PRDI-47 | I15: Mejorar o mantener de forma conservadora en la Facultad de Ingeniería el indicador IND-PRDI-47, con la trayectoria 2027: 71.43%, 2028: 72.86%, 2029: 73.24%, 2030: 74.65%, sustentada en referencia PRDI; no existe serie histórica directamente comparable para la variable. Sustento en la Matriz de consistencia: «Realizar 1 reunión y 1 encuesta a profesorado y estudiantes de cada licenciatura cada año de 2028 a 2030 y documentar los ajustes derivados.» | J15: Indicador | K15: (PTC registrados en la SEP que cuentan con perfil Prodep/Total de PTC registrados en la SEP)*100 | L15: PTC registrados en la SEP que cuentan con perfil Prodep | N15: 50 | O15: 51 | P15: 52 | Q15: 53 | R15: =IF(M16,M15/M16*100,"") | S15: =IF(N16,N15/N16*100,"") -> 71.428571 | T15: =IF(O16,O15/O16*100,"") -> 72.857143 | U15: =IF(P16,P15/P16*100,"") -> 73.239437 | V15: =IF(Q16,Q15/Q16*100,"") -> 74.647887 | W15: Acumulada | X15: Subdirección Académica
L16: Total de PTC registrados en la SEP | N16: 70 | O16: 70 | P16: 71 | Q16: 71
A17: 9 | B17: PRDI25-29-Obj-43 | C17: Fortalecer la habilitación académica, científica y el desarrollo integral del personal académico mediante una formación humanista e innovadora, que dignifique su labor, promueva la excelencia educativa y contribuya al bienestar de la comunidad docente. | D17: PRDI25-29-Obj-93 | E17: Mejorar la habilitación académica y científica de los investigadores para su reconocimiento y excelencia. | F17: 15 | G17: Lograr 34 participantes del personal académico de Estudios Avanzados en actividades de internacionalización (seminarios, coil, cátedras), durante la administración | H17: ACT-PRDI-NS-2927 | I17: Contribuir desde la Facultad de Ingeniería al cumplimiento de la meta PRDI “Lograr 34 participantes del personal académico de Estudios Avanzados en actividades de internacionalización (seminarios, coil, cátedras), durante la administración”, con valores absolutos programados de 2027: 1, 2028: 0, 2029: 0, 2030: 0. | J17: Actividad | K17: Sin fórmula | L17: Lograr participantes del personal académico de Estudios Avanzados en actividades de internacionalización (seminarios, coil, cátedras) | N17: 1 | O17: 0 | P17: 0 | Q17: 0 | R17: =IF(M17="","",M17) | S17: =IF(N17="","",N17) -> 1 | T17: =IF(O17="","",O17) -> 0 | U17: =IF(P17="","",P17) -> 0 | V17: =IF(Q17="","",Q17) -> 0 | W17: Anual | X17: Subdirección Académica
A18: 10 | B18: PRDI25-29-Obj-43 | C18: Fortalecer la habilitación académica, científica y el desarrollo integral del personal académico mediante una formación humanista e innovadora, que dignifique su labor, promueva la excelencia educativa y contribuya al bienestar de la comunidad docente. | D18: PRDI25-29-Obj-93 | E18: Mejorar la habilitación académica y científica de los investigadores para su reconocimiento y excelencia. | F18: 16 | G18: Lograr que 316 académicos e investigadores participen en estancias internacionales o de movilidad durante la administración | H18: ACT-PRDI-NS-2928 | I18: Contribuir desde la Facultad de Ingeniería al cumplimiento de la meta PRDI “Lograr que 316 académicos e investigadores participen en estancias internacionales o de movilidad durante la administración”, con valores absolutos programados de 2027: 2, 2028: 2, 2029: 1, 2030: 1. Sustento en la Matriz de consistencia: «Validar y documentar el valor de Ref. 2026 durante 2027 y, una vez confirmado, mantenerlo o mejorarlo hasta 2030.» | J18: Actividad | K18: Sin fórmula | L18: Lograr que académicos e investigadores participen en estancias internacionales o de movilidad | N18: 2 | O18: 2 | P18: 1 | Q18: 1 | R18: =IF(M18="","",M18) | S18: =IF(N18="","",N18) -> 2 | T18: =IF(O18="","",O18) -> 2 | U18: =IF(P18="","",P18) -> 1 | V18: =IF(Q18="","",Q18) -> 1 | W18: Anual | X18: Subdirección Académica

Sheet 10 Dignificación las y los trab
A1: N.P. | B1: Clave Objetivo General | C1: Objetivo General | D1: Clave Objetivo Específico | E1: Objetivo Específico | F1: No. de meta en el PRDI | G1: Meta PRDI | H1: Clave de la meta | I1: Meta del espacio académico | J1: Actividad/Indicador | K1: Método de cálculo | L1: Nombre de las variables | M1: Valor de las variables | R1: Valor de los indicadores | W1: Medición (anual o acumulada) | X1: Área responsable
M2: Ref. 2026 | N2: 2027 | O2: 2028 | P2: 2029 | Q2: 2030 | R2: Ref. 2026 | S2: 2027 | T2: 2028 | U2: 2029 | V2: 2030
A3: 1 | B3: PRDI25-29-Obj-44 | C3: Mejorar la dignificación de las y los trabajadores universitarios a través del reconocimiento institucional y actualización de conocimiento para fortalecer su perfil profesional y personal; lo cual se verá reflejado en un mejor servicio universitario. | D3: PRDI2025-2029-Obj-66 | E3: Fortalecer las competencias laborales del personal administrativo para la mejora de perfiles de puesto. | F3: 1 | G3: Capacitar a 80% de los integrantes del personal administrativo en competencias básicas y técnicas a 2029 | H3: IND-PRDI-378 | I3: Mejorar o mantener de forma conservadora en la Facultad de Ingeniería el indicador IND-PRDI-378, con la trayectoria 2027: 75.95%, 2028: 77.22%, 2029: 78.75%, 2030: 80%, sustentada en referencia PRDI; no existe serie histórica directamente comparable para la variable. Sustento en la Matriz de consistencia: «Realizar 1 diagnóstico de necesidades del personal en 2027 y ejecutar 1 programa anual de mejora de 2028 a 2030.» | J3: Indicador | K3: (Número de personal administrativo capacitado en competencias básicas y técnicas / Total de personal administrativo)*100 | L3: Número de personal administrativo capacitado en en competencias básicas y técnicas | N3: 60 | O3: 61 | P3: 63 | Q3: 64 | R3: =IF(M4,M3/M4*100,"") | S3: =IF(N4,N3/N4*100,"") -> 75.949367 | T3: =IF(O4,O3/O4*100,"") -> 77.21519 | U3: =IF(P4,P3/P4*100,"") -> 78.75 | V3: =IF(Q4,Q3/Q4*100,"") -> 80 | W3: Anual | X3: Subdirección Administrativa
L4: Total de personal administrativo | M4: ='8 Deporte universitario'!M7 -> 0 | N4: 79 | O4: 79 | P4: 80 | Q4: 80
A5: 2 | B5: PRDI25-29-Obj-44 | C5: Mejorar la dignificación de las y los trabajadores universitarios a través del reconocimiento institucional y actualización de conocimiento para fortalecer su perfil profesional y personal; lo cual se verá reflejado en un mejor servicio universitario. | D5: PRDI2025-2029-Obj-66 | E5: Fortalecer las competencias laborales del personal administrativo para la mejora de perfiles de puesto. | F5: 2 | G5: Capacitar 35.01% del personal administrativo en competencias transversales, equidad de género, ética y cultura de paz a 2029 | H5: IND-PRDI-380 | I5: Mejorar o mantener de forma conservadora en la Facultad de Ingeniería el indicador IND-PRDI-380, con la trayectoria 2027: 32.91%, 2028: 34.18%, 2029: 35%, 2030: 35%, sustentada en referencia PRDI; no existe serie histórica directamente comparable para la variable. Sustento en la Matriz de consistencia: «Realizar 1 reunión y 1 encuesta a personal académico y administrativo cada año de 2028 a 2030 y documentar los ajustes derivados.» | J5: Indicador | K5: (Número de personal administrativo capacitado en competencias transversales, equidad de género, ética y paz / Total de personal administrativo)*100 | L5: Número de personal administrativo capacitado en competencias transversales, equidad de género, ética y paz | N5: 26 | O5: 27 | P5: 28 | Q5: 28 | R5: =IF(M6,M5/M6*100,"") | S5: =IF(N6,N5/N6*100,"") -> 32.911392 | T5: =IF(O6,O5/O6*100,"") -> 34.177215 | U5: =IF(P6,P5/P6*100,"") -> 35 | V5: =IF(Q6,Q5/Q6*100,"") -> 35 | W5: Anual | X5: Subdirección Administrativa
L6: Total de personal administrativo | M6: ='8 Deporte universitario'!M7 -> 0 | N6: 79 | O6: 79 | P6: 80 | Q6: 80
A7: 3 | B7: PRDI25-29-Obj-44 | C7: Mejorar la dignificación de las y los trabajadores universitarios a través del reconocimiento institucional y actualización de conocimiento para fortalecer su perfil profesional y personal; lo cual se verá reflejado en un mejor servicio universitario. | D7: PRDI2025-2029-Obj-66 | E7: Fortalecer las competencias laborales del personal administrativo para la mejora de perfiles de puesto. | F7: 4 | G7: Capacitar a 20% del personal universitario en Tecnologías de la Información y Comunicación, anualmente | H7: IND-PRDI-382 | I7: Mejorar o mantener de forma conservadora en la Facultad de Ingeniería el indicador IND-PRDI-382, con la trayectoria 2027: 19.01%, 2028: 19.45%, 2029: 19.62%, 2030: 20.11%, sustentada en referencia PRDI; no existe serie histórica directamente comparable para la variable. Sustento en la Matriz de consistencia: «Realizar 1 revisión documentada de las condiciones y necesidades del personal en 2027 y actualizarla una vez al año de 2028 a 2030.» | J7: Indicador | K7: (Número de personal universitario capacitado en temas de Tecnologías de la Información/ Total de personal universitario)*100 | L7: Número de personal universitario capacitado en temas de Tecnologías de la Información | N7: 69 | O7: 71 | P7: 72 | Q7: 74 | R7: =IF(M8,M7/M8*100,"") | S7: =IF(N8,N7/N8*100,"") -> 19.008264 | T7: =IF(O8,O7/O8*100,"") -> 19.452055 | U7: =IF(P8,P7/P8*100,"") -> 19.618529 | V7: =IF(Q8,Q7/Q8*100,"") -> 20.108696 | W7: Anual | X7: Subdirección Administrativa
L8: Total de personal universitario | N8: 363 | O8: 365 | P8: 367 | Q8: 368

Sheet 11 Gestión administrativa
A1: N.P. | B1: Clave Objetivo General | C1: Objetivo General | D1: Clave Objetivo Específico | E1: Objetivo Específico | F1: No. de meta en el PRDI | G1: Meta PRDI | H1: Clave de la meta | I1: Meta del espacio académico | J1: Actividad/Indicador | K1: Método de cálculo | L1: Nombre de las variables | M1: Valor de las variables | R1: Valor de los indicadores | W1: Medición (anual o acumulada) | X1: Área responsable
M2: Ref. 2026 | N2: 2027 | O2: 2028 | P2: 2029 | Q2: 2030 | R2: Ref. 2026 | S2: 2027 | T2: 2028 | U2: 2029 | V2: 2030
A3: 1 | B3: PRDI25-29-Obj-45 | C3: Fortalecer la administración universitaria mediante acciones integrales de infraestructura, cultura organizacional de la calidad y proceso orgánico funcional, eficientes para atender las necesidades de la comunidad universitaria. | D3: PRDI25-29-Obj-99 | E3: PRDI25-29-Obj-99 -Fortalecer el proceso orgánico-funcional de la Institución que permita tener una gestión más eficiente en los espacios universitarios. | F3: 24 | G3: Armonizar 70 manuales de organización de espacios universitarios a 2029 | H3: ACT-PRDI-NS-2743 | I3: Contribuir desde la Facultad de Ingeniería al cumplimiento de la meta PRDI “Armonizar 70 manuales de organización de espacios universitarios a 2029”, con valores absolutos programados de 2027: 2, 2028: 2, 2029: 2, 2030: 2. Sustento en la Matriz de consistencia: «Realizar 1 revisión documentada de el estado y uso de aulas y laboratorios en 2027 y actualizarla una vez al año de 2028 a 2030.» | J3: Actividad | K3: Sin fórmula | L3: Armonizar manuales de organización de espacios universitarios | N3: 2 | O3: 2 | P3: 2 | Q3: 2 | R3: =IF(M3="","",M3) | S3: =IF(N3="","",N3) -> 2 | T3: =IF(O3="","",O3) -> 2 | U3: =IF(P3="","",P3) -> 2 | V3: =IF(Q3="","",Q3) -> 2 | W3: Anual | X3: Subdirección Administrativa
A4: 2 | B4: PRDI25-29-Obj-45 | C4: Fortalecer la administración universitaria mediante acciones integrales de infraestructura, cultura organizacional de la calidad y proceso orgánico funcional, eficientes para atender las necesidades de la comunidad universitaria. | D4: PRDI25-29-Obj-99 | E4: PRDI25-29-Obj-99 -Fortalecer el proceso orgánico-funcional de la Institución que permita tener una gestión más eficiente en los espacios universitarios. | F4: 25 | G4: Armonizar 50 manuales de procedimientos de espacios universitarios a 2029 | H4: ACT-PRDI-NS-2957 | I4: Contribuir desde la Facultad de Ingeniería al cumplimiento de la meta PRDI “Armonizar 50 manuales de procedimientos de espacios universitarios a 2029”, con valores absolutos programados de 2027: 1, 2028: 1, 2029: 1, 2030: 1. Sustento en la Matriz de consistencia: «Actualizar 1 inventario de infraestructura en 2027 y ejecutar 1 programa anual de mantenimiento preventivo de 2028 a 2030.» «Registrar 1 acuerdo de mejora sobre el estado y uso de aulas y laboratorios en 2028 y revisar su cumplimiento anualmente hasta 2030.» | J4: Actividad | K4: Sin fórmula | L4: Armonizar manuales de procedimientos de espacios universitarios | N4: 1 | O4: 1 | P4: 1 | Q4: 1 | R4: =IF(M4="","",M4) | S4: =IF(N4="","",N4) -> 1 | T4: =IF(O4="","",O4) -> 1 | U4: =IF(P4="","",P4) -> 1 | V4: =IF(Q4="","",Q4) -> 1 | W4: Anual | X4: Subdirección Administrativa

Sheet 12 Fortalecimiento tecnológico
A1: N.P. | B1: Clave Objetivo General | C1: Objetivo General | D1: Clave Objetivo Específico | E1: Objetivo Específico | F1: No. de meta en el PRDI | G1: Meta PRDI | H1: Clave de la meta | I1: Meta del espacio académico | J1: Actividad/Indicador | K1: Método de cálculo | L1: Nombre de las variables | M1: Valor de las variables | R1: Valor de los indicadores | W1: Medición (anual o acumulada) | X1: Área responsable
M2: Ref. 2026 | N2: 2027 | O2: 2028 | P2: 2029 | Q2: 2030 | R2: Ref. 2026 | S2: 2027 | T2: 2028 | U2: 2029 | V2: 2030
A3: 1 | B3: PRDI25-29-Obj-46 | C3: Fortalecer la infraestructura tecnológica de la Universidad mediante la actualización de recursos, cultura digital, modernización de procesos y seguridad de la información para mejorar la gestión académica, administrativa y de investigación. | D3: PRDI25-29-Obj-101 | E3: PRDI25-29-Obj-101 -Fortalecer la cultura digital de la comunidad universitaria para mejorar sus habilidades tecnológicas y promover un uso efectivo de tic. | F3: 7 | G3: Desarrollar 160 guías de estudio independiente (GEI) al año | H3: ACT-PRDI-NS-2968 | I3: Contribuir desde la Facultad de Ingeniería al cumplimiento de la meta PRDI “Desarrollar 160 guías de estudio independiente (GEI) al año”, con valores absolutos programados de 2027: 3, 2028: 3, 2029: 3, 2030: 3. Sustento en la Matriz de consistencia: «Realizar 1 revisión documentada de la disponibilidad y obsolescencia tecnológica en 2027 y actualizarla una vez al año de 2028 a 2030.» | J3: Actividad | K3: Sin fórmula | L3: Desarrollar guías de estudio independiente (GEI) | N3: 3 | O3: 3 | P3: 3 | Q3: 3 | R3: =IF(M3="","",M3) | S3: =IF(N3="","",N3) -> 3 | T3: =IF(O3="","",O3) -> 3 | U3: =IF(P3="","",P3) -> 3 | V3: =IF(Q3="","",Q3) -> 3 | W3: Anual | X3: Departamento de Tecnologías de la Información
A4: 2 | B4: PRDI25-29-Obj-46 | C4: Fortalecer la infraestructura tecnológica de la Universidad mediante la actualización de recursos, cultura digital, modernización de procesos y seguridad de la información para mejorar la gestión académica, administrativa y de investigación. | D4: PRDI25-29-Obj-103 | E4: PRDI25-29-Obj-103 -Garantizar la operación continua y eficiente de la infraestructura tecnológica institucional para proporcionar la disponibilidad y funcionalidad de los equipos y sistemas en los espacios académicos. | F4: 10 | G4: Contar con 100% de los espacios académicos con mantenimiento preventivo a equipos de salas de cómputo, anualmente | H4: ACT-PRDI-NS-3242 | I4: Contribuir desde la Facultad de Ingeniería al cumplimiento de la meta PRDI “Contar con 100% de los espacios académicos con mantenimiento preventivo a equipos de salas de cómputo, anualmente”, con valores absolutos programados de 2027: 1, 2028: 1, 2029: 1, 2030: 1. Sustento en la Matriz de consistencia: «Levantar 1 diagnóstico tecnológico en 2027 y actualizar 1 cartera priorizada de mejoras cada año de 2028 a 2030.» «Registrar 1 acuerdo de mejora sobre la disponibilidad y obsolescencia tecnológica en 2028 y revisar su cumplimiento anualmente hasta 2030.» | J4: Actividad | K4: Sin fórmula | L4: Dar mantenimiento preventivo a equipos de salas de cómputo | N4: 1 | O4: 1 | P4: 1 | Q4: 1 | R4: =IF(M4="","",M4) | S4: =IF(N4="","",N4) -> 1 | T4: =IF(O4="","",O4) -> 1 | U4: =IF(P4="","",P4) -> 1 | V4: =IF(Q4="","",Q4) -> 1 | W4: Anual | X4: Departamento de Tecnologías de la Información

Sheet 13 Gobernanza
A1: N.P. | B1: Clave Objetivo General | C1: Objetivo General | D1: Clave Objetivo Específico | E1: Objetivo Específico | F1: No. de meta en el PRDI | G1: Meta PRDI | H1: Clave de la meta | I1: Meta del espacio académico | J1: Actividad/Indicador | K1: Método de cálculo | L1: Nombre de las variables | M1: Valor de las variables | R1: Valor de los indicadores | W1: Medición (anual o acumulada) | X1: Área responsable
M2: Ref. 2026 | N2: 2027 | O2: 2028 | P2: 2029 | Q2: 2030 | R2: Ref. 2026 | S2: 2027 | T2: 2028 | U2: 2029 | V2: 2030
A3: 1 | B3: PRDI25-29-Obj-47 | C3: Consolidar el diálogo, la participación y transparencia en la vida institucional, mediante la gestión colaborativa, corresponsable y cercana para incrementar el sentido de pertenencia, construyendo la memoria colectiva y la historia institucional, articular la expresión artística y cultural, la seguridad y el deporte en favor de la comunidad universitaria. | D3: PRDI25-29-Obj-104 | E3: Fortalecer la autoprotección y los protocolos de reacción para salvaguardar la seguridad de la comunidad universitaria. | F3: 8 | G3: Realizar anualmente 1 campaña de protección universitaria en materia de autoprotección y reacción ante emergencias para la comunidad universitaria de nivel superior | H3: ACT-PRDI-NS-2980 | I3: Contribuir desde la Facultad de Ingeniería al cumplimiento de la meta PRDI “Realizar anualmente 1 campaña de protección universitaria en materia de autoprotección y reacción ante emergencias para la comunidad universitaria de nivel superior”, con valores absolutos programados de 2027: 1, 2028: 1, 2029: 1, 2030: 1. | J3: Actividad | K3: Sin fórmula | L3: Realizar campañas de protección universitaria en materia de autoprotección y reacción ante emergencias para la comunidad universitaria de nivel superior | N3: 1 | O3: 1 | P3: 1 | Q3: 1 | R3: =IF(M3="","",M3) | S3: =IF(N3="","",N3) -> 1 | T3: =IF(O3="","",O3) -> 1 | U3: =IF(P3="","",P3) -> 1 | V3: =IF(Q3="","",Q3) -> 1 | W3: Anual | X3: Dirección y órganos colegiados
A4: 2 | B4: PRDI25-29-Obj-47 | C4: Consolidar el diálogo, la participación y transparencia en la vida institucional, mediante la gestión colaborativa, corresponsable y cercana para incrementar el sentido de pertenencia, construyendo la memoria colectiva y la historia institucional, articular la expresión artística y cultural, la seguridad y el deporte en favor de la comunidad universitaria. | D4: PRDI25-29-Obj-104 | E4: Fortalecer la autoprotección y los protocolos de reacción para salvaguardar la seguridad de la comunidad universitaria. | F4: 10 | G4: Realizar anualmente 1 simulacro de acuerdo con la convocatoria nacional | H4: ACT-PRDI-NS-2982 | I4: Contribuir desde la Facultad de Ingeniería al cumplimiento de la meta PRDI “Realizar anualmente 1 simulacro de acuerdo con la convocatoria nacional”, con valores absolutos programados de 2027: 1, 2028: 1, 2029: 1, 2030: 1. | J4: Actividad | K4: Sin fórmula | L4: Realizar simulacro de acuerdo con la convocatoria nacional | N4: 1 | O4: 1 | P4: 1 | Q4: 1 | R4: =IF(M4="","",M4) | S4: =IF(N4="","",N4) -> 1 | T4: =IF(O4="","",O4) -> 1 | U4: =IF(P4="","",P4) -> 1 | V4: =IF(Q4="","",Q4) -> 1 | W4: Anual | X4: Dirección y órganos colegiados
A5: 3 | B5: PRDI25-29-Obj-47 | C5: Consolidar el diálogo, la participación y transparencia en la vida institucional, mediante la gestión colaborativa, corresponsable y cercana para incrementar el sentido de pertenencia, construyendo la memoria colectiva y la historia institucional, articular la expresión artística y cultural, la seguridad y el deporte en favor de la comunidad universitaria. | D5: PRDI25-29-Obj-105 | E5: Capacitar a elementos del personal de Seguridad y Protección Universitaria en materia de perspectiva de género y atención prioritaria a grupos vulnerables para garantizar una atención oportuna. | F5: 11 | G5: Efectuar anualmente 1 campaña del protocolo de atención integral a víctimas en todas las áreas universitarias | H5: ACT-PRDI-NS-2748 | I5: Contribuir desde la Facultad de Ingeniería al cumplimiento de la meta PRDI “Efectuar anualmente 1 campaña del protocolo de atención integral a víctimas en todas las áreas universitarias”, con valores absolutos programados de 2027: 1, 2028: 1, 2029: 1, 2030: 1. | J5: Actividad | K5: Sin fórmula | L5: Efectuar campañas del protocolo de atención integral a víctimas en todas las áreas universitarias | N5: 1 | O5: 1 | P5: 1 | Q5: 1 | R5: =IF(M5="","",M5) | S5: =IF(N5="","",N5) -> 1 | T5: =IF(O5="","",O5) -> 1 | U5: =IF(P5="","",P5) -> 1 | V5: =IF(Q5="","",Q5) -> 1 | W5: Anual | X5: Dirección y órganos colegiados
A6: 4 | B6: PRDI25-29-Obj-47 | C6: Consolidar el diálogo, la participación y transparencia en la vida institucional, mediante la gestión colaborativa, corresponsable y cercana para incrementar el sentido de pertenencia, construyendo la memoria colectiva y la historia institucional, articular la expresión artística y cultural, la seguridad y el deporte en favor de la comunidad universitaria. | D6: PRDI25-29-Obj-105 | E6: Capacitar a elementos del personal de Seguridad y Protección Universitaria en materia de perspectiva de género y atención prioritaria a grupos vulnerables para garantizar una atención oportuna. | F6: 12 | G6: Difundir anualmente 1 campaña de los Protocolos de Seguridad y Protección Civil | H6: ACT-PRDI-NS-2983 | I6: Contribuir desde la Facultad de Ingeniería al cumplimiento de la meta PRDI “Difundir anualmente 1 campaña de los Protocolos de Seguridad y Protección Civil”, con valores absolutos programados de 2027: 1, 2028: 1, 2029: 1, 2030: 1. | J6: Actividad | K6: Sin fórmula | L6: Difundir la campaña de los Protocolos de Seguridad y Protección Civil | N6: 1 | O6: 1 | P6: 1 | Q6: 1 | R6: =IF(M6="","",M6) | S6: =IF(N6="","",N6) -> 1 | T6: =IF(O6="","",O6) -> 1 | U6: =IF(P6="","",P6) -> 1 | V6: =IF(Q6="","",Q6) -> 1 | W6: Anual | X6: Dirección y órganos colegiados
A7: 5 | B7: PRDI25-29-Obj-47 | C7: Consolidar el diálogo, la participación y transparencia en la vida institucional, mediante la gestión colaborativa, corresponsable y cercana para incrementar el sentido de pertenencia, construyendo la memoria colectiva y la historia institucional, articular la expresión artística y cultural, la seguridad y el deporte en favor de la comunidad universitaria. | D7: PRDI25-29-Obj-105 | E7: Capacitar a elementos del personal de Seguridad y Protección Universitaria en materia de perspectiva de género y atención prioritaria a grupos vulnerables para garantizar una atención oportuna. | F7: 13 | G7: Realizar 1 curso anual dirigido al personal de Protección Universitaria sobre Derechos Humanos y perspectiva de Género | H7: ACT-PRDI-NS-2984 | I7: Contribuir desde la Facultad de Ingeniería al cumplimiento de la meta PRDI “Realizar 1 curso anual dirigido al personal de Protección Universitaria sobre Derechos Humanos y perspectiva de Género”, con valores absolutos programados de 2027: 1, 2028: 1, 2029: 1, 2030: 1. | J7: Actividad | K7: Sin fórmula | L7: Realizar cursos dirigidos al personal de Protección Universitaria sobre Derechos Humanos y perspectiva de Género | N7: 1 | O7: 1 | P7: 1 | Q7: 1 | R7: =IF(M7="","",M7) | S7: =IF(N7="","",N7) -> 1 | T7: =IF(O7="","",O7) -> 1 | U7: =IF(P7="","",P7) -> 1 | V7: =IF(Q7="","",Q7) -> 1 | W7: Anual | X7: Dirección y órganos colegiados
A8: 6 | B8: PRDI25-29-Obj-47 | C8: Consolidar el diálogo, la participación y transparencia en la vida institucional, mediante la gestión colaborativa, corresponsable y cercana para incrementar el sentido de pertenencia, construyendo la memoria colectiva y la historia institucional, articular la expresión artística y cultural, la seguridad y el deporte en favor de la comunidad universitaria. | D8: PRDI25-29-Obj-108 | E8: Preservar entre las y los universitarios una pertenencia universitaria fortalecida, así como la valoración y difusión de contenidos promocionales para consolidar productos editoriales y publicaciones sobre la historia y el acontecer universitario, para impulsar el orgullo de pertenencia. | F8: 20 | G8: Atender anualmente a 15 000 asistentes a conferencias, foros y charlas, relacionados con la pertenencia universitaria | H8: ACT-PRDI-NS-2749 | I8: Contribuir desde la Facultad de Ingeniería al cumplimiento de la meta PRDI “Atender anualmente a 15 000 asistentes a conferencias, foros y charlas, relacionados con la pertenencia universitaria”, con valores absolutos programados de 2027: 273, 2028: 273, 2029: 273, 2030: 273. Sustento en la Matriz de consistencia: «Realizar 1 reunión y 1 encuesta a representantes estudiantiles, docentes y administrativos cada año de 2028 a 2030 y documentar los ajustes derivados.» | J8: Actividad | K8: Sin fórmula | L8: Atender anualmente a asistentes a conferencias, foros y charlas, relacionados con la pertenencia universitaria | N8: 273 | O8: 273 | P8: 273 | Q8: 273 | R8: =IF(M8="","",M8) | S8: =IF(N8="","",N8) -> 273 | T8: =IF(O8="","",O8) -> 273 | U8: =IF(P8="","",P8) -> 273 | V8: =IF(Q8="","",Q8) -> 273 | W8: Anual | X8: Dirección y órganos colegiados
A9: 7 | B9: PRDI25-29-Obj-47 | C9: Consolidar el diálogo, la participación y transparencia en la vida institucional, mediante la gestión colaborativa, corresponsable y cercana para incrementar el sentido de pertenencia, construyendo la memoria colectiva y la historia institucional, articular la expresión artística y cultural, la seguridad y el deporte en favor de la comunidad universitaria. | D9: PRDI25-29-Obj-108 | E9: Preservar entre las y los universitarios una pertenencia universitaria fortalecida, así como la valoración y difusión de contenidos promocionales para consolidar productos editoriales y publicaciones sobre la historia y el acontecer universitario, para impulsar el orgullo de pertenencia. | F9: 22 | G9: Contar anualmente con 8 500 asistentes a visitas guiadas | H9: ACT-PRDI-NS-2992 | I9: Contribuir desde la Facultad de Ingeniería al cumplimiento de la meta PRDI “Contar anualmente con 8 500 asistentes a visitas guiadas”, con valores absolutos programados de 2027: 155, 2028: 155, 2029: 155, 2030: 155. Sustento en la Matriz de consistencia: «Realizar 1 revisión documentada de el cumplimiento de acuerdos colegiados en 2027 y actualizarla una vez al año de 2028 a 2030.» | J9: Actividad | K9: Sin fórmula | L9: Contar con asistentes a visitas guiadas | N9: 155 | O9: 155 | P9: 155 | Q9: 155 | R9: =IF(M9="","",M9) | S9: =IF(N9="","",N9) -> 155 | T9: =IF(O9="","",O9) -> 155 | U9: =IF(P9="","",P9) -> 155 | V9: =IF(Q9="","",Q9) -> 155 | W9: Anual | X9: Dirección y órganos colegiados
A10: 8 | B10: PRDI25-29-Obj-47 | C10: Consolidar el diálogo, la participación y transparencia en la vida institucional, mediante la gestión colaborativa, corresponsable y cercana para incrementar el sentido de pertenencia, construyendo la memoria colectiva y la historia institucional, articular la expresión artística y cultural, la seguridad y el deporte en favor de la comunidad universitaria. | D10: PRDI25-29-Obj-108 | E10: Preservar entre las y los universitarios una pertenencia universitaria fortalecida, así como la valoración y difusión de contenidos promocionales para consolidar productos editoriales y publicaciones sobre la historia y el acontecer universitario, para impulsar el orgullo de pertenencia. | F10: 30 | G10: Lograr que 100% de los espacios universitarios con cronista cuente con una nueva crónica sobre la historia de su espacio, al final de la administración | H10: ACT-PRDI-NS-3243 | I10: Contribuir desde la Facultad de Ingeniería al cumplimiento de la meta PRDI “Lograr que 100% de los espacios universitarios con cronista cuente con una nueva crónica sobre la historia de su espacio, al final de la administración”, con valores absolutos programados de 2027: 0, 2028: 0, 2029: 1, 2030: 0. Sustento en la Matriz de consistencia: «Crear 1 registro de acuerdos colegiados en 2027 y publicar 1 balance de seguimiento cada año de 2028 a 2030.» | J10: Actividad | K10: Sin fórmula | L10: Contar con una nueva crónica sobre la historia del espacio universitario | N10: 0 | O10: 0 | P10: 1 | Q10: 0 | R10: =IF(M10="","",M10) | S10: =IF(N10="","",N10) -> 0 | T10: =IF(O10="","",O10) -> 0 | U10: =IF(P10="","",P10) -> 1 | V10: =IF(Q10="","",Q10) -> 0 | W10: Anual | X10: Dirección y órganos colegiados

Sheet 16 Manejo recursos universitari
A1: N.P. | B1: Clave Objetivo General | C1: Objetivo General | D1: Clave Objetivo Específico | E1: Objetivo Específico | F1: No. de meta en el PRDI | G1: Meta PRDI | H1: Clave de la meta | I1: Meta del espacio académico | J1: Actividad/Indicador | K1: Método de cálculo | L1: Nombre de las variables | M1: Valor de las variables | R1: Valor de los indicadores | W1: Medición (anual o acumulada) | X1: Área responsable
M2: Ref. 2026 | N2: 2027 | O2: 2028 | P2: 2029 | Q2: 2030 | R2: Ref. 2026 | S2: 2027 | T2: 2028 | U2: 2029 | V2: 2030
A3: 1 | B3: PRDI25-29-Obj-50 | C3: Lograr que las finanzas universitarias se administren con integridad, transparencia y eficiencia, mediante la implementación de un presupuesto responsable que contribuya a la sostenibilidad institucional bajo los principios de austeridad, equidad y visión estratégica. | D3: PRDI25-29-Obj-117 | E3: Potenciar de manera eficiente, transparente y sostenible la generación de recursos extraordinarios alternos para que contribuyan a fortalecer las funciones sustantivas y adjetivas de la Universidad. | F3: 5 | G3: Implementar anualmente 1 programa institucional que fortalezca la generación de ingresos extraordinarios | H3: ACT-PRDI-NS-2763 | I3: Contribuir desde la Facultad de Ingeniería al cumplimiento de la meta PRDI “Implementar anualmente 1 programa institucional que fortalezca la generación de ingresos extraordinarios”, con valores absolutos programados de 2027: 1, 2028: 1, 2029: 1, 2030: 1. Sustento en la Matriz de consistencia: «Integrar 1 registro anual de programación y ejercicio de recursos entre 2027 y 2030.» «Realizar 1 revisión documentada de la relación entre asignaciones y resultados en 2027 y actualizarla una vez al año de 2028 a 2030.» «Registrar 1 acuerdo de mejora sobre la relación entre asignaciones y resultados en 2028 y revisar su cumplimiento anualmente hasta 2030.» | J3: Actividad | K3: Sin fórmula | L3: Implementar un programa institucional que fortalezca la generación de ingresos extraordinarios | N3: 1 | O3: 1 | P3: 1 | Q3: 1 | R3: =IF(M3="","",M3) | S3: =IF(N3="","",N3) -> 1 | T3: =IF(O3="","",O3) -> 1 | U3: =IF(P3="","",P3) -> 1 | V3: =IF(Q3="","",Q3) -> 1 | W3: Anual | X3: Subdirección Administrativa

Sheet 18 Reconocimiento de la diversi
A1: N.P. | B1: Clave Objetivo General | C1: Objetivo General | D1: Clave Objetivo Específico | E1: Objetivo Específico | F1: No. de meta en el PRDI | G1: Meta PRDI | H1: Clave de la meta | I1: Meta del espacio académico | J1: Actividad/Indicador | K1: Método de cálculo | L1: Nombre de las variables | M1: Valor de las variables | R1: Valor de los indicadores | W1: Medición (anual o acumulada) | X1: Área responsable
M2: Ref. 2026 | N2: 2027 | O2: 2028 | P2: 2029 | Q2: 2030 | R2: Ref. 2026 | S2: 2027 | T2: 2028 | U2: 2029 | V2: 2030
A3: 1 | B3: PRDI25-29-Obj-52 | C3: Fortalecer una cultura universitaria incluyente, equitativa y libre de discriminación mediante la implementación de acciones integrales de reconocimiento, atención y prevención, que incorporen la perspectiva de diversidad, género y cuidados. | D3: PRDI2025-2029-Obj-74 | E3: Fortalecer la igualdad y la inclusión entre la comunidad universitaria para reconocer y respetar la diversidad social. | F3: 1 | G3: Sensibilizar durante la administración a 40% de estudiantado de estudios profesionales en temas de inclusión a grupos históricamente vulnerados | H3: IND-PRDI-431 | I3: Mejorar o mantener de forma conservadora en la Facultad de Ingeniería el indicador IND-PRDI-431, con la trayectoria 2027: 38.01%, 2028: 38.68%, 2029: 39.32%, 2030: 40.01%, sustentada en referencia PRDI; no existe serie histórica directamente comparable para la variable. Sustento en la Matriz de consistencia: «Realizar 1 reunión y 1 encuesta a estudiantes y profesorado de cada licenciatura cada año de 2028 a 2030 y documentar los ajustes derivados.» | J3: Indicador | K3: (Número de estudiantes sensibilizados / Total del estudiantado)*100 | L3: Número de estudiantes sensibilizados | N3: 1136 | O3: 1162 | P3: 1187 | Q3: 1214 | R3: =IF(M4,M3/M4*100,"") | S3: =IF(N4,N3/N4*100,"") -> 38.006022 | T3: =IF(O4,O3/O4*100,"") -> 38.681758 | U3: =IF(P4,P3/P4*100,"") -> 39.317655 | V3: =IF(Q4,Q3/Q4*100,"") -> 40.013184 | W3: Anual | X3: Unidad de Igualdad de Género
L4: Total del estudiantado | N4: 2989 | O4: 3004 | P4: 3019 | Q4: 3034
A5: 2 | B5: PRDI25-29-Obj-52 | C5: Fortalecer una cultura universitaria incluyente, equitativa y libre de discriminación mediante la implementación de acciones integrales de reconocimiento, atención y prevención, que incorporen la perspectiva de diversidad, género y cuidados. | D5: PRDI25-29-Obj-122 | E5: Mejorar los mecanismos y las prácticas institucionales para generar entornos libres de discriminación. | F5: 3 | G5: Difundir 3 materiales de divulgación al año (guías, cartillas y manuales) orientados a promover el respeto y reconocimiento de las identidades entre la comunidad universitaria | H5: ACT-PRDI-NS-3075 | I5: Contribuir desde la Facultad de Ingeniería al cumplimiento de la meta PRDI “Difundir 3 materiales de divulgación al año (guías, cartillas y manuales) orientados a promover el respeto y reconocimiento de las identidades entre la comunidad universitaria”, con valores absolutos programados de 2027: 1, 2028: 1, 2029: 1, 2030: 1. | J5: Actividad | K5: Sin fórmula | L5: Difundir materiales de divulgación (guías, cartillas y manuales) orientados a promover el respeto y reconocimiento de las identidades entre la comunidad universitaria | N5: 1 | O5: 1 | P5: 1 | Q5: 1 | R5: =IF(M5="","",M5) | S5: =IF(N5="","",N5) -> 1 | T5: =IF(O5="","",O5) -> 1 | U5: =IF(P5="","",P5) -> 1 | V5: =IF(Q5="","",Q5) -> 1 | W5: Anual | X5: Unidad de Igualdad de Género
A6: 3 | B6: PRDI25-29-Obj-52 | C6: Fortalecer una cultura universitaria incluyente, equitativa y libre de discriminación mediante la implementación de acciones integrales de reconocimiento, atención y prevención, que incorporen la perspectiva de diversidad, género y cuidados. | D6: PRDI25-29-Obj-124 | E6: Impulsar programas de apoyo dirigidos a grupos en situación de vulnerabilidad, para fomentar su inclusión, desarrollo académico y laboral dentro de la Universidad. | F6: 6 | G6: Incrementar a 4.90% los proyectos de investigación en materia de cultura de paz y estudios de género respecto al total de proyectos de investigación, para 2029 | H6: IND-PRDI-407 | I6: Mejorar o mantener de forma conservadora en la Facultad de Ingeniería el indicador IND-PRDI-407, con la trayectoria 2027: 5%, 2028: 5%, 2029: 5%, 2030: 5%, sustentada en referencia PRDI; no existe serie histórica directamente comparable para la variable. | J6: Indicador | K6: (Proyectos de investigación en materia de cultura de paz y estudios de género/Total de proyectos de investigación)*100 | L6: Proyectos de investigación en materia de cultura de paz y estudios de género | N6: 1 | O6: 1 | P6: 1 | Q6: 1 | R6: =IF(M7,M6/M7*100,"") | S6: =IF(N7,N6/N7*100,"") -> 5 | T6: =IF(O7,O6/O7*100,"") -> 5 | U6: =IF(P7,P6/P7*100,"") -> 5 | V6: =IF(Q7,Q6/Q7*100,"") -> 5 | W6: Anual | X6: Unidad de Igualdad de Género
L7: Total de proyectos de investigación | N7: 20 | O7: 20 | P7: 20 | Q7: 20
A8: 4 | B8: PRDI25-29-Obj-52 | C8: Fortalecer una cultura universitaria incluyente, equitativa y libre de discriminación mediante la implementación de acciones integrales de reconocimiento, atención y prevención, que incorporen la perspectiva de diversidad, género y cuidados. | D8: PRDI25-29-Obj-124 | E8: Impulsar programas de apoyo dirigidos a grupos en situación de vulnerabilidad, para fomentar su inclusión, desarrollo académico y laboral dentro de la Universidad. | F8: 7 | G8: Implementar 2 eventos socioculturales al año con temáticas de inclusión y vulnerabilidad | H8: ACT-PRDI-NS-3081 | I8: Contribuir desde la Facultad de Ingeniería al cumplimiento de la meta PRDI “Implementar 2 eventos socioculturales al año con temáticas de inclusión y vulnerabilidad”, con valores absolutos programados de 2027: 1, 2028: 1, 2029: 1, 2030: 1. | J8: Actividad | K8: Sin fórmula | L8: Implementar eventos socioculturales con temáticas de inclusión y vulnerabilidad | N8: 1 | O8: 1 | P8: 1 | Q8: 1 | R8: =IF(M8="","",M8) | S8: =IF(N8="","",N8) -> 1 | T8: =IF(O8="","",O8) -> 1 | U8: =IF(P8="","",P8) -> 1 | V8: =IF(Q8="","",Q8) -> 1 | W8: Anual | X8: Unidad de Igualdad de Género
A9: 5 | B9: PRDI25-29-Obj-52 | C9: Fortalecer una cultura universitaria incluyente, equitativa y libre de discriminación mediante la implementación de acciones integrales de reconocimiento, atención y prevención, que incorporen la perspectiva de diversidad, género y cuidados. | D9: PRDI25-29-Obj-124 | E9: Impulsar programas de apoyo dirigidos a grupos en situación de vulnerabilidad, para fomentar su inclusión, desarrollo académico y laboral dentro de la Universidad. | F9: 13 | G9: Realizar 1 actividad anual sobre equidad social y de género | H9: ACT-PRDI-NS-3087 | I9: Contribuir desde la Facultad de Ingeniería al cumplimiento de la meta PRDI “Realizar 1 actividad anual sobre equidad social y de género”, con valores absolutos programados de 2027: 1, 2028: 1, 2029: 1, 2030: 1. Sustento en la Matriz de consistencia: «Publicar 1 diagnóstico anual de brechas de participación y apoyos por programa entre 2027 y 2030.» | J9: Actividad | K9: Sin fórmula | L9: Realizar actividades sobre equidad social y de género | N9: 1 | O9: 1 | P9: 1 | Q9: 1 | R9: =IF(M9="","",M9) | S9: =IF(N9="","",N9) -> 1 | T9: =IF(O9="","",O9) -> 1 | U9: =IF(P9="","",P9) -> 1 | V9: =IF(Q9="","",Q9) -> 1 | W9: Anual | X9: Unidad de Igualdad de Género
A10: 6 | B10: PRDI25-29-Obj-52 | C10: Fortalecer una cultura universitaria incluyente, equitativa y libre de discriminación mediante la implementación de acciones integrales de reconocimiento, atención y prevención, que incorporen la perspectiva de diversidad, género y cuidados. | D10: PRDI25-29-Obj-125 | E10: Incorporar la perspectiva de cuidados y corresponsabilidad en los procesos institucionales para garantizar entornos seguros en los espacios universitarios. | F10: 16 | G10: Implementar 4 programas de sensibilización al año en temas de corresponsabilidad y autocuidado | H10: ACT-PRDI-NS-2767 | I10: Contribuir desde la Facultad de Ingeniería al cumplimiento de la meta PRDI “Implementar 4 programas de sensibilización al año en temas de corresponsabilidad y autocuidado”, con valores absolutos programados de 2027: 1, 2028: 1, 2029: 1, 2030: 1. | J10: Actividad | K10: Sin fórmula | L10: Implementar programas de sensibilización en temas de corresponsabilidad y autocuidado | N10: 1 | O10: 1 | P10: 1 | Q10: 1 | R10: =IF(M10="","",M10) | S10: =IF(N10="","",N10) -> 1 | T10: =IF(O10="","",O10) -> 1 | U10: =IF(P10="","",P10) -> 1 | V10: =IF(Q10="","",Q10) -> 1 | W10: Anual | X10: Unidad de Igualdad de Género
A11: 7 | B11: PRDI25-29-Obj-52 | C11: Fortalecer una cultura universitaria incluyente, equitativa y libre de discriminación mediante la implementación de acciones integrales de reconocimiento, atención y prevención, que incorporen la perspectiva de diversidad, género y cuidados. | D11: PRDI25-29-Obj-125 | E11: Incorporar la perspectiva de cuidados y corresponsabilidad en los procesos institucionales para garantizar entornos seguros en los espacios universitarios. | F11: 24 | G11: Realizar anualmente 10 talleres articulados que fortalezcan el Programa Universitario de Bienestar Integral | H11: ACT-PRDI-NS-3097 | I11: Contribuir desde la Facultad de Ingeniería al cumplimiento de la meta PRDI “Realizar anualmente 10 talleres articulados que fortalezcan el Programa Universitario de Bienestar Integral”, con valores absolutos programados de 2027: 1, 2028: 1, 2029: 1, 2030: 1. | J11: Actividad | K11: Sin fórmula | L11: Realizar talleres articulados que fortalezcan el Programa Universitario de Bienestar Integral | N11: 1 | O11: 1 | P11: 1 | Q11: 1 | R11: =IF(M11="","",M11) | S11: =IF(N11="","",N11) -> 1 | T11: =IF(O11="","",O11) -> 1 | U11: =IF(P11="","",P11) -> 1 | V11: =IF(Q11="","",Q11) -> 1 | W11: Anual | X11: Unidad de Igualdad de Género
A12: 8 | B12: PRDI25-29-Obj-52 | C12: Fortalecer una cultura universitaria incluyente, equitativa y libre de discriminación mediante la implementación de acciones integrales de reconocimiento, atención y prevención, que incorporen la perspectiva de diversidad, género y cuidados. | D12: PRDI25-29-Obj-125 | E12: Incorporar la perspectiva de cuidados y corresponsabilidad en los procesos institucionales para garantizar entornos seguros en los espacios universitarios. | F12: 25 | G12: Certificar anualmente a 10% del personal académico, administrativo de confianza y directivo en materia de bienestar integral | H12: ACT-POA-NS-2650 | I12: Contribuir desde la Facultad de Ingeniería al cumplimiento de la meta PRDI “Certificar anualmente a 10% del personal académico, administrativo de confianza y directivo en materia de bienestar integral”, con valores absolutos programados de 2027: 1, 2028: 1, 2029: 1, 2030: 1. Sustento en la Matriz de consistencia: «Realizar 1 revisión documentada de las brechas de acceso y permanencia en 2027 y actualizarla una vez al año de 2028 a 2030.» | J12: Actividad | K12: Sin fórmula | L12: Capacitar anualmente al personal académico, administrativo de confianza y directivo de nivel superior en materia de bienestar integral. | N12: 1 | O12: 1 | P12: 1 | Q12: 1 | R12: =IF(M12="","",M12) | S12: =IF(N12="","",N12) -> 1 | T12: =IF(O12="","",O12) -> 1 | U12: =IF(P12="","",P12) -> 1 | V12: =IF(Q12="","",Q12) -> 1 | W12: Anual | X12: Unidad de Igualdad de Género

Sheet 19 Constr cultura de paz 
A1: N.P. | B1: Clave Objetivo General | C1: Objetivo General | D1: Clave Objetivo Específico | E1: Objetivo Específico | F1: No. de meta en el PRDI | G1: Meta PRDI | H1: Clave de la meta | I1: Meta del espacio académico | J1: Actividad/Indicador | K1: Método de cálculo | L1: Nombre de las variables | M1: Valor de las variables | R1: Valor de los indicadores | W1: Medición (anual o acumulada) | X1: Área responsable
M2: Ref. 2026 | N2: 2027 | O2: 2028 | P2: 2029 | Q2: 2030 | R2: Ref. 2026 | S2: 2027 | T2: 2028 | U2: 2029 | V2: 2030
A3: 1 | B3: PRDI25-29-Obj-53 | C3: Promover la construcción de una cultura de paz en la comunidad universitaria, mediante estrategias educativas, participativas y de sensibilización que fortalezcan la convivencia armónica y el respeto a los derechos humanos. | D3: PRDI25-29-Obj-126 | E3: Generar capacidades individuales y colectivas para la gestión pacífica de los conflictos, la convivencia respetuosa y la prevención de situaciones de violencia entre la comunidad universitaria. | F3: 8 | G3: Certificar anualmente a 10.03% del personal académico, administrativo de confianza y directivo, en competencias básicas de mediación, gestión pacífica de conflictos y atención a las violencias | H3: ACT-POA-NS-2651 | I3: Contribuir desde la Facultad de Ingeniería al cumplimiento de la meta PRDI “Certificar anualmente a 10.03% del personal académico, administrativo de confianza y directivo, en competencias básicas de mediación, gestión pacífica de conflictos y atención a las violencias”, con valores absolutos programados de 2027: 6, 2028: 7, 2029: 7, 2030: 9. Sustento en la Matriz de consistencia: «Mantener al menos 5 acciones de capacitación registradas en cada medición anual de 2027 a 2030.» | J3: Actividad | K3: Sin fórmula | L3: Capacitar anualmente a personal académico, administrativo de confianza y directivo del nivel superior, en competencias básicas de mediación, gestión pacífica de conflictos y atención a las violencias | M3: 5 | N3: 6 | O3: 7 | P3: 7 | Q3: 9 | R3: =IF(M3="","",M3) -> 5 | S3: =IF(N3="","",N3) -> 6 | T3: =IF(O3="","",O3) -> 7 | U3: =IF(P3="","",P3) -> 7 | V3: =IF(Q3="","",Q3) -> 9 | W3: Anual | X3: Unidad de Igualdad de Género y Dirección
A4: 2 | B4: PRDI25-29-Obj-53 | C4: Promover la construcción de una cultura de paz en la comunidad universitaria, mediante estrategias educativas, participativas y de sensibilización que fortalezcan la convivencia armónica y el respeto a los derechos humanos. | D4: PRDI25-29-Obj-126 | E4: Generar capacidades individuales y colectivas para la gestión pacífica de los conflictos, la convivencia respetuosa y la prevención de situaciones de violencia entre la comunidad universitaria. | F4: 13 | G4: Involucrar a 400 estudiantes en actividades comunitarias, proyectos de intervención social y programas extracurriculares orientados a la construcción de paz durante la administración | H4: ACT-PRDI-NS-3188 | I4: Contribuir desde la Facultad de Ingeniería al cumplimiento de la meta PRDI “Involucrar a 400 estudiantes en actividades comunitarias, proyectos de intervención social y programas extracurriculares orientados a la construcción de paz durante la administración”, con valores absolutos programados de 2027: 2, 2028: 2, 2029: 2, 2030: 2. Sustento en la Matriz de consistencia: «Realizar 1 reunión y 1 encuesta a estudiantes, docentes y administrativos cada año de 2028 a 2030 y documentar los ajustes derivados.» | J4: Actividad | K4: Sin fórmula | L4: Involucrar a estudiantes en actividades comunitarias, proyectos de intervención social y programas extracurriculares orientados a la construcción de paz | N4: 2 | O4: 2 | P4: 2 | Q4: 2 | R4: =IF(M4="","",M4) | S4: =IF(N4="","",N4) -> 2 | T4: =IF(O4="","",O4) -> 2 | U4: =IF(P4="","",P4) -> 2 | V4: =IF(Q4="","",Q4) -> 2 | W4: Anual | X4: Unidad de Igualdad de Género y Dirección
A5: 3 | B5: PRDI25-29-Obj-53 | C5: Promover la construcción de una cultura de paz en la comunidad universitaria, mediante estrategias educativas, participativas y de sensibilización que fortalezcan la convivencia armónica y el respeto a los derechos humanos. | D5: PRDI25-29-Obj-127 | E5: Fomentar una cultura institucional de respeto e igualdad para prevenir conductas violentas dentro de los espacios universitarios. | F5: 14 | G5: Lograr que 100% de los espacios académicos, realicen actividades culturales con temáticas de igualdad de género y cultura de paz, durante la administración | H5: ACT-PRDI-NS-3244 | I5: Contribuir desde la Facultad de Ingeniería al cumplimiento de la meta PRDI “Lograr que 100% de los espacios académicos, realicen actividades culturales con temáticas de igualdad de género y cultura de paz, durante la administración”, con valores absolutos programados de 2027: 1, 2028: 0, 2029: 0, 2030: 0. | J5: Actividad | K5: Sin fórmula | L5: Realizar actividades culturales con temáticas de igualdad de género y cultura de paz | N5: 1 | O5: 0 | P5: 0 | Q5: 0 | R5: =IF(M5="","",M5) | S5: =IF(N5="","",N5) -> 1 | T5: =IF(O5="","",O5) -> 0 | U5: =IF(P5="","",P5) -> 0 | V5: =IF(Q5="","",Q5) -> 0 | W5: Anual | X5: Unidad de Igualdad de Género y Dirección
A6: 4 | B6: PRDI25-29-Obj-53 | C6: Promover la construcción de una cultura de paz en la comunidad universitaria, mediante estrategias educativas, participativas y de sensibilización que fortalezcan la convivencia armónica y el respeto a los derechos humanos. | D6: PRDI25-29-Obj-127 | E6: Fomentar una cultura institucional de respeto e igualdad para prevenir conductas violentas dentro de los espacios universitarios. | F6: 15 | G6: Realizar 2 campañas anuales para difundir los protocolos institucionales de atención y prevención de violencias a toda la comunidad universitaria | H6: ACT-PRDI-NS-3189 | I6: Contribuir desde la Facultad de Ingeniería al cumplimiento de la meta PRDI “Realizar 2 campañas anuales para difundir los protocolos institucionales de atención y prevención de violencias a toda la comunidad universitaria”, con valores absolutos programados de 2027: 1, 2028: 1, 2029: 1, 2030: 1. Sustento en la Matriz de consistencia: «Realizar 1 revisión documentada de las barreras para denunciar y recibir atención en 2027 y actualizarla una vez al año de 2028 a 2030.» | J6: Actividad | K6: Sin fórmula | L6: Realizar campañas para difundir los protocolos institucionales de atención y prevención de violencias a toda la comunidad universitaria | N6: 1 | O6: 1 | P6: 1 | Q6: 1 | R6: =IF(M6="","",M6) | S6: =IF(N6="","",N6) -> 1 | T6: =IF(O6="","",O6) -> 1 | U6: =IF(P6="","",P6) -> 1 | V6: =IF(Q6="","",Q6) -> 1 | W6: Anual | X6: Unidad de Igualdad de Género y Dirección
A7: 5 | B7: PRDI25-29-Obj-53 | C7: Promover la construcción de una cultura de paz en la comunidad universitaria, mediante estrategias educativas, participativas y de sensibilización que fortalezcan la convivencia armónica y el respeto a los derechos humanos. | D7: PRDI25-29-Obj-128 | E7: Evaluar el impacto de las acciones implementadas para medir los avances en la construcción de una cultura de paz y la transformación de las relaciones interpersonales e institucionales. | F7: 18 | G7: Lograr la participación de 40% de la comunidad universitaria en actividades y programas que promuevan la convivencia pacífica, la inclusión y el respeto, durante la administración | H7: IND-PRDI-420 | I7: Mejorar o mantener de forma conservadora en la Facultad de Ingeniería el indicador IND-PRDI-420, con la trayectoria 2027: 38.01%, 2028: 38.68%, 2029: 39.34%, 2030: 39.99%, sustentada en referencia PRDI; no existe serie histórica directamente comparable para la variable. | J7: Indicador | K7: (Número de participantes en actividades y programas que promuevan la convivencia pacífica, la inclusión y el respeto/Número de integrantes de la comunidad universitaria)*100 | L7: Número de participantes en actividades y programas que promuevan la convivencia pacífica, la inclusión y el respeto | N7: 1274 | O7: 1303 | P7: 1332 | Q7: 1361 | R7: =IF(M8,M7/M8*100,"") | S7: =IF(N8,N7/N8*100,"") -> 38.00716 | T7: =IF(O8,O7/O8*100,"") -> 38.676165 | U7: =IF(P8,P7/P8*100,"") -> 39.338452 | V7: =IF(Q8,Q7/Q8*100,"") -> 39.994123 | W7: Anual | X7: Unidad de Igualdad de Género y Dirección
L8: Número de integrantes de la comunidad universitaria | N8: 3352 | O8: 3369 | P8: 3386 | Q8: 3403
A9: 6 | B9: PRDI25-29-Obj-53 | C9: Promover la construcción de una cultura de paz en la comunidad universitaria, mediante estrategias educativas, participativas y de sensibilización que fortalezcan la convivencia armónica y el respeto a los derechos humanos. | D9: PRDI25-29-Obj-75 | E9: Fortalecer la educación para la paz, la no violencia y los derechos humanos para lograr la convivencia pacífica en los espacios universitarios. | F9: 3 | G9: Realizar 1 jornada anual sobre los 16 días de activismo con diversas actividades (conferencias, talleres, capacitaciones) presenciales y virtuales en los diversos espacios de la universidad | H9: ACT-PRDI-NS-2766 | I9: Contribuir desde la Facultad de Ingeniería al cumplimiento de la meta PRDI “Realizar 1 jornada anual sobre los 16 días de activismo con diversas actividades (conferencias, talleres, capacitaciones) presenciales y virtuales en los diversos espacios de la universidad”, con valores absolutos programados de 2027: 1, 2028: 1, 2029: 1, 2030: 1. | J9: Actividad | K9: Sin fórmula | L9: Realizar jornadas sobre los 16 días de activismo con diversas actividades (conferencias, talleres, capacitaciones) presenciales y virtuales en los diversos espacios de la universidad | N9: 1 | O9: 1 | P9: 1 | Q9: 1 | R9: =IF(M9="","",M9) | S9: =IF(N9="","",N9) -> 1 | T9: =IF(O9="","",O9) -> 1 | U9: =IF(P9="","",P9) -> 1 | V9: =IF(Q9="","",Q9) -> 1 | W9: Anual | X9: Unidad de Igualdad de Género y Dirección
A10: 7 | B10: PRDI25-29-Obj-53 | C10: Promover la construcción de una cultura de paz en la comunidad universitaria, mediante estrategias educativas, participativas y de sensibilización que fortalezcan la convivencia armónica y el respeto a los derechos humanos. | D10: PRDI25-29-Obj-75 | E10: Fortalecer la educación para la paz, la no violencia y los derechos humanos para lograr la convivencia pacífica en los espacios universitarios. | F10: 5 | G10: Publicar 30 contenidos anuales en las redes sociales oficiales sobre temas que promuevan la igualdad sustantiva, la prevención de las violencias, la inclusión, el cuidado y la cultura de paz | H10: ACT-PRDI-NS-3178 | I10: Contribuir desde la Facultad de Ingeniería al cumplimiento de la meta PRDI “Publicar 30 contenidos anuales en las redes sociales oficiales sobre temas que promuevan la igualdad sustantiva, la prevención de las violencias, la inclusión, el cuidado y la cultura de paz”, con valores absolutos programados de 2027: 1, 2028: 1, 2029: 1, 2030: 1. | J10: Actividad | K10: Sin fórmula | L10: Publicar contenidos en las redes sociales oficiales sobre temas que promuevan la igualdad sustantiva, la prevención de las violencias, la inclusión, el cuidado y la cultura de paz | N10: 1 | O10: 1 | P10: 1 | Q10: 1 | R10: =IF(M10="","",M10) | S10: =IF(N10="","",N10) -> 1 | T10: =IF(O10="","",O10) -> 1 | U10: =IF(P10="","",P10) -> 1 | V10: =IF(Q10="","",Q10) -> 1 | W10: Anual | X10: Unidad de Igualdad de Género y Dirección

Sheet 20 Retribución social 
A1: N.P. | B1: Clave Objetivo General | C1: Objetivo General | D1: Clave Objetivo Específico | E1: Objetivo Específico | F1: No. de meta en el PRDI | G1: Meta PRDI | H1: Clave de la meta | I1: Meta del espacio académico | J1: Actividad/Indicador | K1: Método de cálculo | L1: Nombre de las variables | M1: Valor de las variables | R1: Valor de los indicadores | W1: Medición (anual o acumulada) | X1: Área responsable
M2: Ref. 2026 | N2: 2027 | O2: 2028 | P2: 2029 | Q2: 2030 | R2: Ref. 2026 | S2: 2027 | T2: 2028 | U2: 2029 | V2: 2030
A3: 1 | B3: PRDI25-29-Obj-54 | C3: Fomentar la vinculación estratégica de la Universidad con los sectores social, productivo y gubernamental, para el desarrollo de proyectos inclusivos y sostenibles, que favorezcan el desarrollo humano y la salud; fomenten las competencias profesionales; promuevan la conciencia ética, motiven la responsabilidad social, el interés colectivo; y sean promotores del desarrollo tecnológico y la innovación. | D3: PRDI2025-2029-Obj-76 | E3: Fortalecer las competencias emprendedoras y empresariales de la comunidad universitaria y la sociedad en general, para la creación y consolidación de proyectos innovadores, sostenibles y de alto impacto que contribuyan al desarrollo regional. | F3: 2 | G3: Coordinar cada año 15 eventos de emprendimiento con los responsables del Programa Emprendedor de todos los espacios académicos | H3: ACT-PRDI-NS-3103 | I3: Contribuir desde la Facultad de Ingeniería al cumplimiento de la meta PRDI “Coordinar cada año 15 eventos de emprendimiento con los responsables del Programa Emprendedor de todos los espacios académicos”, con valores absolutos programados de 2027: 1, 2028: 1, 2029: 1, 2030: 1. | J3: Actividad | K3: Sin fórmula | L3: Coordinar eventos de emprendimiento con los responsables del Programa Emprendedor de todos los espacios académicos | N3: 1 | O3: 1 | P3: 1 | Q3: 1 | R3: =IF(M3="","",M3) | S3: =IF(N3="","",N3) -> 1 | T3: =IF(O3="","",O3) -> 1 | U3: =IF(P3="","",P3) -> 1 | V3: =IF(Q3="","",Q3) -> 1 | W3: Anual | X3: Coordinación de Extensión y Vinculación
A4: 2 | B4: PRDI25-29-Obj-54 | C4: Fomentar la vinculación estratégica de la Universidad con los sectores social, productivo y gubernamental, para el desarrollo de proyectos inclusivos y sostenibles, que favorezcan el desarrollo humano y la salud; fomenten las competencias profesionales; promuevan la conciencia ética, motiven la responsabilidad social, el interés colectivo; y sean promotores del desarrollo tecnológico y la innovación. | D4: PRDI2025-2029-Obj-76 | E4: Fortalecer las competencias emprendedoras y empresariales de la comunidad universitaria y la sociedad en general, para la creación y consolidación de proyectos innovadores, sostenibles y de alto impacto que contribuyan al desarrollo regional. | F4: 6 | G4: Realizar 8 pláticas o talleres al año para desarrollar proyectos de negocio, innovación y desarrollo tecnológico, dirigidos a la comunidad universitaria y abiertos a la sociedad en general | H4: ACT-PRDI-NS-3107 | I4: Contribuir desde la Facultad de Ingeniería al cumplimiento de la meta PRDI “Realizar 8 pláticas o talleres al año para desarrollar proyectos de negocio, innovación y desarrollo tecnológico, dirigidos a la comunidad universitaria y abiertos a la sociedad en general”, con valores absolutos programados de 2027: 1, 2028: 1, 2029: 1, 2030: 1. | J4: Actividad | K4: Sin fórmula | L4: Realizar pláticas o talleres para desarrollar proyectos de negocio, innovación y desarrollo tecnológico, dirigidos a la comunidad universitaria y abiertos a la sociedad en general | N4: 1 | O4: 1 | P4: 1 | Q4: 1 | R4: =IF(M4="","",M4) | S4: =IF(N4="","",N4) -> 1 | T4: =IF(O4="","",O4) -> 1 | U4: =IF(P4="","",P4) -> 1 | V4: =IF(Q4="","",Q4) -> 1 | W4: Anual | X4: Coordinación de Extensión y Vinculación
A5: 3 | B5: PRDI25-29-Obj-54 | C5: Fomentar la vinculación estratégica de la Universidad con los sectores social, productivo y gubernamental, para el desarrollo de proyectos inclusivos y sostenibles, que favorezcan el desarrollo humano y la salud; fomenten las competencias profesionales; promuevan la conciencia ética, motiven la responsabilidad social, el interés colectivo; y sean promotores del desarrollo tecnológico y la innovación. | D5: PRDI25-29-Obj-129 | E5: Promover el desarrollo humano, económico, social y medioambiental de las comunidades, especialmente de los grupos sociales minoritarios o vulnerables, a partir de la intervención universitaria, inter y multidisciplinaria. | F5: 12 | G5: Capacitar al año a 250 universitarios y público en general en temas relacionados con la economía social y solidaria | H5: ACT-PRDI-NS-3113 | I5: Contribuir desde la Facultad de Ingeniería al cumplimiento de la meta PRDI “Capacitar al año a 250 universitarios y público en general en temas relacionados con la economía social y solidaria”, con valores absolutos programados de 2027: 5, 2028: 5, 2029: 5, 2030: 5. | J5: Actividad | K5: Sin fórmula | L5: Capacitar a universitarios y público en general en temas relacionados con la economía social y solidaria | N5: 5 | O5: 5 | P5: 5 | Q5: 5 | R5: =IF(M5="","",M5) | S5: =IF(N5="","",N5) -> 5 | T5: =IF(O5="","",O5) -> 5 | U5: =IF(P5="","",P5) -> 5 | V5: =IF(Q5="","",Q5) -> 5 | W5: Anual | X5: Coordinación de Extensión y Vinculación
A6: 4 | B6: PRDI25-29-Obj-54 | C6: Fomentar la vinculación estratégica de la Universidad con los sectores social, productivo y gubernamental, para el desarrollo de proyectos inclusivos y sostenibles, que favorezcan el desarrollo humano y la salud; fomenten las competencias profesionales; promuevan la conciencia ética, motiven la responsabilidad social, el interés colectivo; y sean promotores del desarrollo tecnológico y la innovación. | D6: PRDI25-29-Obj-129 | E6: Promover el desarrollo humano, económico, social y medioambiental de las comunidades, especialmente de los grupos sociales minoritarios o vulnerables, a partir de la intervención universitaria, inter y multidisciplinaria. | F6: 14 | G6: Atender 40 proyectos de economía social y solidaria en el territorio mexiquense al cierre de la administración | H6: ACT-PRDI-NS-2755 | I6: Contribuir desde la Facultad de Ingeniería al cumplimiento de la meta PRDI “Atender 40 proyectos de economía social y solidaria en el territorio mexiquense al cierre de la administración”, con valores absolutos programados de 2027: 0, 2028: 0, 2029: 1, 2030: 0. Sustento en la Matriz de consistencia: «Realizar 1 revisión documentada de los resultados del servicio social y sus beneficiarios en 2027 y actualizarla una vez al año de 2028 a 2030.» | J6: Actividad | K6: Sin fórmula | L6: Atender proyectos de economía social y solidaria en el territorio mexiquense | N6: 0 | O6: 0 | P6: 1 | Q6: 0 | R6: =IF(M6="","",M6) | S6: =IF(N6="","",N6) -> 0 | T6: =IF(O6="","",O6) -> 0 | U6: =IF(P6="","",P6) -> 1 | V6: =IF(Q6="","",Q6) -> 0 | W6: Anual | X6: Coordinación de Extensión y Vinculación
A7: 5 | B7: PRDI25-29-Obj-54 | C7: Fomentar la vinculación estratégica de la Universidad con los sectores social, productivo y gubernamental, para el desarrollo de proyectos inclusivos y sostenibles, que favorezcan el desarrollo humano y la salud; fomenten las competencias profesionales; promuevan la conciencia ética, motiven la responsabilidad social, el interés colectivo; y sean promotores del desarrollo tecnológico y la innovación. | D7: PRDI25-29-Obj-129 | E7: Promover el desarrollo humano, económico, social y medioambiental de las comunidades, especialmente de los grupos sociales minoritarios o vulnerables, a partir de la intervención universitaria, inter y multidisciplinaria. | F7: 15 | G7: Ejecutar 6 colaboraciones de impacto social con organizaciones locales o sectores productivos de mediano y largo plazo durante la administración | H7: ACT-PRDI-NS-3115 | I7: Contribuir desde la Facultad de Ingeniería al cumplimiento de la meta PRDI “Ejecutar 6 colaboraciones de impacto social con organizaciones locales o sectores productivos de mediano y largo plazo durante la administración”, con valores absolutos programados de 2027: 1, 2028: 0, 2029: 0, 2030: 0. | J7: Actividad | K7: Sin fórmula | L7: Ejecutar colaboraciones de impacto social con organizaciones locales o sectores productivos de mediano y largo plazo | N7: 1 | O7: 0 | P7: 0 | Q7: 0 | R7: =IF(M7="","",M7) | S7: =IF(N7="","",N7) -> 1 | T7: =IF(O7="","",O7) -> 0 | U7: =IF(P7="","",P7) -> 0 | V7: =IF(Q7="","",Q7) -> 0 | W7: Anual | X7: Coordinación de Extensión y Vinculación
A8: 6 | B8: PRDI25-29-Obj-54 | C8: Fomentar la vinculación estratégica de la Universidad con los sectores social, productivo y gubernamental, para el desarrollo de proyectos inclusivos y sostenibles, que favorezcan el desarrollo humano y la salud; fomenten las competencias profesionales; promuevan la conciencia ética, motiven la responsabilidad social, el interés colectivo; y sean promotores del desarrollo tecnológico y la innovación. | D8: PRDI25-29-Obj-129 | E8: Promover el desarrollo humano, económico, social y medioambiental de las comunidades, especialmente de los grupos sociales minoritarios o vulnerables, a partir de la intervención universitaria, inter y multidisciplinaria. | F8: 16 | G8: Lograr cada año la participación de 35 espacios académicos en servicios comunitarios de beneficio social y proyectos de Brigadas Universitarias Multidisciplinarias (BUM TUAEMEX) | H8: ACT-PRDI-NS-3116 | I8: Contribuir desde la Facultad de Ingeniería al cumplimiento de la meta PRDI “Lograr cada año la participación de 35 espacios académicos en servicios comunitarios de beneficio social y proyectos de Brigadas Universitarias Multidisciplinarias (BUM TUAEMEX)”, con valores absolutos programados de 2027: 1, 2028: 1, 2029: 1, 2030: 1. | J8: Actividad | K8: Sin fórmula | L8: Lograr la participación de espacios académicos en servicios comunitarios de beneficio social y proyectos de Brigadas Universitarias Multidisciplinarias (BUM TUUAEMEX) | N8: 1 | O8: 1 | P8: 1 | Q8: 1 | R8: =IF(M8="","",M8) | S8: =IF(N8="","",N8) -> 1 | T8: =IF(O8="","",O8) -> 1 | U8: =IF(P8="","",P8) -> 1 | V8: =IF(Q8="","",Q8) -> 1 | W8: Anual | X8: Coordinación de Extensión y Vinculación
A9: 7 | B9: PRDI25-29-Obj-54 | C9: Fomentar la vinculación estratégica de la Universidad con los sectores social, productivo y gubernamental, para el desarrollo de proyectos inclusivos y sostenibles, que favorezcan el desarrollo humano y la salud; fomenten las competencias profesionales; promuevan la conciencia ética, motiven la responsabilidad social, el interés colectivo; y sean promotores del desarrollo tecnológico y la innovación. | D9: PRDI25-29-Obj-130 | E9: PRDI25-29-Obj-130 -Impulsar la colaboración con instancias de los sectores público y privado para fortalecer el desarrollo de competencias profesionales, transversales y complementarias en el estudiantado, favorecer su empleabilidad y contribuir al progreso socialmente responsable. | F9: 20 | G9: Incrementar 5% al año la participación de universitarios en el Programa de Competencias Laborales | H9: IND-PRDI-410 | I9: Mejorar o mantener de forma conservadora en la Facultad de Ingeniería el indicador IND-PRDI-410, con la trayectoria 2027: 3.88%, 2028: 4.31%, 2029: 4.68%, 2030: 5%, sustentada en referencia PRDI; no existe serie histórica directamente comparable para la variable. | J9: Indicador | K9: ((Número de universitarios participantes en el programa de competencias laborales en el año actual/Número de universitarios participantes en el programa de competencias laborales en el año anterior)-1)*100 | L9: Número de universitarios participantes en el programa de competencias laborales en el año actual | N9: 348 | O9: 363 | P9: 380 | Q9: 399 | R9: =IF(M10,((M9/M10)-1)*100,"") | S9: =IF(N10,((N9/N10)-1)*100,"") -> 3.880597 | T9: =IF(O10,((O9/O10)-1)*100,"") -> 4.3103448 | U9: =IF(P10,((P9/P10)-1)*100,"") -> 4.6831956 | V9: =IF(Q10,((Q9/Q10)-1)*100,"") -> 5 | W9: Anual | X9: Coordinación de Extensión y Vinculación
L10: Número de universitarios participantes en el programa de competencias laborales en el año anterior | N10: 335 | O10: 348 | P10: 363 | Q10: 380
A11: 8 | B11: PRDI25-29-Obj-54 | C11: Fomentar la vinculación estratégica de la Universidad con los sectores social, productivo y gubernamental, para el desarrollo de proyectos inclusivos y sostenibles, que favorezcan el desarrollo humano y la salud; fomenten las competencias profesionales; promuevan la conciencia ética, motiven la responsabilidad social, el interés colectivo; y sean promotores del desarrollo tecnológico y la innovación. | D11: PRDI25-29-Obj-130 | E11: Impulsar la colaboración con instancias de los sectores público y privado para fortalecer el desarrollo de competencias profesionales, transversales y complementarias en el estudiantado, favorecer su empleabilidad y contribuir al progreso socialmente responsable. | F11: 25 | G11: Mantener 35 colaboraciones al año con empresas, instituciones y organizaciones para el Catálogo de descuentos universitarios | H11: ACT-PRDI-NS-3125 | I11: Contribuir desde la Facultad de Ingeniería al cumplimiento de la meta PRDI “Mantener 35 colaboraciones al año con empresas, instituciones y organizaciones para el Catálogo de descuentos universitarios”, con valores absolutos programados de 2027: 1, 2028: 1, 2029: 1, 2030: 1. Sustento en la Matriz de consistencia: «Realizar 1 reunión y 1 encuesta a estudiantes y organizaciones receptoras cada año de 2028 a 2030 y documentar los ajustes derivados.» | J11: Actividad | K11: Sin fórmula | L11: Mantener colaboraciones con empresas, instituciones y organizaciones para el Catálogo de descuentos universitarios | N11: 1 | O11: 1 | P11: 1 | Q11: 1 | R11: =IF(M11="","",M11) | S11: =IF(N11="","",N11) -> 1 | T11: =IF(O11="","",O11) -> 1 | U11: =IF(P11="","",P11) -> 1 | V11: =IF(Q11="","",Q11) -> 1 | W11: Anual | X11: Coordinación de Extensión y Vinculación
A12: 9 | B12: PRDI25-29-Obj-54 | C12: Fomentar la vinculación estratégica de la Universidad con los sectores social, productivo y gubernamental, para el desarrollo de proyectos inclusivos y sostenibles, que favorezcan el desarrollo humano y la salud; fomenten las competencias profesionales; promuevan la conciencia ética, motiven la responsabilidad social, el interés colectivo; y sean promotores del desarrollo tecnológico y la innovación. | D12: PRDI25-29-Obj-131 | E12: Fortalecer la formación, evaluación y certificación lingüística para impulsar la empleabilidad, la movilidad académica y la proyección cultural de la comunidad universitaria y la sociedad. | F12: 37 | G12: Aperturar anualmente 1 grupo de lenguas originarias en algún espacio universitario, CELE o extensión de CELE | H12: ACT-PRDI-NS-3135 | I12: Contribuir desde la Facultad de Ingeniería al cumplimiento de la meta PRDI “Aperturar anualmente 1 grupo de lenguas originarias en algún espacio universitario, CELE o extensión de CELE”, con valores absolutos programados de 2027: 1, 2028: 1, 2029: 1, 2030: 1. | J12: Actividad | K12: Sin fórmula | L12: Aperturar grupos de lenguas originarias en algún espacio universitario, CELE o extensión de CELE | N12: 1 | O12: 1 | P12: 1 | Q12: 1 | R12: =IF(M12="","",M12) | S12: =IF(N12="","",N12) -> 1 | T12: =IF(O12="","",O12) -> 1 | U12: =IF(P12="","",P12) -> 1 | V12: =IF(Q12="","",Q12) -> 1 | W12: Anual | X12: Coordinación de Extensión y Vinculación
A13: 10 | B13: PRDI25-29-Obj-54 | C13: Fomentar la vinculación estratégica de la Universidad con los sectores social, productivo y gubernamental, para el desarrollo de proyectos inclusivos y sostenibles, que favorezcan el desarrollo humano y la salud; fomenten las competencias profesionales; promuevan la conciencia ética, motiven la responsabilidad social, el interés colectivo; y sean promotores del desarrollo tecnológico y la innovación. | D13: PRDI25-29-Obj-132 | E13: PRDI25-29-Obj-132 -Fortalecer la promoción, prevención y atención a la salud de primer nivel para mejorar el bienestar integral y la calidad de vida de la comunidad universitaria y la sociedad mexiquense. | F13: 42 | G13: Lograr que 100% de los espacios académicos cuenten con servicios de Atención Psicológica al cierre de la administración | H13: ACT-PRDI-NS-3245 | I13: Contribuir desde la Facultad de Ingeniería al cumplimiento de la meta PRDI “Lograr que 100% de los espacios académicos cuenten con servicios de Atención Psicológica al cierre de la administración”, con valores absolutos programados de 2027: 0, 2028: 0, 2029: 1, 2030: 0. Sustento en la Matriz de consistencia: «Validar y documentar el valor de Ref. 2026 durante 2027 y, una vez confirmado, mantenerlo o mejorarlo hasta 2030.» | J13: Actividad | K13: Sin fórmula | L13: Contar con el Servicio de Atención Psicologíca | N13: 0 | O13: 0 | P13: 1 | Q13: 0 | R13: =IF(M13="","",M13) | S13: =IF(N13="","",N13) -> 0 | T13: =IF(O13="","",O13) -> 0 | U13: =IF(P13="","",P13) -> 1 | V13: =IF(Q13="","",Q13) -> 0 | W13: Anual | X13: Coordinación de Extensión y Vinculación

Sheet 21 Comunicación universitaria
A1: N.P. | B1: Clave Objetivo General | C1: Objetivo General | D1: Clave Objetivo Específico | E1: Objetivo Específico | F1: No. de meta en el PRDI | G1: Meta PRDI | H1: Clave de la meta | I1: Meta del espacio académico | J1: Actividad/Indicador | K1: Método de cálculo | L1: Nombre de las variables | M1: Valor de las variables | R1: Valor de los indicadores | W1: Medición (anual o acumulada) | X1: Área responsable
M2: Ref. 2026 | N2: 2027 | O2: 2028 | P2: 2029 | Q2: 2030 | R2: Ref. 2026 | S2: 2027 | T2: 2028 | U2: 2029 | V2: 2030
A3: 1 | B3: PRDI25-29-Obj-55 | C3: Promover una comunicación social efectiva y cercana que fortalezca la identidad institucional de la uaemex, impulsando la inclusión y el diálogo abierto con toda la comunidad universitaria y la sociedad, a fin de difundir y consolidar valores que contribuyan al desarrollo académico, cultural y social. | D3: PRDI25-29-Obj-77 | E3: Impulsar canales efectivos de comunicación que faciliten el diálogo continuo con la comunidad universitaria, promoviendo la participación, la difusión de logros y el empleo de plataformas tecnológicas modernas. | F3: 2 | G3: Realizar 3 campañas anuales que promuevan los valores universitarios de cercanía, inclusión y progresismo tanto en medios impresos como digitales | H3: ACT-PRDI-NS-2723 | I3: Contribuir desde la Facultad de Ingeniería al cumplimiento de la meta PRDI “Realizar 3 campañas anuales que promuevan los valores universitarios de cercanía, inclusión y progresismo tanto en medios impresos como digitales”, con valores absolutos programados de 2027: 1, 2028: 1, 2029: 1, 2030: 1. Sustento en la Matriz de consistencia: «Aprobar 1 calendario editorial en 2027 y publicar 1 evaluación de alcance por año de 2028 a 2030.» «Realizar 1 revisión documentada de el alcance y la claridad de los canales institucionales en 2027 y actualizarla una vez al año de 2028 a 2030.» «Realizar 1 reunión y 1 encuesta a estudiantes, docentes y administrativos cada año de 2028 a 2030 y documentar los ajustes derivados.» | J3: Actividad | K3: Sin fórmula | L3: Realizar campañas que promuevan los valores universitarios de cercanía, inclusión y progresismo tanto en medios impresos como digitales en apego al enfoque institucional | N3: 1 | O3: 1 | P3: 1 | Q3: 1 | R3: =IF(M3="","",M3) | S3: =IF(N3="","",N3) -> 1 | T3: =IF(O3="","",O3) -> 1 | U3: =IF(P3="","",P3) -> 1 | V3: =IF(Q3="","",Q3) -> 1 | W3: Anual | X3: Departamento de Comunicación

Sheet 22 Sostenibilidad ambiental 
A1: N.P. | B1: Clave Objetivo General | C1: Objetivo General | D1: Clave Objetivo Específico | E1: Objetivo Específico | F1: No. de meta en el PRDI | G1: Meta PRDI | H1: Clave de la meta | I1: Meta del espacio académico | J1: Actividad/Indicador | K1: Método de cálculo | L1: Nombre de las variables | M1: Valor de las variables | R1: Valor de los indicadores | W1: Medición (anual o acumulada) | X1: Área responsable
M2: Ref. 2026 | N2: 2027 | O2: 2028 | P2: 2029 | Q2: 2030 | R2: Ref. 2026 | S2: 2027 | T2: 2028 | U2: 2029 | V2: 2030
A3: 1 | B3: PRDI25-29-Obj-56 | C3: PRDI25-29-Obj-56 -Fortalecer una cultura de respeto mediante la educación ambiental, que permita la conservación y protección del medio ambiente entre la comunidad universitaria, para alcanzar el desarrollo sostenible. | D3: PRDI2025-2029-Obj-78 | E3: PRDI2025-2029-Obj-78 -Impulsar acciones sustentables para reducir el impacto negativo en el medio ambiente, ocasionado por las funciones sustantivas y adjetivas de la Institución. | F3: 7 | G3: Establecer 1 programa de reducción del uso de unicel y desechables | H3: ACT-PRDI-NS-3154 | I3: Contribuir desde la Facultad de Ingeniería al cumplimiento de la meta PRDI “Establecer 1 programa de reducción del uso de unicel y desechables”, con valores absolutos programados de 2027: 0, 2028: 0, 2029: 1, 2030: 0. | J3: Actividad | K3: Sin fórmula | L3: Establecer un programa de reducción del uso de unicel y desechables | N3: 0 | O3: 0 | P3: 1 | Q3: 0 | R3: =IF(M3="","",M3) | S3: =IF(N3="","",N3) -> 0 | T3: =IF(O3="","",O3) -> 0 | U3: =IF(P3="","",P3) -> 1 | V3: =IF(Q3="","",Q3) -> 0 | W3: Anual | X3: Comité de Sustentabilidad y Subdirección Administrativa
A4: 2 | B4: PRDI25-29-Obj-56 | C4: PRDI25-29-Obj-56 -Fortalecer una cultura de respeto mediante la educación ambiental, que permita la conservación y protección del medio ambiente entre la comunidad universitaria, para alcanzar el desarrollo sostenible. | D4: PRDI2025-2029-Obj-78 | E4: PRDI2025-2029-Obj-78 -Impulsar acciones sustentables para reducir el impacto negativo en el medio ambiente, ocasionado por las funciones sustantivas y adjetivas de la Institución. | F4: 8 | G4: Operar anualmente 1 campaña de acopio de residuos de aceite vegetal-comestible generado en las cafeterías de los espacios académicos y cocinas de la Licenciatura en Gastronomía | H4: ACT-PRDI-NS-3155 | I4: Contribuir desde la Facultad de Ingeniería al cumplimiento de la meta PRDI “Operar anualmente 1 campaña de acopio de residuos de aceite vegetal-comestible generado en las cafeterías de los espacios académicos y cocinas de la Licenciatura en Gastronomía”, con valores absolutos programados de 2027: 1, 2028: 1, 2029: 1, 2030: 1. Sustento en la Matriz de consistencia: «Registrar 1 acuerdo de mejora sobre el consumo de agua, energía y la generación de residuos en 2028 y revisar su cumplimiento anualmente hasta 2030.» | J4: Actividad | K4: Sin fórmula | L4: Operar campañas de acopio de residuos de aceite vegetal-comestible generado en las cafeterías de los espacios académicos | N4: 1 | O4: 1 | P4: 1 | Q4: 1 | R4: =IF(M4="","",M4) | S4: =IF(N4="","",N4) -> 1 | T4: =IF(O4="","",O4) -> 1 | U4: =IF(P4="","",P4) -> 1 | V4: =IF(Q4="","",Q4) -> 1 | W4: Anual | X4: Comité de Sustentabilidad y Subdirección Administrativa
A5: 3 | B5: PRDI25-29-Obj-56 | C5: PRDI25-29-Obj-56 -Fortalecer una cultura de respeto mediante la educación ambiental, que permita la conservación y protección del medio ambiente entre la comunidad universitaria, para alcanzar el desarrollo sostenible. | D5: PRDI2025-2029-Obj-78 | E5: PRDI2025-2029-Obj-78 -Impulsar acciones sustentables para reducir el impacto negativo en el medio ambiente, ocasionado por las funciones sustantivas y adjetivas de la Institución. | F5: 10 | G5: Realizar anualmente 1 campaña institucional de reforestación que incluya las 4 regiones con presencia universitaria | H5: ACT-PRDI-NS-3157 | I5: Contribuir desde la Facultad de Ingeniería al cumplimiento de la meta PRDI “Realizar anualmente 1 campaña institucional de reforestación que incluya las 4 regiones con presencia universitaria”, con valores absolutos programados de 2027: 1, 2028: 1, 2029: 1, 2030: 1. | J5: Actividad | K5: Sin fórmula | L5: Realizar campañas institucionales de reforestación que incluya las regiones con presencia universitaria | N5: 1 | O5: 1 | P5: 1 | Q5: 1 | R5: =IF(M5="","",M5) | S5: =IF(N5="","",N5) -> 1 | T5: =IF(O5="","",O5) -> 1 | U5: =IF(P5="","",P5) -> 1 | V5: =IF(Q5="","",Q5) -> 1 | W5: Anual | X5: Comité de Sustentabilidad y Subdirección Administrativa
A6: 4 | B6: PRDI25-29-Obj-56 | C6: PRDI25-29-Obj-56 -Fortalecer una cultura de respeto mediante la educación ambiental, que permita la conservación y protección del medio ambiente entre la comunidad universitaria, para alcanzar el desarrollo sostenible. | D6: PRDI2025-2029-Obj-78 | E6: PRDI2025-2029-Obj-78 -Impulsar acciones sustentables para reducir el impacto negativo en el medio ambiente, ocasionado por las funciones sustantivas y adjetivas de la Institución. | F6: 13 | G6: Operar anualmente 1 programa de mantenimiento y fortalecimiento de huertos universitarios | H6: ACT-PRDI-NS-3161 | I6: Contribuir desde la Facultad de Ingeniería al cumplimiento de la meta PRDI “Operar anualmente 1 programa de mantenimiento y fortalecimiento de huertos universitarios”, con valores absolutos programados de 2027: 1, 2028: 1, 2029: 1, 2030: 1. | J6: Actividad | K6: Sin fórmula | L6: Operar un programa de mantenimiento y fortalecimiento de huertos universitarios | N6: 1 | O6: 1 | P6: 1 | Q6: 1 | R6: =IF(M6="","",M6) | S6: =IF(N6="","",N6) -> 1 | T6: =IF(O6="","",O6) -> 1 | U6: =IF(P6="","",P6) -> 1 | V6: =IF(Q6="","",Q6) -> 1 | W6: Anual | X6: Comité de Sustentabilidad y Subdirección Administrativa
A7: 5 | B7: PRDI25-29-Obj-56 | C7: PRDI25-29-Obj-56 -Fortalecer una cultura de respeto mediante la educación ambiental, que permita la conservación y protección del medio ambiente entre la comunidad universitaria, para alcanzar el desarrollo sostenible. | D7: PRDI2025-2029-Obj-78 | E7: PRDI2025-2029-Obj-78 -Impulsar acciones sustentables para reducir el impacto negativo en el medio ambiente, ocasionado por las funciones sustantivas y adjetivas de la Institución. | F7: 15 | G7: Lograr que 100% de los espacios académicos operen el Plan Institucional de Manejo de Residuos Sólidos Urbanos a 2029 | H7: ACT-PRDI-NS-3247 | I7: Contribuir desde la Facultad de Ingeniería al cumplimiento de la meta PRDI “Lograr que 100% de los espacios académicos operen el Plan Institucional de Manejo de Residuos Sólidos Urbanos a 2029”, con valores absolutos programados de 2027: 1, 2028: 1, 2029: 1, 2030: 1. Sustento en la Matriz de consistencia: «Medir 1 línea base de agua, energía y residuos en 2027 y aprobar 1 plan ambiental medible en 2028.» | J7: Actividad | K7: Sin fórmula | L7: Operar el plan de manejo de residuos sólidos urbano | N7: 1 | O7: 1 | P7: 1 | Q7: 1 | R7: =IF(M7="","",M7) | S7: =IF(N7="","",N7) -> 1 | T7: =IF(O7="","",O7) -> 1 | U7: =IF(P7="","",P7) -> 1 | V7: =IF(Q7="","",Q7) -> 1 | W7: Anual | X7: Comité de Sustentabilidad y Subdirección Administrativa
A8: 6 | B8: PRDI25-29-Obj-56 | C8: PRDI25-29-Obj-56 -Fortalecer una cultura de respeto mediante la educación ambiental, que permita la conservación y protección del medio ambiente entre la comunidad universitaria, para alcanzar el desarrollo sostenible. | D8: PRDI2025-2029-Obj-78 | E8: PRDI2025-2029-Obj-78 -Impulsar acciones sustentables para reducir el impacto negativo en el medio ambiente, ocasionado por las funciones sustantivas y adjetivas de la Institución. | F8: 16 | G8: Promover en 22 espacios académicos el proceso de compostaje de los residuos orgánicos de poda y jardinería a 2029 | H8: ACT-PRDI-NS-3163 | I8: Contribuir desde la Facultad de Ingeniería al cumplimiento de la meta PRDI “Promover en 22 espacios académicos el proceso de compostaje de los residuos orgánicos de poda y jardinería a 2029”, con valores absolutos programados de 2027: 1, 2028: 1, 2029: 1, 2030: 1. | J8: Actividad | K8: Sin fórmula | L8: Promover en espacios académicos el proceso de compostaje de los residuos orgánicos de poda y jardinería | N8: 1 | O8: 1 | P8: 1 | Q8: 1 | R8: =IF(M8="","",M8) | S8: =IF(N8="","",N8) -> 1 | T8: =IF(O8="","",O8) -> 1 | U8: =IF(P8="","",P8) -> 1 | V8: =IF(Q8="","",Q8) -> 1 | W8: Anual | X8: Comité de Sustentabilidad y Subdirección Administrativa
A9: 7 | B9: PRDI25-29-Obj-56 | C9: PRDI25-29-Obj-56 -Fortalecer una cultura de respeto mediante la educación ambiental, que permita la conservación y protección del medio ambiente entre la comunidad universitaria, para alcanzar el desarrollo sostenible. | D9: PRDI25-29-Obj-135 | E9: PRDI25-29-Obj-135 -Formar agentes universitarios de cambio comprometidos para la construcción de un medio ambiente sostenible. | F9: 1 | G9: Capacitar anualmente a 1 736 estudiantes de nivel superior en temas de sustentabilidad | H9: ACT-PRDI-NS-2747 | I9: Contribuir desde la Facultad de Ingeniería al cumplimiento de la meta PRDI “Capacitar anualmente a 1 736 estudiantes de nivel superior en temas de sustentabilidad”, con valores absolutos programados de 2027: 32, 2028: 32, 2029: 32, 2030: 32. | J9: Actividad | K9: Sin fórmula | L9: Capacitar a estudiantes de nivel superior en temas de sustentabilidad | N9: 32 | O9: 32 | P9: 32 | Q9: 32 | R9: =IF(M9="","",M9) | S9: =IF(N9="","",N9) -> 32 | T9: =IF(O9="","",O9) -> 32 | U9: =IF(P9="","",P9) -> 32 | V9: =IF(Q9="","",Q9) -> 32 | W9: Anual | X9: Comité de Sustentabilidad y Subdirección Administrativa
A10: 8 | B10: PRDI25-29-Obj-56 | C10: PRDI25-29-Obj-56 -Fortalecer una cultura de respeto mediante la educación ambiental, que permita la conservación y protección del medio ambiente entre la comunidad universitaria, para alcanzar el desarrollo sostenible. | D10: PRDI25-29-Obj-135 | E10: PRDI25-29-Obj-135 -Formar agentes universitarios de cambio comprometidos para la construcción de un medio ambiente sostenible. | F10: 3 | G10: Capacitar a 1 034 integrantes del personal docente en temas de sustentabilidad a 2029 | H10: ACT-PRDI-NS-2392 | I10: Contribuir desde la Facultad de Ingeniería al cumplimiento de la meta PRDI “Capacitar a 1 034 integrantes del personal docente en temas de sustentabilidad a 2029”, con valores absolutos programados de 2027: 10, 2028: 15, 2029: 19, 2030: 19. | J10: Actividad | K10: Sin fórmula | L10: Capacitar a académicos en temas de sustentabilidad | N10: 10 | O10: 15 | P10: 19 | Q10: 19 | R10: =IF(M10="","",M10) | S10: =IF(N10="","",N10) -> 10 | T10: =IF(O10="","",O10) -> 15 | U10: =IF(P10="","",P10) -> 19 | V10: =IF(Q10="","",Q10) -> 19 | W10: Anual | X10: Comité de Sustentabilidad y Subdirección Administrativa
A11: 9 | B11: PRDI25-29-Obj-56 | C11: PRDI25-29-Obj-56 -Fortalecer una cultura de respeto mediante la educación ambiental, que permita la conservación y protección del medio ambiente entre la comunidad universitaria, para alcanzar el desarrollo sostenible. | D11: PRDI25-29-Obj-135 | E11: PRDI25-29-Obj-135 -Formar agentes universitarios de cambio comprometidos para la construcción de un medio ambiente sostenible. | F11: 4 | G11: Capacitar a 2 115 integrantes del personal administrativo en temas de sustentabilidad a 2029 | H11: ACT-PRDI-NS-2391 | I11: Contribuir desde la Facultad de Ingeniería al cumplimiento de la meta PRDI “Capacitar a 2 115 integrantes del personal administrativo en temas de sustentabilidad a 2029”, con valores absolutos programados de 2027: 20, 2028: 30, 2029: 39, 2030: 39. | J11: Actividad | K11: Sin fórmula | L11: Capacitar a administrativos en temas de sustentabilidad | N11: 20 | O11: 30 | P11: 39 | Q11: 39 | R11: =IF(M11="","",M11) | S11: =IF(N11="","",N11) -> 20 | T11: =IF(O11="","",O11) -> 30 | U11: =IF(P11="","",P11) -> 39 | V11: =IF(Q11="","",Q11) -> 39 | W11: Anual | X11: Comité de Sustentabilidad y Subdirección Administrativa
A12: 10 | B12: PRDI25-29-Obj-56 | C12: PRDI25-29-Obj-56 -Fortalecer una cultura de respeto mediante la educación ambiental, que permita la conservación y protección del medio ambiente entre la comunidad universitaria, para alcanzar el desarrollo sostenible. | D12: PRDI25-29-Obj-136 | E12: PRDI25-29-Obj-136 -Desarrollar una cultura de sustentabilidad, aplicable a las funciones adjetivas y sustantivas de la Universidad para contribuir al uso eficiente de los recursos. | F12: 21 | G12: Implementar 1 programa de cuidado y ahorro de agua en 100% de los espacios universitarios a 2029 | H12: ACT-PRDI-NS-3248 | I12: Contribuir desde la Facultad de Ingeniería al cumplimiento de la meta PRDI “Implementar 1 programa de cuidado y ahorro de agua en 100% de los espacios universitarios a 2029”, con valores absolutos programados de 2027: 1, 2028: 1, 2029: 1, 2030: 1. Sustento en la Matriz de consistencia: «Realizar 1 revisión documentada de el consumo de agua, energía y la generación de residuos en 2027 y actualizarla una vez al año de 2028 a 2030.» | J12: Actividad | K12: Sin fórmula | L12: Implementar un programa de cuidado y ahorro de agua | N12: 1 | O12: 1 | P12: 1 | Q12: 1 | R12: =IF(M12="","",M12) | S12: =IF(N12="","",N12) -> 1 | T12: =IF(O12="","",O12) -> 1 | U12: =IF(P12="","",P12) -> 1 | V12: =IF(Q12="","",Q12) -> 1 | W12: Anual | X12: Comité de Sustentabilidad y Subdirección Administrativa
A13: 11 | B13: PRDI25-29-Obj-56 | C13: PRDI25-29-Obj-56 -Fortalecer una cultura de respeto mediante la educación ambiental, que permita la conservación y protección del medio ambiente entre la comunidad universitaria, para alcanzar el desarrollo sostenible. | D13: PRDI25-29-Obj-136 | E13: PRDI25-29-Obj-136 -Desarrollar una cultura de sustentabilidad, aplicable a las funciones adjetivas y sustantivas de la Universidad para contribuir al uso eficiente de los recursos. | F13: 22 | G13: Ejecutar anualmente 1 programa institucional de eficiencia energética | H13: ACT-PRDI-NS-3170 | I13: Contribuir desde la Facultad de Ingeniería al cumplimiento de la meta PRDI “Ejecutar anualmente 1 programa institucional de eficiencia energética”, con valores absolutos programados de 2027: 1, 2028: 1, 2029: 1, 2030: 1. | J13: Actividad | K13: Sin fórmula | L13: Ejecutar el programa institucional de eficiencia energética | N13: 1 | O13: 1 | P13: 1 | Q13: 1 | R13: =IF(M13="","",M13) | S13: =IF(N13="","",N13) -> 1 | T13: =IF(O13="","",O13) -> 1 | U13: =IF(P13="","",P13) -> 1 | V13: =IF(Q13="","",Q13) -> 1 | W13: Anual | X13: Comité de Sustentabilidad y Subdirección Administrativa
A14: 12 | B14: PRDI25-29-Obj-56 | C14: PRDI25-29-Obj-56 -Fortalecer una cultura de respeto mediante la educación ambiental, que permita la conservación y protección del medio ambiente entre la comunidad universitaria, para alcanzar el desarrollo sostenible. | D14: PRDI25-29-Obj-136 | E14: PRDI25-29-Obj-136 -Desarrollar una cultura de sustentabilidad, aplicable a las funciones adjetivas y sustantivas de la Universidad para contribuir al uso eficiente de los recursos. | F14: 23 | G14: Efectuar anualmente 1 programa institucional de reducción de uso de papel | H14: ACT-PRDI-NS-3171 | I14: Contribuir desde la Facultad de Ingeniería al cumplimiento de la meta PRDI “Efectuar anualmente 1 programa institucional de reducción de uso de papel”, con valores absolutos programados de 2027: 1, 2028: 1, 2029: 1, 2030: 1. | J14: Actividad | K14: Sin fórmula | L14: Efectua rel programa institucional de reducción de uso de papel | N14: 1 | O14: 1 | P14: 1 | Q14: 1 | R14: =IF(M14="","",M14) | S14: =IF(N14="","",N14) -> 1 | T14: =IF(O14="","",O14) -> 1 | U14: =IF(P14="","",P14) -> 1 | V14: =IF(Q14="","",Q14) -> 1 | W14: Anual | X14: Comité de Sustentabilidad y Subdirección Administrativa

Sheet Indicadores x proyec
A4: I. Estudiantado con oportunidades para su pleno desarrollo personal
A5: 2. Estudiantado con oportunidades para su pleno desarrollo y pertinencia en los estudios profesionales
A6: Num Progresivo de meta | B6: Meta | C6: Valor de los indicadores | I6: Medición (anual o acumulada) | J6: Área responsable
C7: Ref. 2025 | D7: 2026 | E7: 2027 | F7: 2028 | G7: 2029 | H7: 2030
A8: 3 | B8: ='2 EstudiantadoEstProf'!I5 -> Mejorar o mantener de forma conservadora en la Facultad de Ingeniería el indicador IND-NS-210, con la trayectoria 2027: 80%, 2028: 80%, 2029: 80%, 2030: 80%, sustentada en referencia PRDI; no existe serie histórica directamente comparable para la variable. | C8: ='2 EstudiantadoEstProf'!#REF! -> #REF! | D8: ='2 EstudiantadoEstProf'!R5 | E8: ='2 EstudiantadoEstProf'!S5 -> 80 | F8: ='2 EstudiantadoEstProf'!T5 -> 80 | G8: ='2 EstudiantadoEstProf'!U5 -> 80 | H8: ='2 EstudiantadoEstProf'!V5 -> 80 | I8: ='2 EstudiantadoEstProf'!W3 -> Anual | J8: ='2 EstudiantadoEstProf'!X5 -> Subdirección Académica y coordinaciones de licenciatura
A10: 4 | B10: ='2 EstudiantadoEstProf'!I7 -> Mejorar o mantener de forma conservadora en la Facultad de Ingeniería el indicador IND-PRDI-351, con la trayectoria 2027: 88.89%, 2028: 90.25%, 2029: 91.55%, 2030: 92.91%, sustentada en referencia PRDI; no existe serie histórica directamente comparable para la variable. | C10: ='2 EstudiantadoEstProf'!#REF! -> #REF! | D10: ='2 EstudiantadoEstProf'!R7 | E10: ='2 EstudiantadoEstProf'!S7 -> 88.892606 | F10: ='2 EstudiantadoEstProf'!T7 -> 90.246338 | G10: ='2 EstudiantadoEstProf'!U7 -> 91.553495 | H10: ='2 EstudiantadoEstProf'!V7 -> 92.913645 | I10: ='2 EstudiantadoEstProf'!W5 -> Anual | J10: ='2 EstudiantadoEstProf'!X7 -> Subdirección Académica y coordinaciones de licenciatura
A12: 5 | B12: ='2 EstudiantadoEstProf'!I9 -> Mejorar o mantener de forma conservadora en la Facultad de Ingeniería el indicador IND-PRDI-200, con la trayectoria 2027: 68%, 2028: 70%, 2029: 71.29%, 2030: 71.57%, sustentada en referencia PRDI; no existe serie histórica directamente comparable para la variable. | C12: ='2 EstudiantadoEstProf'!#REF! -> #REF! | D12: ='2 EstudiantadoEstProf'!R9 | E12: ='2 EstudiantadoEstProf'!S9 -> 68 | F12: ='2 EstudiantadoEstProf'!T9 -> 70 | G12: ='2 EstudiantadoEstProf'!U9 -> 71.287129 | H12: ='2 EstudiantadoEstProf'!V9 -> 71.568627 | I12: ='2 EstudiantadoEstProf'!W9 -> Anual | J12: ='2 EstudiantadoEstProf'!X9 -> Subdirección Académica y coordinaciones de licenciatura
A14: 8 | B14: ='2 EstudiantadoEstProf'!I13 -> Mejorar o mantener de forma conservadora en la Facultad de Ingeniería el indicador IND-PRDI-353, con la trayectoria 2027: 98.13%, 2028: 98.74%, 2029: 99.37%, 2030: 100%, sustentada en serie histórica directamente comparable del sitio. | C14: ='2 EstudiantadoEstProf'!#REF! -> #REF! | D14: ='2 EstudiantadoEstProf'!R13 | E14: ='2 EstudiantadoEstProf'!S13 -> 98.126464 | F14: ='2 EstudiantadoEstProf'!T13 -> 98.73502 | G14: ='2 EstudiantadoEstProf'!U13 -> 99.370653 | H14: ='2 EstudiantadoEstProf'!V13 -> 100 | I14: ='2 EstudiantadoEstProf'!W13 -> Anual | J14: ='2 EstudiantadoEstProf'!X13 -> Subdirección Académica y coordinaciones de licenciatura
A16: 12 | B16: ='2 EstudiantadoEstProf'!I18 -> Mejorar o mantener de forma conservadora en la Facultad de Ingeniería el indicador IND-PRDI-357, con la trayectoria 2027: 80%, 2028: 80%, 2029: 80%, 2030: 80%, sustentada en referencia PRDI; no existe serie histórica directamente comparable para la variable. | C16: ='2 EstudiantadoEstProf'!#REF! -> #REF! | D16: ='2 EstudiantadoEstProf'!R18 | E16: ='2 EstudiantadoEstProf'!S18 -> 80 | F16: ='2 EstudiantadoEstProf'!T18 -> 80 | G16: ='2 EstudiantadoEstProf'!U18 -> 80 | H16: ='2 EstudiantadoEstProf'!V18 -> 80 | I16: ='2 EstudiantadoEstProf'!W18 -> Anual | J16: ='2 EstudiantadoEstProf'!X18 -> Subdirección Académica y coordinaciones de licenciatura
A18: 18 | B18: ='2 EstudiantadoEstProf'!I24 -> Mejorar o mantener de forma conservadora en la Facultad de Ingeniería el indicador IND-PRDI-40, con la trayectoria 2027: 3%, 2028: 4%, 2029: 4.95%, 2030: 5.88%, sustentada en serie histórica directamente comparable del sitio. | C18: ='2 EstudiantadoEstProf'!#REF! -> #REF! | D18: ='2 EstudiantadoEstProf'!R24 | E18: ='2 EstudiantadoEstProf'!S24 -> 3 | F18: ='2 EstudiantadoEstProf'!T24 -> 4 | G18: ='2 EstudiantadoEstProf'!U24 -> 4.950495 | H18: ='2 EstudiantadoEstProf'!V24 -> 5.8823529 | I18: ='2 EstudiantadoEstProf'!W24 -> Anual | J18: ='2 EstudiantadoEstProf'!X24 -> Subdirección Académica y coordinaciones de licenciatura
A20: 20 | B20: ='2 EstudiantadoEstProf'!I27 -> Mejorar o mantener de forma conservadora en la Facultad de Ingeniería el indicador IND-NS-127, con la trayectoria 2027: 5.19%, 2028: 6.19%, 2029: 7.19%, 2030: 8.21%, sustentada en serie histórica directamente comparable del sitio. | C20: ='2 EstudiantadoEstProf'!#REF! -> #REF! | D20: ='2 EstudiantadoEstProf'!R27 | E20: ='2 EstudiantadoEstProf'!S27 -> 5.1856808 | F20: ='2 EstudiantadoEstProf'!T27 -> 6.1917443 | G20: ='2 EstudiantadoEstProf'!U27 -> 7.1878105 | H20: ='2 EstudiantadoEstProf'!V27 -> 8.2069875 | I20: ='2 EstudiantadoEstProf'!W27 -> Anual | J20: ='2 EstudiantadoEstProf'!X27 -> Subdirección Académica y coordinaciones de licenciatura
A22: 21 | B22: ='2 EstudiantadoEstProf'!I29 -> Mejorar o mantener de forma conservadora en la Facultad de Ingeniería el indicador IND-PRDI-34, con la trayectoria 2027: 8.03%, 2028: 7.96%, 2029: 7.88%, 2030: 7.81%, sustentada en serie histórica directamente comparable del sitio. | C22: ='2 EstudiantadoEstProf'!#REF! -> #REF! | D22: ='2 EstudiantadoEstProf'!R29 | E22: ='2 EstudiantadoEstProf'!S29 -> 8.0294413 | F22: ='2 EstudiantadoEstProf'!T29 -> 7.9560586 | G22: ='2 EstudiantadoEstProf'!U29 -> 7.8834051 | H22: ='2 EstudiantadoEstProf'!V29 -> 7.81147 | I22: ='2 EstudiantadoEstProf'!W29 -> Anual | J22: ='2 EstudiantadoEstProf'!X29 -> Subdirección Académica y coordinaciones de licenciatura
A26: 23 | B26: ='2 EstudiantadoEstProf'!I34 -> Mejorar o mantener de forma conservadora en la Facultad de Ingeniería el indicador IND-PRDI-366, con la trayectoria 2027: 94.01%, 2028: 95.34%, 2029: 96.65%, 2030: 97.99%, sustentada en referencia PRDI; no existe serie histórica directamente comparable para la variable. | C26: ='2 EstudiantadoEstProf'!#REF! -> #REF! | D26: ='2 EstudiantadoEstProf'!R34 | E26: ='2 EstudiantadoEstProf'!S34 -> 94.011375 | F26: ='2 EstudiantadoEstProf'!T34 -> 95.339547 | G26: ='2 EstudiantadoEstProf'!U34 -> 96.654521 | H26: ='2 EstudiantadoEstProf'!V34 -> 97.989453 | I26: ='2 EstudiantadoEstProf'!W34 -> Anual | J26: ='2 EstudiantadoEstProf'!X34 -> Subdirección Académica y coordinaciones de licenciatura
A29: 3. Estudios avanzados de excelencia y pertinencia social
A30: Num Progresivo de meta | B30: Meta | C30: Valor de los indicadores | I30: Medición (anual o acumulada) | J30: Área responsable
C31: Ref. 2025 | D31: 2026 | E31: 2027 | F31: 2028 | G31: 2029 | H31: 2030
A32: 7 | B32: ='3 Est avanzados excelencia'!I9 -> Mejorar o mantener de forma conservadora en la Facultad de Ingeniería el indicador IND-PRDI-365, con la trayectoria 2027: 15.15%, 2028: 18.18%, 2029: 18.18%, 2030: 18.18%, sustentada en referencia PRDI; no existe serie histórica directamente comparable para la variable. Sustento en la Matriz de consistencia: «Validar y documentar el valor de Ref. 2026 durante 2027 y, una vez confirmado, mantenerlo o mejorarlo hasta 2030.» | C32: ='3 Est avanzados excelencia'!#REF! -> #REF! | D32: ='3 Est avanzados excelencia'!R9 | E32: ='3 Est avanzados excelencia'!S9 -> 15.151515 | F32: ='3 Est avanzados excelencia'!T9 -> 18.181818 | G32: ='3 Est avanzados excelencia'!U9 -> 18.181818 | H32: ='3 Est avanzados excelencia'!V9 -> 18.181818 | I32: ='3 Est avanzados excelencia'!W9 -> Anual | J32: ='3 Est avanzados excelencia'!X9 -> Coordinación de Estudios Avanzados
A35: 4. Investigación abierta, inclusiva, equitativa y de calidad
A36: Num Progresivo de meta | B36: Meta | C36: Valor de los indicadores | I36: Medición (anual o acumulada) | J36: Área responsable
C37: Ref. 2025 | D37: 2026 | E37: 2027 | F37: 2028 | G37: 2029 | H37: 2030
A38: 2 | B38: ='4 Investigación abierta'!I4 -> Mejorar o mantener de forma conservadora en la Facultad de Ingeniería el indicador IND-PRDI-221, con la trayectoria 2027: 100%, 2028: 100%, 2029: 100%, 2030: 100%, sustentada en serie histórica directamente comparable del sitio. | C38: ='4 Investigación abierta'!#REF! -> #REF! | D38: ='4 Investigación abierta'!R4 | E38: ='4 Investigación abierta'!S4 -> 100 | F38: ='4 Investigación abierta'!T4 -> 100 | G38: ='4 Investigación abierta'!U4 -> 100 | H38: ='4 Investigación abierta'!V4 -> 100 | I38: ='4 Investigación abierta'!W4 -> Anual | J38: ='4 Investigación abierta'!X4 -> Coordinación de Investigación
A40: 3 | B40: ='4 Investigación abierta'!I6 -> Mejorar o mantener de forma conservadora en la Facultad de Ingeniería el indicador IND-PRDI-368, con la trayectoria 2027: 47.14%, 2028: 48.57%, 2029: 49.3%, 2030: 49.3%, sustentada en referencia PRDI; no existe serie histórica directamente comparable para la variable. | C40: ='4 Investigación abierta'!#REF! -> #REF! | D40: ='4 Investigación abierta'!R6 | E40: ='4 Investigación abierta'!S6 -> 47.142857 | F40: ='4 Investigación abierta'!T6 -> 48.571429 | G40: ='4 Investigación abierta'!U6 -> 49.295775 | H40: ='4 Investigación abierta'!V6 -> 49.295775 | I40: ='4 Investigación abierta'!W6 -> Anual | J40: ='4 Investigación abierta'!X6 -> Coordinación de Investigación
A42: 4 | B42: ='4 Investigación abierta'!I8 -> Mejorar o mantener de forma conservadora en la Facultad de Ingeniería el indicador IND-PRDI-370, con la trayectoria 2027: 47.14%, 2028: 48.57%, 2029: 49.3%, 2030: 49.3%, sustentada en referencia PRDI; no existe serie histórica directamente comparable para la variable. | C42: ='4 Investigación abierta'!#REF! -> #REF! | D42: ='4 Investigación abierta'!R8 | E42: ='4 Investigación abierta'!S8 -> 47.142857 | F42: ='4 Investigación abierta'!T8 -> 48.571429 | G42: ='4 Investigación abierta'!U8 -> 49.295775 | H42: ='4 Investigación abierta'!V8 -> 49.295775 | I42: ='4 Investigación abierta'!W8 -> Anual | J42: ='4 Investigación abierta'!X8 -> Coordinación de Investigación
